{
  "type": "Feature",
  "properties": {
    "gn:admin1_code":"00",
    "gn:asciiname":"Shulaveri",
    "gn:country_code":"GE",
    "gn:dem":1435,
    "gn:feature_class":"P",
    "gn:feature_code":"PPL",
    "gn:name":"Shulaveri",
    "gn:population":0,
    "gn:timezone":"Asia/Tbilisi",
    "iso:country":"GE",
    "name:ceb_x_preferred":[
        "Shulaveri"
    ],
    "name:hye_x_preferred":[
        "\u0547\u0578\u0582\u056c\u0561\u057e\u0565\u0580"
    ],
    "name:swe_x_preferred":[
        "Shulaveri"
    ],
    "wof:name":"Shulaveri",
    "wof:placetype":"locality"
},
  "geometry": {"coordinates":[44.12417,41.40361],"type":"Point"}
}