{
  "type": "Feature",
  "properties": {
    "gn:admin1_code":"73",
    "gn:asciiname":"Ruisi",
    "gn:country_code":"GE",
    "gn:dem":665,
    "gn:feature_class":"P",
    "gn:feature_code":"PPL",
    "gn:name":"Ruisi",
    "gn:population":0,
    "gn:timezone":"Asia/Tbilisi",
    "iso:country":"GE",
    "name:eng_x_preferred":[
        "Ruisi"
    ],
    "name:rus_x_preferred":[
        "\u0420\u0443\u0438\u0441\u0438"
    ],
    "wof:name":"Ruisi",
    "wof:placetype":"locality"
},
  "geometry": {"coordinates":[43.95956,42.03565],"type":"Point"}
}