{
  "type": "Feature",
  "properties": {
    "gn:admin1_code":"04",
    "gn:asciiname":"Chikuneti",
    "gn:country_code":"GE",
    "gn:dem":610,
    "gn:feature_class":"P",
    "gn:feature_code":"PPL",
    "gn:name":"Chikuneti",
    "gn:population":0,
    "gn:timezone":"Asia/Tbilisi",
    "iso:country":"GE",
    "name:kat_x_preferred":[
        "Chikuneti"
    ],
    "name:kat_x_variant":[
        "\u10e9\u10d8\u10e5\u10e3\u10dc\u10d4\u10d7\u10d8"
    ],
    "wof:name":"Chikuneti",
    "wof:placetype":"locality"
},
  "geometry": {"coordinates":[41.84861,41.51],"type":"Point"}
}