{
  "type": "Feature",
  "properties": {
    "gn:admin1_code":"70",
    "gn:asciiname":"Zeda-Shavra",
    "gn:country_code":"GE",
    "gn:dem":1059,
    "gn:feature_class":"P",
    "gn:feature_code":"PPL",
    "gn:name":"Zeda-Shavra",
    "gn:population":0,
    "gn:timezone":"Asia/Tbilisi",
    "iso:country":"GE",
    "name:kat_x_preferred":[
        "\u10d6\u10d4\u10d3\u10d0 \u10e8\u10d0\u10d5\u10e0\u10d0"
    ],
    "name:und_x_variant":[
        "Shavra",
        "Verkhnyaya Shavra",
        "Zeda-Shavra"
    ],
    "wof:name":"Zeda-Shavra",
    "wof:placetype":"locality"
},
  "geometry": {"coordinates":[42.98824000000001,42.49947],"type":"Point"}
}