{
  "type": "Feature",
  "properties": {
    "gn:admin1_code":"00",
    "gn:asciiname":"Tkispiri",
    "gn:country_code":"GE",
    "gn:dem":1365,
    "gn:feature_class":"P",
    "gn:feature_code":"PPL",
    "gn:name":"Tkispiri",
    "gn:population":0,
    "gn:timezone":"Asia/Tbilisi",
    "iso:country":"GE",
    "name:und_x_variant":[
        "Bogaskasani",
        "Tkispiri"
    ],
    "wof:name":"Tkispiri",
    "wof:placetype":"locality"
},
  "geometry": {"coordinates":[44.20897,41.25],"type":"Point"}
}