{
  "type": "Feature",
  "properties": {
    "gn:admin1_code":"02",
    "gn:asciiname":"K'ut'oli",
    "gn:country_code":"GE",
    "gn:dem":64,
    "gn:feature_class":"P",
    "gn:feature_code":"PPL",
    "gn:name":"K\u2019ut\u2019oli",
    "gn:population":0,
    "gn:timezone":"Asia/Tbilisi",
    "iso:country":"GE",
    "name:eng_x_preferred":[
        "Kutoli"
    ],
    "name:kat_x_preferred":[
        "K\u2019ut\u2019oli"
    ],
    "name:kat_x_variant":[
        "\u10d9\u10e3\u10e2\u10dd\u10da\u10d8"
    ],
    "name:rus_x_preferred":[
        "\u041a\u0443\u0442\u043e\u043b"
    ],
    "name:und_x_variant":[
        "Kutol"
    ],
    "wof:name":"K'ut'oli",
    "wof:placetype":"locality"
},
  "geometry": {"coordinates":[41.37806,42.84861],"type":"Point"}
}