{
  "type": "Feature",
  "properties": {
    "gn:admin1_code":"00",
    "gn:asciiname":"Didi-Nedzi",
    "gn:country_code":"GE",
    "gn:dem":14,
    "gn:feature_class":"P",
    "gn:feature_code":"PPL",
    "gn:name":"Didi-Nedzi",
    "gn:population":0,
    "gn:timezone":"Asia/Tbilisi",
    "iso:country":"GE",
    "wof:name":"Didi-Nedzi",
    "wof:placetype":"locality"
},
  "geometry": {"coordinates":[41.73667,42.40889],"type":"Point"}
}