{
  "type": "Feature",
  "properties": {
    "gn:admin1_code":"73",
    "gn:asciiname":"Aghaiani",
    "gn:country_code":"GE",
    "gn:dem":547,
    "gn:feature_class":"P",
    "gn:feature_code":"PPL",
    "gn:name":"Aghaiani",
    "gn:population":0,
    "gn:timezone":"Asia/Tbilisi",
    "iso:country":"GE",
    "name:che_x_preferred":[
        "\u0410\u0433\u0430\u044f\u043d\u0438"
    ],
    "name:eng_x_preferred":[
        "Aghaiani"
    ],
    "name:kat_x_preferred":[
        "\u10d0\u10e6\u10d0\u10d8\u10d0\u10dc\u10d8"
    ],
    "name:rus_x_preferred":[
        "\u0410\u0433\u0430\u0438\u0430\u043d\u0438"
    ],
    "name:und_x_variant":[
        "Agiani",
        "Agayani",
        "Agaiani"
    ],
    "wof:name":"Aghaiani",
    "wof:placetype":"locality"
},
  "geometry": {"coordinates":[44.54318,41.91438],"type":"Point"}
}