{
  "type": "Feature",
  "properties": {
    "gn:admin1_code":"73",
    "gn:asciiname":"Sanebeli",
    "gn:country_code":"GE",
    "gn:dem":698,
    "gn:feature_class":"P",
    "gn:feature_code":"PPL",
    "gn:name":"Sanebeli",
    "gn:population":0,
    "gn:timezone":"Asia/Tbilisi",
    "iso:country":"GE",
    "name:kat_x_preferred":[
        "Sanebeli"
    ],
    "wof:name":"Sanebeli",
    "wof:placetype":"locality"
},
  "geometry": {"coordinates":[43.83255,41.9924],"type":"Point"}
}