{
  "type": "Feature",
  "properties": {
    "gn:admin1_code":"71",
    "gn:asciiname":"Shamgona",
    "gn:country_code":"GE",
    "gn:dem":76,
    "gn:feature_class":"P",
    "gn:feature_code":"PPL",
    "gn:name":"Shamgona",
    "gn:population":0,
    "gn:timezone":"Asia/Tbilisi",
    "iso:country":"GE",
    "name:kat_x_preferred":[
        "Shamgona"
    ],
    "name:kat_x_variant":[
        "\u10e8\u10d0\u10db\u10d2\u10dd\u10dc\u10d0"
    ],
    "wof:name":"Shamgona",
    "wof:placetype":"locality"
},
  "geometry": {"coordinates":[41.79971,42.53649],"type":"Point"}
}