{
  "type": "Feature",
  "properties": {
    "gn:admin1_code":"70",
    "gn:asciiname":"Kachayeti",
    "gn:country_code":"GE",
    "gn:dem":1239,
    "gn:feature_class":"P",
    "gn:feature_code":"PPL",
    "gn:name":"Kachayeti",
    "gn:population":0,
    "gn:timezone":"Asia/Tbilisi",
    "iso:country":"GE",
    "name:und_x_variant":[
        "Kachaeti",
        "Kachayeti"
    ],
    "wof:name":"Kachayeti",
    "wof:placetype":"locality"
},
  "geometry": {"coordinates":[43.10923,42.47464],"type":"Point"}
}