{
  "type": "Feature",
  "properties": {
    "gn:admin1_code":"73",
    "gn:asciiname":"Mokhisi",
    "gn:country_code":"GE",
    "gn:dem":691,
    "gn:feature_class":"P",
    "gn:feature_code":"PPL",
    "gn:name":"Mokhisi",
    "gn:population":0,
    "gn:timezone":"Asia/Tbilisi",
    "iso:country":"GE",
    "name:kat_x_preferred":[
        "\u10db\u10dd\u10ee\u10d8\u10e1\u10d8"
    ],
    "wof:name":"Mokhisi",
    "wof:placetype":"locality"
},
  "geometry": {"coordinates":[43.76917,42.05249],"type":"Point"}
}