{
  "type": "Feature",
  "properties": {
    "gn:admin1_code":"71",
    "gn:asciiname":"P'irveli Ets'eri",
    "gn:country_code":"GE",
    "gn:dem":15,
    "gn:feature_class":"P",
    "gn:feature_code":"PPL",
    "gn:name":"P\u2019irveli Ets\u2019eri",
    "gn:population":0,
    "gn:timezone":"Asia/Tbilisi",
    "iso:country":"GE",
    "name:kat_x_preferred":[
        "P\u2019irveli Ets\u2019eri"
    ],
    "name:kat_x_variant":[
        "\u10de\u10d8\u10e0\u10d5\u10d4\u10da\u10d8 \u10d4\u10ec\u10d4\u10e0\u10d8"
    ],
    "name:und_x_variant":[
        "Etseri"
    ],
    "wof:name":"P'irveli Ets'eri",
    "wof:placetype":"locality"
},
  "geometry": {"coordinates":[42.15803,42.18092],"type":"Point"}
}