{
  "type": "Feature",
  "properties": {
    "gn:admin1_code":"72",
    "gn:asciiname":"Varevani",
    "gn:country_code":"GE",
    "gn:dem":1682,
    "gn:feature_class":"P",
    "gn:feature_code":"PPL",
    "gn:name":"Varevani",
    "gn:population":0,
    "gn:timezone":"Asia/Tbilisi",
    "iso:country":"GE",
    "name:kat_x_preferred":[
        "Varevani"
    ],
    "name:kat_x_variant":[
        "\u10d5\u10d0\u10e0\u10d4\u10d5\u10d0\u10dc\u10d8"
    ],
    "wof:name":"Varevani",
    "wof:placetype":"locality"
},
  "geometry": {"coordinates":[43.38989,41.51558],"type":"Point"}
}