{
  "type": "Feature",
  "properties": {
    "gn:admin1_code":"25",
    "gn:asciiname":"Bredza",
    "gn:country_code":"GE",
    "gn:dem":715,
    "gn:feature_class":"P",
    "gn:feature_code":"PPL",
    "gn:name":"Bredza",
    "gn:population":0,
    "gn:timezone":"Asia/Tbilisi",
    "iso:country":"GE",
    "wof:name":"Bredza",
    "wof:placetype":"locality"
},
  "geometry": {"coordinates":[43.74722,42.12673],"type":"Point"}
}