{
  "type": "Feature",
  "properties": {
    "gn:admin1_code":"00",
    "gn:asciiname":"Gagida",
    "gn:country_code":"GE",
    "gn:dem":-1,
    "gn:feature_class":"P",
    "gn:feature_code":"PPL",
    "gn:name":"Gagida",
    "gn:population":0,
    "gn:timezone":"Asia/Tbilisi",
    "iso:country":"GE",
    "wof:name":"Gagida",
    "wof:placetype":"locality"
},
  "geometry": {"coordinates":[41.5425,42.51278],"type":"Point"}
}