{
  "type": "Feature",
  "properties": {
    "gn:admin1_code":"69",
    "gn:asciiname":"Matura",
    "gn:country_code":"GE",
    "gn:dem":1499,
    "gn:feature_class":"P",
    "gn:feature_code":"PPL",
    "gn:name":"Matura",
    "gn:population":0,
    "gn:timezone":"Asia/Tbilisi",
    "iso:country":"GE",
    "name:kat_x_preferred":[
        "Matura"
    ],
    "name:kat_x_variant":[
        "\u10db\u10d0\u10d7\u10e3\u10e0\u10d0"
    ],
    "wof:name":"Matura",
    "wof:placetype":"locality"
},
  "geometry": {"coordinates":[45.07389000000001,42.44],"type":"Point"}
}