{
  "type": "Feature",
  "properties": {
    "gn:admin1_code":"69",
    "gn:asciiname":"Matura",
    "gn:country_code":"GE",
    "gn:dem":1499,
    "gn:feature_class":"P",
    "gn:feature_code":"PPL",
    "gn:name":"Matura",
    "gn:population":0,
    "gn:timezone":"Asia/Tbilisi",
    "iso:country":"GE",
    "name:bul_x_preferred":[
        "\u041c\u0430\u0442\u0443\u0440\u0430"
    ],
    "name:ces_x_preferred":[
        "Maturita"
    ],
    "name:deu_x_preferred":[
        "Matura"
    ],
    "name:fin_x_preferred":[
        "Matura"
    ],
    "name:fra_x_preferred":[
        "Maturit\u00e9"
    ],
    "name:hrv_x_preferred":[
        "Dr\u017eavna matura"
    ],
    "name:hun_x_preferred":[
        "\u00c9retts\u00e9gi vizsga"
    ],
    "name:ind_x_preferred":[
        "Matura"
    ],
    "name:kat_x_preferred":[
        "Matura"
    ],
    "name:kat_x_variant":[
        "\u10db\u10d0\u10d7\u10e3\u10e0\u10d0"
    ],
    "name:lit_x_preferred":[
        "Brandos atestatas"
    ],
    "name:nor_x_preferred":[
        "Matura"
    ],
    "name:pol_x_preferred":[
        "Matura"
    ],
    "name:slk_x_preferred":[
        "Maturitn\u00e1 sk\u00fa\u0161ka"
    ],
    "name:slv_x_preferred":[
        "Matura"
    ],
    "name:sqi_x_preferred":[
        "Matura"
    ],
    "name:tur_x_preferred":[
        "Matura"
    ],
    "wof:name":"Matura",
    "wof:placetype":"locality"
},
  "geometry": {"coordinates":[45.07389000000001,42.44],"type":"Point"}
}