{
  "type": "Feature",
  "properties": {
    "gn:admin1_code":"00",
    "gn:asciiname":"Kvemo-Rekha",
    "gn:country_code":"GE",
    "gn:dem":637,
    "gn:feature_class":"P",
    "gn:feature_code":"PPL",
    "gn:name":"Kvemo-Rekha",
    "gn:population":0,
    "gn:timezone":"Asia/Tbilisi",
    "iso:country":"GE",
    "name:und_x_variant":[
        "Nizhnyaya Reka",
        "Nizhnyaya Rekha",
        "Kvemo-Rekha"
    ],
    "wof:name":"Kvemo-Rekha",
    "wof:placetype":"locality"
},
  "geometry": {"coordinates":[44.11446,42.03631],"type":"Point"}
}