{
  "type": "Feature",
  "properties": {
    "gn:admin1_code":"66",
    "gn:asciiname":"Leghva",
    "gn:country_code":"GE",
    "gn:dem":352,
    "gn:feature_class":"P",
    "gn:feature_code":"PPL",
    "gn:name":"Leghva",
    "gn:population":0,
    "gn:timezone":"Asia/Tbilisi",
    "iso:country":"GE",
    "name:kat_x_preferred":[
        "Leghva"
    ],
    "name:kat_x_variant":[
        "\u10da\u10d4\u10e6\u10d5\u10d0"
    ],
    "name:und_x_variant":[
        "Legva"
    ],
    "wof:name":"Leghva",
    "wof:placetype":"locality"
},
  "geometry": {"coordinates":[42.89282,42.34132],"type":"Point"}
}