{
  "type": "Feature",
  "properties": {
    "gn:admin1_code":"70",
    "gn:asciiname":"Bugeuli",
    "gn:country_code":"GE",
    "gn:dem":706,
    "gn:feature_class":"P",
    "gn:feature_code":"PPL",
    "gn:name":"Bugeuli",
    "gn:population":0,
    "gn:timezone":"Asia/Tbilisi",
    "iso:country":"GE",
    "wof:name":"Bugeuli",
    "wof:placetype":"locality"
},
  "geometry": {"coordinates":[43.0695,42.53039],"type":"Point"}
}