{
  "type": "Feature",
  "properties": {
    "gn:admin1_code":"00",
    "gn:asciiname":"Gumatiges",
    "gn:country_code":"GE",
    "gn:dem":354,
    "gn:feature_class":"P",
    "gn:feature_code":"PPL",
    "gn:name":"Gumatiges",
    "gn:population":0,
    "gn:timezone":"Asia/Tbilisi",
    "iso:country":"GE",
    "name:und_x_variant":[
        "Gumati",
        "Gumatiges"
    ],
    "wof:name":"Gumatiges",
    "wof:placetype":"locality"
},
  "geometry": {"coordinates":[42.67559,42.33859],"type":"Point"}
}