{
  "type": "Feature",
  "properties": {
    "gn:admin1_code":"73",
    "gn:asciiname":"Ipnara",
    "gn:country_code":"GE",
    "gn:dem":1288,
    "gn:feature_class":"P",
    "gn:feature_code":"PPL",
    "gn:name":"Ipnara",
    "gn:population":0,
    "gn:timezone":"Asia/Tbilisi",
    "iso:country":"GE",
    "name:kat_x_preferred":[
        "Ipnara"
    ],
    "name:kat_x_variant":[
        "\u10d8\u10e4\u10dc\u10d0\u10e0\u10d0"
    ],
    "wof:name":"Ipnara",
    "wof:placetype":"locality"
},
  "geometry": {"coordinates":[43.97263,41.85181],"type":"Point"}
}