{
  "type": "Feature",
  "properties": {
    "gn:admin1_code":"04",
    "gn:asciiname":"Gori Q'uli",
    "gn:country_code":"GE",
    "gn:dem":1451,
    "gn:feature_class":"P",
    "gn:feature_code":"PPL",
    "gn:name":"Gori Q\u2019uli",
    "gn:population":0,
    "gn:timezone":"Asia/Tbilisi",
    "iso:country":"GE",
    "name:kat_x_preferred":[
        "Gori Q\u2019uli"
    ],
    "name:kat_x_variant":[
        "\u10d2\u10dd\u10e0\u10d8 \u10e7\u10e3\u10da\u10d8"
    ],
    "wof:name":"Gori Q'uli",
    "wof:placetype":"locality"
},
  "geometry": {"coordinates":[42.28145,41.76575],"type":"Point"}
}