{
  "type": "Feature",
  "properties": {
    "gn:admin1_code":"00",
    "gn:asciiname":"Zemo-Okona",
    "gn:country_code":"GE",
    "gn:dem":847,
    "gn:feature_class":"P",
    "gn:feature_code":"PPL",
    "gn:name":"Zemo-Okona",
    "gn:population":0,
    "gn:timezone":"Asia/Tbilisi",
    "iso:country":"GE",
    "name:und_x_variant":[
        "Okona Verkhnyaya",
        "Zemo-Okona"
    ],
    "wof:name":"Zemo-Okona",
    "wof:placetype":"locality"
},
  "geometry": {"coordinates":[43.78855,42.16848],"type":"Point"}
}