{
  "type": "Feature",
  "properties": {
    "gn:admin1_code":"00",
    "gn:asciiname":"Didtsipela",
    "gn:country_code":"GE",
    "gn:dem":506,
    "gn:feature_class":"P",
    "gn:feature_code":"PPL",
    "gn:name":"Didtsipela",
    "gn:population":0,
    "gn:timezone":"Asia/Tbilisi",
    "iso:country":"GE",
    "wof:name":"Didtsipela",
    "wof:placetype":"locality"
},
  "geometry": {"coordinates":[43.14111,42.21583],"type":"Point"}
}