{
  "type": "Feature",
  "properties": {
    "gn:admin1_code":"02",
    "gn:asciiname":"Ts'vindirta",
    "gn:country_code":"GE",
    "gn:dem":184,
    "gn:feature_class":"P",
    "gn:feature_code":"PPL",
    "gn:name":"Ts\u2019vindirta",
    "gn:population":0,
    "gn:timezone":"Asia/Tbilisi",
    "iso:country":"GE",
    "name:kat_x_preferred":[
        "Ts\u2019vindirta"
    ],
    "name:kat_x_variant":[
        "\u10ec\u10d5\u10d8\u10dc\u10d3\u10d8\u10e0\u10d7\u10d0"
    ],
    "name:und_x_variant":[
        "Tsvyndyrta"
    ],
    "wof:name":"Ts'vindirta",
    "wof:placetype":"locality"
},
  "geometry": {"coordinates":[40.72332,43.16843],"type":"Point"}
}