{
  "type": "Feature",
  "properties": {
    "gn:admin1_code":"70",
    "gn:asciiname":"Kheledi",
    "gn:country_code":"GE",
    "gn:dem":985,
    "gn:feature_class":"P",
    "gn:feature_code":"PPL",
    "gn:name":"Kheledi",
    "gn:population":0,
    "gn:timezone":"Asia/Tbilisi",
    "iso:country":"GE",
    "name:eng_x_preferred":[
        "Kheledi"
    ],
    "name:kat_x_preferred":[
        "\u10ee\u10d4\u10da\u10d4\u10d3\u10d8"
    ],
    "name:rus_x_preferred":[
        "\u0425\u0435\u043b\u0435\u0434\u0438"
    ],
    "name:und_x_variant":[
        "Kheleda",
        "Kheledi"
    ],
    "wof:name":"Kheledi",
    "wof:placetype":"locality"
},
  "geometry": {"coordinates":[42.64383,42.79034],"type":"Point"}
}