{
  "type": "Feature",
  "properties": {
    "gn:admin1_code":"00",
    "gn:asciiname":"Rokit'i",
    "gn:country_code":"GE",
    "gn:dem":1307,
    "gn:feature_class":"P",
    "gn:feature_code":"PPL",
    "gn:name":"Rokit\u2019i",
    "gn:population":0,
    "gn:timezone":"Asia/Tbilisi",
    "iso:country":"GE",
    "name:und_x_variant":[
        "Roketi",
        "Rokit\u2019i"
    ],
    "wof:name":"Rokit'i",
    "wof:placetype":"locality"
},
  "geometry": {"coordinates":[43.23333,41.48333],"type":"Point"}
}