{
  "type": "Feature",
  "properties": {
    "gn:admin1_code":"00",
    "gn:asciiname":"Uruna",
    "gn:country_code":"GE",
    "gn:dem":839,
    "gn:feature_class":"P",
    "gn:feature_code":"PPL",
    "gn:name":"Uruna",
    "gn:population":0,
    "gn:timezone":"Asia/Tbilisi",
    "iso:country":"GE",
    "wof:name":"Uruna",
    "wof:placetype":"locality"
},
  "geometry": {"coordinates":[43.56375,42.25278],"type":"Point"}
}