{
  "type": "Feature",
  "properties": {
    "gn:admin1_code":"66",
    "gn:asciiname":"Gormaghali",
    "gn:country_code":"GE",
    "gn:dem":157,
    "gn:feature_class":"P",
    "gn:feature_code":"PPL",
    "gn:name":"Gormaghali",
    "gn:population":0,
    "gn:timezone":"Asia/Tbilisi",
    "iso:country":"GE",
    "name:und_x_variant":[
        "Gormagali",
        "Gormaghali"
    ],
    "wof:name":"Gormaghali",
    "wof:placetype":"locality"
},
  "geometry": {"coordinates":[42.31908,42.05116],"type":"Point"}
}