{
  "type": "Feature",
  "properties": {
    "gn:admin1_code":"00",
    "gn:asciiname":"Kobeti",
    "gn:country_code":"GE",
    "gn:dem":1666,
    "gn:feature_class":"P",
    "gn:feature_code":"PPL",
    "gn:name":"Kobeti",
    "gn:population":0,
    "gn:timezone":"Asia/Tbilisi",
    "iso:country":"GE",
    "name:und_x_variant":[
        "Kobeota",
        "Kobeti"
    ],
    "wof:name":"Kobeti",
    "wof:placetype":"locality"
},
  "geometry": {"coordinates":[43.76875,42.52501],"type":"Point"}
}