{
  "type": "Feature",
  "properties": {
    "gn:admin1_code":"02",
    "gn:asciiname":"Souakvara",
    "gn:country_code":"GE",
    "gn:dem":325,
    "gn:feature_class":"P",
    "gn:feature_code":"PPL",
    "gn:name":"Souakvara",
    "gn:population":0,
    "gn:timezone":"Asia/Tbilisi",
    "iso:country":"GE",
    "wof:name":"Souakvara",
    "wof:placetype":"locality"
},
  "geometry": {"coordinates":[41.75278,42.85472],"type":"Point"}
}