{
  "type": "Feature",
  "properties": {
    "gn:admin1_code":"02",
    "gn:asciiname":"Meore Shesheleti",
    "gn:country_code":"GE",
    "gn:dem":20,
    "gn:feature_class":"P",
    "gn:feature_code":"PPL",
    "gn:name":"Meore Shesheleti",
    "gn:population":0,
    "gn:timezone":"Asia/Tbilisi",
    "iso:country":"GE",
    "name:kat_x_preferred":[
        "Meore Shesheleti"
    ],
    "name:kat_x_variant":[
        "\u10db\u10d4\u10dd\u10e0\u10d4 \u10e8\u10d4\u10e8\u10d4\u10da\u10d4\u10d7\u10d8"
    ],
    "name:und_x_variant":[
        "Sheshleti",
        "Shesheleti"
    ],
    "wof:name":"Meore Shesheleti",
    "wof:placetype":"locality"
},
  "geometry": {"coordinates":[41.64327,42.64305],"type":"Point"}
}