{
  "type": "Feature",
  "properties": {
    "gn:admin1_code":"00",
    "gn:asciiname":"Chetar",
    "gn:country_code":"GE",
    "gn:dem":1171,
    "gn:feature_class":"P",
    "gn:feature_code":"PPL",
    "gn:name":"Chetar",
    "gn:population":0,
    "gn:timezone":"Asia/Tbilisi",
    "iso:country":"GE",
    "name:und_x_variant":[
        "Chetor",
        "Chetar"
    ],
    "wof:name":"Chetar",
    "wof:placetype":"locality"
},
  "geometry": {"coordinates":[43.97543,42.42472],"type":"Point"}
}