{
  "type": "Feature",
  "properties": {
    "gn:admin1_code":"70",
    "gn:asciiname":"Ukuleshi",
    "gn:country_code":"GE",
    "gn:dem":1202,
    "gn:feature_class":"P",
    "gn:feature_code":"PPL",
    "gn:name":"Ukuleshi",
    "gn:population":0,
    "gn:timezone":"Asia/Tbilisi",
    "iso:country":"GE",
    "wof:name":"Ukuleshi",
    "wof:placetype":"locality"
},
  "geometry": {"coordinates":[42.87139000000001,42.85028],"type":"Point"}
}