{
  "type": "Feature",
  "properties": {
    "gn:admin1_code":"66",
    "gn:asciiname":"Zeda Gordi",
    "gn:country_code":"GE",
    "gn:dem":671,
    "gn:feature_class":"P",
    "gn:feature_code":"PPL",
    "gn:name":"Zeda Gordi",
    "gn:population":0,
    "gn:timezone":"Asia/Tbilisi",
    "iso:country":"GE",
    "name:kat_x_preferred":[
        "Zeda Gordi"
    ],
    "name:kat_x_variant":[
        "\u10d6\u10d4\u10d3\u10d0 \u10d2\u10dd\u10e0\u10d3\u10d8"
    ],
    "name:und_x_variant":[
        "Verkhniye Gordi"
    ],
    "wof:name":"Zeda Gordi",
    "wof:placetype":"locality"
},
  "geometry": {"coordinates":[42.52702,42.45914000000001],"type":"Point"}
}