{
  "type": "Feature",
  "properties": {
    "gn:admin1_code":"71",
    "gn:asciiname":"Khelra",
    "gn:country_code":"GE",
    "gn:dem":1200,
    "gn:feature_class":"P",
    "gn:feature_code":"PPL",
    "gn:name":"Khelra",
    "gn:population":0,
    "gn:timezone":"Asia/Tbilisi",
    "iso:country":"GE",
    "name:kat_x_preferred":[
        "Khelra"
    ],
    "name:kat_x_variant":[
        "\u10d6\u10d4\u10da\u10e0\u10d0"
    ],
    "wof:name":"Khelra",
    "wof:placetype":"locality"
},
  "geometry": {"coordinates":[42.31772,42.98811],"type":"Point"}
}