{
  "type": "Feature",
  "properties": {
    "gn:admin1_code":"70",
    "gn:asciiname":"Somitso",
    "gn:country_code":"GE",
    "gn:dem":1013,
    "gn:feature_class":"P",
    "gn:feature_code":"PPL",
    "gn:name":"Somitso",
    "gn:population":0,
    "gn:timezone":"Asia/Tbilisi",
    "iso:country":"GE",
    "name:und_x_variant":[
        "Samitso",
        "Somitso"
    ],
    "wof:name":"Somitso",
    "wof:placetype":"locality"
},
  "geometry": {"coordinates":[43.4425,42.56643],"type":"Point"}
}