{
  "type": "Feature",
  "properties": {
    "gn:country":"GE",
    "gn:fcode":"PPL",
    "gn:population":450,
    "iso:country":"GE",
    "qs:name":"Tkhubun",
    "qs:photos_9r":0,
    "qs:photos_sr":0,
    "qs:pop_sr":"2",
    "wof:name":"Tkhubun",
    "wof:placetype":"locality",
    "wof:population":450
},
  "geometry": {"coordinates":[41.0737,42.96462],"type":"Point"}
}