{
  "type": "Feature",
  "properties": {
    "gn:admin1_code":"72",
    "gn:asciiname":"Tqemlana",
    "gn:country_code":"GE",
    "gn:dem":1037,
    "gn:feature_class":"P",
    "gn:feature_code":"PPL",
    "gn:name":"Tqemlana",
    "gn:population":0,
    "gn:timezone":"Asia/Tbilisi",
    "iso:country":"GE",
    "name:kat_x_preferred":[
        "\u10e2\u10e7\u10d4\u10db\u10da\u10d0\u10dc\u10d0"
    ],
    "name:und_x_variant":[
        "Tkemlana",
        "Tqemlana"
    ],
    "wof:name":"Tqemlana",
    "wof:placetype":"locality"
},
  "geometry": {"coordinates":[43.16807,41.70272],"type":"Point"}
}