{
  "type": "Feature",
  "properties": {
    "gn:admin1_code":"69",
    "gn:asciiname":"Magharoskari",
    "gn:country_code":"GE",
    "gn:dem":927,
    "gn:feature_class":"P",
    "gn:feature_code":"PPL",
    "gn:name":"Magharoskari",
    "gn:population":0,
    "gn:timezone":"Asia/Tbilisi",
    "iso:country":"GE",
    "name:eng_x_preferred":[
        "Magharoskari"
    ],
    "name:rus_x_preferred":[
        "\u041c\u0430\u0433\u0430\u0440\u043e\u0441\u043a\u0430\u0440\u0438"
    ],
    "name:und_x_variant":[
        "Magaroskari",
        "Magharoskari"
    ],
    "wof:name":"Magharoskari",
    "wof:placetype":"locality"
},
  "geometry": {"coordinates":[44.86709000000001,42.28778],"type":"Point"}
}