{
  "type": "Feature",
  "properties": {
    "gn:admin1_code":"04",
    "gn:asciiname":"Ach'arisaghmarti",
    "gn:country_code":"GE",
    "gn:dem":226,
    "gn:feature_class":"P",
    "gn:feature_code":"PPL",
    "gn:name":"Ach\u2019arisaghmarti",
    "gn:population":0,
    "gn:timezone":"Asia/Tbilisi",
    "iso:country":"GE",
    "name:kat_x_preferred":[
        "Ach\u2019arisaghmarti"
    ],
    "name:kat_x_variant":[
        "\u10d0\u10ed\u10d0\u10e0\u10d8\u10e1\u10d0\u10e6\u10db\u10d0\u10e0\u10d7\u10d8"
    ],
    "name:und_x_variant":[
        "Atcharis-Aghmarti",
        "Adzharisagmarti",
        "Acharis-Agmarti"
    ],
    "wof:name":"Ach'arisaghmarti",
    "wof:placetype":"locality"
},
  "geometry": {"coordinates":[41.79611,41.51889],"type":"Point"}
}