{
  "type": "Feature",
  "properties": {
    "gn:admin1_code":"71",
    "gn:asciiname":"P'irveli Nosiri",
    "gn:country_code":"GE",
    "gn:dem":40,
    "gn:feature_class":"P",
    "gn:feature_code":"PPL",
    "gn:name":"P\u2019irveli Nosiri",
    "gn:population":0,
    "gn:timezone":"Asia/Tbilisi",
    "iso:country":"GE",
    "name:kat_x_preferred":[
        "\u10de\u10d8\u10e0\u10d5\u10d4\u10da\u10d8 \u10dc\u10dd\u10e1\u10d8\u10e0\u10d8"
    ],
    "name:und_x_variant":[
        "Nosiri Pervyye",
        "P\u2019irveli Nosiri"
    ],
    "wof:name":"P'irveli Nosiri",
    "wof:placetype":"locality"
},
  "geometry": {"coordinates":[42.15091,42.28084000000001],"type":"Point"}
}