{
  "type": "Feature",
  "properties": {
    "gn:admin1_code":"68",
    "gn:asciiname":"Sart'ichala",
    "gn:country_code":"GE",
    "gn:dem":707,
    "gn:feature_class":"P",
    "gn:feature_code":"PPL",
    "gn:name":"Sart\u2019ichala",
    "gn:population":0,
    "gn:timezone":"Asia/Tbilisi",
    "iso:country":"GE",
    "name:deu_x_historical":[
        "Marienfeld"
    ],
    "name:deu_x_preferred":[
        "Marienfeld"
    ],
    "name:eng_x_preferred":[
        "Sart'ichala"
    ],
    "name:rus_x_preferred":[
        "\u0421\u0430\u0440\u0442\u0438\u0447\u0430\u043b\u0430"
    ],
    "name:und_x_variant":[
        "Sartitsalo",
        "Sartashali",
        "Sart\u2019ichala"
    ],
    "wof:name":"Sart'ichala",
    "wof:placetype":"locality"
},
  "geometry": {"coordinates":[45.17567,41.7179],"type":"Point"}
}