{
  "type": "Feature",
  "properties": {
    "gn:admin1_code":"72",
    "gn:asciiname":"Tadzrisi",
    "gn:country_code":"GE",
    "gn:dem":1299,
    "gn:feature_class":"P",
    "gn:feature_code":"PPL",
    "gn:name":"Tadzrisi",
    "gn:population":0,
    "gn:timezone":"Asia/Tbilisi",
    "iso:country":"GE",
    "name:kat_x_preferred":[
        "\u10e2\u10d0\u10eb\u10e0\u10d8\u10e1\u10d8"
    ],
    "wof:name":"Tadzrisi",
    "wof:placetype":"locality"
},
  "geometry": {"coordinates":[43.27686,41.73444],"type":"Point"}
}