{
  "type": "Feature",
  "properties": {
    "gn:admin1_code":"00",
    "gn:asciiname":"Dzhakismani",
    "gn:country_code":"GE",
    "gn:dem":1487,
    "gn:feature_class":"P",
    "gn:feature_code":"PPL",
    "gn:name":"Dzhakismani",
    "gn:population":0,
    "gn:timezone":"Asia/Tbilisi",
    "iso:country":"GE",
    "wof:name":"Dzhakismani",
    "wof:placetype":"locality"
},
  "geometry": {"coordinates":[42.82375,41.51871],"type":"Point"}
}