{
  "type": "Feature",
  "properties": {
    "gn:admin1_code":"00",
    "gn:asciiname":"Mariamdzhvari",
    "gn:country_code":"GE",
    "gn:dem":907,
    "gn:feature_class":"P",
    "gn:feature_code":"PPL",
    "gn:name":"Mariamdzhvari",
    "gn:population":0,
    "gn:timezone":"Asia/Tbilisi",
    "iso:country":"GE",
    "name:und_x_variant":[
        "Mariamdzhvar",
        "Mariamdzhvari"
    ],
    "wof:name":"Mariamdzhvari",
    "wof:placetype":"locality"
},
  "geometry": {"coordinates":[45.39292,41.74597],"type":"Point"}
}