{
  "type": "Feature",
  "properties": {
    "gn:admin1_code":"00",
    "gn:asciiname":"Dgvaba",
    "gn:country_code":"GE",
    "gn:dem":9,
    "gn:feature_class":"P",
    "gn:feature_code":"PPL",
    "gn:name":"Dgvaba",
    "gn:population":0,
    "gn:timezone":"Asia/Tbilisi",
    "iso:country":"GE",
    "wof:name":"Dgvaba",
    "wof:placetype":"locality"
},
  "geometry": {"coordinates":[41.75306,42.36222],"type":"Point"}
}