{
  "type": "Feature",
  "properties": {
    "gn:admin1_code":"66",
    "gn:asciiname":"Kveletubani",
    "gn:country_code":"GE",
    "gn:dem":420,
    "gn:feature_class":"P",
    "gn:feature_code":"PPL",
    "gn:name":"Kveletubani",
    "gn:population":0,
    "gn:timezone":"Asia/Tbilisi",
    "iso:country":"GE",
    "name:kat_x_preferred":[
        "\u10e5\u10d5\u10d4\u10da\u10d4\u10d7\u10e3\u10d1\u10d0\u10dc\u10d8"
    ],
    "wof:name":"Kveletubani",
    "wof:placetype":"locality"
},
  "geometry": {"coordinates":[43.10502,42.17692],"type":"Point"}
}