{
  "type": "Feature",
  "properties": {
    "gn:admin1_code":"04",
    "gn:asciiname":"Maniak'eti",
    "gn:country_code":"GE",
    "gn:dem":1236,
    "gn:feature_class":"P",
    "gn:feature_code":"PPL",
    "gn:name":"Maniak\u2019eti",
    "gn:population":0,
    "gn:timezone":"Asia/Tbilisi",
    "iso:country":"GE",
    "name:kat_x_preferred":[
        "Maniak\u2019eti"
    ],
    "name:kat_x_variant":[
        "\u10db\u10d0\u10dc\u10d8\u10d0\u10d9\u10d4\u10d7\u10d8"
    ],
    "wof:name":"Maniak'eti",
    "wof:placetype":"locality"
},
  "geometry": {"coordinates":[42.38119,41.62566],"type":"Point"}
}