{
  "type": "Feature",
  "properties": {
    "gn:admin1_code":"00",
    "gn:asciiname":"Kazakh",
    "gn:country_code":"GE",
    "gn:dem":1297,
    "gn:feature_class":"P",
    "gn:feature_code":"PPL",
    "gn:name":"Kazakh",
    "gn:population":0,
    "gn:timezone":"Asia/Tbilisi",
    "iso:country":"GE",
    "name:deu_x_preferred":[
        "Kazakh"
    ],
    "name:ita_x_preferred":[
        "Kazako"
    ],
    "name:kaz_x_preferred":[
        "\u049a\u0430\u0437\u0430\u049b"
    ],
    "name:kor_x_preferred":[
        "\uce74\uc790\ud750"
    ],
    "name:mon_x_preferred":[
        "\u041a\u0430\u0437\u0430\u0445"
    ],
    "name:por_x_preferred":[
        "Cazaque"
    ],
    "name:swe_x_preferred":[
        "Kazakisk"
    ],
    "name:vie_x_preferred":[
        "Kazakh"
    ],
    "name:zho_x_preferred":[
        "\u54c8\u8428\u514b"
    ],
    "wof:name":"Kazakh",
    "wof:placetype":"locality"
},
  "geometry": {"coordinates":[42.25304000000001,43.00677],"type":"Point"}
}