{
  "type": "Feature",
  "properties": {
    "gn:admin1_code":"00",
    "gn:asciiname":"Shibliani",
    "gn:country_code":"GE",
    "gn:dem":702,
    "gn:feature_class":"P",
    "gn:feature_code":"PPL",
    "gn:name":"Shibliani",
    "gn:population":0,
    "gn:timezone":"Asia/Tbilisi",
    "iso:country":"GE",
    "wof:name":"Shibliani",
    "wof:placetype":"locality"
},
  "geometry": {"coordinates":[45.62008,41.66881],"type":"Point"}
}