{
  "type": "Feature",
  "properties": {
    "gn:admin1_code":"70",
    "gn:asciiname":"Zemo-Skhvava",
    "gn:country_code":"GE",
    "gn:dem":1159,
    "gn:feature_class":"P",
    "gn:feature_code":"PPL",
    "gn:name":"Zemo-Skhvava",
    "gn:population":0,
    "gn:timezone":"Asia/Tbilisi",
    "iso:country":"GE",
    "name:eng_x_preferred":[
        "Zemo-Skhvava"
    ],
    "name:rus_x_preferred":[
        "\u0428\u0443\u0430-\u0421\u0445\u0432\u0430\u0432\u0430"
    ],
    "name:und_x_variant":[
        "Zeda Skhvava"
    ],
    "wof:name":"Zemo-Skhvava",
    "wof:placetype":"locality"
},
  "geometry": {"coordinates":[43.24658,42.50887],"type":"Point"}
}