{
  "type": "Feature",
  "properties": {
    "gn:admin1_code":"70",
    "gn:asciiname":"Utskheri",
    "gn:country_code":"GE",
    "gn:dem":741,
    "gn:feature_class":"P",
    "gn:feature_code":"PPL",
    "gn:name":"Utskheri",
    "gn:population":0,
    "gn:timezone":"Asia/Tbilisi",
    "iso:country":"GE",
    "name:kat_x_preferred":[
        "\u10e3\u10ea\u10ee\u10d4\u10e0\u10d8"
    ],
    "wof:name":"Utskheri",
    "wof:placetype":"locality"
},
  "geometry": {"coordinates":[42.80107,42.59069],"type":"Point"}
}