{
  "type": "Feature",
  "properties": {
    "gn:admin1_code":"71",
    "gn:asciiname":"Okhvamek'ari",
    "gn:country_code":"GE",
    "gn:dem":29,
    "gn:feature_class":"P",
    "gn:feature_code":"PPL",
    "gn:name":"Okhvamek\u2019ari",
    "gn:population":0,
    "gn:timezone":"Asia/Tbilisi",
    "iso:country":"GE",
    "name:kat_x_preferred":[
        "\u10dd\u10ee\u10d5\u10d0\u10db\u10d4\u10d9\u10d0\u10e0\u10d8"
    ],
    "name:rus_x_preferred":[
        "Okhvamek\u2019ari"
    ],
    "name:und_x_variant":[
        "Okhvame"
    ],
    "wof:name":"Okhvamek'ari",
    "wof:placetype":"locality"
},
  "geometry": {"coordinates":[41.83315,42.36643],"type":"Point"}
}