{
  "type": "Feature",
  "properties": {
    "gn:admin1_code":"00",
    "gn:asciiname":"Kharavi",
    "gn:country_code":"GE",
    "gn:dem":820,
    "gn:feature_class":"P",
    "gn:feature_code":"PPL",
    "gn:name":"Kharavi",
    "gn:population":0,
    "gn:timezone":"Asia/Tbilisi",
    "iso:country":"GE",
    "wof:name":"Kharavi",
    "wof:placetype":"locality"
},
  "geometry": {"coordinates":[43.77056,42.21611],"type":"Point"}
}