{
  "type": "Feature",
  "properties": {
    "gn:admin1_code":"72",
    "gn:asciiname":"Machatia",
    "gn:country_code":"GE",
    "gn:dem":1716,
    "gn:feature_class":"P",
    "gn:feature_code":"PPL",
    "gn:name":"Machatia",
    "gn:population":0,
    "gn:timezone":"Asia/Tbilisi",
    "iso:country":"GE",
    "name:eng_x_preferred":[
        "Machatia"
    ],
    "name:kat_x_preferred":[
        "\u10db\u10d7\u10ed\u10d0\u10e2\u10d8\u10d0"
    ],
    "name:rus_x_preferred":[
        "\u041c\u0430\u0447\u0430\u0442\u0438\u0430"
    ],
    "name:und_x_variant":[
        "Matchatia",
        "Madzhidia"
    ],
    "wof:name":"Machatia",
    "wof:placetype":"locality"
},
  "geometry": {"coordinates":[43.51583,41.44777],"type":"Point"}
}