{
  "type": "Feature",
  "properties": {
    "gn:admin1_code":"70",
    "gn:asciiname":"Samtisi",
    "gn:country_code":"GE",
    "gn:dem":1047,
    "gn:feature_class":"P",
    "gn:feature_code":"PPL",
    "gn:name":"Samtisi",
    "gn:population":0,
    "gn:timezone":"Asia/Tbilisi",
    "iso:country":"GE",
    "name:kat_x_preferred":[
        "\u10e1\u10d0\u10db\u10d7\u10d8\u10e1\u10d8"
    ],
    "wof:name":"Samtisi",
    "wof:placetype":"locality"
},
  "geometry": {"coordinates":[43.25669,42.53209],"type":"Point"}
}