{
  "type": "Feature",
  "properties": {
    "gn:admin1_code":"66",
    "gn:asciiname":"Merevi",
    "gn:country_code":"GE",
    "gn:dem":636,
    "gn:feature_class":"P",
    "gn:feature_code":"PPL",
    "gn:name":"Merevi",
    "gn:population":0,
    "gn:timezone":"Asia/Tbilisi",
    "iso:country":"GE",
    "name:kat_x_preferred":[
        "\u10db\u10d4\u10e0\u10d4\u10d5\u10d8"
    ],
    "wof:name":"Merevi",
    "wof:placetype":"locality"
},
  "geometry": {"coordinates":[43.32152,42.25486],"type":"Point"}
}