{
  "type": "Feature",
  "properties": {
    "gn:admin1_code":"00",
    "gn:asciiname":"Dghvaba",
    "gn:country_code":"GE",
    "gn:dem":4,
    "gn:feature_class":"P",
    "gn:feature_code":"PPL",
    "gn:name":"Dghvaba",
    "gn:population":0,
    "gn:timezone":"Asia/Tbilisi",
    "iso:country":"GE",
    "name:kat_x_preferred":[
        "Dghvaba"
    ],
    "name:kat_x_variant":[
        "\u10d3\u10e6\u10d5\u10d0\u10d1\u10d0"
    ],
    "name:und_x_variant":[
        "Dgvaba"
    ],
    "wof:name":"Dghvaba",
    "wof:placetype":"locality"
},
  "geometry": {"coordinates":[41.73502,42.34257],"type":"Point"}
}