{
  "type": "Feature",
  "properties": {
    "gn:admin1_code":"69",
    "gn:asciiname":"Makhiaret'i",
    "gn:country_code":"GE",
    "gn:dem":1581,
    "gn:feature_class":"P",
    "gn:feature_code":"PPL",
    "gn:name":"Makhiaret\u2019i",
    "gn:population":0,
    "gn:timezone":"Asia/Tbilisi",
    "iso:country":"GE",
    "name:kat_x_preferred":[
        "Makhiaret\u2019i"
    ],
    "wof:name":"Makhiaret'i",
    "wof:placetype":"locality"
},
  "geometry": {"coordinates":[44.5427,42.31739],"type":"Point"}
}