{
  "type": "Feature",
  "properties": {
    "gn:admin1_code":"71",
    "gn:asciiname":"Zeda Sort'a",
    "gn:country_code":"GE",
    "gn:dem":201,
    "gn:feature_class":"P",
    "gn:feature_code":"PPL",
    "gn:name":"Zeda Sort\u2019a",
    "gn:population":0,
    "gn:timezone":"Asia/Tbilisi",
    "iso:country":"GE",
    "name:kat_x_preferred":[
        "Zeda Sort\u2019a"
    ],
    "name:kat_x_variant":[
        "\u10d6\u10d4\u10d3\u10d0 \u10e1\u10dd\u10e0\u10e2\u10d0"
    ],
    "name:und_x_variant":[
        "Sorta"
    ],
    "wof:name":"Zeda Sort'a",
    "wof:placetype":"locality"
},
  "geometry": {"coordinates":[42.12119000000001,42.30252],"type":"Point"}
}