{
  "type": "Feature",
  "properties": {
    "gn:admin1_code":"00",
    "gn:asciiname":"Telepa",
    "gn:country_code":"GE",
    "gn:dem":275,
    "gn:feature_class":"P",
    "gn:feature_code":"PPL",
    "gn:name":"Telepa",
    "gn:population":0,
    "gn:timezone":"Asia/Tbilisi",
    "iso:country":"GE",
    "wof:name":"Telepa",
    "wof:placetype":"locality"
},
  "geometry": {"coordinates":[43.01264000000001,42.19917],"type":"Point"}
}