{
  "type": "Feature",
  "properties": {
    "gn:admin1_code":"08",
    "gn:asciiname":"Diklo",
    "gn:country_code":"GE",
    "gn:dem":2152,
    "gn:feature_class":"P",
    "gn:feature_code":"PPL",
    "gn:name":"Diklo",
    "gn:population":0,
    "gn:timezone":"Asia/Tbilisi",
    "iso:country":"GE",
    "wof:name":"Diklo",
    "wof:placetype":"locality"
},
  "geometry": {"coordinates":[45.69013,42.39685],"type":"Point"}
}