{
  "type": "Feature",
  "properties": {
    "gn:admin1_code":"02",
    "gn:asciiname":"Rek'a",
    "gn:country_code":"GE",
    "gn:dem":148,
    "gn:feature_class":"P",
    "gn:feature_code":"PPL",
    "gn:name":"Rek\u2019a",
    "gn:population":0,
    "gn:timezone":"Asia/Tbilisi",
    "iso:country":"GE",
    "name:kat_x_preferred":[
        "Rek\u2019a"
    ],
    "name:kat_x_variant":[
        "\u10e0\u10d4\u10d9\u10d0"
    ],
    "wof:name":"Rek'a",
    "wof:placetype":"locality"
},
  "geometry": {"coordinates":[41.62662,42.77742],"type":"Point"}
}