{
  "type": "Feature",
  "properties": {
    "gn:admin1_code":"02",
    "gn:asciiname":"At'ishadu",
    "gn:country_code":"GE",
    "gn:dem":189,
    "gn:feature_class":"P",
    "gn:feature_code":"PPL",
    "gn:name":"At\u2019ishadu",
    "gn:population":0,
    "gn:timezone":"Asia/Tbilisi",
    "iso:country":"GE",
    "name:kat_x_preferred":[
        "At\u2019ishadu"
    ],
    "name:kat_x_variant":[
        "\u10d0\u10e2\u10d8\u10e8\u10d0\u10d3\u10e3"
    ],
    "name:und_x_variant":[
        "Atyshadu"
    ],
    "wof:name":"At'ishadu",
    "wof:placetype":"locality"
},
  "geometry": {"coordinates":[41.63399,42.85306],"type":"Point"}
}