{
  "type": "Feature",
  "properties": {
    "gn:admin1_code":"70",
    "gn:asciiname":"Patara-Oni",
    "gn:country_code":"GE",
    "gn:dem":880,
    "gn:feature_class":"P",
    "gn:feature_code":"PPL",
    "gn:name":"Patara-Oni",
    "gn:population":0,
    "gn:timezone":"Asia/Tbilisi",
    "iso:country":"GE",
    "name:kat_x_preferred":[
        "Patara-Oni"
    ],
    "name:kat_x_variant":[
        "\u10de\u10d0\u10e2\u10d0\u10e0\u10d0 \u10dd\u10dc\u10d8"
    ],
    "wof:name":"Patara-Oni",
    "wof:placetype":"locality"
},
  "geometry": {"coordinates":[42.97736,42.5372],"type":"Point"}
}