{
  "type": "Feature",
  "properties": {
    "gn:admin1_code":"00",
    "gn:asciiname":"Chotori",
    "gn:country_code":"GE",
    "gn:dem":854,
    "gn:feature_class":"P",
    "gn:feature_code":"PPL",
    "gn:name":"Chotori",
    "gn:population":0,
    "gn:timezone":"Asia/Tbilisi",
    "iso:country":"GE",
    "name:kat_x_preferred":[
        "Chotori"
    ],
    "name:und_x_variant":[
        "Chotoris-Kaloyebi"
    ],
    "wof:name":"Chotori",
    "wof:placetype":"locality"
},
  "geometry": {"coordinates":[45.86371,41.60329],"type":"Point"}
}