{
  "type": "Feature",
  "properties": {
    "gn:admin1_code":"00",
    "gn:asciiname":"Sabirk'endi",
    "gn:country_code":"GE",
    "gn:dem":368,
    "gn:feature_class":"P",
    "gn:feature_code":"PPL",
    "gn:name":"Sabirk\u2019endi",
    "gn:population":0,
    "gn:timezone":"Asia/Tbilisi",
    "iso:country":"GE",
    "name:und_x_variant":[
        "Sabriakend",
        "Sabirk\u2019endi"
    ],
    "wof:name":"Sabirk'endi",
    "wof:placetype":"locality"
},
  "geometry": {"coordinates":[44.865,41.45146],"type":"Point"}
}