{
  "type": "Feature",
  "properties": {
    "gn:admin1_code":"08",
    "gn:asciiname":"P'ich'khovani",
    "gn:country_code":"GE",
    "gn:dem":489,
    "gn:feature_class":"P",
    "gn:feature_code":"PPL",
    "gn:name":"P\u2019ich\u2019khovani",
    "gn:population":0,
    "gn:timezone":"Asia/Tbilisi",
    "iso:country":"GE",
    "name:kat_x_preferred":[
        "P\u2019ich\u2019khovani"
    ],
    "wof:name":"P'ich'khovani",
    "wof:placetype":"locality"
},
  "geometry": {"coordinates":[45.32653,42.09316],"type":"Point"}
}