{
  "type": "Feature",
  "properties": {
    "gn:country":"GE",
    "gn:fcode":"PPL",
    "gn:pop":4172,
    "iso:country":"GE",
    "name:eng_x_preferred":[
        "Tsqnet'i"
    ],
    "name:rus_x_preferred":[
        "\u0426\u0445\u043d\u0435\u0442\u0438"
    ],
    "name:unk_x_variant":[
        "Tskhneti"
    ],
    "qs:name":"Tsqnet\u2019i",
    "qs:photos_9r":0,
    "qs:photos_sr":0,
    "qs:pop_sr":"4",
    "wof:name":"Tsqnet\u2019i",
    "wof:placetype":"locality",
    "wof:population":4172
},
  "geometry": {"coordinates":[44.69861,41.69472],"type":"Point"}
}