{
  "type": "Feature",
  "properties": {
    "gn:admin1_code":"00",
    "gn:asciiname":"Berdzenauli",
    "gn:country_code":"GE",
    "gn:dem":669,
    "gn:feature_class":"P",
    "gn:feature_code":"PPL",
    "gn:name":"Berdzenauli",
    "gn:population":0,
    "gn:timezone":"Asia/Tbilisi",
    "iso:country":"GE",
    "name:und_x_variant":[
        "Bendzenauli",
        "Berdzenauli"
    ],
    "wof:name":"Berdzenauli",
    "wof:placetype":"locality"
},
  "geometry": {"coordinates":[43.77165,42.07876],"type":"Point"}
}