{
  "type": "Feature",
  "properties": {
    "gn:admin1_code":"70",
    "gn:asciiname":"Gadamshi",
    "gn:country_code":"GE",
    "gn:dem":1058,
    "gn:feature_class":"P",
    "gn:feature_code":"PPL",
    "gn:name":"Gadamshi",
    "gn:population":0,
    "gn:timezone":"Asia/Tbilisi",
    "iso:country":"GE",
    "name:kat_x_preferred":[
        "\u10d2\u10d0\u10d3\u10d0\u10db\u10e8\u10d8"
    ],
    "wof:name":"Gadamshi",
    "wof:placetype":"locality"
},
  "geometry": {"coordinates":[43.33798,42.61789],"type":"Point"}
}