{
  "type": "Feature",
  "properties": {
    "gn:admin1_code":"66",
    "gn:asciiname":"P'irveli Maisi",
    "gn:country_code":"GE",
    "gn:dem":22,
    "gn:feature_class":"P",
    "gn:feature_code":"PPL",
    "gn:name":"P\u2019irveli Maisi",
    "gn:population":0,
    "gn:timezone":"Asia/Tbilisi",
    "iso:country":"GE",
    "name:kat_x_preferred":[
        "P\u2019irveli Maisi"
    ],
    "name:kat_x_variant":[
        "\u10de\u10d8\u10e0\u10d5\u10d4\u10da\u10d8 \u10db\u10d0\u10d8\u10e1\u10d8"
    ],
    "name:und_x_variant":[
        "Pirvelmaisi"
    ],
    "wof:name":"P'irveli Maisi",
    "wof:placetype":"locality"
},
  "geometry": {"coordinates":[42.29053,42.15085],"type":"Point"}
}