{
  "type": "Feature",
  "properties": {
    "gn:admin1_code":"66",
    "gn:asciiname":"Chiat'ura",
    "gn:country_code":"GE",
    "gn:dem":495,
    "gn:feature_class":"P",
    "gn:feature_code":"PPL",
    "gn:name":"Chiat\u2019ura",
    "gn:population":12803,
    "gn:timezone":"Asia/Tbilisi",
    "iso:country":"GE",
    "name:aze_x_preferred":[
        "\u00c7iatura"
    ],
    "name:bel_x_preferred":[
        "\u0427\u044b\u044f\u0442\u0443\u0440\u0430"
    ],
    "name:bul_x_preferred":[
        "\u0427\u0438\u0430\u0442\u0443\u0440\u0430"
    ],
    "name:ceb_x_preferred":[
        "Chiat'ura"
    ],
    "name:ces_x_preferred":[
        "\u010ciatura"
    ],
    "name:che_x_preferred":[
        "\u0427\u0438\u0430\u0442\u0443\u0440\u0430"
    ],
    "name:dan_x_preferred":[
        "Tjiatura"
    ],
    "name:deu_x_preferred":[
        "Tschiatura"
    ],
    "name:eng_x_preferred":[
        "Chiat'ura"
    ],
    "name:epo_x_preferred":[
        "\u0108iatura"
    ],
    "name:est_x_preferred":[
        "T\u0161iathura"
    ],
    "name:fas_x_preferred":[
        "\u0686\u06cc\u0627\u062a\u0648\u0631\u0627"
    ],
    "name:fin_x_preferred":[
        "T\u0161iatura"
    ],
    "name:fra_x_preferred":[
        "Tchiatoura"
    ],
    "name:heb_x_preferred":[
        "\u05e6'\u05d9\u05d0\u05ea\u05d5\u05e8\u05d4"
    ],
    "name:hsb_x_preferred":[
        "\u010ciatura"
    ],
    "name:hye_x_preferred":[
        "\u0543\u056b\u0561\u0569\u0578\u0582\u0580\u0561"
    ],
    "name:ind_x_preferred":[
        "Chiatura"
    ],
    "name:ita_x_preferred":[
        "Chiatura"
    ],
    "name:jpn_x_preferred":[
        "\u30c1\u30a2\u30c8\u30a5\u30e9"
    ],
    "name:kat_x_preferred":[
        "\u10ed\u10d8\u10d0\u10d7\u10e3\u10e0\u10d0"
    ],
    "name:kor_x_preferred":[
        "\uce58\uc544\ud22c\ub77c"
    ],
    "name:lit_x_preferred":[
        "\u010ciatura"
    ],
    "name:mal_x_preferred":[
        "\u0d1a\u0d3f\u0d2f\u0d3e\u0d24\u0d41\u0d30"
    ],
    "name:mzn_x_preferred":[
        "\u0686\u06cc\u0627\u062a\u0648\u0631\u0627"
    ],
    "name:nld_x_preferred":[
        "Tsjiatoera"
    ],
    "name:nno_x_preferred":[
        "Tsjiatura"
    ],
    "name:oss_x_preferred":[
        "\u0427\u0438\u0430\u0442\u0443\u0440\u0430"
    ],
    "name:pol_x_preferred":[
        "Cziatura"
    ],
    "name:ron_x_preferred":[
        "Ciatura"
    ],
    "name:rus_x_preferred":[
        "\u0427\u0438\u0430\u0442\u0443\u0440\u0430"
    ],
    "name:spa_x_preferred":[
        "Chiatura"
    ],
    "name:srp_x_preferred":[
        "\u0427\u0438\u0458\u0430\u0442\u0443\u0440\u0430"
    ],
    "name:swe_x_preferred":[
        "Tjiatura"
    ],
    "name:tur_x_preferred":[
        "\u00c7iatura"
    ],
    "name:ukr_x_preferred":[
        "\u0427\u0438\u0430\u0442\u0443\u0440\u0430"
    ],
    "name:und_x_variant":[
        "\u010ciat\u2019ura",
        "Chitura"
    ],
    "name:urd_x_preferred":[
        "\u0686\u06cc\u0627\u062a\u0648\u0631\u0627"
    ],
    "name:war_x_preferred":[
        "Chiatura"
    ],
    "name:xmf_x_preferred":[
        "\u10ed\u10d8\u10d0\u10d7\u10e3\u10e0\u10d0"
    ],
    "name:zho_x_preferred":[
        "\u5947\u963f\u5716\u62c9"
    ],
    "wof:name":"Chiat'ura",
    "wof:placetype":"locality",
    "wof:population":12803
},
  "geometry": {"coordinates":[43.29889,42.29806],"type":"Point"}
}