{
  "type": "Feature",
  "properties": {
    "gn:admin1_code":"66",
    "gn:asciiname":"Chiat'ura",
    "gn:country_code":"GE",
    "gn:dem":495,
    "gn:feature_class":"P",
    "gn:feature_code":"PPL",
    "gn:name":"Chiat\u2019ura",
    "gn:population":12803,
    "gn:timezone":"Asia/Tbilisi",
    "iso:country":"GE",
    "name:eng_x_preferred":[
        "Chiat'ura"
    ],
    "name:rus_x_preferred":[
        "\u0427\u0438\u0430\u0442\u0443\u0440\u0430"
    ],
    "name:und_x_variant":[
        "Tschiatura",
        "\u010ciat\u2019ura",
        "Chitura"
    ],
    "wof:name":"Chiat'ura",
    "wof:placetype":"locality",
    "wof:population":12803
},
  "geometry": {"coordinates":[43.29889,42.29806],"type":"Point"}
}