{
  "type": "Feature",
  "properties": {
    "gn:admin1_code":"00",
    "gn:asciiname":"Leladziseuli",
    "gn:country_code":"GE",
    "gn:dem":430,
    "gn:feature_class":"P",
    "gn:feature_code":"PPL",
    "gn:name":"Leladziseuli",
    "gn:population":0,
    "gn:timezone":"Asia/Tbilisi",
    "iso:country":"GE",
    "wof:name":"Leladziseuli",
    "wof:placetype":"locality"
},
  "geometry": {"coordinates":[43.13474,42.06466],"type":"Point"}
}