{
  "type": "Feature",
  "properties": {
    "gn:admin1_code":"70",
    "gn:asciiname":"Uravi",
    "gn:country_code":"GE",
    "gn:dem":954,
    "gn:feature_class":"P",
    "gn:feature_code":"PPL",
    "gn:name":"Uravi",
    "gn:population":0,
    "gn:timezone":"Asia/Tbilisi",
    "iso:country":"GE",
    "name:ceb_x_preferred":[
        "Uravi"
    ],
    "name:eng_x_preferred":[
        "Uravi"
    ],
    "name:kat_x_preferred":[
        "\u10e3\u10e0\u10d0\u10d5\u10d8"
    ],
    "name:oss_x_preferred":[
        "\u0423\u0440\u0430\u0443"
    ],
    "name:rus_x_preferred":[
        "\u0423\u0440\u0430\u0432\u0438"
    ],
    "wof:name":"Uravi",
    "wof:placetype":"locality"
},
  "geometry": {"coordinates":[43.29093,42.64951],"type":"Point"}
}