{
  "type": "Feature",
  "properties": {
    "gn:admin1_code":"69",
    "gn:asciiname":"Sashaburo",
    "gn:country_code":"GE",
    "gn:dem":880,
    "gn:feature_class":"P",
    "gn:feature_code":"PPL",
    "gn:name":"Sashaburo",
    "gn:population":0,
    "gn:timezone":"Asia/Tbilisi",
    "iso:country":"GE",
    "wof:name":"Sashaburo",
    "wof:placetype":"locality"
},
  "geometry": {"coordinates":[44.70101,42.03367],"type":"Point"}
}