{
  "type": "Feature",
  "properties": {
    "gn:admin1_code":"02",
    "gn:asciiname":"Gup'agu",
    "gn:country_code":"GE",
    "gn:dem":262,
    "gn:feature_class":"P",
    "gn:feature_code":"PPL",
    "gn:name":"Gup\u2019agu",
    "gn:population":0,
    "gn:timezone":"Asia/Tbilisi",
    "iso:country":"GE",
    "name:eng_x_preferred":[
        "Gup'agu"
    ],
    "name:kat_x_preferred":[
        "Gup\u2019agu"
    ],
    "name:rus_x_preferred":[
        "\u0413\u0443\u043f-\u0410\u0433\u0443"
    ],
    "name:und_x_variant":[
        "Achandara"
    ],
    "wof:name":"Gup'agu",
    "wof:placetype":"locality"
},
  "geometry": {"coordinates":[41.59444000000001,42.89139],"type":"Point"}
}