{
  "type": "Feature",
  "properties": {
    "gn:admin1_code":"71",
    "gn:asciiname":"Lekharchile",
    "gn:country_code":"GE",
    "gn:dem":274,
    "gn:feature_class":"P",
    "gn:feature_code":"PPL",
    "gn:name":"Lekharchile",
    "gn:population":0,
    "gn:timezone":"Asia/Tbilisi",
    "iso:country":"GE",
    "name:kat_x_preferred":[
        "\u10da\u10d4\u10ee\u10d0\u10e0\u10e9\u10d8\u10da\u10d4"
    ],
    "wof:name":"Lekharchile",
    "wof:placetype":"locality"
},
  "geometry": {"coordinates":[42.13504,42.64458],"type":"Point"}
}