{
  "type": "Feature",
  "properties": {
    "gn:admin1_code":"02",
    "gn:asciiname":"Akhivaa",
    "gn:country_code":"GE",
    "gn:dem":34,
    "gn:feature_class":"P",
    "gn:feature_code":"PPL",
    "gn:name":"Akhivaa",
    "gn:population":0,
    "gn:timezone":"Asia/Tbilisi",
    "iso:country":"GE",
    "name:kat_x_preferred":[
        "Akhivaa"
    ],
    "name:kat_x_variant":[
        "\u10d0\u10ee\u10d8\u10d5\u10d0\u10d0"
    ],
    "name:und_x_variant":[
        "Akhuaa",
        "Akhyvaa"
    ],
    "wof:name":"Akhivaa",
    "wof:placetype":"locality"
},
  "geometry": {"coordinates":[41.30759000000001,42.82124],"type":"Point"}
}