{
  "type": "Feature",
  "properties": {
    "gn:admin1_code":"73",
    "gn:asciiname":"Khakheti",
    "gn:country_code":"GE",
    "gn:dem":975,
    "gn:feature_class":"P",
    "gn:feature_code":"PPL",
    "gn:name":"Khakheti",
    "gn:population":0,
    "gn:timezone":"Asia/Tbilisi",
    "iso:country":"GE",
    "name:kat_x_preferred":[
        "\u10ee\u10d0\u10ee\u10d4\u10d7\u10d8"
    ],
    "wof:name":"Khakheti",
    "wof:placetype":"locality"
},
  "geometry": {"coordinates":[43.6125,42.39374],"type":"Point"}
}