{
  "type": "Feature",
  "properties": {
    "gn:admin1_code":"70",
    "gn:asciiname":"Gembuli",
    "gn:country_code":"GE",
    "gn:dem":1421,
    "gn:feature_class":"P",
    "gn:feature_code":"PPL",
    "gn:name":"Gembuli",
    "gn:population":0,
    "gn:timezone":"Asia/Tbilisi",
    "iso:country":"GE",
    "wof:name":"Gembuli",
    "wof:placetype":"locality"
},
  "geometry": {"coordinates":[43.62889000000001,42.5075],"type":"Point"}
}