{
  "type": "Feature",
  "properties": {
    "gn:admin1_code":"00",
    "gn:asciiname":"Patara Dmanisi",
    "gn:country_code":"GE",
    "gn:dem":858,
    "gn:feature_class":"P",
    "gn:feature_code":"PPL",
    "gn:name":"Patara Dmanisi",
    "gn:population":0,
    "gn:timezone":"Asia/Tbilisi",
    "iso:country":"GE",
    "name:und_x_variant":[
        "Dmanisi-Patara",
        "Patara Dmanisi"
    ],
    "wof:name":"Patara Dmanisi",
    "wof:placetype":"locality"
},
  "geometry": {"coordinates":[44.34267,41.33062],"type":"Point"}
}