{
  "type": "Feature",
  "properties": {
    "gn:admin1_code":"72",
    "gn:asciiname":"Saqunet'i",
    "gn:country_code":"GE",
    "gn:dem":930,
    "gn:feature_class":"P",
    "gn:feature_code":"PPL",
    "gn:name":"Saqunet\u2019i",
    "gn:population":0,
    "gn:timezone":"Asia/Tbilisi",
    "iso:country":"GE",
    "name:kat_x_preferred":[
        "\u10e1\u10d0\u10e7\u10e3\u10dc\u10d4\u10d7\u10d8"
    ],
    "name:und_x_variant":[
        "Sakuneti",
        "Saqunet\u2019i"
    ],
    "wof:name":"Saqunet'i",
    "wof:placetype":"locality"
},
  "geometry": {"coordinates":[43.13115,41.68796],"type":"Point"}
}