{
  "type": "Feature",
  "properties": {
    "gn:admin1_code":"02",
    "gn:asciiname":"Akvaskia",
    "gn:country_code":"GE",
    "gn:dem":129,
    "gn:feature_class":"P",
    "gn:feature_code":"PPL",
    "gn:name":"Akvaskia",
    "gn:population":0,
    "gn:timezone":"Asia/Tbilisi",
    "iso:country":"GE",
    "name:und_x_variant":[
        "Akvaske",
        "Akvaskia"
    ],
    "wof:name":"Akvaskia",
    "wof:placetype":"locality"
},
  "geometry": {"coordinates":[41.56645,42.81983],"type":"Point"}
}