{
  "type": "Feature",
  "properties": {
    "gn:admin1_code":"71",
    "gn:asciiname":"Gakhomela",
    "gn:country_code":"GE",
    "gn:dem":87,
    "gn:feature_class":"P",
    "gn:feature_code":"PPL",
    "gn:name":"Gakhomela",
    "gn:population":0,
    "gn:timezone":"Asia/Tbilisi",
    "iso:country":"GE",
    "name:kat_x_preferred":[
        "Gakhomela"
    ],
    "name:kat_x_variant":[
        "\u10d2\u10d0\u10ee\u10dd\u10db\u10d4\u10da\u10d0"
    ],
    "name:und_x_variant":[
        "Gazomela"
    ],
    "wof:name":"Gakhomela",
    "wof:placetype":"locality"
},
  "geometry": {"coordinates":[42.19487,42.35081],"type":"Point"}
}