{
  "type": "Feature",
  "properties": {
    "gn:admin1_code":"72",
    "gn:asciiname":"Dabnia",
    "gn:country_code":"GE",
    "gn:dem":1721,
    "gn:feature_class":"P",
    "gn:feature_code":"PPL",
    "gn:name":"Dabnia",
    "gn:population":0,
    "gn:timezone":"Asia/Tbilisi",
    "iso:country":"GE",
    "name:kat_x_preferred":[
        "Dabnia"
    ],
    "name:kat_x_variant":[
        "\u10d3\u10d0\u10d1\u10dc\u10d8\u10d0"
    ],
    "wof:name":"Dabnia",
    "wof:placetype":"locality"
},
  "geometry": {"coordinates":[43.25662,41.28077],"type":"Point"}
}