{
  "type": "Feature",
  "properties": {
    "gn:admin1_code":"00",
    "gn:asciiname":"Bidzhnisi",
    "gn:country_code":"GE",
    "gn:dem":839,
    "gn:feature_class":"P",
    "gn:feature_code":"PPL",
    "gn:name":"Bidzhnisi",
    "gn:population":0,
    "gn:timezone":"Asia/Tbilisi",
    "iso:country":"GE",
    "wof:name":"Bidzhnisi",
    "wof:placetype":"locality"
},
  "geometry": {"coordinates":[43.53167,42.055],"type":"Point"}
}