{
  "type": "Feature",
  "properties": {
    "gn:admin1_code":"00",
    "gn:asciiname":"K'veda Tsip'lavake",
    "gn:country_code":"GE",
    "gn:dem":461,
    "gn:feature_class":"P",
    "gn:feature_code":"PPL",
    "gn:name":"K\u2019veda Tsip\u2019lavake",
    "gn:population":0,
    "gn:timezone":"Asia/Tbilisi",
    "iso:country":"GE",
    "name:und_x_variant":[
        "Tsiplavake",
        "K\u2019veda Tsip\u2019lavake"
    ],
    "wof:name":"K'veda Tsip'lavake",
    "wof:placetype":"locality"
},
  "geometry": {"coordinates":[43.1269,42.11064],"type":"Point"}
}