{
  "type": "Feature",
  "properties": {
    "gn:admin1_code":"00",
    "gn:asciiname":"Lakoba",
    "gn:country_code":"GE",
    "gn:dem":381,
    "gn:feature_class":"P",
    "gn:feature_code":"PPL",
    "gn:name":"Lakoba",
    "gn:population":0,
    "gn:timezone":"Asia/Tbilisi",
    "iso:country":"GE",
    "wof:name":"Lakoba",
    "wof:placetype":"locality"
},
  "geometry": {"coordinates":[40.91556,43.08194],"type":"Point"}
}