{
  "type": "Feature",
  "properties": {
    "gn:admin1_code":"00",
    "gn:asciiname":"Patara-Shiraki",
    "gn:cc2":"GE",
    "gn:country_code":"GE",
    "gn:dem":592,
    "gn:feature_class":"P",
    "gn:feature_code":"PPL",
    "gn:name":"Patara-Shiraki",
    "gn:population":0,
    "gn:timezone":"Asia/Tbilisi",
    "iso:country":"GE",
    "name:und_x_variant":[
        "Malyye Shiraki",
        "Patara-Shiraki"
    ],
    "wof:name":"Patara-Shiraki",
    "wof:placetype":"locality"
},
  "geometry": {"coordinates":[46.34083,41.29389000000001],"type":"Point"}
}