{
  "type": "Feature",
  "properties": {
    "gn:admin1_code":"00",
    "gn:asciiname":"Telagina",
    "gn:country_code":"GE",
    "gn:dem":1051,
    "gn:feature_class":"P",
    "gn:feature_code":"PPL",
    "gn:name":"Telagina",
    "gn:population":0,
    "gn:timezone":"Asia/Tbilisi",
    "iso:country":"GE",
    "name:und_x_variant":[
        "Telagini",
        "Telagina"
    ],
    "wof:name":"Telagina",
    "wof:placetype":"locality"
},
  "geometry": {"coordinates":[44.25408,42.16861],"type":"Point"}
}