{
  "type": "Feature",
  "properties": {
    "gn:admin1_code":"02",
    "gn:asciiname":"Adzigezhi",
    "gn:country_code":"GE",
    "gn:dem":140,
    "gn:feature_class":"P",
    "gn:feature_code":"PPL",
    "gn:name":"Adzigezhi",
    "gn:population":0,
    "gn:timezone":"Asia/Tbilisi",
    "iso:country":"GE",
    "name:kat_x_preferred":[
        "\u10d0\u10eb\u10d8\u10d2\u10d4\u10df\u10d8"
    ],
    "name:kat_x_variant":[
        "Adzigezhi"
    ],
    "name:und_x_variant":[
        "Adzigezh"
    ],
    "wof:name":"Adzigezhi",
    "wof:placetype":"locality"
},
  "geometry": {"coordinates":[40.97984,43.0542],"type":"Point"}
}