{
  "type": "Feature",
  "properties": {
    "gn:admin1_code":"69",
    "gn:asciiname":"Zak'at'kari",
    "gn:country_code":"GE",
    "gn:dem":1641,
    "gn:feature_class":"P",
    "gn:feature_code":"PPL",
    "gn:name":"Zak\u2019at\u2019kari",
    "gn:population":0,
    "gn:timezone":"Asia/Tbilisi",
    "iso:country":"GE",
    "name:kat_x_preferred":[
        "Zak\u2019at\u2019kari"
    ],
    "name:kat_x_variant":[
        "\u10d6\u10d0\u10d9\u10d0\u10d7\u10d9\u10d0\u10e0\u10d8"
    ],
    "wof:name":"Zak'at'kari",
    "wof:placetype":"locality"
},
  "geometry": {"coordinates":[44.52095,42.4404],"type":"Point"}
}