{
  "type": "Feature",
  "properties": {
    "gn:admin1_code":"01",
    "gn:asciiname":"Gezati",
    "gn:country_code":"GE",
    "gn:dem":44,
    "gn:feature_class":"P",
    "gn:feature_code":"PPL",
    "gn:name":"Gezati",
    "gn:population":0,
    "gn:timezone":"Asia/Tbilisi",
    "iso:country":"GE",
    "wof:name":"Gezati",
    "wof:placetype":"locality"
},
  "geometry": {"coordinates":[42.28917,42.24056],"type":"Point"}
}