{
  "type": "Feature",
  "properties": {
    "gn:admin1_code":"02",
    "gn:asciiname":"Zakharovka",
    "gn:country_code":"GE",
    "gn:dem":449,
    "gn:feature_class":"P",
    "gn:feature_code":"PPL",
    "gn:name":"Zakharovka",
    "gn:population":0,
    "gn:timezone":"Asia/Tbilisi",
    "iso:country":"GE",
    "wof:name":"Zakharovka",
    "wof:placetype":"locality"
},
  "geometry": {"coordinates":[41.31667,43.03333],"type":"Point"}
}