{
  "type": "Feature",
  "properties": {
    "gn:admin1_code":"00",
    "gn:asciiname":"Khomuli",
    "gn:country_code":"GE",
    "gn:dem":127,
    "gn:feature_class":"P",
    "gn:feature_code":"PPL",
    "gn:name":"Khomuli",
    "gn:population":0,
    "gn:timezone":"Asia/Tbilisi",
    "iso:country":"GE",
    "wof:name":"Khomuli",
    "wof:placetype":"locality"
},
  "geometry": {"coordinates":[42.62821,42.32827],"type":"Point"}
}