{
  "type": "Feature",
  "properties": {
    "gn:admin1_code":"04",
    "gn:asciiname":"K'arapet'i",
    "gn:country_code":"GE",
    "gn:dem":1341,
    "gn:feature_class":"P",
    "gn:feature_code":"PPL",
    "gn:name":"K\u2019arapet\u2019i",
    "gn:population":0,
    "gn:timezone":"Asia/Tbilisi",
    "iso:country":"GE",
    "name:kat_x_preferred":[
        "K\u2019arapet\u2019i"
    ],
    "name:kat_x_variant":[
        "\u10d9\u10d0\u10e0\u10d0\u10de\u10d4\u10e2\u10d8"
    ],
    "wof:name":"K'arapet'i",
    "wof:placetype":"locality"
},
  "geometry": {"coordinates":[42.2566,41.55485],"type":"Point"}
}