{
  "type": "Feature",
  "properties": {
    "gn:admin1_code":"04",
    "gn:asciiname":"Shua-Bakhvi",
    "gn:country_code":"GE",
    "gn:dem":153,
    "gn:feature_class":"P",
    "gn:feature_code":"PPL",
    "gn:name":"Shua-Bakhvi",
    "gn:population":0,
    "gn:timezone":"Asia/Tbilisi",
    "iso:country":"GE",
    "name:kat_x_preferred":[
        "Shua-Bakhvi"
    ],
    "wof:name":"Shua-Bakhvi",
    "wof:placetype":"locality"
},
  "geometry": {"coordinates":[42.08333,41.95],"type":"Point"}
}