{
  "type": "Feature",
  "properties": {
    "gn:admin1_code":"00",
    "gn:asciiname":"Macharashvilebi",
    "gn:country_code":"GE",
    "gn:dem":807,
    "gn:feature_class":"P",
    "gn:feature_code":"PPL",
    "gn:name":"Macharashvilebi",
    "gn:population":0,
    "gn:timezone":"Asia/Tbilisi",
    "iso:country":"GE",
    "wof:name":"Macharashvilebi",
    "wof:placetype":"locality"
},
  "geometry": {"coordinates":[43.42139,42.20639],"type":"Point"}
}