{
  "type": "Feature",
  "properties": {
    "gn:admin1_code":"68",
    "gn:asciiname":"Pitareti",
    "gn:country_code":"GE",
    "gn:dem":887,
    "gn:feature_class":"P",
    "gn:feature_code":"PPL",
    "gn:name":"Pitareti",
    "gn:population":0,
    "gn:timezone":"Asia/Tbilisi",
    "iso:country":"GE",
    "name:kat_x_preferred":[
        "\u10e4\u10d8\u10e2\u10d0\u10e0\u10d4\u10d7\u10d8"
    ],
    "name:und_x_variant":[
        "Pitarayeti",
        "Pitareti"
    ],
    "wof:name":"Pitareti",
    "wof:placetype":"locality"
},
  "geometry": {"coordinates":[44.31747,41.47952],"type":"Point"}
}