{
  "type": "Feature",
  "properties": {
    "gn:admin1_code":"69",
    "gn:asciiname":"Korsha",
    "gn:country_code":"GE",
    "gn:dem":1383,
    "gn:feature_class":"P",
    "gn:feature_code":"PPL",
    "gn:name":"Korsha",
    "gn:population":0,
    "gn:timezone":"Asia/Tbilisi",
    "iso:country":"GE",
    "wof:name":"Korsha",
    "wof:placetype":"locality"
},
  "geometry": {"coordinates":[44.92591,42.48093],"type":"Point"}
}