{
  "type": "Feature",
  "properties": {
    "gn:admin1_code":"71",
    "gn:asciiname":"K'ot'ianeti",
    "gn:country_code":"GE",
    "gn:dem":64,
    "gn:feature_class":"P",
    "gn:feature_code":"PPL",
    "gn:name":"K\u2019ot\u2019ianeti",
    "gn:population":0,
    "gn:timezone":"Asia/Tbilisi",
    "iso:country":"GE",
    "name:kat_x_preferred":[
        "K\u2019ot\u2019ianeti"
    ],
    "name:und_x_variant":[
        "\u10d9\u10dd\u10e2\u10d8\u10d0\u10dc\u10d4\u10d7\u10d8"
    ],
    "wof:name":"K'ot'ianeti",
    "wof:placetype":"locality"
},
  "geometry": {"coordinates":[42.17382,42.32063],"type":"Point"}
}