{
  "type": "Feature",
  "properties": {
    "gn:admin1_code":"02",
    "gn:asciiname":"Zhirghalishk'a",
    "gn:country_code":"GE",
    "gn:dem":317,
    "gn:feature_class":"P",
    "gn:feature_code":"PPL",
    "gn:name":"Zhirghalishk\u2019a",
    "gn:population":0,
    "gn:timezone":"Asia/Tbilisi",
    "iso:country":"GE",
    "name:kat_x_preferred":[
        "Zhirghalishk\u2019a"
    ],
    "name:kat_x_variant":[
        "\u10df\u10d8\u10e0\u10e6\u10d0\u10da\u10d8\u10e8\u10d9\u10d0"
    ],
    "name:und_x_variant":[
        "Zhiri-Galishka",
        "Zhirgalishka"
    ],
    "wof:name":"Zhirghalishk'a",
    "wof:placetype":"locality"
},
  "geometry": {"coordinates":[41.9222,42.69659],"type":"Point"}
}