{
  "type": "Feature",
  "properties": {
    "gn:admin1_code":"00",
    "gn:asciiname":"Patashuri",
    "gn:country_code":"GE",
    "gn:dem":1671,
    "gn:feature_class":"P",
    "gn:feature_code":"PPL",
    "gn:name":"Patashuri",
    "gn:population":0,
    "gn:timezone":"Asia/Tbilisi",
    "iso:country":"GE",
    "wof:name":"Patashuri",
    "wof:placetype":"locality"
},
  "geometry": {"coordinates":[44.71167,42.37361],"type":"Point"}
}