{
  "type": "Feature",
  "properties": {
    "iso:country":"GE",
    "name:bul_x_preferred":[
        "\u0416\u0438\u043d\u0432\u0430\u043b\u0438"
    ],
    "name:ceb_x_preferred":[
        "Zhinvali"
    ],
    "name:che_x_preferred":[
        "\u0416\u0438\u043d\u0432\u0430\u043b\u0438"
    ],
    "name:eng_x_preferred":[
        "Zhinvali"
    ],
    "name:kat_x_preferred":[
        "\u10df\u10d8\u10dc\u10d5\u10d0\u10da\u10d8"
    ],
    "name:nld_x_preferred":[
        "Zhinvali"
    ],
    "name:oss_x_preferred":[
        "\u0416\u0438\u043d\u0432\u0430\u043b\u0438"
    ],
    "name:rus_x_preferred":[
        "\u0416\u0438\u043d\u0432\u0430\u043b\u0438"
    ],
    "name:swe_x_preferred":[
        "Zhinvali"
    ],
    "name:und_x_variant":[
        "Zhinvani"
    ],
    "qs:gn_country":"GE",
    "qs:gn_fcode":"PPL",
    "qs:gn_pop":3446,
    "qs:name":"Zhinvali",
    "qs:name_adm0":"Georgia",
    "qs:name_adm1":"Dushet\u00b4is Raioni",
    "qs:photos":194,
    "qs:photos_1k":39,
    "qs:photos_9k":1,
    "qs:photos_9r":4,
    "qs:photos_all":194,
    "qs:photos_sr":4,
    "qs:placetype":"Town",
    "qs:pop_sr":"4",
    "qs:woe_adm0":23424823,
    "wd:wordcount":45,
    "wof:name":"Zhinvali",
    "wof:placetype":"locality",
    "wof:population":3446
},
  "geometry": {"coordinates":[44.77264,42.13181],"type":"Point"}
}