{
  "type": "Feature",
  "properties": {
    "gn:admin1_code":"66",
    "gn:asciiname":"Sulori",
    "gn:country_code":"GE",
    "gn:dem":228,
    "gn:feature_class":"P",
    "gn:feature_code":"PPL",
    "gn:name":"Sulori",
    "gn:population":0,
    "gn:timezone":"Asia/Tbilisi",
    "iso:country":"GE",
    "name:eng_x_preferred":[
        "Sulori"
    ],
    "name:kat_x_preferred":[
        "\u10e1\u10e3\u10da\u10dd\u10e0\u10d8"
    ],
    "name:rus_x_preferred":[
        "\u0421\u0443\u043b\u043e\u0440\u0438"
    ],
    "name:und_x_variant":[
        "Sulari"
    ],
    "wof:name":"Sulori",
    "wof:placetype":"locality"
},
  "geometry": {"coordinates":[42.57232,42.02577],"type":"Point"}
}