{
  "type": "Feature",
  "properties": {
    "gn:admin1_code":"27",
    "gn:asciiname":"Vardzia",
    "gn:country_code":"GE",
    "gn:dem":390,
    "gn:feature_class":"P",
    "gn:feature_code":"PPL",
    "gn:name":"Vardzia",
    "gn:population":0,
    "gn:timezone":"Asia/Tbilisi",
    "iso:country":"GE",
    "name:eng_x_preferred":[
        "Vardzia"
    ],
    "name:rus_x_preferred":[
        "\u0412\u0430\u0440\u0434\u0437\u0438\u0430"
    ],
    "name:und_x_variant":[
        "Vardziya",
        "Vardzia"
    ],
    "wof:name":"Vardzia",
    "wof:placetype":"locality"
},
  "geometry": {"coordinates":[43.08271,42.02976],"type":"Point"}
}