{
  "type": "Feature",
  "properties": {
    "gn:admin1_code":"27",
    "gn:asciiname":"Vardzia",
    "gn:country_code":"GE",
    "gn:dem":390,
    "gn:feature_class":"P",
    "gn:feature_code":"PPL",
    "gn:name":"Vardzia",
    "gn:population":0,
    "gn:timezone":"Asia/Tbilisi",
    "iso:country":"GE",
    "name:bak_x_preferred":[
        "\u0412\u0430\u0440\u0434\u0437\u0438\u0430"
    ],
    "name:bel_x_preferred":[
        "\u0412\u0430\u0440\u0434\u0437\u0456\u0430"
    ],
    "name:bul_x_preferred":[
        "\u0412\u0430\u0440\u0434\u0437\u0438\u044f"
    ],
    "name:ceb_x_preferred":[
        "Vardzia"
    ],
    "name:ces_x_preferred":[
        "Kl\u00e1\u0161ter Vardzia"
    ],
    "name:deu_x_preferred":[
        "Wardsia"
    ],
    "name:ell_x_preferred":[
        "\u0392\u03ac\u03c1\u03c4\u03b6\u03b9\u03b1"
    ],
    "name:eng_x_preferred":[
        "Vardzia"
    ],
    "name:epo_x_preferred":[
        "Vardzia"
    ],
    "name:est_x_preferred":[
        "Vardzia"
    ],
    "name:fas_x_preferred":[
        "\u0648\u0627\u0631\u062f\u0632\u06cc\u0627"
    ],
    "name:fin_x_preferred":[
        "Vardzia"
    ],
    "name:fra_x_preferred":[
        "Vardzia"
    ],
    "name:heb_x_preferred":[
        "\u05d5\u05e8\u05d3\u05d6\u05d9\u05d4"
    ],
    "name:hrv_x_preferred":[
        "Vardzia"
    ],
    "name:hun_x_preferred":[
        "Vardzia"
    ],
    "name:hye_x_preferred":[
        "\u054e\u0561\u0580\u0571\u056b\u0561"
    ],
    "name:ita_x_preferred":[
        "Vardzia"
    ],
    "name:kat_x_preferred":[
        "\u10d5\u10d0\u10e0\u10eb\u10d8\u10d0"
    ],
    "name:kor_x_preferred":[
        "\ubc14\ub974\uc9c0\uc544"
    ],
    "name:lit_x_preferred":[
        "Vardzija"
    ],
    "name:nld_x_preferred":[
        "Vardzia"
    ],
    "name:pol_x_preferred":[
        "Wardzia"
    ],
    "name:por_x_preferred":[
        "Vardzia"
    ],
    "name:rus_x_preferred":[
        "\u0412\u0430\u0440\u0434\u0437\u0438\u0430"
    ],
    "name:spa_x_preferred":[
        "Vardzia"
    ],
    "name:srp_x_preferred":[
        "\u0412\u0430\u0440\u0434\u0437\u0438\u0458\u0430"
    ],
    "name:swe_x_preferred":[
        "Vardzia"
    ],
    "name:tur_x_preferred":[
        "Vardzia"
    ],
    "name:ukr_x_preferred":[
        "\u0412\u0430\u0440\u0434\u0437\u0456\u0430"
    ],
    "name:und_x_variant":[
        "Vardziya",
        "Vardzia"
    ],
    "wof:name":"Vardzia",
    "wof:placetype":"locality"
},
  "geometry": {"coordinates":[43.08271,42.02976],"type":"Point"}
}