{
  "type": "Feature",
  "properties": {
    "gn:admin1_code":"00",
    "gn:asciiname":"Dzhagaraantkari",
    "gn:country_code":"GE",
    "gn:dem":862,
    "gn:feature_class":"P",
    "gn:feature_code":"PPL",
    "gn:name":"Dzhagaraantkari",
    "gn:population":0,
    "gn:timezone":"Asia/Tbilisi",
    "iso:country":"GE",
    "name:kat_x_preferred":[
        "Jagaraantk\u2019ari"
    ],
    "name:kat_x_variant":[
        "\u10ef\u10d0\u10d2\u10d0\u10e0\u10d0\u10d0\u10dc\u10d7\u10d9\u10d0\u10e0\u10d8"
    ],
    "wof:name":"Dzhagaraantkari",
    "wof:placetype":"locality"
},
  "geometry": {"coordinates":[43.80051,41.99091],"type":"Point"}
}