{
  "type": "Feature",
  "properties": {
    "gn:admin1_code":"04",
    "gn:asciiname":"Zemo Khevi",
    "gn:country_code":"GE",
    "gn:dem":1098,
    "gn:feature_class":"P",
    "gn:feature_code":"PPL",
    "gn:name":"Zemo Khevi",
    "gn:population":0,
    "gn:timezone":"Asia/Tbilisi",
    "iso:country":"GE",
    "name:kat_x_preferred":[
        "Zemo Khevi"
    ],
    "name:kat_x_variant":[
        "\u10d6\u10d4\u10db\u10dd \u10ee\u10d4\u10d5\u10d8"
    ],
    "wof:name":"Zemo Khevi",
    "wof:placetype":"locality"
},
  "geometry": {"coordinates":[42.18333,41.68333],"type":"Point"}
}