{
  "type": "Feature",
  "properties": {
    "gn:admin1_code":"04",
    "gn:asciiname":"Zemo Khevi",
    "gn:country_code":"GE",
    "gn:dem":1098,
    "gn:feature_class":"P",
    "gn:feature_code":"PPL",
    "gn:name":"Zemo Khevi",
    "gn:population":0,
    "gn:timezone":"Asia/Tbilisi",
    "iso:country":"GE",
    "name:abk_x_preferred":[
        "\u0426\u0430\u043d\u0433\u04d9\u0430\u0440\u0430"
    ],
    "name:hye_x_preferred":[
        "\u054e\u0565\u0580\u056b\u0576 \u053d\u0587\u056b"
    ],
    "name:kat_x_preferred":[
        "Zemo Khevi"
    ],
    "name:kat_x_variant":[
        "\u10d6\u10d4\u10db\u10dd \u10ee\u10d4\u10d5\u10d8"
    ],
    "name:rus_x_preferred":[
        "\u0417\u0435\u043c\u043e \u0425\u0435\u0432\u0438"
    ],
    "name:ukr_x_preferred":[
        "\u0417\u0435\u043c\u043e \u0425\u0435\u0432\u0456"
    ],
    "wof:name":"Zemo Khevi",
    "wof:placetype":"locality"
},
  "geometry": {"coordinates":[42.18333,41.68333],"type":"Point"}
}