{
  "type": "Feature",
  "properties": {
    "gn:admin1_code":"51",
    "gn:asciiname":"Lap'anquri",
    "gn:country_code":"GE",
    "gn:dem":589,
    "gn:feature_class":"P",
    "gn:feature_code":"PPL",
    "gn:name":"Lap\u2019anquri",
    "gn:population":0,
    "gn:timezone":"Asia/Tbilisi",
    "iso:country":"GE",
    "name:eng_x_preferred":[
        "Lap'anquri"
    ],
    "name:kat_x_preferred":[
        "Lap\u2019anquri"
    ],
    "name:rus_x_preferred":[
        "\u041b\u0430\u043f\u0430\u043d\u043a\u0443\u0440\u0438"
    ],
    "name:und_x_variant":[
        "Lapan-Kure",
        "Lapatskuri",
        "Lapankuri"
    ],
    "wof:name":"Lap'anquri",
    "wof:placetype":"locality"
},
  "geometry": {"coordinates":[45.59417,42.0623],"type":"Point"}
}