{
  "type": "Feature",
  "properties": {
    "gn:admin1_code":"67",
    "gn:asciiname":"Ozhio",
    "gn:country_code":"GE",
    "gn:dem":523,
    "gn:feature_class":"P",
    "gn:feature_code":"PPL",
    "gn:name":"Ozhio",
    "gn:population":0,
    "gn:timezone":"Asia/Tbilisi",
    "iso:country":"GE",
    "name:kat_x_preferred":[
        "\u10dd\u10df\u10d8\u10dd"
    ],
    "wof:name":"Ozhio",
    "wof:placetype":"locality"
},
  "geometry": {"coordinates":[45.37586,41.97946],"type":"Point"}
}