{
  "type": "Feature",
  "properties": {
    "gn:admin1_code":"66",
    "gn:asciiname":"Satsable",
    "gn:country_code":"GE",
    "gn:dem":609,
    "gn:feature_class":"P",
    "gn:feature_code":"PPL",
    "gn:name":"Satsable",
    "gn:population":0,
    "gn:timezone":"Asia/Tbilisi",
    "iso:country":"GE",
    "name:kat_x_preferred":[
        "\u10e1\u10d0\u10ec\u10d0\u10d1\u10da\u10d4"
    ],
    "wof:name":"Satsable",
    "wof:placetype":"locality"
},
  "geometry": {"coordinates":[43.17757,42.15149],"type":"Point"}
}