{
  "type": "Feature",
  "properties": {
    "gn:admin1_code":"69",
    "gn:asciiname":"Ukankhadu",
    "gn:country_code":"GE",
    "gn:dem":1753,
    "gn:feature_class":"P",
    "gn:feature_code":"PPL",
    "gn:name":"Ukankhadu",
    "gn:population":0,
    "gn:timezone":"Asia/Tbilisi",
    "iso:country":"GE",
    "name:kat_x_preferred":[
        "\u10e3\u10d9\u10d0\u10dc\u10ee\u10d0\u10d3\u10e3"
    ],
    "wof:name":"Ukankhadu",
    "wof:placetype":"locality"
},
  "geometry": {"coordinates":[44.98021,42.57213],"type":"Point"}
}