{
  "type": "Feature",
  "properties": {
    "gn:admin1_code":"00",
    "gn:asciiname":"Kachret'i",
    "gn:country_code":"GE",
    "gn:dem":594,
    "gn:feature_class":"P",
    "gn:feature_code":"PPL",
    "gn:name":"Kachret\u2019i",
    "gn:population":0,
    "gn:timezone":"Asia/Tbilisi",
    "iso:country":"GE",
    "name:eng_x_preferred":[
        "Kachret'i"
    ],
    "name:kat_x_preferred":[
        "Kachret\u2019i"
    ],
    "name:rus_x_preferred":[
        "\u041a\u0430\u0447\u0440\u0435\u0442\u0438"
    ],
    "wof:name":"Kachret'i",
    "wof:placetype":"locality"
},
  "geometry": {"coordinates":[45.68153,41.65361],"type":"Point"}
}