{
  "type": "Feature",
  "properties": {
    "gn:admin1_code":"00",
    "gn:asciiname":"Didi Ch'ailuri",
    "gn:country_code":"GE",
    "gn:dem":692,
    "gn:feature_class":"P",
    "gn:feature_code":"PPL",
    "gn:name":"Didi Ch\u2019ailuri",
    "gn:population":0,
    "gn:timezone":"Asia/Tbilisi",
    "iso:country":"GE",
    "name:kat_x_preferred":[
        "Didi Ch\u2019ailuri"
    ],
    "name:und_x_variant":[
        "Didi-Chiluri",
        "Chailuri",
        "Chayluri"
    ],
    "wof:name":"Didi Ch'ailuri",
    "wof:placetype":"locality"
},
  "geometry": {"coordinates":[45.50379,41.71468],"type":"Point"}
}