{
  "type": "Feature",
  "properties": {
    "gn:admin1_code":"00",
    "gn:asciiname":"Gekhavi",
    "gn:country_code":"GE",
    "gn:dem":1511,
    "gn:feature_class":"P",
    "gn:feature_code":"PPL",
    "gn:name":"Gekhavi",
    "gn:population":0,
    "gn:timezone":"Asia/Tbilisi",
    "iso:country":"GE",
    "wof:name":"Gekhavi",
    "wof:placetype":"locality"
},
  "geometry": {"coordinates":[44.43306,42.1425],"type":"Point"}
}