{
  "type": "Feature",
  "properties": {
    "gn:admin1_code":"02",
    "gn:asciiname":"Abzhaq'va",
    "gn:country_code":"GE",
    "gn:dem":64,
    "gn:feature_class":"P",
    "gn:feature_code":"PPL",
    "gn:name":"Abzhaq\u2019va",
    "gn:population":0,
    "gn:timezone":"Asia/Tbilisi",
    "iso:country":"GE",
    "name:kat_x_preferred":[
        "\u10d0\u10d1\u10df\u10d0\u10e7\u10d5\u10d0"
    ],
    "name:kat_x_variant":[
        "Abzhaq\u2019va"
    ],
    "name:und_x_variant":[
        "Abzhakva"
    ],
    "wof:name":"Abzhaq'va",
    "wof:placetype":"locality"
},
  "geometry": {"coordinates":[41.07581,43.02858],"type":"Point"}
}