{
  "type": "Feature",
  "properties": {
    "gn:admin1_code":"02",
    "gn:asciiname":"Shkashisuk'i",
    "gn:country_code":"GE",
    "gn:dem":254,
    "gn:feature_class":"P",
    "gn:feature_code":"PPL",
    "gn:name":"Shkashisuk\u2019i",
    "gn:population":0,
    "gn:timezone":"Asia/Tbilisi",
    "iso:country":"GE",
    "name:kat_x_preferred":[
        "Shkashisuk\u2019i"
    ],
    "name:kat_x_variant":[
        "\u10e8\u10e5\u10d0\u10e8\u10d8\u10e1\u10e3\u10d9\u10d8"
    ],
    "name:und_x_variant":[
        "Shkashikhuki"
    ],
    "wof:name":"Shkashisuk'i",
    "wof:placetype":"locality"
},
  "geometry": {"coordinates":[41.9296,42.65756],"type":"Point"}
}