{
  "type": "Feature",
  "properties": {
    "gn:admin1_code":"69",
    "gn:asciiname":"Garuyeti",
    "gn:country_code":"GE",
    "gn:dem":1212,
    "gn:feature_class":"P",
    "gn:feature_code":"PPL",
    "gn:name":"Garuyeti",
    "gn:population":0,
    "gn:timezone":"Asia/Tbilisi",
    "iso:country":"GE",
    "wof:name":"Garuyeti",
    "wof:placetype":"locality"
},
  "geometry": {"coordinates":[44.50167,42.25167],"type":"Point"}
}