{
  "type": "Feature",
  "properties": {
    "gn:admin1_code":"69",
    "gn:asciiname":"Arboyeti",
    "gn:country_code":"GE",
    "gn:dem":1264,
    "gn:feature_class":"P",
    "gn:feature_code":"PPL",
    "gn:name":"Arboyeti",
    "gn:population":0,
    "gn:timezone":"Asia/Tbilisi",
    "iso:country":"GE",
    "wof:name":"Arboyeti",
    "wof:placetype":"locality"
},
  "geometry": {"coordinates":[44.60167,42.11222],"type":"Point"}
}