{
  "type": "Feature",
  "properties": {
    "gn:admin1_code":"69",
    "gn:asciiname":"Muts'o",
    "gn:country_code":"GE",
    "gn:dem":1724,
    "gn:feature_class":"P",
    "gn:feature_code":"PPL",
    "gn:name":"Muts\u2019o",
    "gn:population":0,
    "gn:timezone":"Asia/Tbilisi",
    "iso:country":"GE",
    "name:kat_x_preferred":[
        "\u10db\u10e3\u10ea\u10dd"
    ],
    "name:und_x_variant":[
        "Muts\u2019o"
    ],
    "wof:name":"Muts'o",
    "wof:placetype":"locality"
},
  "geometry": {"coordinates":[45.20767,42.60241],"type":"Point"}
}