{
  "type": "Feature",
  "properties": {
    "gn:admin1_code":"69",
    "gn:asciiname":"Muts'o",
    "gn:country_code":"GE",
    "gn:dem":1724,
    "gn:feature_class":"P",
    "gn:feature_code":"PPL",
    "gn:name":"Muts\u2019o",
    "gn:population":0,
    "gn:timezone":"Asia/Tbilisi",
    "iso:country":"GE",
    "name:bak_x_preferred":[
        "\u041c\u0443\u0446\u043e"
    ],
    "name:ces_x_preferred":[
        "Muco"
    ],
    "name:che_x_preferred":[
        "\u041c\u0443\u0446\u043e"
    ],
    "name:deu_x_preferred":[
        "Muzo"
    ],
    "name:hye_x_preferred":[
        "\u0544\u0578\u0582\u0581\u0578"
    ],
    "name:ita_x_preferred":[
        "Mutso"
    ],
    "name:kat_x_preferred":[
        "\u10db\u10e3\u10ea\u10dd"
    ],
    "name:nld_x_preferred":[
        "Moetso"
    ],
    "name:spa_x_preferred":[
        "Mutso"
    ],
    "name:tur_x_preferred":[
        "Mutso"
    ],
    "name:und_x_variant":[
        "Muts\u2019o"
    ],
    "wof:name":"Muts'o",
    "wof:placetype":"locality"
},
  "geometry": {"coordinates":[45.20767,42.60241],"type":"Point"}
}