{
  "type": "Feature",
  "properties": {
    "gn:admin1_code":"71",
    "gn:asciiname":"Saghvamich'avo",
    "gn:country_code":"GE",
    "gn:dem":2,
    "gn:feature_class":"P",
    "gn:feature_code":"PPL",
    "gn:name":"Saghvamich\u2019avo",
    "gn:population":0,
    "gn:timezone":"Asia/Tbilisi",
    "iso:country":"GE",
    "name:kat_x_preferred":[
        "Saghvamich\u2019avo"
    ],
    "name:kat_x_variant":[
        "\u10e1\u10d0\u10e6\u10d5\u10d0\u10db\u10d8\u10e9\u10d0\u10d5\u10dd"
    ],
    "name:und_x_variant":[
        "Sagvamichavo",
        "Sagvamichao"
    ],
    "wof:name":"Saghvamich'avo",
    "wof:placetype":"locality"
},
  "geometry": {"coordinates":[41.83663,42.22882],"type":"Point"}
}