{
  "type": "Feature",
  "properties": {
    "gn:admin1_code":"71",
    "gn:asciiname":"Kveda Vedi",
    "gn:country_code":"GE",
    "gn:dem":847,
    "gn:feature_class":"P",
    "gn:feature_code":"PPL",
    "gn:name":"Kveda Vedi",
    "gn:population":0,
    "gn:timezone":"Asia/Tbilisi",
    "iso:country":"GE",
    "name:kat_x_preferred":[
        "Kveda Vedi"
    ],
    "name:kat_x_variant":[
        "\u10e5\u10d5\u10d4\u10d3\u10d0 \u10d5\u10d4\u10d3\u10d8"
    ],
    "name:und_x_variant":[
        "Kueda-Vedi",
        "Odzhi"
    ],
    "wof:name":"Kveda Vedi",
    "wof:placetype":"locality"
},
  "geometry": {"coordinates":[42.20047,42.90763],"type":"Point"}
}