{
  "type": "Feature",
  "properties": {
    "gn:admin1_code":"71",
    "gn:asciiname":"Meore Gurdzemi",
    "gn:country_code":"GE",
    "gn:dem":209,
    "gn:feature_class":"P",
    "gn:feature_code":"PPL",
    "gn:name":"Meore Gurdzemi",
    "gn:population":0,
    "gn:timezone":"Asia/Tbilisi",
    "iso:country":"GE",
    "name:kat_x_preferred":[
        "Meore Gurdzemi"
    ],
    "name:kat_x_variant":[
        "\u10db\u10d4\u10dd\u10e0\u10d4 \u10d2\u10e3\u10e0\u10eb\u10d4\u10db\u10d8"
    ],
    "wof:name":"Meore Gurdzemi",
    "wof:placetype":"locality"
},
  "geometry": {"coordinates":[42.24104000000001,42.4397],"type":"Point"}
}