{
  "type": "Feature",
  "properties": {
    "gn:admin1_code":"22",
    "gn:asciiname":"K'urt'a",
    "gn:country_code":"GE",
    "gn:dem":932,
    "gn:feature_class":"P",
    "gn:feature_code":"PPL",
    "gn:name":"K\u2019urt\u2019a",
    "gn:population":0,
    "gn:timezone":"Asia/Tbilisi",
    "iso:country":"GE",
    "wof:name":"K'urt'a",
    "wof:placetype":"locality"
},
  "geometry": {"coordinates":[43.95306,42.28653],"type":"Point"}
}