{
  "type": "Feature",
  "properties": {
    "gn:admin1_code":"66",
    "gn:asciiname":"Shua Bashi",
    "gn:country_code":"GE",
    "gn:dem":39,
    "gn:feature_class":"P",
    "gn:feature_code":"PPL",
    "gn:name":"Shua Bashi",
    "gn:population":0,
    "gn:timezone":"Asia/Tbilisi",
    "iso:country":"GE",
    "name:kat_x_preferred":[
        "Shua Bashi"
    ],
    "name:kat_x_variant":[
        "\u10e8\u10e3\u10d0 \u10d1\u10d0\u10e8\u10d8"
    ],
    "wof:name":"Shua Bashi",
    "wof:placetype":"locality"
},
  "geometry": {"coordinates":[42.49124000000001,42.14124],"type":"Point"}
}