{
  "type": "Feature",
  "properties": {
    "gn:admin1_code":"69",
    "gn:asciiname":"Buch'ukurt'a",
    "gn:country_code":"GE",
    "gn:dem":1634,
    "gn:feature_class":"P",
    "gn:feature_code":"PPL",
    "gn:name":"Buch\u2019ukurt\u2019a",
    "gn:population":0,
    "gn:timezone":"Asia/Tbilisi",
    "iso:country":"GE",
    "name:und_x_variant":[
        "Buchukurt-Kari",
        "Buch\u2019ukurt\u2019a"
    ],
    "wof:name":"Buch'ukurt'a",
    "wof:placetype":"locality"
},
  "geometry": {"coordinates":[44.89616,42.48439000000001],"type":"Point"}
}