{
  "type": "Feature",
  "properties": {
    "gn:admin1_code":"69",
    "gn:asciiname":"T'okht'a",
    "gn:country_code":"GE",
    "gn:dem":1462,
    "gn:feature_class":"P",
    "gn:feature_code":"PPL",
    "gn:name":"T\u2019okht\u2019a",
    "gn:population":0,
    "gn:timezone":"Asia/Tbilisi",
    "iso:country":"GE",
    "name:kat_x_preferred":[
        "T\u2019okht\u2019a"
    ],
    "name:und_x_variant":[
        "Sokhta",
        "Takhta"
    ],
    "wof:name":"T'okht'a",
    "wof:placetype":"locality"
},
  "geometry": {"coordinates":[44.55382,42.30702],"type":"Point"}
}