{
  "type": "Feature",
  "properties": {
    "gn:admin1_code":"71",
    "gn:asciiname":"Dzveli Abasha",
    "gn:country_code":"GE",
    "gn:dem":38,
    "gn:feature_class":"P",
    "gn:feature_code":"PPL",
    "gn:name":"Dzveli Abasha",
    "gn:population":0,
    "gn:timezone":"Asia/Tbilisi",
    "iso:country":"GE",
    "name:kat_x_preferred":[
        "\u10eb\u10d5\u10d4\u10da\u10d8 \u10d0\u10d1\u10d0\u10e8\u10d0"
    ],
    "wof:name":"Dzveli Abasha",
    "wof:placetype":"locality"
},
  "geometry": {"coordinates":[42.24667,42.23973],"type":"Point"}
}