{
  "type": "Feature",
  "properties": {
    "gn:admin1_code":"00",
    "gn:asciiname":"Prialoura",
    "gn:country_code":"GE",
    "gn:dem":491,
    "gn:feature_class":"P",
    "gn:feature_code":"PPL",
    "gn:name":"Prialoura",
    "gn:population":0,
    "gn:timezone":"Asia/Tbilisi",
    "iso:country":"GE",
    "wof:name":"Prialoura",
    "wof:placetype":"locality"
},
  "geometry": {"coordinates":[42.86667,42.38333],"type":"Point"}
}