{
  "type": "Feature",
  "properties": {
    "gn:admin1_code":"00",
    "gn:asciiname":"Dzhaparlo",
    "gn:country_code":"GE",
    "gn:dem":462,
    "gn:feature_class":"P",
    "gn:feature_code":"PPL",
    "gn:name":"Dzhaparlo",
    "gn:population":0,
    "gn:timezone":"Asia/Tbilisi",
    "iso:country":"GE",
    "name:und_x_variant":[
        "Dzhafarlo",
        "Dzhaparlo"
    ],
    "wof:name":"Dzhaparlo",
    "wof:placetype":"locality"
},
  "geometry": {"coordinates":[44.60764,41.4377],"type":"Point"}
}