{
  "type": "Feature",
  "properties": {
    "gn:admin1_code":"71",
    "gn:asciiname":"Nochkhoni",
    "gn:country_code":"GE",
    "gn:dem":7,
    "gn:feature_class":"P",
    "gn:feature_code":"PPL",
    "gn:name":"Nochkhoni",
    "gn:population":0,
    "gn:timezone":"Asia/Tbilisi",
    "iso:country":"GE",
    "name:kat_x_preferred":[
        "\u10dc\u10dd\u10e9\u10ee\u10dd\u10dc\u10d8"
    ],
    "wof:name":"Nochkhoni",
    "wof:placetype":"locality"
},
  "geometry": {"coordinates":[41.81722,42.35356],"type":"Point"}
}