{
  "type": "Feature",
  "properties": {
    "gn:admin1_code":"02",
    "gn:asciiname":"Dep'egindze",
    "gn:country_code":"GE",
    "gn:dem":202,
    "gn:feature_class":"P",
    "gn:feature_code":"PPL",
    "gn:name":"Dep\u2019egindze",
    "gn:population":0,
    "gn:timezone":"Asia/Tbilisi",
    "iso:country":"GE",
    "name:kat_x_preferred":[
        "Dep\u2019egindze"
    ],
    "name:kat_x_variant":[
        "\u10d3\u10d4\u10de\u10d4\u10d2\u10d8\u10dc\u10eb\u10d4"
    ],
    "wof:name":"Dep'egindze",
    "wof:placetype":"locality"
},
  "geometry": {"coordinates":[41.31306,42.91194],"type":"Point"}
}