{
  "type": "Feature",
  "properties": {
    "gn:admin1_code":"00",
    "gn:asciiname":"K'ariani",
    "gn:country_code":"GE",
    "gn:dem":1476,
    "gn:feature_class":"P",
    "gn:feature_code":"PPL",
    "gn:name":"K\u2019ariani",
    "gn:population":0,
    "gn:timezone":"Asia/Tbilisi",
    "iso:country":"GE",
    "name:und_x_variant":[
        "Busukala",
        "K\u2019ariani"
    ],
    "wof:name":"K'ariani",
    "wof:placetype":"locality"
},
  "geometry": {"coordinates":[44.1268,41.36545],"type":"Point"}
}