{
  "type": "Feature",
  "properties": {
    "gn:admin1_code":"00",
    "gn:asciiname":"Natbeuri",
    "gn:country_code":"GE",
    "gn:dem":1442,
    "gn:feature_class":"P",
    "gn:feature_code":"PPL",
    "gn:name":"Natbeuri",
    "gn:population":0,
    "gn:timezone":"Asia/Tbilisi",
    "iso:country":"GE",
    "wof:name":"Natbeuri",
    "wof:placetype":"locality"
},
  "geometry": {"coordinates":[44.51139000000001,41.78333],"type":"Point"}
}