{
  "type": "Feature",
  "properties": {
    "gn:admin1_code":"69",
    "gn:asciiname":"Bodorna",
    "gn:country_code":"GE",
    "gn:dem":726,
    "gn:feature_class":"P",
    "gn:feature_code":"PPL",
    "gn:name":"Bodorna",
    "gn:population":0,
    "gn:timezone":"Asia/Tbilisi",
    "iso:country":"GE",
    "name:che_x_preferred":[
        "\u0411\u043e\u0434\u043e\u0440\u043d\u0430"
    ],
    "name:fin_x_preferred":[
        "Bodorna"
    ],
    "name:hye_x_preferred":[
        "\u0532\u0578\u0564\u0578\u0580\u0576\u0561"
    ],
    "name:kat_x_preferred":[
        "\u10d1\u10dd\u10d3\u10dd\u10e0\u10dc\u10d0"
    ],
    "name:nld_x_preferred":[
        "Bodorna"
    ],
    "name:und_x_variant":[
        "Vodorna",
        "Bodorna"
    ],
    "wof:name":"Bodorna",
    "wof:placetype":"locality"
},
  "geometry": {"coordinates":[44.74256,42.05421],"type":"Point"}
}