{
  "type": "Feature",
  "properties": {
    "gn:admin1_code":"71",
    "gn:asciiname":"Lekhaindravo",
    "gn:country_code":"GE",
    "gn:dem":115,
    "gn:feature_class":"P",
    "gn:feature_code":"PPL",
    "gn:name":"Lekhaindravo",
    "gn:population":0,
    "gn:timezone":"Asia/Tbilisi",
    "iso:country":"GE",
    "name:kat_x_preferred":[
        "\u10da\u10d4\u10ee\u10d0\u10d8\u10dc\u10d3\u10e0\u10d0\u10d5\u10dd"
    ],
    "name:und_x_variant":[
        "Lekhaindrao",
        "Lekhaindravo"
    ],
    "wof:name":"Lekhaindravo",
    "wof:placetype":"locality"
},
  "geometry": {"coordinates":[42.33246,42.35298],"type":"Point"}
}