{
  "type": "Feature",
  "properties": {
    "gn:admin1_code":"65",
    "gn:asciiname":"Jikhanjiri",
    "gn:country_code":"GE",
    "gn:dem":61,
    "gn:feature_class":"P",
    "gn:feature_code":"PPL",
    "gn:name":"Jikhanjiri",
    "gn:population":0,
    "gn:timezone":"Asia/Tbilisi",
    "iso:country":"GE",
    "name:kat_x_preferred":[
        "Jikhanjiri"
    ],
    "name:kat_x_variant":[
        "\u10ef\u10d8\u10ee\u10d0\u10dc\u10ef\u10d8\u10e0\u10d8"
    ],
    "name:rus_x_preferred":[
        "\u0414\u0436\u0438\u0445\u0430\u043d\u0434\u0436\u0438\u0440\u0438"
    ],
    "name:und_x_variant":[
        "Dzhikhandzhiri"
    ],
    "wof:name":"Jikhanjiri",
    "wof:placetype":"locality"
},
  "geometry": {"coordinates":[41.87898,42.04435],"type":"Point"}
}