{
  "type": "Feature",
  "properties": {
    "gn:admin1_code":"73",
    "gn:asciiname":"Tsablovana",
    "gn:country_code":"GE",
    "gn:dem":818,
    "gn:feature_class":"P",
    "gn:feature_code":"PPL",
    "gn:name":"Tsablovana",
    "gn:population":0,
    "gn:timezone":"Asia/Tbilisi",
    "iso:country":"GE",
    "name:kat_x_preferred":[
        "\u10ea\u10d0\u10d1\u10da\u10dd\u10d5\u10d0\u10dc\u10d0"
    ],
    "name:rus_x_preferred":[
        "\u0426\u0430\u0431\u043b\u043e\u0432\u0430\u043d\u0430"
    ],
    "name:und_x_variant":[
        "Tsablovani",
        "Tsablovana"
    ],
    "wof:name":"Tsablovana",
    "wof:placetype":"locality"
},
  "geometry": {"coordinates":[43.58795,42.0637],"type":"Point"}
}