{
  "type": "Feature",
  "properties": {
    "gn:admin1_code":"00",
    "gn:asciiname":"Shekouli",
    "gn:country_code":"GE",
    "gn:dem":1042,
    "gn:feature_class":"P",
    "gn:feature_code":"PPL",
    "gn:name":"Shekouli",
    "gn:population":0,
    "gn:timezone":"Asia/Tbilisi",
    "iso:country":"GE",
    "wof:name":"Shekouli",
    "wof:placetype":"locality"
},
  "geometry": {"coordinates":[43.54806,42.29306],"type":"Point"}
}