{
  "type": "Feature",
  "properties": {
    "gn:admin1_code":"71",
    "gn:asciiname":"Lek'obale",
    "gn:country_code":"GE",
    "gn:dem":357,
    "gn:feature_class":"P",
    "gn:feature_code":"PPL",
    "gn:name":"Lek\u2019obale",
    "gn:population":0,
    "gn:timezone":"Asia/Tbilisi",
    "iso:country":"GE",
    "name:kat_x_preferred":[
        "Lek\u2019obale"
    ],
    "name:kat_x_variant":[
        "\u10da\u10d4\u10e5\u10dd\u10d1\u10d0\u10da\u10d4"
    ],
    "wof:name":"Lek'obale",
    "wof:placetype":"locality"
},
  "geometry": {"coordinates":[42.25391,42.56157],"type":"Point"}
}