{
  "type": "Feature",
  "properties": {
    "gn:admin1_code":"00",
    "gn:asciiname":"Gorana",
    "gn:country_code":"GE",
    "gn:dem":1002,
    "gn:feature_class":"P",
    "gn:feature_code":"PPL",
    "gn:name":"Gorana",
    "gn:population":0,
    "gn:timezone":"Asia/Tbilisi",
    "iso:country":"GE",
    "name:ceb_x_preferred":[
        "Gorana"
    ],
    "name:swe_x_preferred":[
        "Gorana"
    ],
    "wof:name":"Gorana",
    "wof:placetype":"locality"
},
  "geometry": {"coordinates":[45.1093,41.87306],"type":"Point"}
}