{
  "type": "Feature",
  "properties": {
    "gn:admin1_code":"70",
    "gn:asciiname":"Nasp'eri",
    "gn:country_code":"GE",
    "gn:dem":912,
    "gn:feature_class":"P",
    "gn:feature_code":"PPL",
    "gn:name":"Nasp\u2019eri",
    "gn:population":0,
    "gn:timezone":"Asia/Tbilisi",
    "iso:country":"GE",
    "name:kat_x_preferred":[
        "Nasp\u2019eri"
    ],
    "name:kat_x_variant":[
        "\u10dc\u10d0\u10e1\u10de\u10d4\u10e0\u10d8"
    ],
    "wof:name":"Nasp'eri",
    "wof:placetype":"locality"
},
  "geometry": {"coordinates":[42.77187,42.59389],"type":"Point"}
}