{
  "type": "Feature",
  "properties": {
    "gn:admin1_code":"04",
    "gn:asciiname":"Mirveti",
    "gn:country_code":"GE",
    "gn:dem":47,
    "gn:feature_class":"P",
    "gn:feature_code":"PPL",
    "gn:name":"Mirveti",
    "gn:population":0,
    "gn:timezone":"Asia/Tbilisi",
    "iso:country":"GE",
    "name:kat_x_preferred":[
        "Mirveti"
    ],
    "name:kat_x_variant":[
        "\u10db\u10d8\u10e0\u10d5\u10d4\u10d7\u10d8"
    ],
    "wof:name":"Mirveti",
    "wof:placetype":"locality"
},
  "geometry": {"coordinates":[41.71829,41.53108],"type":"Point"}
}