{
  "type": "Feature",
  "properties": {
    "gn:admin1_code":"58",
    "gn:asciiname":"Ashkala",
    "gn:country_code":"GE",
    "gn:dem":1658,
    "gn:feature_class":"P",
    "gn:feature_code":"PPL",
    "gn:name":"Ashkala",
    "gn:population":0,
    "gn:timezone":"Asia/Tbilisi",
    "iso:country":"GE",
    "name:eng_x_preferred":[
        "Ashkala"
    ],
    "name:kat_x_preferred":[
        "\u10d0\u10e8\u10d9\u10d0\u10da\u10d0"
    ],
    "name:rus_x_preferred":[
        "\u0410\u0448\u043a\u0430\u043b\u0430"
    ],
    "wof:name":"Ashkala",
    "wof:placetype":"locality"
},
  "geometry": {"coordinates":[43.94472,41.64778],"type":"Point"}
}