{
  "type": "Feature",
  "properties": {
    "gn:admin1_code":"02",
    "gn:asciiname":"Akui",
    "gn:country_code":"GE",
    "gn:dem":509,
    "gn:feature_class":"P",
    "gn:feature_code":"PPL",
    "gn:name":"Akui",
    "gn:population":0,
    "gn:timezone":"Asia/Tbilisi",
    "iso:country":"GE",
    "wof:name":"Akui",
    "wof:placetype":"locality"
},
  "geometry": {"coordinates":[40.82917,43.10083],"type":"Point"}
}