{
  "type": "Feature",
  "properties": {
    "gn:admin1_code":"00",
    "gn:asciiname":"Dzhria",
    "gn:country_code":"GE",
    "gn:dem":1160,
    "gn:feature_class":"P",
    "gn:feature_code":"PPL",
    "gn:name":"Dzhria",
    "gn:population":0,
    "gn:timezone":"Asia/Tbilisi",
    "iso:country":"GE",
    "wof:name":"Dzhria",
    "wof:placetype":"locality"
},
  "geometry": {"coordinates":[43.93615,42.36175],"type":"Point"}
}