{
  "type": "Feature",
  "properties": {
    "gn:admin1_code":"66",
    "gn:asciiname":"Saghandzile",
    "gn:country_code":"GE",
    "gn:dem":555,
    "gn:feature_class":"P",
    "gn:feature_code":"PPL",
    "gn:name":"Saghandzile",
    "gn:population":0,
    "gn:timezone":"Asia/Tbilisi",
    "iso:country":"GE",
    "name:kat_x_preferred":[
        "\u10e1\u10d0\u10e6\u10d0\u10dc\u10eb\u10d8\u10da\u10d4"
    ],
    "name:kat_x_variant":[
        "Saghandzile"
    ],
    "name:und_x_variant":[
        "Sagandzile"
    ],
    "wof:name":"Saghandzile",
    "wof:placetype":"locality"
},
  "geometry": {"coordinates":[43.19545,41.99169000000001],"type":"Point"}
}