{
  "type": "Feature",
  "properties": {
    "gn:admin1_code":"71",
    "gn:asciiname":"Zhabeshi",
    "gn:country_code":"GE",
    "gn:dem":1641,
    "gn:feature_class":"P",
    "gn:feature_code":"PPL",
    "gn:name":"Zhabeshi",
    "gn:population":0,
    "gn:timezone":"Asia/Tbilisi",
    "iso:country":"GE",
    "name:kat_x_preferred":[
        "\u10df\u10d0\u10d1\u10d4\u10e8\u10d8"
    ],
    "name:und_x_variant":[
        "Kabeshi"
    ],
    "wof:name":"Zhabeshi",
    "wof:placetype":"locality"
},
  "geometry": {"coordinates":[42.86749,43.04682],"type":"Point"}
}