{
  "type": "Feature",
  "properties": {
    "gn:admin1_code":"02",
    "gn:asciiname":"Duripshi",
    "gn:country_code":"GE",
    "gn:dem":274,
    "gn:feature_class":"P",
    "gn:feature_code":"PPL",
    "gn:name":"Duripshi",
    "gn:population":0,
    "gn:timezone":"Asia/Tbilisi",
    "iso:country":"GE",
    "name:kat_x_preferred":[
        "\u10d3\u10e3\u10e0\u10d8\u10e4\u10e8\u10d8"
    ],
    "name:kat_x_variant":[
        "Duripshi"
    ],
    "name:und_x_variant":[
        "Duripsh"
    ],
    "wof:name":"Duripshi",
    "wof:placetype":"locality"
},
  "geometry": {"coordinates":[40.6308,43.20518],"type":"Point"}
}