{
  "type": "Feature",
  "properties": {
    "gn:admin1_code":"00",
    "gn:asciiname":"Mukhrovani",
    "gn:cc2":"GE",
    "gn:country_code":"GE",
    "gn:dem":875,
    "gn:feature_class":"P",
    "gn:feature_code":"PPL",
    "gn:name":"Mukhrovani",
    "gn:population":0,
    "gn:timezone":"Asia/Tbilisi",
    "iso:country":"GE",
    "name:nld_x_preferred":[
        "Moechrovani"
    ],
    "name:ukr_x_preferred":[
        "\u041c\u0443\u0445\u0440\u043e\u0432\u0430\u043d\u0456"
    ],
    "name:und_x_variant":[
        "Mukhrovan",
        "Mukhrovani"
    ],
    "wof:name":"Mukhrovani",
    "wof:placetype":"locality"
},
  "geometry": {"coordinates":[45.15,41.78333],"type":"Point"}
}