{
  "type": "Feature",
  "properties": {
    "gn:admin1_code":"69",
    "gn:asciiname":"Bedoni",
    "gn:country_code":"GE",
    "gn:dem":1345,
    "gn:feature_class":"P",
    "gn:feature_code":"PPL",
    "gn:name":"Bedoni",
    "gn:population":0,
    "gn:timezone":"Asia/Tbilisi",
    "iso:country":"GE",
    "name:kat_x_preferred":[
        "Bedoni"
    ],
    "wof:name":"Bedoni",
    "wof:placetype":"locality"
},
  "geometry": {"coordinates":[44.55,42.42972],"type":"Point"}
}