{
  "type": "Feature",
  "properties": {
    "gn:admin1_code":"70",
    "gn:asciiname":"Abano",
    "gn:country_code":"GE",
    "gn:dem":1746,
    "gn:feature_class":"P",
    "gn:feature_code":"PPL",
    "gn:name":"Abano",
    "gn:population":0,
    "gn:timezone":"Asia/Tbilisi",
    "iso:country":"GE",
    "name:ces_x_preferred":[
        "Abano"
    ],
    "name:deu_x_preferred":[
        "Abano"
    ],
    "name:fas_x_preferred":[
        "\u0622\u0628\u0627\u0646\u0648"
    ],
    "name:kat_x_preferred":[
        "\u10d0\u10d1\u10d0\u10dc\u10dd"
    ],
    "name:oss_x_preferred":[
        "\u0410\u0431\u0430\u043d\u0430"
    ],
    "name:por_x_preferred":[
        "Abano"
    ],
    "name:rus_x_preferred":[
        "\u0410\u0431\u0430\u043d\u043e"
    ],
    "name:sco_x_preferred":[
        "Abano"
    ],
    "name:ukr_x_preferred":[
        "\u0410\u0431\u0430\u043d\u043e"
    ],
    "wof:name":"Abano",
    "wof:placetype":"locality"
},
  "geometry": {"coordinates":[43.7625,42.52694],"type":"Point"}
}