{
  "type": "Feature",
  "properties": {
    "gn:admin1_code":"70",
    "gn:asciiname":"Abano",
    "gn:country_code":"GE",
    "gn:dem":1746,
    "gn:feature_class":"P",
    "gn:feature_code":"PPL",
    "gn:name":"Abano",
    "gn:population":0,
    "gn:timezone":"Asia/Tbilisi",
    "iso:country":"GE",
    "wof:name":"Abano",
    "wof:placetype":"locality"
},
  "geometry": {"coordinates":[43.7625,42.52694],"type":"Point"}
}