{
  "type": "Feature",
  "properties": {
    "gn:admin1_code":"02",
    "gn:asciiname":"Balani",
    "gn:country_code":"GE",
    "gn:dem":18,
    "gn:feature_class":"P",
    "gn:feature_code":"PPL",
    "gn:name":"Balani",
    "gn:population":0,
    "gn:timezone":"Asia/Tbilisi",
    "iso:country":"GE",
    "name:kat_x_preferred":[
        "Balani"
    ],
    "name:kat_x_variant":[
        "\u10d1\u10d0\u10da\u10d0\u10dc\u10d8"
    ],
    "name:und_x_variant":[
        "Balan"
    ],
    "wof:name":"Balani",
    "wof:placetype":"locality"
},
  "geometry": {"coordinates":[41.21552,42.80837],"type":"Point"}
}