{
  "type": "Feature",
  "properties": {
    "gn:admin1_code":"66",
    "gn:asciiname":"Zeindari",
    "gn:country_code":"GE",
    "gn:dem":97,
    "gn:feature_class":"P",
    "gn:feature_code":"PPL",
    "gn:name":"Zeindari",
    "gn:population":0,
    "gn:timezone":"Asia/Tbilisi",
    "iso:country":"GE",
    "name:eng_x_preferred":[
        "Zeindari"
    ],
    "name:kat_x_preferred":[
        "\u10d6\u10d4\u10d8\u10dc\u10d3\u10d0\u10e0\u10d8"
    ],
    "name:rus_x_preferred":[
        "\u0417\u0435\u0438\u043d\u0434\u0430\u0440\u0438"
    ],
    "wof:name":"Zeindari",
    "wof:placetype":"locality"
},
  "geometry": {"coordinates":[42.66859,42.09751],"type":"Point"}
}