{
  "type": "Feature",
  "properties": {
    "gn:admin1_code":"00",
    "gn:asciiname":"Bziskhevi",
    "gn:country_code":"GE",
    "gn:dem":900,
    "gn:feature_class":"P",
    "gn:feature_code":"PPL",
    "gn:name":"Bziskhevi",
    "gn:population":0,
    "gn:timezone":"Asia/Tbilisi",
    "iso:country":"GE",
    "wof:name":"Bziskhevi",
    "wof:placetype":"locality"
},
  "geometry": {"coordinates":[43.63292,42.21597],"type":"Point"}
}