{
  "type": "Feature",
  "properties": {
    "gn:admin1_code":"69",
    "gn:asciiname":"Kuchecha",
    "gn:country_code":"GE",
    "gn:dem":909,
    "gn:feature_class":"P",
    "gn:feature_code":"PPL",
    "gn:name":"Kuchecha",
    "gn:population":0,
    "gn:timezone":"Asia/Tbilisi",
    "iso:country":"GE",
    "wof:name":"Kuchecha",
    "wof:placetype":"locality"
},
  "geometry": {"coordinates":[44.86361,42.28],"type":"Point"}
}