{
  "type": "Feature",
  "properties": {
    "gn:admin1_code":"00",
    "gn:asciiname":"Rachisubani",
    "gn:country_code":"GE",
    "gn:dem":482,
    "gn:feature_class":"P",
    "gn:feature_code":"PPL",
    "gn:name":"Rachisubani",
    "gn:population":0,
    "gn:timezone":"Asia/Tbilisi",
    "iso:country":"GE",
    "wof:name":"Rachisubani",
    "wof:placetype":"locality"
},
  "geometry": {"coordinates":[44.5982,41.44784],"type":"Point"}
}