{
  "type": "Feature",
  "properties": {
    "gn:admin1_code":"00",
    "gn:asciiname":"Tedzhisi",
    "gn:country_code":"GE",
    "gn:dem":1736,
    "gn:feature_class":"P",
    "gn:feature_code":"PPL",
    "gn:name":"Tedzhisi",
    "gn:population":0,
    "gn:timezone":"Asia/Tbilisi",
    "iso:country":"GE",
    "wof:name":"Tedzhisi",
    "wof:placetype":"locality"
},
  "geometry": {"coordinates":[44.09318,41.69514],"type":"Point"}
}