{
  "type": "Feature",
  "properties": {
    "iso:country":"GE",
    "name:deu_x_preferred":[
        "Sioni"
    ],
    "name:eng_x_preferred":[
        "Sioni"
    ],
    "name:kat_x_preferred":[
        "Sioni"
    ],
    "name:rus_x_preferred":[
        "\u0421\u0438\u043e\u043d\u0438"
    ],
    "qs:gn_country":"GE",
    "qs:gn_fcode":"PPL",
    "qs:gn_pop":777,
    "qs:name":"Sioni",
    "qs:name_adm0":"Georgia",
    "qs:name_adm1":"Qazbegis Raioni",
    "qs:photos":91,
    "qs:photos_1k":18,
    "qs:photos_9k":1,
    "qs:photos_9r":3,
    "qs:photos_all":91,
    "qs:photos_sr":3,
    "qs:placetype":"Town",
    "qs:pop_sr":"5",
    "qs:woe_adm0":23424823,
    "wd:wordcount":67,
    "wof:name":"Sioni",
    "wof:placetype":"locality",
    "wof:population":777
},
  "geometry": {"coordinates":[44.58512,42.60799],"type":"Point"}
}