{
  "type": "Feature",
  "properties": {
    "gn:admin1_code":"00",
    "gn:asciiname":"Tliakana",
    "gn:country_code":"GE",
    "gn:dem":1539,
    "gn:feature_class":"P",
    "gn:feature_code":"PPL",
    "gn:name":"Tliakana",
    "gn:population":0,
    "gn:timezone":"Asia/Tbilisi",
    "iso:country":"GE",
    "name:und_x_variant":[
        "Tila-Kana",
        "Tliakana"
    ],
    "wof:name":"Tliakana",
    "wof:placetype":"locality"
},
  "geometry": {"coordinates":[44.0025,42.30395],"type":"Point"}
}