{
  "type": "Feature",
  "properties": {
    "gn:admin1_code":"69",
    "gn:asciiname":"At'nokhi",
    "gn:country_code":"GE",
    "gn:dem":1593,
    "gn:feature_class":"P",
    "gn:feature_code":"PPL",
    "gn:name":"At\u2019nokhi",
    "gn:population":0,
    "gn:timezone":"Asia/Tbilisi",
    "iso:country":"GE",
    "wof:name":"At'nokhi",
    "wof:placetype":"locality"
},
  "geometry": {"coordinates":[44.7061,42.45837],"type":"Point"}
}