{
  "type": "Feature",
  "properties": {
    "gn:admin1_code":"00",
    "gn:asciiname":"Baytalo",
    "gn:country_code":"GE",
    "gn:dem":360,
    "gn:feature_class":"P",
    "gn:feature_code":"PPL",
    "gn:name":"Baytalo",
    "gn:population":0,
    "gn:timezone":"Asia/Tbilisi",
    "iso:country":"GE",
    "name:kat_x_preferred":[
        "\u10d1\u10d0\u10d8\u10d7\u10d0\u10da\u10dd"
    ],
    "name:und_x_variant":[
        "Baytelo",
        "Baytalo"
    ],
    "wof:name":"Baytalo",
    "wof:placetype":"locality"
},
  "geometry": {"coordinates":[44.84252,41.32558],"type":"Point"}
}