{
  "type": "Feature",
  "properties": {
    "gn:admin1_code":"00",
    "gn:asciiname":"Bochorishvilebi",
    "gn:country_code":"GE",
    "gn:dem":851,
    "gn:feature_class":"P",
    "gn:feature_code":"PPL",
    "gn:name":"Bochorishvilebi",
    "gn:population":0,
    "gn:timezone":"Asia/Tbilisi",
    "iso:country":"GE",
    "wof:name":"Bochorishvilebi",
    "wof:placetype":"locality"
},
  "geometry": {"coordinates":[43.11139,42.34],"type":"Point"}
}