{
  "type": "Feature",
  "properties": {
    "gn:admin1_code":"66",
    "gn:asciiname":"Q'umuri",
    "gn:country_code":"GE",
    "gn:dem":240,
    "gn:feature_class":"P",
    "gn:feature_code":"PPL",
    "gn:name":"Q\u2019umuri",
    "gn:population":0,
    "gn:timezone":"Asia/Tbilisi",
    "iso:country":"GE",
    "name:kat_x_preferred":[
        "Q\u2019umuri"
    ],
    "name:kat_x_variant":[
        "\u10e7\u10e3\u10db\u10e3\u10e0\u10d8"
    ],
    "name:und_x_variant":[
        "Kumuri"
    ],
    "wof:name":"Q'umuri",
    "wof:placetype":"locality"
},
  "geometry": {"coordinates":[42.46917,42.03389],"type":"Point"}
}