{
  "type": "Feature",
  "properties": {
    "gn:admin1_code":"00",
    "gn:asciiname":"Elontkau",
    "gn:country_code":"GE",
    "gn:dem":1536,
    "gn:feature_class":"P",
    "gn:feature_code":"PPL",
    "gn:name":"Elontkau",
    "gn:population":0,
    "gn:timezone":"Asia/Tbilisi",
    "iso:country":"GE",
    "wof:name":"Elontkau",
    "wof:placetype":"locality"
},
  "geometry": {"coordinates":[44.11667,42.55],"type":"Point"}
}