{
  "type": "Feature",
  "properties": {
    "gn:admin1_code":"69",
    "gn:asciiname":"Chalisop'eli",
    "gn:country_code":"GE",
    "gn:dem":1724,
    "gn:feature_class":"P",
    "gn:feature_code":"PPL",
    "gn:name":"Chalisop\u2019eli",
    "gn:population":0,
    "gn:timezone":"Asia/Tbilisi",
    "iso:country":"GE",
    "name:kat_x_preferred":[
        "\u10ed\u10d0\u10da\u10d8\u10e1\u10dd\u10e4\u10d4\u10da\u10d8"
    ],
    "name:und_x_variant":[
        "Chalis-Sopeli",
        "Chalisop\u2019eli"
    ],
    "wof:name":"Chalisop'eli",
    "wof:placetype":"locality"
},
  "geometry": {"coordinates":[44.98193,42.50281],"type":"Point"}
}