{
  "type": "Feature",
  "properties": {
    "gn:admin1_code":"02",
    "gn:asciiname":"Attarkhabla",
    "gn:country_code":"GE",
    "gn:dem":228,
    "gn:feature_class":"P",
    "gn:feature_code":"PPL",
    "gn:name":"Attarkhabla",
    "gn:population":0,
    "gn:timezone":"Asia/Tbilisi",
    "iso:country":"GE",
    "name:und_x_variant":[
        "Ashir-Khobla",
        "Attarkhabla"
    ],
    "wof:name":"Attarkhabla",
    "wof:placetype":"locality"
},
  "geometry": {"coordinates":[40.63611,43.18639],"type":"Point"}
}