{
  "type": "Feature",
  "properties": {
    "gn:admin1_code":"00",
    "gn:asciiname":"Charekauli",
    "gn:country_code":"GE",
    "gn:dem":744,
    "gn:feature_class":"P",
    "gn:feature_code":"PPL",
    "gn:name":"Charekauli",
    "gn:population":0,
    "gn:timezone":"Asia/Tbilisi",
    "iso:country":"GE",
    "name:kat_x_preferred":[
        "\u10e9\u10d0\u10e0\u10d4\u10e5\u10d0\u10e3\u10da\u10d8"
    ],
    "name:und_x_variant":[
        "Charkauli",
        "Charekauli"
    ],
    "wof:name":"Charekauli",
    "wof:placetype":"locality"
},
  "geometry": {"coordinates":[45.31796,41.95257],"type":"Point"}
}