{
  "type": "Feature",
  "properties": {
    "gn:admin1_code":"71",
    "gn:asciiname":"Narazeni",
    "gn:country_code":"GE",
    "gn:dem":89,
    "gn:feature_class":"P",
    "gn:feature_code":"PPL",
    "gn:name":"Narazeni",
    "gn:population":0,
    "gn:timezone":"Asia/Tbilisi",
    "iso:country":"GE",
    "name:che_x_preferred":[
        "\u041d\u0430\u0440\u0430\u0437\u0435\u043d\u0438"
    ],
    "name:hye_x_preferred":[
        "\u0546\u0561\u0580\u0561\u0566\u0565\u0576"
    ],
    "name:kat_x_preferred":[
        "Narazeni"
    ],
    "name:kat_x_variant":[
        "\u10dc\u10d0\u10e0\u10d0\u10d6\u10d4\u10dc\u10d8"
    ],
    "name:rus_x_preferred":[
        "\u041d\u0430\u0440\u0430\u0437\u0435\u043d\u0438"
    ],
    "name:xmf_x_preferred":[
        "\u10dc\u10d0\u10e0\u10d0\u10d6\u10d4\u10dc\u10d8"
    ],
    "wof:name":"Narazeni",
    "wof:placetype":"locality"
},
  "geometry": {"coordinates":[41.9228,42.39267],"type":"Point"}
}