{
  "type": "Feature",
  "properties": {
    "gn:admin1_code":"00",
    "gn:asciiname":"Kadagali",
    "gn:country_code":"GE",
    "gn:dem":403,
    "gn:feature_class":"P",
    "gn:feature_code":"PPL",
    "gn:name":"Kadagali",
    "gn:population":0,
    "gn:timezone":"Asia/Tbilisi",
    "iso:country":"GE",
    "wof:name":"Kadagali",
    "wof:placetype":"locality"
},
  "geometry": {"coordinates":[41.95972,42.69917],"type":"Point"}
}