{
  "type": "Feature",
  "properties": {
    "gn:admin1_code":"66",
    "gn:asciiname":"Chashleti",
    "gn:country_code":"GE",
    "gn:dem":600,
    "gn:feature_class":"P",
    "gn:feature_code":"PPL",
    "gn:name":"Chashleti",
    "gn:population":0,
    "gn:timezone":"Asia/Tbilisi",
    "iso:country":"GE",
    "name:kat_x_preferred":[
        "\u10ed\u10d0\u10e8\u10da\u10d4\u10d7\u10d8"
    ],
    "name:und_x_variant":[
        "Chasleti",
        "Chashleti"
    ],
    "wof:name":"Chashleti",
    "wof:placetype":"locality"
},
  "geometry": {"coordinates":[42.79543,42.44651],"type":"Point"}
}