{
  "type": "Feature",
  "properties": {
    "gn:admin1_code":"69",
    "gn:asciiname":"Zemo Na'kalak'ari",
    "gn:country_code":"GE",
    "gn:dem":1105,
    "gn:feature_class":"P",
    "gn:feature_code":"PPL",
    "gn:name":"Zemo Na\u2019kalak\u2019ari",
    "gn:population":0,
    "gn:timezone":"Asia/Tbilisi",
    "iso:country":"GE",
    "name:und_x_variant":[
        "Nakalakari",
        "Verkhniye Nakalakari",
        "Zemo Na\u2019kalak\u2019ari"
    ],
    "wof:name":"Zemo Na'kalak'ari",
    "wof:placetype":"locality"
},
  "geometry": {"coordinates":[45.01416,41.93722],"type":"Point"}
}