{
  "type": "Feature",
  "properties": {
    "gn:admin1_code":"00",
    "gn:asciiname":"Etseri",
    "gn:country_code":"GE",
    "gn:dem":40,
    "gn:feature_class":"P",
    "gn:feature_code":"PPL",
    "gn:name":"Etseri",
    "gn:population":0,
    "gn:timezone":"Asia/Tbilisi",
    "iso:country":"GE",
    "wof:name":"Etseri",
    "wof:placetype":"locality"
},
  "geometry": {"coordinates":[41.54556,42.73694],"type":"Point"}
}