{
  "type": "Feature",
  "properties": {
    "gn:admin1_code":"71",
    "gn:asciiname":"Alert'i",
    "gn:country_code":"GE",
    "gn:dem":194,
    "gn:feature_class":"P",
    "gn:feature_code":"PPL",
    "gn:name":"Alert\u2019i",
    "gn:population":0,
    "gn:timezone":"Asia/Tbilisi",
    "iso:country":"GE",
    "name:kat_x_preferred":[
        "Alert\u2019i"
    ],
    "name:kat_x_variant":[
        "\u10d0\u10da\u10d4\u10e0\u10e2\u10d8"
    ],
    "wof:name":"Alert'i",
    "wof:placetype":"locality"
},
  "geometry": {"coordinates":[42.20377,42.44685],"type":"Point"}
}