{
  "type": "Feature",
  "properties": {
    "gn:admin1_code":"71",
    "gn:asciiname":"Khabume",
    "gn:country_code":"GE",
    "gn:dem":213,
    "gn:feature_class":"P",
    "gn:feature_code":"PPL",
    "gn:name":"Khabume",
    "gn:population":0,
    "gn:timezone":"Asia/Tbilisi",
    "iso:country":"GE",
    "name:eng_x_preferred":[
        "Khabume"
    ],
    "name:kat_x_preferred":[
        "\u10ee\u10d0\u10d1\u10e3\u10db\u10d4"
    ],
    "name:rus_x_preferred":[
        "\u0425\u0430\u0431\u0443\u043c\u0435"
    ],
    "wof:name":"Khabume",
    "wof:placetype":"locality"
},
  "geometry": {"coordinates":[42.15924,42.56925],"type":"Point"}
}