{
  "type": "Feature",
  "properties": {
    "gn:admin1_code":"02",
    "gn:asciiname":"Amzara",
    "gn:country_code":"GE",
    "gn:dem":234,
    "gn:feature_class":"P",
    "gn:feature_code":"PPL",
    "gn:name":"Amzara",
    "gn:population":0,
    "gn:timezone":"Asia/Tbilisi",
    "iso:country":"GE",
    "name:kat_x_preferred":[
        "\u10d0\u10db\u10d6\u10d0\u10e0\u10d0"
    ],
    "name:kat_x_variant":[
        "Amzara"
    ],
    "wof:name":"Amzara",
    "wof:placetype":"locality"
},
  "geometry": {"coordinates":[40.99912,43.08896],"type":"Point"}
}