{
  "type": "Feature",
  "properties": {
    "gn:admin1_code":"72",
    "gn:asciiname":"Gorelovka",
    "gn:country_code":"GE",
    "gn:dem":2054,
    "gn:feature_class":"P",
    "gn:feature_code":"PPL",
    "gn:name":"Gorelovka",
    "gn:population":700,
    "gn:timezone":"Asia/Tbilisi",
    "iso:country":"GE",
    "name:kat_x_preferred":[
        "\u10d2\u10e0\u10dd\u10d4\u10da\u10dd\u10d5\u10d9\u10d0"
    ],
    "name:und_x_variant":[
        "Goryelovka",
        "Goreloye",
        "Gorelovka"
    ],
    "wof:name":"Gorelovka",
    "wof:placetype":"locality",
    "wof:population":700
},
  "geometry": {"coordinates":[43.69313,41.21725],"type":"Point"}
}