{
  "type": "Feature",
  "properties": {
    "gn:admin1_code":"02",
    "gn:asciiname":"Kvemo Ts'q'aro",
    "gn:country_code":"GE",
    "gn:dem":520,
    "gn:feature_class":"P",
    "gn:feature_code":"PPL",
    "gn:name":"Kvemo Ts\u2019q\u2019aro",
    "gn:population":0,
    "gn:timezone":"Asia/Tbilisi",
    "iso:country":"GE",
    "name:kat_x_preferred":[
        "\u10e5\u10d5\u10d4\u10db\u10dd \u10ec\u10e7\u10d0\u10e0\u10dd"
    ],
    "name:kat_x_variant":[
        "Kvemo Ts\u2019q\u2019aro"
    ],
    "name:und_x_variant":[
        "Kvemo-Tskaro",
        "Kvemo Lemsa"
    ],
    "wof:name":"Kvemo Ts'q'aro",
    "wof:placetype":"locality"
},
  "geometry": {"coordinates":[41.26694000000001,43.03171],"type":"Point"}
}