{
  "type": "Feature",
  "properties": {
    "gn:admin1_code":"69",
    "gn:asciiname":"Tsikhisdziri",
    "gn:country_code":"GE",
    "gn:dem":1354,
    "gn:feature_class":"P",
    "gn:feature_code":"PPL",
    "gn:name":"Tsikhisdziri",
    "gn:population":0,
    "gn:timezone":"Asia/Tbilisi",
    "iso:country":"GE",
    "wof:name":"Tsikhisdziri",
    "wof:placetype":"locality"
},
  "geometry": {"coordinates":[44.59417,42.15806],"type":"Point"}
}