{
  "type": "Feature",
  "properties": {
    "gn:admin1_code":"72",
    "gn:asciiname":"Sadgeri",
    "gn:country_code":"GE",
    "gn:dem":1031,
    "gn:feature_class":"P",
    "gn:feature_code":"PPL",
    "gn:name":"Sadgeri",
    "gn:population":0,
    "gn:timezone":"Asia/Tbilisi",
    "iso:country":"GE",
    "name:kat_x_preferred":[
        "Sadgeri"
    ],
    "name:kat_x_variant":[
        "\u10e1\u10d0\u10d3\u10d2\u10d4\u10e0\u10d8"
    ],
    "wof:name":"Sadgeri",
    "wof:placetype":"locality"
},
  "geometry": {"coordinates":[43.41438,41.809],"type":"Point"}
}