{
  "type": "Feature",
  "properties": {
    "gn:admin1_code":"69",
    "gn:asciiname":"Lap'anaant'kari",
    "gn:country_code":"GE",
    "gn:dem":882,
    "gn:feature_class":"P",
    "gn:feature_code":"PPL",
    "gn:name":"Lap\u2019anaant\u2019kari",
    "gn:population":0,
    "gn:timezone":"Asia/Tbilisi",
    "iso:country":"GE",
    "wof:name":"Lap'anaant'kari",
    "wof:placetype":"locality"
},
  "geometry": {"coordinates":[44.80154,42.00972],"type":"Point"}
}