{
  "type": "Feature",
  "properties": {
    "gn:admin1_code":"69",
    "gn:asciiname":"Zhozhoni",
    "gn:country_code":"GE",
    "gn:dem":1394,
    "gn:feature_class":"P",
    "gn:feature_code":"PPL",
    "gn:name":"Zhozhoni",
    "gn:population":0,
    "gn:timezone":"Asia/Tbilisi",
    "iso:country":"GE",
    "name:kat_x_preferred":[
        "Zhozhoni"
    ],
    "name:und_x_variant":[
        "Zhizhoyani",
        "Zhizhoni"
    ],
    "wof:name":"Zhozhoni",
    "wof:placetype":"locality"
},
  "geometry": {"coordinates":[44.68093,42.38726],"type":"Point"}
}