{
  "type": "Feature",
  "properties": {
    "gn:admin1_code":"00",
    "gn:asciiname":"Gorgasheni",
    "gn:country_code":"GE",
    "gn:dem":1008,
    "gn:feature_class":"P",
    "gn:feature_code":"PPL",
    "gn:name":"Gorgasheni",
    "gn:population":0,
    "gn:timezone":"Asia/Tbilisi",
    "iso:country":"GE",
    "wof:name":"Gorgasheni",
    "wof:placetype":"locality"
},
  "geometry": {"coordinates":[44.45472,42.0575],"type":"Point"}
}