{
  "type": "Feature",
  "properties": {
    "gn:admin1_code":"71",
    "gn:asciiname":"K'ortskheli",
    "gn:country_code":"GE",
    "gn:dem":313,
    "gn:feature_class":"P",
    "gn:feature_code":"PPL",
    "gn:name":"K\u2019ortskheli",
    "gn:population":0,
    "gn:timezone":"Asia/Tbilisi",
    "iso:country":"GE",
    "name:kat_x_preferred":[
        "K\u2019ortskheli"
    ],
    "name:kat_x_variant":[
        "\u10d9\u10dd\u10e0\u10ea\u10ee\u10d4\u10da\u10d8"
    ],
    "wof:name":"K'ortskheli",
    "wof:placetype":"locality"
},
  "geometry": {"coordinates":[41.94387,42.56096],"type":"Point"}
}