{
  "type": "Feature",
  "properties": {
    "gn:admin1_code":"69",
    "gn:asciiname":"Kvemo-Mna",
    "gn:country_code":"GE",
    "gn:dem":2122,
    "gn:feature_class":"P",
    "gn:feature_code":"PPL",
    "gn:name":"Kvemo-Mna",
    "gn:population":0,
    "gn:timezone":"Asia/Tbilisi",
    "iso:country":"GE",
    "name:und_x_variant":[
        "Nizhnyaya Mna",
        "Kvemo-Mna"
    ],
    "wof:name":"Kvemo-Mna",
    "wof:placetype":"locality"
},
  "geometry": {"coordinates":[44.44843,42.59006],"type":"Point"}
}