{
  "type": "Feature",
  "properties": {
    "gn:admin1_code":"69",
    "gn:asciiname":"Galavani",
    "gn:country_code":"GE",
    "gn:dem":721,
    "gn:feature_class":"P",
    "gn:feature_code":"PPL",
    "gn:name":"Galavani",
    "gn:population":0,
    "gn:timezone":"Asia/Tbilisi",
    "iso:country":"GE",
    "name:kat_x_preferred":[
        "Galavani"
    ],
    "name:und_x_variant":[
        "Golovani"
    ],
    "wof:name":"Galavani",
    "wof:placetype":"locality"
},
  "geometry": {"coordinates":[44.815,41.91306],"type":"Point"}
}