{
  "type": "Feature",
  "properties": {
    "gn:admin1_code":"72",
    "gn:asciiname":"Zanavi",
    "gn:country_code":"GE",
    "gn:dem":801,
    "gn:feature_class":"P",
    "gn:feature_code":"PPL",
    "gn:name":"Zanavi",
    "gn:population":0,
    "gn:timezone":"Asia/Tbilisi",
    "iso:country":"GE",
    "name:kat_x_preferred":[
        "Zanavi"
    ],
    "name:kat_x_variant":[
        "\u10d6\u10d0\u10dc\u10d0\u10d5\u10d8"
    ],
    "wof:name":"Zanavi",
    "wof:placetype":"locality"
},
  "geometry": {"coordinates":[43.43167,41.89271],"type":"Point"}
}