{
  "type": "Feature",
  "properties": {
    "gn:admin1_code":"02",
    "gn:asciiname":"Kvaloni",
    "gn:country_code":"GE",
    "gn:dem":740,
    "gn:feature_class":"P",
    "gn:feature_code":"PPL",
    "gn:name":"Kvaloni",
    "gn:population":0,
    "gn:timezone":"Asia/Tbilisi",
    "iso:country":"GE",
    "name:kat_x_preferred":[
        "\u10e5\u10d5\u10d0\u10da\u10dd\u10dc\u10d8"
    ],
    "name:kat_x_variant":[
        "Kvaloni"
    ],
    "wof:name":"Kvaloni",
    "wof:placetype":"locality"
},
  "geometry": {"coordinates":[41.09973,43.12407],"type":"Point"}
}