{
  "type": "Feature",
  "properties": {
    "gn:admin1_code":"69",
    "gn:asciiname":"Akhali Kadoyeti",
    "gn:country_code":"GE",
    "gn:dem":808,
    "gn:feature_class":"P",
    "gn:feature_code":"PPL",
    "gn:name":"Akhali Kadoyeti",
    "gn:population":0,
    "gn:timezone":"Asia/Tbilisi",
    "iso:country":"GE",
    "wof:name":"Akhali Kadoyeti",
    "wof:placetype":"locality"
},
  "geometry": {"coordinates":[44.57556,42.005],"type":"Point"}
}