{
  "type": "Feature",
  "properties": {
    "gn:admin1_code":"69",
    "gn:asciiname":"Giorgitsminda",
    "gn:country_code":"GE",
    "gn:dem":1979,
    "gn:feature_class":"P",
    "gn:feature_code":"PPL",
    "gn:name":"Giorgitsminda",
    "gn:population":0,
    "gn:timezone":"Asia/Tbilisi",
    "iso:country":"GE",
    "wof:name":"Giorgitsminda",
    "wof:placetype":"locality"
},
  "geometry": {"coordinates":[45.10788,42.64028],"type":"Point"}
}