{
  "type": "Feature",
  "properties": {
    "gn:admin1_code":"69",
    "gn:asciiname":"Akhalts'ikhe",
    "gn:country_code":"GE",
    "gn:dem":977,
    "gn:feature_class":"P",
    "gn:feature_code":"PPL",
    "gn:name":"Akhalts\u2019ikhe",
    "gn:population":0,
    "gn:timezone":"Asia/Tbilisi",
    "iso:country":"GE",
    "wof:name":"Akhalts'ikhe",
    "wof:placetype":"locality"
},
  "geometry": {"coordinates":[44.78667,42.08083],"type":"Point"}
}