{
  "type": "Feature",
  "properties": {
    "gn:admin1_code":"65",
    "gn:asciiname":"T'obakhcha",
    "gn:country_code":"GE",
    "gn:dem":624,
    "gn:feature_class":"P",
    "gn:feature_code":"PPL",
    "gn:name":"T\u2019obakhcha",
    "gn:population":0,
    "gn:timezone":"Asia/Tbilisi",
    "iso:country":"GE",
    "name:kat_x_preferred":[
        "T\u2019obakhcha"
    ],
    "name:kat_x_variant":[
        "\u10e2\u10dd\u10d1\u10d0\u10ee\u10e9\u10d0"
    ],
    "name:und_x_variant":[
        "Tobakhcha-Tavsurebi",
        "Tobakhcho"
    ],
    "wof:name":"T'obakhcha",
    "wof:placetype":"locality"
},
  "geometry": {"coordinates":[42.48558,41.9466],"type":"Point"}
}