{
  "type": "Feature",
  "properties": {
    "gn:admin1_code":"00",
    "gn:asciiname":"Purashi",
    "gn:country_code":"GE",
    "gn:dem":662,
    "gn:feature_class":"P",
    "gn:feature_code":"PPL",
    "gn:name":"Purashi",
    "gn:population":0,
    "gn:timezone":"Asia/Tbilisi",
    "iso:country":"GE",
    "wof:name":"Purashi",
    "wof:placetype":"locality"
},
  "geometry": {"coordinates":[42.01954,42.76509],"type":"Point"}
}