{
  "type": "Feature",
  "properties": {
    "gn:admin1_code":"71",
    "gn:asciiname":"Satskhvit'ao",
    "gn:country_code":"GE",
    "gn:dem":86,
    "gn:feature_class":"P",
    "gn:feature_code":"PPL",
    "gn:name":"Satskhvit\u2019ao",
    "gn:population":0,
    "gn:timezone":"Asia/Tbilisi",
    "iso:country":"GE",
    "name:kat_x_preferred":[
        "Satskhvit\u2019ao"
    ],
    "name:kat_x_variant":[
        "\u10e1\u10d0\u10ea\u10ee\u10d5\u10d8\u10e2\u10d0\u10dd"
    ],
    "wof:name":"Satskhvit'ao",
    "wof:placetype":"locality"
},
  "geometry": {"coordinates":[42.08534,42.33794],"type":"Point"}
}