{
  "type": "Feature",
  "properties": {
    "gn:admin1_code":"02",
    "gn:asciiname":"Agudzera",
    "gn:country_code":"GE",
    "gn:dem":7,
    "gn:feature_class":"P",
    "gn:feature_code":"PPL",
    "gn:name":"Agudzera",
    "gn:population":0,
    "gn:timezone":"Asia/Tbilisi",
    "iso:country":"GE",
    "name:und_x_variant":[
        "Agudzery",
        "Agudzera"
    ],
    "wof:name":"Agudzera",
    "wof:placetype":"locality"
},
  "geometry": {"coordinates":[41.09954000000001,42.92038],"type":"Point"}
}