{
  "type": "Feature",
  "properties": {
    "gn:admin1_code":"02",
    "gn:asciiname":"Mukhuri",
    "gn:country_code":"GE",
    "gn:dem":94,
    "gn:feature_class":"P",
    "gn:feature_code":"PPL",
    "gn:name":"Mukhuri",
    "gn:population":0,
    "gn:timezone":"Asia/Tbilisi",
    "iso:country":"GE",
    "name:kat_x_preferred":[
        "Mukhuri"
    ],
    "name:kat_x_variant":[
        "\u10db\u10e3\u10ee\u10e3\u10e0\u10d8"
    ],
    "wof:name":"Mukhuri",
    "wof:placetype":"locality"
},
  "geometry": {"coordinates":[41.69978,42.69109],"type":"Point"}
}