{
  "type": "Feature",
  "properties": {
    "gn:admin1_code":"02",
    "gn:asciiname":"Suni",
    "gn:country_code":"GE",
    "gn:dem":8,
    "gn:feature_class":"P",
    "gn:feature_code":"PPL",
    "gn:name":"Suni",
    "gn:population":0,
    "gn:timezone":"Asia/Tbilisi",
    "iso:country":"GE",
    "wof:name":"Suni",
    "wof:placetype":"locality"
},
  "geometry": {"coordinates":[41.50472,42.70167],"type":"Point"}
}