{
  "type": "Feature",
  "properties": {
    "gn:admin1_code":"02",
    "gn:asciiname":"Suni",
    "gn:country_code":"GE",
    "gn:dem":8,
    "gn:feature_class":"P",
    "gn:feature_code":"PPL",
    "gn:name":"Suni",
    "gn:population":0,
    "gn:timezone":"Asia/Tbilisi",
    "iso:country":"GE",
    "name:afr_x_preferred":[
        "Soenie"
    ],
    "name:ara_x_preferred":[
        "\u0633\u0648\u0646\u064a"
    ],
    "name:ava_x_preferred":[
        "\u0421\u0443\u043d\u0438"
    ],
    "name:bre_x_preferred":[
        "Antilopenn-vusk"
    ],
    "name:cat_x_preferred":[
        "Suni"
    ],
    "name:ceb_x_preferred":[
        "Neotragus moschatus"
    ],
    "name:ces_x_preferred":[
        "Antilopka pi\u017emov\u00e1"
    ],
    "name:deu_x_preferred":[
        "Moschusb\u00f6ckchen"
    ],
    "name:eus_x_preferred":[
        "Neotragus moschatus"
    ],
    "name:fas_x_preferred":[
        "\u06a9\u0644\u200c\u0631\u06cc\u0632\u0647"
    ],
    "name:fin_x_preferred":[
        "Suni"
    ],
    "name:fra_x_preferred":[
        "Neotragus moschatus"
    ],
    "name:glg_x_preferred":[
        "Neotragus moschatus"
    ],
    "name:heb_x_preferred":[
        "\u05d3\u05dc\u05e7\u05e8\u05df \u05d4\u05de\u05d5\u05e9\u05e7"
    ],
    "name:hun_x_preferred":[
        "P\u00e9zsmaantilop"
    ],
    "name:ita_x_preferred":[
        "Neotragus moschatus"
    ],
    "name:kor_x_preferred":[
        "\uc218\ub2c8\uc601\uc591"
    ],
    "name:lez_x_preferred":[
        "\u0421\u0443\u043d\u0438"
    ],
    "name:lit_x_preferred":[
        "Sun\u0117"
    ],
    "name:nld_x_preferred":[
        "Nesotragus moschatus"
    ],
    "name:pnb_x_preferred":[
        "\u0633\u0648\u0646\u06cc \u06c1\u0631\u0646"
    ],
    "name:pol_x_preferred":[
        "Antylopka pi\u017cmowa"
    ],
    "name:rus_x_preferred":[
        "\u0421\u0443\u043d\u0438"
    ],
    "name:spa_x_preferred":[
        "Neotragus moschatus"
    ],
    "name:srp_x_preferred":[
        "\u0421\u0443\u043d\u0438"
    ],
    "name:swe_x_preferred":[
        "Suniantilop"
    ],
    "name:udm_x_preferred":[
        "\u0421\u0443\u043d\u0438"
    ],
    "name:war_x_preferred":[
        "Neotragus moschatus"
    ],
    "name:zho_x_preferred":[
        "\u6851\u5c9b\u65b0\u5c0f\u7f9a"
    ],
    "wof:name":"Suni",
    "wof:placetype":"locality"
},
  "geometry": {"coordinates":[41.50472,42.70167],"type":"Point"}
}