{
  "type": "Feature",
  "properties": {
    "gn:admin1_code":"00",
    "gn:asciiname":"K'veda Tseva",
    "gn:country_code":"GE",
    "gn:dem":419,
    "gn:feature_class":"P",
    "gn:feature_code":"PPL",
    "gn:name":"K\u2019veda Tseva",
    "gn:population":0,
    "gn:timezone":"Asia/Tbilisi",
    "iso:country":"GE",
    "name:und_x_variant":[
        "Tseva-Nizhnyaya",
        "K\u2019veda Tseva"
    ],
    "wof:name":"K'veda Tseva",
    "wof:placetype":"locality"
},
  "geometry": {"coordinates":[43.13333,42.08333],"type":"Point"}
}