{
  "type": "Feature",
  "properties": {
    "gn:admin1_code":"00",
    "gn:asciiname":"Kheiti",
    "gn:country_code":"GE",
    "gn:dem":893,
    "gn:feature_class":"P",
    "gn:feature_code":"PPL",
    "gn:name":"Kheiti",
    "gn:population":0,
    "gn:timezone":"Asia/Tbilisi",
    "iso:country":"GE",
    "name:und_x_variant":[
        "Kheyti",
        "Kheiti"
    ],
    "wof:name":"Kheiti",
    "wof:placetype":"locality"
},
  "geometry": {"coordinates":[43.9718,42.25874],"type":"Point"}
}