{
  "type": "Feature",
  "properties": {
    "gn:admin1_code":"00",
    "gn:asciiname":"Kakhati",
    "gn:country_code":"GE",
    "gn:dem":29,
    "gn:feature_class":"P",
    "gn:feature_code":"PPL",
    "gn:name":"Kakhati",
    "gn:population":0,
    "gn:timezone":"Asia/Tbilisi",
    "iso:country":"GE",
    "wof:name":"Kakhati",
    "wof:placetype":"locality"
},
  "geometry": {"coordinates":[41.74694,42.46389],"type":"Point"}
}