{
  "type": "Feature",
  "properties": {
    "gn:admin1_code":"66",
    "gn:asciiname":"Tsinsop'eli",
    "gn:country_code":"GE",
    "gn:dem":522,
    "gn:feature_class":"P",
    "gn:feature_code":"PPL",
    "gn:name":"Tsinsop\u2019eli",
    "gn:population":0,
    "gn:timezone":"Asia/Tbilisi",
    "iso:country":"GE",
    "name:kat_x_preferred":[
        "\u10ec\u10d8\u10dc\u10e1\u10dd\u10e4\u10d4\u10da\u10d8"
    ],
    "name:rus_x_preferred":[
        "\u0426\u0438\u043d\u0441\u043e\u043f\u0435\u043b\u0438"
    ],
    "name:und_x_variant":[
        "Tsinasopeli",
        "Tsinsop\u2019eli",
        "Tsinsopeli"
    ],
    "wof:name":"Tsinsop'eli",
    "wof:placetype":"locality"
},
  "geometry": {"coordinates":[43.28972,42.28306],"type":"Point"}
}