{
  "type": "Feature",
  "properties": {
    "gn:admin1_code":"71",
    "gn:asciiname":"Vedidk'ari",
    "gn:country_code":"GE",
    "gn:dem":82,
    "gn:feature_class":"P",
    "gn:feature_code":"PPL",
    "gn:name":"Vedidk\u2019ari",
    "gn:population":0,
    "gn:timezone":"Asia/Tbilisi",
    "iso:country":"GE",
    "name:kat_x_preferred":[
        "Vedidk\u2019ari"
    ],
    "name:kat_x_variant":[
        "\u10d5\u10d4\u10d3\u10d8\u10d3\u10d9\u10d0\u10e0\u10d8"
    ],
    "name:und_x_variant":[
        "Veditkari"
    ],
    "wof:name":"Vedidk'ari",
    "wof:placetype":"locality"
},
  "geometry": {"coordinates":[42.27214,42.33013],"type":"Point"}
}