{
  "type": "Feature",
  "properties": {
    "gn:admin1_code":"00",
    "gn:asciiname":"Qaraghaji",
    "gn:country_code":"GE",
    "gn:dem":318,
    "gn:feature_class":"P",
    "gn:feature_code":"PPL",
    "gn:name":"Qaraghaji",
    "gn:population":0,
    "gn:timezone":"Asia/Tbilisi",
    "iso:country":"GE",
    "name:kat_x_preferred":[
        "Qaraghaji"
    ],
    "name:und_x_variant":[
        "Karagadzhi",
        "Karaghaji"
    ],
    "wof:name":"Qaraghaji",
    "wof:placetype":"locality"
},
  "geometry": {"coordinates":[46.13321,41.51157],"type":"Point"}
}