{
  "type": "Feature",
  "properties": {
    "gn:admin1_code":"71",
    "gn:asciiname":"Labsq'aldi",
    "gn:country_code":"GE",
    "gn:dem":1599,
    "gn:feature_class":"P",
    "gn:feature_code":"PPL",
    "gn:name":"Labsq\u2019aldi",
    "gn:population":0,
    "gn:timezone":"Asia/Tbilisi",
    "iso:country":"GE",
    "name:kat_x_preferred":[
        "Labsq\u2019aldi"
    ],
    "name:kat_x_variant":[
        "\u10da\u10d0\u10d1\u10e1\u10e7\u10d0\u10da\u10d3\u10d8"
    ],
    "name:und_x_variant":[
        "Labskaldi"
    ],
    "wof:name":"Labsq'aldi",
    "wof:placetype":"locality"
},
  "geometry": {"coordinates":[42.57462,42.99697000000001],"type":"Point"}
}