{
  "type": "Feature",
  "properties": {
    "gn:admin1_code":"65",
    "gn:asciiname":"Kvemo Mak'vaneti",
    "gn:country_code":"GE",
    "gn:dem":75,
    "gn:feature_class":"P",
    "gn:feature_code":"PPL",
    "gn:name":"Kvemo Mak\u2019vaneti",
    "gn:population":0,
    "gn:timezone":"Asia/Tbilisi",
    "iso:country":"GE",
    "name:kat_x_preferred":[
        "Kvemo Mak\u2019vaneti"
    ],
    "name:kat_x_variant":[
        "\u10e5\u10d5\u10d4\u10db\u10dd \u10db\u10d0\u10d9\u10d5\u10d0\u10dc\u10d4\u10d7\u10d8"
    ],
    "name:und_x_variant":[
        "Nizhniye Makvaneti"
    ],
    "wof:name":"Kvemo Mak'vaneti",
    "wof:placetype":"locality"
},
  "geometry": {"coordinates":[42.00101,41.91484000000001],"type":"Point"}
}