{
  "type": "Feature",
  "properties": {
    "gn:admin1_code":"00",
    "gn:asciiname":"Zemo Ts'khiloni",
    "gn:country_code":"GE",
    "gn:dem":969,
    "gn:feature_class":"P",
    "gn:feature_code":"PPL",
    "gn:name":"Zemo Ts\u2019khiloni",
    "gn:population":0,
    "gn:timezone":"Asia/Tbilisi",
    "iso:country":"GE",
    "name:kat_x_preferred":[
        "Zemo Ts\u2019khiloni"
    ],
    "name:und_x_variant":[
        "Verkhniye Tskhiloni"
    ],
    "wof:name":"Zemo Ts'khiloni",
    "wof:placetype":"locality"
},
  "geometry": {"coordinates":[44.3625,42.08806],"type":"Point"}
}