{
  "type": "Feature",
  "properties": {
    "gn:admin1_code":"45",
    "gn:asciiname":"Sinaguri",
    "gn:country_code":"GE",
    "gn:dem":1057,
    "gn:feature_class":"P",
    "gn:feature_code":"PPL",
    "gn:name":"Sinaguri",
    "gn:population":0,
    "gn:timezone":"Asia/Tbilisi",
    "iso:country":"GE",
    "wof:name":"Sinaguri",
    "wof:placetype":"locality"
},
  "geometry": {"coordinates":[43.62613,42.39483],"type":"Point"}
}