{
  "type": "Feature",
  "properties": {
    "gn:admin1_code":"08",
    "gn:asciiname":"Matani",
    "gn:country_code":"GE",
    "gn:dem":559,
    "gn:feature_class":"P",
    "gn:feature_code":"PPL",
    "gn:name":"Matani",
    "gn:population":0,
    "gn:timezone":"Asia/Tbilisi",
    "iso:country":"GE",
    "name:eng_x_preferred":[
        "Matani"
    ],
    "name:rus_x_preferred":[
        "\u041c\u0430\u0442\u0430\u043d\u0438"
    ],
    "name:und_x_variant":[
        "Matani-Marelisi",
        "Matani"
    ],
    "wof:name":"Matani",
    "wof:placetype":"locality"
},
  "geometry": {"coordinates":[45.19562,42.07804],"type":"Point"}
}