{
  "type": "Feature",
  "properties": {
    "gn:admin1_code":"60",
    "gn:asciiname":"Salominao",
    "gn:country_code":"GE",
    "gn:dem":133,
    "gn:feature_class":"P",
    "gn:feature_code":"PPL",
    "gn:name":"Salominao",
    "gn:population":0,
    "gn:timezone":"Asia/Tbilisi",
    "iso:country":"GE",
    "name:kat_x_preferred":[
        "\u10e1\u10d0\u10da\u10dd\u10db\u10d8\u10dc\u10d0\u10dd"
    ],
    "wof:name":"Salominao",
    "wof:placetype":"locality"
},
  "geometry": {"coordinates":[42.71,42.08333],"type":"Point"}
}