{
  "type": "Feature",
  "properties": {
    "gn:admin1_code":"04",
    "gn:asciiname":"T'omasheti",
    "gn:country_code":"GE",
    "gn:dem":1343,
    "gn:feature_class":"P",
    "gn:feature_code":"PPL",
    "gn:name":"T\u2019omasheti",
    "gn:population":0,
    "gn:timezone":"Asia/Tbilisi",
    "iso:country":"GE",
    "name:kat_x_preferred":[
        "T\u2019omasheti"
    ],
    "name:kat_x_variant":[
        "\u10e2\u10dd\u10db\u10d0\u10e8\u10d4\u10d7\u10d8"
    ],
    "wof:name":"T'omasheti",
    "wof:placetype":"locality"
},
  "geometry": {"coordinates":[42.37455,41.51166],"type":"Point"}
}