{
  "type": "Feature",
  "properties": {
    "gn:admin1_code":"71",
    "gn:asciiname":"Didi Jikhaishi",
    "gn:country_code":"GE",
    "gn:dem":59,
    "gn:feature_class":"P",
    "gn:feature_code":"PPL",
    "gn:name":"Didi Jikhaishi",
    "gn:population":0,
    "gn:timezone":"Asia/Tbilisi",
    "iso:country":"GE",
    "name:eng_x_preferred":[
        "Didi Jikhaishi"
    ],
    "name:kat_x_preferred":[
        "\u10d3\u10d8\u10d3\u10d8 \u10ef\u10d8\u10ee\u10d0\u10d8\u10e8\u10d8"
    ],
    "name:rus_x_preferred":[
        "\u0414\u0438\u0434\u0438-\u0414\u0436\u0438\u0445\u0430\u0438\u0448\u0438"
    ],
    "name:und_x_variant":[
        "Dzhikhaishi",
        "Didi-Dzhikhaishchi",
        "Didi-Dzhikhaishi",
        "Didi-Dzhikhayshchi",
        "Bol\u2019shiye Dzhikhaishchi",
        "Didi Jikhaishi"
    ],
    "wof:name":"Didi Jikhaishi",
    "wof:placetype":"locality"
},
  "geometry": {"coordinates":[42.42632,42.22727],"type":"Point"}
}