{
  "type": "Feature",
  "properties": {
    "gn:admin1_code":"72",
    "gn:asciiname":"Lomaturts'khi",
    "gn:country_code":"GE",
    "gn:dem":1771,
    "gn:feature_class":"P",
    "gn:feature_code":"PPL",
    "gn:name":"Lomaturts\u2019khi",
    "gn:population":0,
    "gn:timezone":"Asia/Tbilisi",
    "iso:country":"GE",
    "name:kat_x_preferred":[
        "\u10da\u10dd\u10db\u10d0\u10e2\u10e3\u10e0\u10ea\u10ee\u10d8"
    ],
    "name:und_x_variant":[
        "Lomaturts\u2019khi"
    ],
    "wof:name":"Lomaturts'khi",
    "wof:placetype":"locality"
},
  "geometry": {"coordinates":[43.48369,41.56827],"type":"Point"}
}