{
  "type": "Feature",
  "properties": {
    "gn:admin1_code":"00",
    "gn:asciiname":"Mendzhi",
    "gn:country_code":"GE",
    "gn:dem":37,
    "gn:feature_class":"P",
    "gn:feature_code":"PPL",
    "gn:name":"Mendzhi",
    "gn:population":0,
    "gn:timezone":"Asia/Tbilisi",
    "iso:country":"GE",
    "wof:name":"Mendzhi",
    "wof:placetype":"locality"
},
  "geometry": {"coordinates":[42.03611,42.27778],"type":"Point"}
}