{
  "type": "Feature",
  "properties": {
    "gn:admin1_code":"65",
    "gn:asciiname":"Akhalsheni",
    "gn:country_code":"GE",
    "gn:dem":164,
    "gn:feature_class":"P",
    "gn:feature_code":"PPL",
    "gn:name":"Akhalsheni",
    "gn:population":0,
    "gn:timezone":"Asia/Tbilisi",
    "iso:country":"GE",
    "name:kat_x_preferred":[
        "\u10d0\u10d6\u10d0\u10da\u10e8\u10d4\u10dc\u10d8"
    ],
    "wof:name":"Akhalsheni",
    "wof:placetype":"locality"
},
  "geometry": {"coordinates":[42.20926,41.98434],"type":"Point"}
}