{
  "type": "Feature",
  "properties": {
    "gn:admin1_code":"67",
    "gn:asciiname":"Kitaani",
    "gn:country_code":"GE",
    "gn:dem":307,
    "gn:feature_class":"P",
    "gn:feature_code":"PPL",
    "gn:name":"Kitaani",
    "gn:population":0,
    "gn:timezone":"Asia/Tbilisi",
    "iso:country":"GE",
    "name:kat_x_preferred":[
        "\u10e7\u10d8\u10e2\u10d0\u10d0\u10dc\u10d8"
    ],
    "wof:name":"Kitaani",
    "wof:placetype":"locality"
},
  "geometry": {"coordinates":[45.81431,41.79375],"type":"Point"}
}