{
  "type": "Feature",
  "properties": {
    "gn:admin1_code":"69",
    "gn:asciiname":"Vashlobi",
    "gn:country_code":"GE",
    "gn:dem":1330,
    "gn:feature_class":"P",
    "gn:feature_code":"PPL",
    "gn:name":"Vashlobi",
    "gn:population":0,
    "gn:timezone":"Asia/Tbilisi",
    "iso:country":"GE",
    "wof:name":"Vashlobi",
    "wof:placetype":"locality"
},
  "geometry": {"coordinates":[44.72889,42.29222],"type":"Point"}
}