{
  "type": "Feature",
  "properties": {
    "gn:admin1_code":"67",
    "gn:asciiname":"P'aldo",
    "gn:country_code":"GE",
    "gn:dem":471,
    "gn:feature_class":"P",
    "gn:feature_code":"PPL",
    "gn:name":"P\u2019aldo",
    "gn:population":0,
    "gn:timezone":"Asia/Tbilisi",
    "iso:country":"GE",
    "name:kat_x_preferred":[
        "P\u2019aldo"
    ],
    "name:kat_x_variant":[
        "\u10de\u10d0\u10da\u10d3\u10dd"
    ],
    "wof:name":"P'aldo",
    "wof:placetype":"locality"
},
  "geometry": {"coordinates":[45.50306,41.61284000000001],"type":"Point"}
}