{
  "type": "Feature",
  "properties": {
    "gn:admin1_code":"02",
    "gn:asciiname":"Aibga",
    "gn:country_code":"GE",
    "gn:dem":530,
    "gn:feature_class":"P",
    "gn:feature_code":"PPL",
    "gn:name":"Aibga",
    "gn:population":0,
    "gn:timezone":"Asia/Tbilisi",
    "iso:country":"GE",
    "name:kat_x_preferred":[
        "\u10d0\u10d8\u10d1\u10d2\u10d0"
    ],
    "name:kat_x_variant":[
        "Aibga"
    ],
    "wof:name":"Aibga",
    "wof:placetype":"locality"
},
  "geometry": {"coordinates":[40.21178,43.57112],"type":"Point"}
}