{
  "type": "Feature",
  "properties": {
    "gn:admin1_code":"71",
    "gn:asciiname":"Urta",
    "gn:country_code":"GE",
    "gn:dem":64,
    "gn:feature_class":"P",
    "gn:feature_code":"PPL",
    "gn:name":"Urta",
    "gn:population":0,
    "gn:timezone":"Asia/Tbilisi",
    "iso:country":"GE",
    "name:kat_x_preferred":[
        "Urta"
    ],
    "name:kat_x_variant":[
        "\u10e3\u10e0\u10d7\u10d0"
    ],
    "wof:name":"Urta",
    "wof:placetype":"locality"
},
  "geometry": {"coordinates":[41.84111,42.4315],"type":"Point"}
}