{
  "type": "Feature",
  "properties": {
    "gn:admin1_code":"69",
    "gn:asciiname":"Ino",
    "gn:country_code":"GE",
    "gn:dem":1208,
    "gn:feature_class":"P",
    "gn:feature_code":"PPL",
    "gn:name":"Ino",
    "gn:population":0,
    "gn:timezone":"Asia/Tbilisi",
    "iso:country":"GE",
    "name:bul_x_preferred":[
        "\u0418\u043d\u043e"
    ],
    "name:ceb_x_preferred":[
        "Ino"
    ],
    "name:fin_x_preferred":[
        "Ino"
    ],
    "name:fra_x_preferred":[
        "Ino"
    ],
    "name:heb_x_preferred":[
        "\u05d0\u05d9\u05e0\u05d5"
    ],
    "name:lat_x_preferred":[
        "Ino"
    ],
    "name:mlg_x_preferred":[
        "Ino"
    ],
    "name:nld_x_preferred":[
        "Ino"
    ],
    "name:por_x_preferred":[
        "Ino"
    ],
    "name:rus_x_preferred":[
        "\u0418\u043d\u043e"
    ],
    "name:swe_x_preferred":[
        "Ino"
    ],
    "name:ukr_x_preferred":[
        "\u0406\u043d\u043e"
    ],
    "wof:name":"Ino",
    "wof:placetype":"locality"
},
  "geometry": {"coordinates":[44.91278,42.35167],"type":"Point"}
}