{
  "type": "Feature",
  "properties": {
    "gn:admin1_code":"71",
    "gn:asciiname":"Akhuti",
    "gn:country_code":"GE",
    "gn:dem":204,
    "gn:feature_class":"P",
    "gn:feature_code":"PPL",
    "gn:name":"Akhuti",
    "gn:population":0,
    "gn:timezone":"Asia/Tbilisi",
    "iso:country":"GE",
    "name:eng_x_preferred":[
        "Akhut'i"
    ],
    "name:kat_x_preferred":[
        "Akhuti"
    ],
    "name:kat_x_variant":[
        "\u10d0\u10ee\u10e3\u10d7\u10d8"
    ],
    "name:rus_x_preferred":[
        "\u0410\u0445\u0443\u0442\u0438"
    ],
    "wof:name":"Akhuti",
    "wof:placetype":"locality"
},
  "geometry": {"coordinates":[42.1705,42.46724],"type":"Point"}
}