{
  "type": "Feature",
  "properties": {
    "gn:admin1_code":"02",
    "gn:asciiname":"Mtisk'alta",
    "gn:country_code":"GE",
    "gn:dem":343,
    "gn:feature_class":"P",
    "gn:feature_code":"PPL",
    "gn:name":"Mtisk\u2019alta",
    "gn:population":0,
    "gn:timezone":"Asia/Tbilisi",
    "iso:country":"GE",
    "name:kat_x_preferred":[
        "\u10db\u10d7\u10d8\u10e1\u10d9\u10d0\u10da\u10d7\u10d0"
    ],
    "name:kat_x_variant":[
        "Mtisk\u2019alta"
    ],
    "wof:name":"Mtisk'alta",
    "wof:placetype":"locality"
},
  "geometry": {"coordinates":[41.05273,43.12757],"type":"Point"}
}