{
  "type": "Feature",
  "properties": {
    "gn:admin1_code":"66",
    "gn:asciiname":"Gegut'i",
    "gn:country_code":"GE",
    "gn:dem":90,
    "gn:feature_class":"P",
    "gn:feature_code":"PPL",
    "gn:name":"Gegut\u2019i",
    "gn:population":0,
    "gn:timezone":"Asia/Tbilisi",
    "iso:country":"GE",
    "name:eng_x_preferred":[
        "Gegut'i"
    ],
    "name:rus_x_preferred":[
        "\u0413\u0435\u0433\u0443\u0442\u0438"
    ],
    "name:und_x_variant":[
        "Gegut\u2019i"
    ],
    "wof:name":"Gegut'i",
    "wof:placetype":"locality"
},
  "geometry": {"coordinates":[42.67749,42.16873],"type":"Point"}
}