{
  "type": "Feature",
  "properties": {
    "gn:admin1_code":"66",
    "gn:asciiname":"Nabak'evi",
    "gn:country_code":"GE",
    "gn:dem":35,
    "gn:feature_class":"P",
    "gn:feature_code":"PPL",
    "gn:name":"Nabak\u2019evi",
    "gn:population":0,
    "gn:timezone":"Asia/Tbilisi",
    "iso:country":"GE",
    "name:kat_x_preferred":[
        "\u10dc\u10d0\u10d1\u10d0\u10d9\u10d4\u10d5\u10d8"
    ],
    "name:und_x_variant":[
        "Nabokevi",
        "Nabak\u2019evi"
    ],
    "wof:name":"Nabak'evi",
    "wof:placetype":"locality"
},
  "geometry": {"coordinates":[42.32125,42.20764000000001],"type":"Point"}
}