{
  "type": "Feature",
  "properties": {
    "gn:admin1_code":"71",
    "gn:asciiname":"Totani",
    "gn:country_code":"GE",
    "gn:dem":544,
    "gn:feature_class":"P",
    "gn:feature_code":"PPL",
    "gn:name":"Totani",
    "gn:population":0,
    "gn:timezone":"Asia/Tbilisi",
    "iso:country":"GE",
    "name:kat_x_preferred":[
        "\u10d7\u10dd\u10d7\u10d0\u10dc\u10d8"
    ],
    "name:und_x_variant":[
        "Totona",
        "Totana",
        "Totani"
    ],
    "wof:name":"Totani",
    "wof:placetype":"locality"
},
  "geometry": {"coordinates":[42.04041,42.89048],"type":"Point"}
}