{
  "type": "Feature",
  "properties": {
    "gn:admin1_code":"66",
    "gn:asciiname":"Babi",
    "gn:country_code":"GE",
    "gn:dem":669,
    "gn:feature_class":"P",
    "gn:feature_code":"PPL",
    "gn:name":"Babi",
    "gn:population":0,
    "gn:timezone":"Asia/Tbilisi",
    "iso:country":"GE",
    "name:cat_x_preferred":[
        "Babi"
    ],
    "name:ceb_x_preferred":[
        "Babi"
    ],
    "name:deu_x_preferred":[
        "Babi"
    ],
    "name:ind_x_preferred":[
        "Babi"
    ],
    "name:ita_x_preferred":[
        "Babi"
    ],
    "name:kat_x_preferred":[
        "Babi"
    ],
    "name:kat_x_variant":[
        "\u10d1\u10d0\u10d1\u10d8"
    ],
    "name:por_x_preferred":[
        "Babi"
    ],
    "name:spa_x_preferred":[
        "Babi"
    ],
    "name:swe_x_preferred":[
        "Babi"
    ],
    "wof:name":"Babi",
    "wof:placetype":"locality"
},
  "geometry": {"coordinates":[43.33333,41.96465],"type":"Point"}
}