{
  "type": "Feature",
  "properties": {
    "gn:admin1_code":"02",
    "gn:asciiname":"Ambarikhuts'a",
    "gn:country_code":"GE",
    "gn:dem":660,
    "gn:feature_class":"P",
    "gn:feature_code":"PPL",
    "gn:name":"Ambarikhuts\u2019a",
    "gn:population":0,
    "gn:timezone":"Asia/Tbilisi",
    "iso:country":"GE",
    "name:kat_x_preferred":[
        "\u10d0\u10db\u10d1\u10d0\u10e0\u10d8\u10ee\u10e3\u10ec\u10d0"
    ],
    "name:kat_x_variant":[
        "Ambarikhuts\u2019a"
    ],
    "name:und_x_variant":[
        "Amba-Rykhutsa"
    ],
    "wof:name":"Ambarikhuts'a",
    "wof:placetype":"locality"
},
  "geometry": {"coordinates":[40.96983,43.08644],"type":"Point"}
}