{
  "type": "Feature",
  "properties": {
    "gn:admin1_code":"67",
    "gn:asciiname":"Sabue",
    "gn:country_code":"GE",
    "gn:dem":711,
    "gn:feature_class":"P",
    "gn:feature_code":"PPL",
    "gn:name":"Sabue",
    "gn:population":0,
    "gn:timezone":"Asia/Tbilisi",
    "iso:country":"GE",
    "name:kat_x_preferred":[
        "\u10e1\u10d0\u10d1\u10e3\u10d4"
    ],
    "name:rus_x_preferred":[
        "\u0421\u0430\u0431\u0443\u0435"
    ],
    "name:und_x_variant":[
        "Sabuye",
        "Sabue"
    ],
    "wof:name":"Sabue",
    "wof:placetype":"locality"
},
  "geometry": {"coordinates":[45.12546,42.05082],"type":"Point"}
}