{
  "type": "Feature",
  "properties": {
    "gn:admin1_code":"00",
    "gn:asciiname":"Khovle",
    "gn:country_code":"GE",
    "gn:dem":749,
    "gn:feature_class":"P",
    "gn:feature_code":"PPL",
    "gn:name":"Khovle",
    "gn:population":0,
    "gn:timezone":"Asia/Tbilisi",
    "iso:country":"GE",
    "name:eng_x_preferred":[
        "Khovle"
    ],
    "name:rus_x_preferred":[
        "\u0425\u043e\u0432\u043b\u0435"
    ],
    "name:und_x_variant":[
        "Knovle"
    ],
    "wof:name":"Khovle",
    "wof:placetype":"locality"
},
  "geometry": {"coordinates":[44.23967,41.89379],"type":"Point"}
}