{
  "type": "Feature",
  "properties": {
    "gn:admin1_code":"00",
    "gn:asciiname":"Ukaneti",
    "gn:country_code":"GE",
    "gn:dem":92,
    "gn:feature_class":"P",
    "gn:feature_code":"PPL",
    "gn:name":"Ukaneti",
    "gn:population":0,
    "gn:timezone":"Asia/Tbilisi",
    "iso:country":"GE",
    "wof:name":"Ukaneti",
    "wof:placetype":"locality"
},
  "geometry": {"coordinates":[42.64709000000001,42.18116],"type":"Point"}
}