{
  "type": "Feature",
  "properties": {
    "gn:admin1_code":"00",
    "gn:asciiname":"Morgo",
    "gn:country_code":"GE",
    "gn:dem":1205,
    "gn:feature_class":"P",
    "gn:feature_code":"PPL",
    "gn:name":"Morgo",
    "gn:population":0,
    "gn:timezone":"Asia/Tbilisi",
    "iso:country":"GE",
    "wof:name":"Morgo",
    "wof:placetype":"locality"
},
  "geometry": {"coordinates":[43.92947,42.37057],"type":"Point"}
}