{
  "type": "Feature",
  "properties": {
    "gn:admin1_code":"00",
    "gn:asciiname":"Busheti",
    "gn:country_code":"GE",
    "gn:dem":584,
    "gn:feature_class":"P",
    "gn:feature_code":"PPL",
    "gn:name":"Busheti",
    "gn:population":0,
    "gn:timezone":"Asia/Tbilisi",
    "iso:country":"GE",
    "name:che_x_preferred":[
        "\u0411\u0443\u0448\u0435\u0442\u0438"
    ],
    "name:hye_x_preferred":[
        "\u0532\u0578\u0582\u0577\u0565\u0569"
    ],
    "name:kat_x_preferred":[
        "\u10d1\u10e3\u10e8\u10d4\u10e2\u10d8"
    ],
    "name:und_x_variant":[
        "Bushati",
        "Busheti"
    ],
    "wof:name":"Busheti",
    "wof:placetype":"locality"
},
  "geometry": {"coordinates":[45.60167,41.87963],"type":"Point"}
}