{
  "type": "Feature",
  "properties": {
    "gn:admin1_code":"00",
    "gn:asciiname":"Busheti",
    "gn:country_code":"GE",
    "gn:dem":584,
    "gn:feature_class":"P",
    "gn:feature_code":"PPL",
    "gn:name":"Busheti",
    "gn:population":0,
    "gn:timezone":"Asia/Tbilisi",
    "iso:country":"GE",
    "name:und_x_variant":[
        "Bushati",
        "Busheti"
    ],
    "wof:name":"Busheti",
    "wof:placetype":"locality"
},
  "geometry": {"coordinates":[45.60167,41.87963],"type":"Point"}
}