{
  "type": "Feature",
  "properties": {
    "gn:admin1_code":"71",
    "gn:asciiname":"Ch'eliri",
    "gn:country_code":"GE",
    "gn:dem":1656,
    "gn:feature_class":"P",
    "gn:feature_code":"PPL",
    "gn:name":"Ch\u2019eliri",
    "gn:population":0,
    "gn:timezone":"Asia/Tbilisi",
    "iso:country":"GE",
    "name:kat_x_preferred":[
        "Ch\u2019eliri"
    ],
    "name:kat_x_variant":[
        "\u10ed\u10d4\u10da\u10d8\u10e0\u10d8"
    ],
    "wof:name":"Ch'eliri",
    "wof:placetype":"locality"
},
  "geometry": {"coordinates":[42.52818,43.05256],"type":"Point"}
}