{
  "type": "Feature",
  "properties": {
    "gn:admin1_code":"69",
    "gn:asciiname":"Gogolaurt'a",
    "gn:country_code":"GE",
    "gn:dem":1371,
    "gn:feature_class":"P",
    "gn:feature_code":"PPL",
    "gn:name":"Gogolaurt\u2019a",
    "gn:population":0,
    "gn:timezone":"Asia/Tbilisi",
    "iso:country":"GE",
    "name:kat_x_preferred":[
        "\u10d2\u10dd\u10d2\u10dd\u10da\u10d0\u10e3\u10e0\u10d7\u10d0"
    ],
    "name:und_x_variant":[
        "Gogolaurt",
        "Gogolaurt\u2019a"
    ],
    "wof:name":"Gogolaurt'a",
    "wof:placetype":"locality"
},
  "geometry": {"coordinates":[45.02777,42.40933],"type":"Point"}
}