{
  "type": "Feature",
  "properties": {
    "gn:admin1_code":"02",
    "gn:asciiname":"Nakhshira",
    "gn:country_code":"GE",
    "gn:dem":618,
    "gn:feature_class":"P",
    "gn:feature_code":"PPL",
    "gn:name":"Nakhshira",
    "gn:population":0,
    "gn:timezone":"Asia/Tbilisi",
    "iso:country":"GE",
    "name:kat_x_preferred":[
        "\u10dc\u10d0\u10ee\u10e8\u10d8\u10e0\u10d0"
    ],
    "name:kat_x_variant":[
        "Nakhshira"
    ],
    "wof:name":"Nakhshira",
    "wof:placetype":"locality"
},
  "geometry": {"coordinates":[41.09958,43.10786],"type":"Point"}
}