{
  "type": "Feature",
  "properties": {
    "gn:admin1_code":"70",
    "gn:asciiname":"Korti",
    "gn:country_code":"GE",
    "gn:dem":1006,
    "gn:feature_class":"P",
    "gn:feature_code":"PPL",
    "gn:name":"Korti",
    "gn:population":0,
    "gn:timezone":"Asia/Tbilisi",
    "iso:country":"GE",
    "name:ara_x_preferred":[
        "\u0643\u0648\u0631\u062a\u064a"
    ],
    "name:azb_x_preferred":[
        "\u06a9\u0648\u0631\u062a\u06cc"
    ],
    "name:cat_x_preferred":[
        "Korti"
    ],
    "name:deu_x_preferred":[
        "Kurti"
    ],
    "name:fas_x_preferred":[
        "\u06a9\u0648\u0631\u062a\u06cc"
    ],
    "name:spa_x_preferred":[
        "Korti"
    ],
    "name:und_x_variant":[
        "Kordi",
        "Korti"
    ],
    "wof:name":"Korti",
    "wof:placetype":"locality"
},
  "geometry": {"coordinates":[43.17507,42.48295],"type":"Point"}
}