{
  "type": "Feature",
  "properties": {
    "gn:admin1_code":"67",
    "gn:asciiname":"Ozaani",
    "gn:country_code":"GE",
    "gn:dem":560,
    "gn:feature_class":"P",
    "gn:feature_code":"PPL",
    "gn:name":"Ozaani",
    "gn:population":0,
    "gn:timezone":"Asia/Tbilisi",
    "iso:country":"GE",
    "name:kat_x_preferred":[
        "Ozaani"
    ],
    "name:kat_x_variant":[
        "\u10dd\u10d6\u10d0\u10d0\u10dc\u10d8"
    ],
    "wof:name":"Ozaani",
    "wof:placetype":"locality"
},
  "geometry": {"coordinates":[45.9995,41.5507],"type":"Point"}
}