{
  "type": "Feature",
  "properties": {
    "gn:admin1_code":"70",
    "gn:asciiname":"Khonchiori",
    "gn:country_code":"GE",
    "gn:dem":1159,
    "gn:feature_class":"P",
    "gn:feature_code":"PPL",
    "gn:name":"Khonchiori",
    "gn:population":0,
    "gn:timezone":"Asia/Tbilisi",
    "iso:country":"GE",
    "name:kat_x_preferred":[
        "\u10ee\u10dd\u10dc\u10ed\u10d8\u10dd\u10e0\u10d8"
    ],
    "name:kat_x_variant":[
        "Khontchiori"
    ],
    "wof:name":"Khonchiori",
    "wof:placetype":"locality"
},
  "geometry": {"coordinates":[43.03998,42.49641],"type":"Point"}
}