{
  "type": "Feature",
  "properties": {
    "gn:admin1_code":"67",
    "gn:asciiname":"Lapniani",
    "gn:country_code":"GE",
    "gn:dem":287,
    "gn:feature_class":"P",
    "gn:feature_code":"PPL",
    "gn:name":"Lapniani",
    "gn:population":0,
    "gn:timezone":"Asia/Tbilisi",
    "iso:country":"GE",
    "name:kat_x_preferred":[
        "\u10da\u10d0\u10e4\u10dc\u10d8\u10d0\u10dc\u10d8"
    ],
    "wof:name":"Lapniani",
    "wof:placetype":"locality"
},
  "geometry": {"coordinates":[46.08445,41.83403],"type":"Point"}
}