{
  "type": "Feature",
  "properties": {
    "gn:admin1_code":"52",
    "gn:asciiname":"Navenakhevi",
    "gn:country_code":"GE",
    "gn:dem":287,
    "gn:feature_class":"P",
    "gn:feature_code":"PPL",
    "gn:name":"Navenakhevi",
    "gn:population":0,
    "gn:timezone":"Asia/Tbilisi",
    "iso:country":"GE",
    "wof:name":"Navenakhevi",
    "wof:placetype":"locality"
},
  "geometry": {"coordinates":[42.86047,42.24919000000001],"type":"Point"}
}