{
  "type": "Feature",
  "properties": {
    "gn:admin1_code":"68",
    "gn:asciiname":"Q'udro",
    "gn:country_code":"GE",
    "gn:dem":953,
    "gn:feature_class":"P",
    "gn:feature_code":"PPL",
    "gn:name":"Q\u2019udro",
    "gn:population":0,
    "gn:timezone":"Asia/Tbilisi",
    "iso:country":"GE",
    "name:kat_x_preferred":[
        "Kudro"
    ],
    "name:kat_x_variant":[
        "\u10e7\u10e3\u10d3\u10e0\u10dd",
        "Q\u2019udro"
    ],
    "name:und_x_variant":[
        "Kurdo"
    ],
    "wof:name":"Q'udro",
    "wof:placetype":"locality"
},
  "geometry": {"coordinates":[44.6509,41.33908],"type":"Point"}
}