{
  "type": "Feature",
  "properties": {
    "gn:admin1_code":"04",
    "gn:asciiname":"Salibauri",
    "gn:country_code":"GE",
    "gn:dem":39,
    "gn:feature_class":"P",
    "gn:feature_code":"PPL",
    "gn:name":"Salibauri",
    "gn:population":0,
    "gn:timezone":"Asia/Tbilisi",
    "iso:country":"GE",
    "name:kat_x_preferred":[
        "Salibauri"
    ],
    "name:kat_x_variant":[
        "\u10e1\u10d0\u10da\u10d8\u10d1\u10d0\u10e3\u10e0\u10d8"
    ],
    "name:rus_x_preferred":[
        "\u0421\u0430\u043b\u0438\u0431\u0430\u0443\u0440\u0438"
    ],
    "wof:name":"Salibauri",
    "wof:placetype":"locality"
},
  "geometry": {"coordinates":[41.67489000000001,41.64525],"type":"Point"}
}