{
  "type": "Feature",
  "properties": {
    "gn:admin1_code":"00",
    "gn:asciiname":"Vashliani",
    "gn:country_code":"GE",
    "gn:dem":1126,
    "gn:feature_class":"P",
    "gn:feature_code":"PPL",
    "gn:name":"Vashliani",
    "gn:population":0,
    "gn:timezone":"Asia/Tbilisi",
    "iso:country":"GE",
    "wof:name":"Vashliani",
    "wof:placetype":"locality"
},
  "geometry": {"coordinates":[45.16278,41.89067],"type":"Point"}
}