{
  "type": "Feature",
  "properties": {
    "gn:admin1_code":"00",
    "gn:asciiname":"Kurdghelauri",
    "gn:country_code":"GE",
    "gn:dem":597,
    "gn:feature_class":"P",
    "gn:feature_code":"PPL",
    "gn:name":"Kurdghelauri",
    "gn:population":0,
    "gn:timezone":"Asia/Tbilisi",
    "iso:country":"GE",
    "name:che_x_preferred":[
        "\u041a\u0443\u0440\u0434\u0433\u0435\u043b\u0430\u0443\u0440\u0438"
    ],
    "name:eng_x_preferred":[
        "Kurdghelauri"
    ],
    "name:hye_x_preferred":[
        "\u053f\u0578\u0582\u0580\u0564\u0563\u0565\u056c\u0561\u0578\u0582\u0580"
    ],
    "name:kat_x_preferred":[
        "\u10d9\u10e3\u10e0\u10d3\u10e6\u10d4\u10da\u10d0\u10e3\u10e0\u10d8"
    ],
    "name:rus_x_preferred":[
        "\u041a\u0443\u0440\u0434\u0433\u0435\u043b\u0430\u0443\u0440\u0438"
    ],
    "name:und_x_variant":[
        "Kurdgelauri",
        "Kurdghelauri"
    ],
    "wof:name":"Kurdghelauri",
    "wof:placetype":"locality"
},
  "geometry": {"coordinates":[45.4881,41.92937],"type":"Point"}
}