{
  "type": "Feature",
  "properties": {
    "gn:admin1_code":"69",
    "gn:asciiname":"Ch'abano",
    "gn:country_code":"GE",
    "gn:dem":1171,
    "gn:feature_class":"P",
    "gn:feature_code":"PPL",
    "gn:name":"Ch\u2019abano",
    "gn:population":0,
    "gn:timezone":"Asia/Tbilisi",
    "iso:country":"GE",
    "name:eng_x_preferred":[
        "Ch'abano"
    ],
    "name:rus_x_preferred":[
        "\u0427\u0430\u0431\u0430\u043d\u043e"
    ],
    "name:und_x_variant":[
        "Chobano",
        "Ch\u2019abano"
    ],
    "wof:name":"Ch'abano",
    "wof:placetype":"locality"
},
  "geometry": {"coordinates":[45.01789,42.14071],"type":"Point"}
}