{
  "type": "Feature",
  "properties": {
    "iso:country":"GE",
    "name:eng_x_preferred":[
        "Sno"
    ],
    "name:kat_x_preferred":[
        "Sno"
    ],
    "name:rus_x_preferred":[
        "\u0421\u043d\u043e"
    ],
    "qs:gn_country":"GE",
    "qs:gn_fcode":"PPL",
    "qs:gn_pop":0,
    "qs:name":"Sno",
    "qs:name_adm0":"Georgia",
    "qs:name_adm1":"Qazbegis Raioni",
    "qs:photos":60,
    "qs:photos_1k":12,
    "qs:photos_9k":1,
    "qs:photos_9r":2,
    "qs:photos_all":60,
    "qs:photos_sr":2,
    "qs:placetype":"Town",
    "qs:pop_sr":"0",
    "qs:woe_adm0":23424823,
    "wof:name":"Sno",
    "wof:placetype":"locality"
},
  "geometry": {"coordinates":[44.63889,42.60722],"type":"Point"}
}