{
  "type": "Feature",
  "properties": {
    "gn:admin1_code":"04",
    "gn:asciiname":"Namlisevi",
    "gn:country_code":"GE",
    "gn:dem":402,
    "gn:feature_class":"P",
    "gn:feature_code":"PPL",
    "gn:name":"Namlisevi",
    "gn:population":0,
    "gn:timezone":"Asia/Tbilisi",
    "iso:country":"GE",
    "name:kat_x_preferred":[
        "Namlisevi"
    ],
    "name:kat_x_variant":[
        "\u10dc\u10d0\u10db\u10da\u10d8\u10e1\u10d4\u10d5\u10d8"
    ],
    "wof:name":"Namlisevi",
    "wof:placetype":"locality"
},
  "geometry": {"coordinates":[41.81944,41.55083],"type":"Point"}
}