{
  "type": "Feature",
  "properties": {
    "gn:admin1_code":"66",
    "gn:asciiname":"Mekvena",
    "gn:country_code":"GE",
    "gn:dem":386,
    "gn:feature_class":"P",
    "gn:feature_code":"PPL",
    "gn:name":"Mekvena",
    "gn:population":0,
    "gn:timezone":"Asia/Tbilisi",
    "iso:country":"GE",
    "name:kat_x_preferred":[
        "Mekvena"
    ],
    "name:kat_x_variant":[
        "\u10db\u10d4\u10e5\u10d5\u10d4\u10dc\u10d0"
    ],
    "wof:name":"Mekvena",
    "wof:placetype":"locality"
},
  "geometry": {"coordinates":[42.75559000000001,42.47879],"type":"Point"}
}