{
  "type": "Feature",
  "properties": {
    "gn:admin1_code":"66",
    "gn:asciiname":"T'olebi",
    "gn:country_code":"GE",
    "gn:dem":191,
    "gn:feature_class":"P",
    "gn:feature_code":"PPL",
    "gn:name":"T\u2019olebi",
    "gn:population":0,
    "gn:timezone":"Asia/Tbilisi",
    "iso:country":"GE",
    "name:kat_x_preferred":[
        "T\u2019olebi"
    ],
    "name:kat_x_variant":[
        "\u10e2\u10dd\u10da\u10d4\u10d1\u10d8"
    ],
    "name:und_x_variant":[
        "Tolehi",
        "Tobati"
    ],
    "wof:name":"T'olebi",
    "wof:placetype":"locality"
},
  "geometry": {"coordinates":[42.23575,42.07081],"type":"Point"}
}