{
  "type": "Feature",
  "properties": {
    "gn:admin1_code":"00",
    "gn:asciiname":"Sakorintlo",
    "gn:cc2":"GE",
    "gn:country_code":"GE",
    "gn:dem":785,
    "gn:feature_class":"P",
    "gn:feature_code":"PPL",
    "gn:name":"Sakorintlo",
    "gn:population":0,
    "gn:timezone":"Asia/Tbilisi",
    "iso:country":"GE",
    "name:und_x_variant":[
        "Sakorintalo",
        "Sakorintlo"
    ],
    "wof:name":"Sakorintlo",
    "wof:placetype":"locality"
},
  "geometry": {"coordinates":[44.37861,42.04639],"type":"Point"}
}