{
  "type": "Feature",
  "properties": {
    "gn:admin1_code":"71",
    "gn:asciiname":"Ets'eri",
    "gn:country_code":"GE",
    "gn:dem":110,
    "gn:feature_class":"P",
    "gn:feature_code":"PPL",
    "gn:name":"Ets\u2019eri",
    "gn:population":0,
    "gn:timezone":"Asia/Tbilisi",
    "iso:country":"GE",
    "name:kat_x_preferred":[
        "Ets\u2019eri"
    ],
    "name:kat_x_variant":[
        "\u10d4\u10ec\u10d4\u10e0\u10d8"
    ],
    "wof:name":"Ets'eri",
    "wof:placetype":"locality"
},
  "geometry": {"coordinates":[42.05557,42.37345],"type":"Point"}
}