{
  "type": "Feature",
  "properties": {
    "gn:admin1_code":"00",
    "gn:asciiname":"Pikali",
    "gn:country_code":"GE",
    "gn:dem":1472,
    "gn:feature_class":"P",
    "gn:feature_code":"PPL",
    "gn:name":"Pikali",
    "gn:population":0,
    "gn:timezone":"Asia/Tbilisi",
    "iso:country":"GE",
    "wof:name":"Pikali",
    "wof:placetype":"locality"
},
  "geometry": {"coordinates":[45.73333,42.08333],"type":"Point"}
}