{
  "type": "Feature",
  "properties": {
    "gn:admin1_code":"66",
    "gn:asciiname":"Pateleseuli",
    "gn:country_code":"GE",
    "gn:dem":280,
    "gn:feature_class":"P",
    "gn:feature_code":"PPL",
    "gn:name":"Pateleseuli",
    "gn:population":0,
    "gn:timezone":"Asia/Tbilisi",
    "iso:country":"GE",
    "wof:name":"Pateleseuli",
    "wof:placetype":"locality"
},
  "geometry": {"coordinates":[42.46583,42.02528],"type":"Point"}
}