{
  "type": "Feature",
  "properties": {
    "gn:admin1_code":"71",
    "gn:asciiname":"Meore Mokhashi",
    "gn:country_code":"GE",
    "gn:dem":184,
    "gn:feature_class":"P",
    "gn:feature_code":"PPL",
    "gn:name":"Meore Mokhashi",
    "gn:population":0,
    "gn:timezone":"Asia/Tbilisi",
    "iso:country":"GE",
    "name:kat_x_preferred":[
        "Meore Mokhashi"
    ],
    "name:kat_x_variant":[
        "\u10db\u10d4\u10dd\u10e0\u10d4 \u10db\u10dd\u10ee\u10d0\u10e8\u10d8"
    ],
    "wof:name":"Meore Mokhashi",
    "wof:placetype":"locality"
},
  "geometry": {"coordinates":[42.1691,42.38664],"type":"Point"}
}