{
  "type": "Feature",
  "properties": {
    "gn:admin1_code":"69",
    "gn:asciiname":"Bazuani",
    "gn:country_code":"GE",
    "gn:dem":876,
    "gn:feature_class":"P",
    "gn:feature_code":"PPL",
    "gn:name":"Bazuani",
    "gn:population":0,
    "gn:timezone":"Asia/Tbilisi",
    "iso:country":"GE",
    "name:kat_x_preferred":[
        "Bazuani"
    ],
    "name:und_x_variant":[
        "Bazuant-Kari"
    ],
    "wof:name":"Bazuani",
    "wof:placetype":"locality"
},
  "geometry": {"coordinates":[44.47236,42.15111],"type":"Point"}
}