{
  "type": "Feature",
  "properties": {
    "gn:admin1_code":"71",
    "gn:asciiname":"Kolobani",
    "gn:country_code":"GE",
    "gn:dem":30,
    "gn:feature_class":"P",
    "gn:feature_code":"PPL",
    "gn:name":"Kolobani",
    "gn:population":0,
    "gn:timezone":"Asia/Tbilisi",
    "iso:country":"GE",
    "name:kat_x_preferred":[
        "\u10e5\u10dd\u10da\u10dd\u10d1\u10d0\u10dc\u10d8"
    ],
    "wof:name":"Kolobani",
    "wof:placetype":"locality"
},
  "geometry": {"coordinates":[42.27097,42.20306],"type":"Point"}
}