{
  "type": "Feature",
  "properties": {
    "gn:admin1_code":"00",
    "gn:asciiname":"Arpalo",
    "gn:country_code":"GE",
    "gn:dem":348,
    "gn:feature_class":"P",
    "gn:feature_code":"PPL",
    "gn:name":"Arpalo",
    "gn:population":0,
    "gn:timezone":"Asia/Tbilisi",
    "iso:country":"GE",
    "name:und_x_variant":[
        "Araplo",
        "Arpalo"
    ],
    "wof:name":"Arpalo",
    "wof:placetype":"locality"
},
  "geometry": {"coordinates":[44.85135,41.35789000000001],"type":"Point"}
}