{
  "type": "Feature",
  "properties": {
    "gn:admin1_code":"02",
    "gn:asciiname":"Zhabna",
    "gn:country_code":"GE",
    "gn:dem":133,
    "gn:feature_class":"P",
    "gn:feature_code":"PPL",
    "gn:name":"Zhabna",
    "gn:population":0,
    "gn:timezone":"Asia/Tbilisi",
    "iso:country":"GE",
    "name:kat_x_preferred":[
        "\u10df\u10d0\u10d1\u10dc\u10d0"
    ],
    "name:kat_x_variant":[
        "Zhabna"
    ],
    "wof:name":"Zhabna",
    "wof:placetype":"locality"
},
  "geometry": {"coordinates":[40.51472,43.22833],"type":"Point"}
}