{
  "type": "Feature",
  "properties": {
    "gn:country":"GE",
    "gn:fcode":"PPL",
    "gn:pop":3640,
    "iso:country":"GE",
    "name:dut_x_preferred":[
        "Akhaldaba"
    ],
    "name:eng_x_preferred":[
        "Akhaldaba"
    ],
    "name:geo_x_preferred":[
        "\u10d0\u10ee\u10d0\u10da\u10d3\u10d0\u10d1\u10d0"
    ],
    "name:kat_x_preferred":[
        "Akhaldaba"
    ],
    "name:kat_x_variant":[
        "\u10d0\u10ee\u10d0\u10da\u10d3\u10d0\u10d1\u10d0"
    ],
    "name:rus_x_preferred":[
        "\u0410\u0445\u0430\u043b\u0434\u0430\u0431\u0430"
    ],
    "qs:name":"Akhaldaba",
    "qs:photos_9r":0,
    "qs:photos_sr":0,
    "qs:pop_sr":"4",
    "wof:name":"Akhaldaba",
    "wof:placetype":"locality",
    "wof:population":3640
},
  "geometry": {"coordinates":[42.15163,41.65395],"type":"Point"}
}