{
  "type": "Feature",
  "properties": {
    "gn:admin1_code":"00",
    "gn:asciiname":"Omaraani",
    "gn:country_code":"GE",
    "gn:dem":1077,
    "gn:feature_class":"P",
    "gn:feature_code":"PPL",
    "gn:name":"Omaraani",
    "gn:population":0,
    "gn:timezone":"Asia/Tbilisi",
    "iso:country":"GE",
    "wof:name":"Omaraani",
    "wof:placetype":"locality"
},
  "geometry": {"coordinates":[45.12557,41.92714],"type":"Point"}
}