{
  "type": "Feature",
  "properties": {
    "iso:country":"GE",
    "name:aze_x_preferred":[
        "\u00c7aca\u015fi"
    ],
    "name:bak_x_preferred":[
        "\u0427\u0430\u0436\u0430\u0448\u0438"
    ],
    "name:bel_x_preferred":[
        "\u0427\u0430\u0436\u0430\u0448\u044b"
    ],
    "name:hye_x_preferred":[
        "\u0549\u0561\u056a\u0561\u0577"
    ],
    "name:kat_x_preferred":[
        "\u10e9\u10d0\u10df\u10d0\u10e8\u10d8"
    ],
    "name:rus_x_preferred":[
        "\u0427\u0430\u0436\u0430\u0448\u0438"
    ],
    "name:spa_x_preferred":[
        "Chazhashi"
    ],
    "name:srp_x_preferred":[
        "\u0427\u0430\u0436\u0430\u0448\u0438"
    ],
    "name:tur_x_preferred":[
        "\u00c7aja\u015fi"
    ],
    "name:unk_x_variant":[
        "Ch\u2019azhashi"
    ],
    "name:xmf_x_preferred":[
        "\u10e9\u10d0\u10df\u10d0\u10e8\u10d8"
    ],
    "qs:gn_country":"GE",
    "qs:gn_fcode":"PPL",
    "qs:gn_pop":0,
    "qs:name":"Chazhashi",
    "qs:name_adm0":"Georgia",
    "qs:name_adm1":"Lentekhis Raioni",
    "qs:photos":338,
    "qs:photos_1k":68,
    "qs:photos_9k":1,
    "qs:photos_9r":5,
    "qs:photos_all":338,
    "qs:photos_sr":5,
    "qs:placetype":"Town",
    "qs:pop_sr":"0",
    "qs:woe_adm0":23424823,
    "wof:name":"Chazhashi",
    "wof:placetype":"locality"
},
  "geometry": {"coordinates":[43.01744,42.91801],"type":"Point"}
}