{
  "type": "Feature",
  "properties": {
    "gn:admin1_code":"32",
    "gn:asciiname":"Akhalsop'eli",
    "gn:country_code":"GE",
    "gn:dem":18,
    "gn:feature_class":"P",
    "gn:feature_code":"PPL",
    "gn:name":"Akhalsop\u2019eli",
    "gn:population":0,
    "gn:timezone":"Asia/Tbilisi",
    "iso:country":"GE",
    "name:kat_x_preferred":[
        "Akhalsop\u2019eli"
    ],
    "name:kat_x_variant":[
        "\u10d0\u10ee\u10d0\u10da\u10e1\u10dd\u10e4\u10d4\u10da\u10d8"
    ],
    "wof:name":"Akhalsop'eli",
    "wof:placetype":"locality"
},
  "geometry": {"coordinates":[41.84109,42.05486],"type":"Point"}
}