{
  "type": "Feature",
  "properties": {
    "gn:admin1_code":"00",
    "gn:asciiname":"Urmi",
    "gn:country_code":"GE",
    "gn:dem":1813,
    "gn:feature_class":"P",
    "gn:feature_code":"PPL",
    "gn:name":"Urmi",
    "gn:population":0,
    "gn:timezone":"Asia/Tbilisi",
    "iso:country":"GE",
    "wof:name":"Urmi",
    "wof:placetype":"locality"
},
  "geometry": {"coordinates":[44.4575,42.47444],"type":"Point"}
}