{
  "type": "Feature",
  "properties": {
    "gn:admin1_code":"65",
    "gn:asciiname":"Tavp'ant'a",
    "gn:country_code":"GE",
    "gn:dem":423,
    "gn:feature_class":"P",
    "gn:feature_code":"PPL",
    "gn:name":"Tavp\u2019ant\u2019a",
    "gn:population":0,
    "gn:timezone":"Asia/Tbilisi",
    "iso:country":"GE",
    "name:kat_x_preferred":[
        "Tavp\u2019ant\u2019a"
    ],
    "name:kat_x_variant":[
        "\u10d7\u10d0\u10d5\u10de\u10d0\u10dc\u10e2\u10d0"
    ],
    "wof:name":"Tavp'ant'a",
    "wof:placetype":"locality"
},
  "geometry": {"coordinates":[42.34445,41.94394000000001],"type":"Point"}
}