{
  "type": "Feature",
  "properties": {
    "gn:admin1_code":"04",
    "gn:asciiname":"T'beti",
    "gn:country_code":"GE",
    "gn:dem":2449,
    "gn:elevation":"2463.0",
    "gn:feature_class":"P",
    "gn:feature_code":"PPL",
    "gn:name":"T\u2019beti",
    "gn:population":0,
    "gn:timezone":"Asia/Tbilisi",
    "iso:country":"GE",
    "name:kat_x_preferred":[
        "T\u2019beti"
    ],
    "name:kat_x_variant":[
        "\u10e2\u10d1\u10d4\u10d7\u10d8"
    ],
    "wof:name":"T'beti",
    "wof:placetype":"locality"
},
  "geometry": {"coordinates":[42.18927,41.54008],"type":"Point"}
}