{
  "type": "Feature",
  "properties": {
    "gn:admin1_code":"71",
    "gn:asciiname":"Olori",
    "gn:country_code":"GE",
    "gn:dem":932,
    "gn:feature_class":"P",
    "gn:feature_code":"PPL",
    "gn:name":"Olori",
    "gn:population":0,
    "gn:timezone":"Asia/Tbilisi",
    "iso:country":"GE",
    "name:kat_x_preferred":[
        "Olori"
    ],
    "name:kat_x_variant":[
        "\u10dd\u10da\u10dd\u10e0\u10d8"
    ],
    "wof:name":"Olori",
    "wof:placetype":"locality"
},
  "geometry": {"coordinates":[41.9944,42.7456],"type":"Point"}
}