{
  "type": "Feature",
  "properties": {
    "gn:admin1_code":"71",
    "gn:asciiname":"T'it'a",
    "gn:country_code":"GE",
    "gn:dem":1101,
    "gn:feature_class":"P",
    "gn:feature_code":"PPL",
    "gn:name":"T\u2019it\u2019a",
    "gn:population":0,
    "gn:timezone":"Asia/Tbilisi",
    "iso:country":"GE",
    "name:eng_x_preferred":[
        "Tita"
    ],
    "name:kat_x_preferred":[
        "\u10e2\u10d8\u10e2\u10d0"
    ],
    "name:kat_x_variant":[
        "T\u2019it\u2019a"
    ],
    "name:rus_x_preferred":[
        "\u0422\u0438\u0442\u0430"
    ],
    "name:und_x_variant":[
        "Tito"
    ],
    "wof:name":"T'it'a",
    "wof:placetype":"locality"
},
  "geometry": {"coordinates":[42.18556,43.09274],"type":"Point"}
}