{
  "type": "Feature",
  "properties": {
    "gn:admin1_code":"00",
    "gn:asciiname":"Zeni",
    "gn:country_code":"GE",
    "gn:dem":14,
    "gn:feature_class":"P",
    "gn:feature_code":"PPL",
    "gn:name":"Zeni",
    "gn:population":0,
    "gn:timezone":"Asia/Tbilisi",
    "iso:country":"GE",
    "name:ita_x_preferred":[
        "Zeni"
    ],
    "name:jpn_x_preferred":[
        "\u92ad"
    ],
    "name:kat_x_preferred":[
        "\u10d6\u10d4\u10dc\u10d8"
    ],
    "name:vie_x_preferred":[
        "Ti\u1ec1n"
    ],
    "name:zho_x_preferred":[
        "\u9322"
    ],
    "wof:name":"Zeni",
    "wof:placetype":"locality"
},
  "geometry": {"coordinates":[41.92167,42.30931],"type":"Point"}
}