{
  "type": "Feature",
  "properties": {
    "gn:admin1_code":"66",
    "gn:asciiname":"Bangveti",
    "gn:country_code":"GE",
    "gn:dem":608,
    "gn:feature_class":"P",
    "gn:feature_code":"PPL",
    "gn:name":"Bangveti",
    "gn:population":0,
    "gn:timezone":"Asia/Tbilisi",
    "iso:country":"GE",
    "name:kat_x_preferred":[
        "\u10d1\u10d4\u10dc\u10d2\u10d5\u10d4\u10d7\u10d8"
    ],
    "name:und_x_variant":[
        "Banchueti",
        "Banchuet"
    ],
    "wof:name":"Bangveti",
    "wof:placetype":"locality"
},
  "geometry": {"coordinates":[42.54457,42.45151],"type":"Point"}
}