{
  "type": "Feature",
  "properties": {
    "gn:admin1_code":"04",
    "gn:asciiname":"Beselashvilebi",
    "gn:country_code":"GE",
    "gn:dem":388,
    "gn:feature_class":"P",
    "gn:feature_code":"PPL",
    "gn:name":"Beselashvilebi",
    "gn:population":0,
    "gn:timezone":"Asia/Tbilisi",
    "iso:country":"GE",
    "name:kat_x_preferred":[
        "Beselashvilebi"
    ],
    "name:kat_x_variant":[
        "\u10d1\u10d4\u10e1\u10d4\u10da\u10d0\u10e8\u10d5\u10d8\u10da\u10d4\u10d1\u10d8"
    ],
    "wof:name":"Beselashvilebi",
    "wof:placetype":"locality"
},
  "geometry": {"coordinates":[42.15536,41.63661],"type":"Point"}
}