{
  "type": "Feature",
  "properties": {
    "gn:admin1_code":"00",
    "gn:asciiname":"Amlevi",
    "gn:country_code":"GE",
    "gn:dem":1100,
    "gn:feature_class":"P",
    "gn:feature_code":"PPL",
    "gn:name":"Amlevi",
    "gn:population":0,
    "gn:timezone":"Asia/Tbilisi",
    "iso:country":"GE",
    "name:kat_x_preferred":[
        "\u10d0\u10db\u10da\u10d4\u10d5\u10d8"
    ],
    "name:und_x_variant":[
        "Amlivi",
        "Amlevi"
    ],
    "wof:name":"Amlevi",
    "wof:placetype":"locality"
},
  "geometry": {"coordinates":[44.5155,41.62708],"type":"Point"}
}