{
  "type": "Feature",
  "properties": {
    "gn:admin1_code":"71",
    "gn:asciiname":"Zemo Bia",
    "gn:country_code":"GE",
    "gn:dem":124,
    "gn:feature_class":"P",
    "gn:feature_code":"PPL",
    "gn:name":"Zemo Bia",
    "gn:population":0,
    "gn:timezone":"Asia/Tbilisi",
    "iso:country":"GE",
    "name:kat_x_preferred":[
        "Zemo Bia"
    ],
    "name:kat_x_variant":[
        "\u10d6\u10d4\u10db\u10dd \u10d1\u10d8\u10d0"
    ],
    "wof:name":"Zemo Bia",
    "wof:placetype":"locality"
},
  "geometry": {"coordinates":[41.95652000000001,42.33987],"type":"Point"}
}