{
  "type": "Feature",
  "properties": {
    "gn:admin1_code":"00",
    "gn:asciiname":"Buyeti",
    "gn:country_code":"GE",
    "gn:dem":471,
    "gn:feature_class":"P",
    "gn:feature_code":"PPL",
    "gn:name":"Buyeti",
    "gn:population":0,
    "gn:timezone":"Asia/Tbilisi",
    "iso:country":"GE",
    "name:und_x_variant":[
        "Bueti",
        "\u10d1\u10e3\u10d4\u10d7\u10d8",
        "Buyeti"
    ],
    "wof:name":"Buyeti",
    "wof:placetype":"locality"
},
  "geometry": {"coordinates":[42.8819,42.33529],"type":"Point"}
}