{
  "type": "Feature",
  "properties": {
    "gn:admin1_code":"71",
    "gn:asciiname":"Namik'olavo Meore",
    "gn:country_code":"GE",
    "gn:dem":211,
    "gn:feature_class":"P",
    "gn:feature_code":"PPL",
    "gn:name":"Namik\u2019olavo Meore",
    "gn:population":0,
    "gn:timezone":"Asia/Tbilisi",
    "iso:country":"GE",
    "name:eng_x_preferred":[
        "Namikolavo Meore"
    ],
    "name:kat_x_preferred":[
        "Namik\u2019olavo Meore"
    ],
    "name:kat_x_variant":[
        "\u10dc\u10d0\u10db\u10d8\u10d9\u10dd\u10da\u10d0\u10d5\u10dd \u10db\u10d4\u10dd\u10e0\u10d4"
    ],
    "name:rus_x_preferred":[
        "\u041d\u0430\u043c\u0438\u043a\u043e\u043b\u0430\u0432\u043e-\u041c\u0435\u043e\u0440\u0435"
    ],
    "wof:name":"Namik'olavo Meore",
    "wof:placetype":"locality"
},
  "geometry": {"coordinates":[42.33188,42.47494],"type":"Point"}
}