{
  "type": "Feature",
  "properties": {
    "gn:admin1_code":"00",
    "gn:asciiname":"Patara-Medzhvriskhevi",
    "gn:country_code":"GE",
    "gn:dem":811,
    "gn:feature_class":"P",
    "gn:feature_code":"PPL",
    "gn:name":"Patara-Medzhvriskhevi",
    "gn:population":0,
    "gn:timezone":"Asia/Tbilisi",
    "iso:country":"GE",
    "wof:name":"Patara-Medzhvriskhevi",
    "wof:placetype":"locality"
},
  "geometry": {"coordinates":[44.20831,42.13264],"type":"Point"}
}