{
  "type": "Feature",
  "properties": {
    "gn:admin1_code":"71",
    "gn:asciiname":"Tsaleri",
    "gn:country_code":"GE",
    "gn:dem":1658,
    "gn:feature_class":"P",
    "gn:feature_code":"PPL",
    "gn:name":"Tsaleri",
    "gn:population":0,
    "gn:timezone":"Asia/Tbilisi",
    "iso:country":"GE",
    "name:kat_x_preferred":[
        "\u10ea\u10d0\u10da\u10d4\u10e0\u10d8"
    ],
    "wof:name":"Tsaleri",
    "wof:placetype":"locality"
},
  "geometry": {"coordinates":[42.4334,43.0781],"type":"Point"}
}