{
  "type": "Feature",
  "properties": {
    "gn:admin1_code":"04",
    "gn:asciiname":"Gorgadzeebi",
    "gn:country_code":"GE",
    "gn:dem":1462,
    "gn:feature_class":"P",
    "gn:feature_code":"PPL",
    "gn:name":"Gorgadzeebi",
    "gn:population":0,
    "gn:timezone":"Asia/Tbilisi",
    "iso:country":"GE",
    "name:kat_x_preferred":[
        "Gorgadzeebi"
    ],
    "name:kat_x_variant":[
        "\u10d2\u10dd\u10e0\u10d2\u10d0\u10eb\u10d4\u10d4\u10d1\u10d8"
    ],
    "name:rus_x_preferred":[
        "\u0413\u043e\u0440\u0433\u0430\u0434\u0437\u0435\u0435\u0431\u0438"
    ],
    "name:und_x_variant":[
        "Gorgadzeyebi"
    ],
    "wof:name":"Gorgadzeebi",
    "wof:placetype":"locality"
},
  "geometry": {"coordinates":[42.36929,41.72314],"type":"Point"}
}