{
  "type": "Feature",
  "properties": {
    "gn:admin1_code":"73",
    "gn:asciiname":"Ts'ots'khnara",
    "gn:country_code":"GE",
    "gn:dem":788,
    "gn:feature_class":"P",
    "gn:feature_code":"PPL",
    "gn:name":"Ts\u2019ots\u2019khnara",
    "gn:population":0,
    "gn:timezone":"Asia/Tbilisi",
    "iso:country":"GE",
    "name:kat_x_preferred":[
        "\u10ea\u10dd\u10ea\u10ee\u10dc\u10d0\u10e0\u10d0"
    ],
    "name:und_x_variant":[
        "Ts\u2019ots\u2019khnara"
    ],
    "wof:name":"Ts'ots'khnara",
    "wof:placetype":"locality"
},
  "geometry": {"coordinates":[43.57988,42.04826],"type":"Point"}
}