{
  "type": "Feature",
  "properties": {
    "gn:admin1_code":"69",
    "gn:asciiname":"Dzeglevi",
    "gn:country_code":"GE",
    "gn:dem":1076,
    "gn:feature_class":"P",
    "gn:feature_code":"PPL",
    "gn:name":"Dzeglevi",
    "gn:population":0,
    "gn:timezone":"Asia/Tbilisi",
    "iso:country":"GE",
    "wof:name":"Dzeglevi",
    "wof:placetype":"locality"
},
  "geometry": {"coordinates":[44.51944,42.11236],"type":"Point"}
}