{
  "type": "Feature",
  "properties": {
    "gn:admin1_code":"00",
    "gn:asciiname":"Verkhniye Sochi",
    "gn:cc2":"GE",
    "gn:country_code":"GE",
    "gn:dem":1746,
    "gn:feature_class":"P",
    "gn:feature_code":"PPL",
    "gn:name":"Verkhniye Sochi",
    "gn:population":0,
    "gn:timezone":"Asia/Tbilisi",
    "iso:country":"GE",
    "name:und_x_variant":[
        "Sotsi",
        "Verkhne-Sochi"
    ],
    "wof:name":"Verkhniye Sochi",
    "wof:placetype":"locality"
},
  "geometry": {"coordinates":[44.15,42.33389],"type":"Point"}
}