{
  "type": "Feature",
  "properties": {
    "gn:admin1_code":"71",
    "gn:asciiname":"Tamak'oni",
    "gn:country_code":"GE",
    "gn:dem":181,
    "gn:feature_class":"P",
    "gn:feature_code":"PPL",
    "gn:name":"Tamak\u2019oni",
    "gn:population":0,
    "gn:timezone":"Asia/Tbilisi",
    "iso:country":"GE",
    "name:kat_x_preferred":[
        "Tamak\u2019oni"
    ],
    "name:kat_x_variant":[
        "\u10d7\u10d0\u10db\u10d0\u10d9\u10dd\u10dc\u10d8"
    ],
    "wof:name":"Tamak'oni",
    "wof:placetype":"locality"
},
  "geometry": {"coordinates":[42.30095,42.45649],"type":"Point"}
}