{
  "type": "Feature",
  "properties": {
    "gn:admin1_code":"00",
    "gn:asciiname":"Svetmagali",
    "gn:country_code":"GE",
    "gn:dem":178,
    "gn:feature_class":"P",
    "gn:feature_code":"PPL",
    "gn:name":"Svetmagali",
    "gn:population":0,
    "gn:timezone":"Asia/Tbilisi",
    "iso:country":"GE",
    "wof:name":"Svetmagali",
    "wof:placetype":"locality"
},
  "geometry": {"coordinates":[42.87069,42.1513],"type":"Point"}
}