{
  "type": "Feature",
  "properties": {
    "gn:admin1_code":"04",
    "gn:asciiname":"K'ap'reshumi",
    "gn:country_code":"GE",
    "gn:dem":54,
    "gn:feature_class":"P",
    "gn:feature_code":"PPL",
    "gn:name":"K\u2019ap\u2019reshumi",
    "gn:population":0,
    "gn:timezone":"Asia/Tbilisi",
    "iso:country":"GE",
    "name:kat_x_preferred":[
        "K\u2019ap\u2019reshumi"
    ],
    "name:kat_x_variant":[
        "\u10d9\u10d0\u10de\u10e0\u10d4\u10e8\u10e3\u10db\u10d8"
    ],
    "name:rus_x_preferred":[
        "\u041a\u0430\u043f\u0440\u0435\u0448\u0443\u043c\u0438"
    ],
    "name:und_x_variant":[
        "Kapreshumi"
    ],
    "wof:name":"K'ap'reshumi",
    "wof:placetype":"locality"
},
  "geometry": {"coordinates":[41.70556,41.65361],"type":"Point"}
}