{
  "type": "Feature",
  "properties": {
    "gn:admin1_code":"00",
    "gn:asciiname":"Churnali",
    "gn:country_code":"GE",
    "gn:dem":741,
    "gn:feature_class":"P",
    "gn:feature_code":"PPL",
    "gn:name":"Churnali",
    "gn:population":0,
    "gn:timezone":"Asia/Tbilisi",
    "iso:country":"GE",
    "wof:name":"Churnali",
    "wof:placetype":"locality"
},
  "geometry": {"coordinates":[43.60104000000001,42.36497],"type":"Point"}
}