{
  "type": "Feature",
  "properties": {
    "gn:admin1_code":"00",
    "gn:asciiname":"Ortsva",
    "gn:country_code":"GE",
    "gn:dem":853,
    "gn:feature_class":"P",
    "gn:feature_code":"PPL",
    "gn:name":"Ortsva",
    "gn:population":0,
    "gn:timezone":"Asia/Tbilisi",
    "iso:country":"GE",
    "wof:name":"Ortsva",
    "wof:placetype":"locality"
},
  "geometry": {"coordinates":[41.91667,41.73333],"type":"Point"}
}