{
  "type": "Feature",
  "properties": {
    "gn:admin1_code":"04",
    "gn:asciiname":"Kveda Bzubzu",
    "gn:country_code":"GE",
    "gn:dem":238,
    "gn:feature_class":"P",
    "gn:feature_code":"PPL",
    "gn:name":"Kveda Bzubzu",
    "gn:population":0,
    "gn:timezone":"Asia/Tbilisi",
    "iso:country":"GE",
    "name:kat_x_preferred":[
        "Kveda Bzubzu"
    ],
    "name:kat_x_variant":[
        "\u10e5\u10d5\u10d4\u10d3\u10d0 \u10d1\u10d6\u10e3\u10d1\u10d6\u10e3"
    ],
    "wof:name":"Kveda Bzubzu",
    "wof:placetype":"locality"
},
  "geometry": {"coordinates":[41.83944,41.56167],"type":"Point"}
}