{
  "type": "Feature",
  "properties": {
    "gn:admin1_code":"02",
    "gn:asciiname":"Vtoroy Arasadzykh",
    "gn:country_code":"GE",
    "gn:dem":189,
    "gn:feature_class":"P",
    "gn:feature_code":"PPL",
    "gn:name":"Vtoroy Arasadzykh",
    "gn:population":0,
    "gn:timezone":"Asia/Tbilisi",
    "iso:country":"GE",
    "name:und_x_variant":[
        "Vtoroy Arasadzikh",
        "Vtoroy Arasadzykhi",
        "Vtoroy Arasadzykh"
    ],
    "wof:name":"Vtoroy Arasadzykh",
    "wof:placetype":"locality"
},
  "geometry": {"coordinates":[41.58867,42.89674],"type":"Point"}
}