{
  "type": "Feature",
  "properties": {
    "gn:admin1_code":"00",
    "gn:asciiname":"Chabarukhi",
    "gn:country_code":"GE",
    "gn:dem":1448,
    "gn:feature_class":"P",
    "gn:feature_code":"PPL",
    "gn:name":"Chabarukhi",
    "gn:population":0,
    "gn:timezone":"Asia/Tbilisi",
    "iso:country":"GE",
    "wof:name":"Chabarukhi",
    "wof:placetype":"locality"
},
  "geometry": {"coordinates":[44.66917,42.35667],"type":"Point"}
}