{
  "type": "Feature",
  "properties": {
    "gn:admin1_code":"00",
    "gn:asciiname":"Ertisi",
    "gn:country_code":"GE",
    "gn:dem":844,
    "gn:feature_class":"P",
    "gn:feature_code":"PPL",
    "gn:name":"Ertisi",
    "gn:population":0,
    "gn:timezone":"Asia/Tbilisi",
    "iso:country":"GE",
    "name:kat_x_preferred":[
        "\u10d4\u10e0\u10e2\u10d8\u10e1\u10d8"
    ],
    "wof:name":"Ertisi",
    "wof:placetype":"locality"
},
  "geometry": {"coordinates":[44.73179,41.61845],"type":"Point"}
}