{
  "type": "Feature",
  "properties": {
    "gn:admin1_code":"00",
    "gn:asciiname":"Sagartskio",
    "gn:country_code":"GE",
    "gn:dem":93,
    "gn:feature_class":"P",
    "gn:feature_code":"PPL",
    "gn:name":"Sagartskio",
    "gn:population":0,
    "gn:timezone":"Asia/Tbilisi",
    "iso:country":"GE",
    "wof:name":"Sagartskio",
    "wof:placetype":"locality"
},
  "geometry": {"coordinates":[41.66667,42.76667],"type":"Point"}
}