{
  "type": "Feature",
  "properties": {
    "gn:admin1_code":"71",
    "gn:asciiname":"Zeda Ets'eri",
    "gn:country_code":"GE",
    "gn:dem":204,
    "gn:feature_class":"P",
    "gn:feature_code":"PPL",
    "gn:name":"Zeda Ets\u2019eri",
    "gn:population":0,
    "gn:timezone":"Asia/Tbilisi",
    "iso:country":"GE",
    "name:eng_x_preferred":[
        "Zeda Etseri"
    ],
    "name:kat_x_preferred":[
        "Zeda Ets\u2019eri"
    ],
    "name:kat_x_variant":[
        "\u10d6\u10d4\u10d3\u10d0 \u10d4\u10ec\u10d4\u10e0\u10d8"
    ],
    "name:rus_x_preferred":[
        "\u0417\u0435\u0434\u0430-\u042d\u0446\u0435\u0440\u0438"
    ],
    "wof:name":"Zeda Ets'eri",
    "wof:placetype":"locality"
},
  "geometry": {"coordinates":[41.93836,42.58957],"type":"Point"}
}