{
  "type": "Feature",
  "properties": {
    "gn:admin1_code":"69",
    "gn:asciiname":"Pitavi",
    "gn:country_code":"GE",
    "gn:dem":945,
    "gn:feature_class":"P",
    "gn:feature_code":"PPL",
    "gn:name":"Pitavi",
    "gn:population":0,
    "gn:timezone":"Asia/Tbilisi",
    "iso:country":"GE",
    "wof:name":"Pitavi",
    "wof:placetype":"locality"
},
  "geometry": {"coordinates":[44.72806,42.15556],"type":"Point"}
}