{
  "type": "Feature",
  "properties": {
    "gn:admin1_code":"65",
    "gn:asciiname":"Ch'ala Kadagauri",
    "gn:country_code":"GE",
    "gn:dem":585,
    "gn:feature_class":"P",
    "gn:feature_code":"PPL",
    "gn:name":"Ch\u2019ala Kadagauri",
    "gn:population":0,
    "gn:timezone":"Asia/Tbilisi",
    "iso:country":"GE",
    "name:kat_x_preferred":[
        "Kala Kadagauri"
    ],
    "name:kat_x_variant":[
        "\u10e5\u10d0\u10da\u10d0 \u10e5\u10d0\u10d3\u10d0\u10d2\u10d0\u10e3\u10e0\u10d8",
        "Ch\u2019ala Kadagauri",
        "\u10ed\u10d0\u10da\u10d0 \u10e5\u10d0\u10d3\u10d0\u10d2\u10d0\u10e3\u10e0\u10d8"
    ],
    "wof:name":"Ch'ala Kadagauri",
    "wof:placetype":"locality"
},
  "geometry": {"coordinates":[42.4567,41.94909000000001],"type":"Point"}
}