{
  "type": "Feature",
  "properties": {
    "gn:admin1_code":"00",
    "gn:asciiname":"Zedubani",
    "gn:country_code":"GE",
    "gn:dem":731,
    "gn:feature_class":"P",
    "gn:feature_code":"PPL",
    "gn:name":"Zedubani",
    "gn:population":0,
    "gn:timezone":"Asia/Tbilisi",
    "iso:country":"GE",
    "wof:name":"Zedubani",
    "wof:placetype":"locality"
},
  "geometry": {"coordinates":[45.77944,41.65278],"type":"Point"}
}