{
  "type": "Feature",
  "properties": {
    "gn:admin1_code":"69",
    "gn:asciiname":"Akhalsop'eli",
    "gn:country_code":"GE",
    "gn:dem":1131,
    "gn:feature_class":"P",
    "gn:feature_code":"PPL",
    "gn:name":"Akhalsop\u2019eli",
    "gn:population":0,
    "gn:timezone":"Asia/Tbilisi",
    "iso:country":"GE",
    "wof:name":"Akhalsop'eli",
    "wof:placetype":"locality"
},
  "geometry": {"coordinates":[44.99722,42.13028],"type":"Point"}
}