{
  "type": "Feature",
  "properties": {
    "gn:admin1_code":"00",
    "gn:asciiname":"Chkheri",
    "gn:country_code":"GE",
    "gn:dem":547,
    "gn:feature_class":"P",
    "gn:feature_code":"PPL",
    "gn:name":"Chkheri",
    "gn:population":0,
    "gn:timezone":"Asia/Tbilisi",
    "iso:country":"GE",
    "wof:name":"Chkheri",
    "wof:placetype":"locality"
},
  "geometry": {"coordinates":[43.23715,42.00481],"type":"Point"}
}