{
  "type": "Feature",
  "properties": {
    "gn:admin1_code":"04",
    "gn:asciiname":"Khvarbeti",
    "gn:country_code":"GE",
    "gn:dem":93,
    "gn:feature_class":"P",
    "gn:feature_code":"PPL",
    "gn:name":"Khvarbeti",
    "gn:population":0,
    "gn:timezone":"Asia/Tbilisi",
    "iso:country":"GE",
    "name:hye_x_preferred":[
        "\u053d\u057e\u0561\u0580\u0562\u0565\u0569"
    ],
    "name:kat_x_preferred":[
        "\u10d6\u10d5\u10d0\u10e0\u10d1\u10d4\u10d7\u10d8"
    ],
    "name:kat_x_variant":[
        "\u10ee\u10d5\u10d0\u10e0\u10d1\u10d4\u10d7\u10d8"
    ],
    "name:rus_x_preferred":[
        "\u0425\u0432\u0430\u0440\u0431\u0435\u0442\u0438"
    ],
    "name:ukr_x_preferred":[
        "\u0425\u0432\u0430\u0440\u0431\u0435\u0442\u0456"
    ],
    "wof:name":"Khvarbeti",
    "wof:placetype":"locality"
},
  "geometry": {"coordinates":[41.91604,41.95546],"type":"Point"}
}