{
  "type": "Feature",
  "properties": {
    "gn:admin1_code":"04",
    "gn:asciiname":"Khvarbeti",
    "gn:country_code":"GE",
    "gn:dem":93,
    "gn:feature_class":"P",
    "gn:feature_code":"PPL",
    "gn:name":"Khvarbeti",
    "gn:population":0,
    "gn:timezone":"Asia/Tbilisi",
    "iso:country":"GE",
    "name:kat_x_preferred":[
        "\u10d6\u10d5\u10d0\u10e0\u10d1\u10d4\u10d7\u10d8"
    ],
    "wof:name":"Khvarbeti",
    "wof:placetype":"locality"
},
  "geometry": {"coordinates":[41.91604,41.95546],"type":"Point"}
}