{
  "type": "Feature",
  "properties": {
    "gn:admin1_code":"69",
    "gn:asciiname":"Tsodoreti",
    "gn:country_code":"GE",
    "gn:dem":889,
    "gn:feature_class":"P",
    "gn:feature_code":"PPL",
    "gn:name":"Tsodoreti",
    "gn:population":0,
    "gn:timezone":"Asia/Tbilisi",
    "iso:country":"GE",
    "wof:name":"Tsodoreti",
    "wof:placetype":"locality"
},
  "geometry": {"coordinates":[44.65656,41.76145],"type":"Point"}
}