{
  "type": "Feature",
  "properties": {
    "gn:admin1_code":"69",
    "gn:asciiname":"Dzhervalidzeyebi",
    "gn:country_code":"GE",
    "gn:dem":1254,
    "gn:feature_class":"P",
    "gn:feature_code":"PPL",
    "gn:name":"Dzhervalidzeyebi",
    "gn:population":0,
    "gn:timezone":"Asia/Tbilisi",
    "iso:country":"GE",
    "wof:name":"Dzhervalidzeyebi",
    "wof:placetype":"locality"
},
  "geometry": {"coordinates":[44.88,42.14778],"type":"Point"}
}