{
  "type": "Feature",
  "properties": {
    "gn:admin1_code":"04",
    "gn:asciiname":"Sachino",
    "gn:country_code":"GE",
    "gn:dem":81,
    "gn:feature_class":"P",
    "gn:feature_code":"PPL",
    "gn:name":"Sachino",
    "gn:population":0,
    "gn:timezone":"Asia/Tbilisi",
    "iso:country":"GE",
    "name:kat_x_preferred":[
        "Zeda Ulianovka"
    ],
    "name:kat_x_variant":[
        "Sachino",
        "\u10e1\u10d0\u10e9\u10d8\u10dc\u10dd"
    ],
    "name:rus_x_preferred":[
        "Zeda-Ul\u2019yanovka"
    ],
    "wof:name":"Sachino",
    "wof:placetype":"locality"
},
  "geometry": {"coordinates":[41.75597,41.7372],"type":"Point"}
}