{
  "type": "Feature",
  "properties": {
    "gn:admin1_code":"04",
    "gn:asciiname":"Sakhalvasho",
    "gn:country_code":"GE",
    "gn:dem":48,
    "gn:feature_class":"P",
    "gn:feature_code":"PPL",
    "gn:name":"Sakhalvasho",
    "gn:population":0,
    "gn:timezone":"Asia/Tbilisi",
    "iso:country":"GE",
    "name:kat_x_preferred":[
        "Sakhalvasho"
    ],
    "name:kat_x_variant":[
        "\u10e1\u10d0\u10ee\u10d0\u10da\u10d5\u10d0\u10e8\u10dd"
    ],
    "wof:name":"Sakhalvasho",
    "wof:placetype":"locality"
},
  "geometry": {"coordinates":[41.72425,41.70299],"type":"Point"}
}