{
  "type": "Feature",
  "properties": {
    "gn:admin1_code":"71",
    "gn:asciiname":"Mukhurcha",
    "gn:country_code":"GE",
    "gn:dem":68,
    "gn:feature_class":"P",
    "gn:feature_code":"PPL",
    "gn:name":"Mukhurcha",
    "gn:population":0,
    "gn:timezone":"Asia/Tbilisi",
    "iso:country":"GE",
    "name:kat_x_preferred":[
        "Mukhurcha"
    ],
    "name:kat_x_variant":[
        "\u10db\u10e3\u10ee\u10e3\u10e0\u10e9\u10d0"
    ],
    "wof:name":"Mukhurcha",
    "wof:placetype":"locality"
},
  "geometry": {"coordinates":[42.24635,42.3168],"type":"Point"}
}