{
  "type": "Feature",
  "properties": {
    "gn:admin1_code":"00",
    "gn:asciiname":"Kvarkhiti",
    "gn:country_code":"GE",
    "gn:dem":716,
    "gn:feature_class":"P",
    "gn:feature_code":"PPL",
    "gn:name":"Kvarkhiti",
    "gn:population":0,
    "gn:timezone":"Asia/Tbilisi",
    "iso:country":"GE",
    "wof:name":"Kvarkhiti",
    "wof:placetype":"locality"
},
  "geometry": {"coordinates":[44.19311,42.07722],"type":"Point"}
}