{
  "type": "Feature",
  "properties": {
    "gn:admin1_code":"00",
    "gn:asciiname":"Tsorbisi",
    "gn:country_code":"GE",
    "gn:dem":921,
    "gn:feature_class":"P",
    "gn:feature_code":"PPL",
    "gn:name":"Tsorbisi",
    "gn:population":0,
    "gn:timezone":"Asia/Tbilisi",
    "iso:country":"GE",
    "wof:name":"Tsorbisi",
    "wof:placetype":"locality"
},
  "geometry": {"coordinates":[43.79986,42.26972],"type":"Point"}
}