{
  "type": "Feature",
  "properties": {
    "gn:admin1_code":"04",
    "gn:asciiname":"Gundauri",
    "gn:country_code":"GE",
    "gn:dem":438,
    "gn:feature_class":"P",
    "gn:feature_code":"PPL",
    "gn:name":"Gundauri",
    "gn:population":0,
    "gn:timezone":"Asia/Tbilisi",
    "iso:country":"GE",
    "name:kat_x_preferred":[
        "Gundauri"
    ],
    "name:kat_x_variant":[
        "\u10d2\u10e3\u10dc\u10d3\u10d0\u10e3\u10e0\u10d8"
    ],
    "name:und_x_variant":[
        "Baramoghlebi",
        "Baramoglebi"
    ],
    "wof:name":"Gundauri",
    "wof:placetype":"locality"
},
  "geometry": {"coordinates":[42.00912,41.57312],"type":"Point"}
}