{
  "type": "Feature",
  "properties": {
    "gn:admin1_code":"00",
    "gn:asciiname":"Zemo Tsolda",
    "gn:country_code":"GE",
    "gn:dem":1293,
    "gn:feature_class":"P",
    "gn:feature_code":"PPL",
    "gn:name":"Zemo Tsolda",
    "gn:population":0,
    "gn:timezone":"Asia/Tbilisi",
    "iso:country":"GE",
    "name:kat_x_preferred":[
        "Zemo Tsolda"
    ],
    "name:und_x_variant":[
        "Verkhnyaya Tsolda"
    ],
    "wof:name":"Zemo Tsolda",
    "wof:placetype":"locality"
},
  "geometry": {"coordinates":[44.32442,42.17437],"type":"Point"}
}