{
  "type": "Feature",
  "properties": {
    "gn:admin1_code":"00",
    "gn:asciiname":"Kudoti",
    "gn:country_code":"GE",
    "gn:dem":321,
    "gn:feature_class":"P",
    "gn:feature_code":"PPL",
    "gn:name":"Kudoti",
    "gn:population":0,
    "gn:timezone":"Asia/Tbilisi",
    "iso:country":"GE",
    "wof:name":"Kudoti",
    "wof:placetype":"locality"
},
  "geometry": {"coordinates":[42.71944000000001,42.36167],"type":"Point"}
}