{
  "type": "Feature",
  "properties": {
    "gn:admin1_code":"72",
    "gn:asciiname":"Ozni",
    "gn:country_code":"GE",
    "gn:dem":1566,
    "gn:feature_class":"P",
    "gn:feature_code":"PPL",
    "gn:name":"Ozni",
    "gn:population":0,
    "gn:timezone":"Asia/Tbilisi",
    "iso:country":"GE",
    "name:kat_x_preferred":[
        "Ozni"
    ],
    "name:kat_x_variant":[
        "\u10dd\u10d6\u10dc\u10d8"
    ],
    "wof:name":"Ozni",
    "wof:placetype":"locality"
},
  "geometry": {"coordinates":[43.86232,41.62882000000001],"type":"Point"}
}