{
  "type": "Feature",
  "properties": {
    "gn:admin1_code":"71",
    "gn:asciiname":"Magardeli",
    "gn:country_code":"GE",
    "gn:dem":1228,
    "gn:feature_class":"P",
    "gn:feature_code":"PPL",
    "gn:name":"Magardeli",
    "gn:population":0,
    "gn:timezone":"Asia/Tbilisi",
    "iso:country":"GE",
    "name:kat_x_preferred":[
        "\u10db\u10d0\u10d2\u10d0\u10e0\u10d3\u10d4\u10da\u10d8"
    ],
    "wof:name":"Magardeli",
    "wof:placetype":"locality"
},
  "geometry": {"coordinates":[42.55808,43.00484],"type":"Point"}
}