{
  "type": "Feature",
  "properties": {
    "gn:admin1_code":"00",
    "gn:asciiname":"Prisi",
    "gn:country_code":"GE",
    "gn:dem":1014,
    "gn:feature_class":"P",
    "gn:feature_code":"PPL",
    "gn:name":"Prisi",
    "gn:population":0,
    "gn:timezone":"Asia/Tbilisi",
    "iso:country":"GE",
    "wof:name":"Prisi",
    "wof:placetype":"locality"
},
  "geometry": {"coordinates":[43.99083,42.23389],"type":"Point"}
}