{
  "type": "Feature",
  "properties": {
    "gn:admin1_code":"00",
    "gn:asciiname":"Chkharetseri",
    "gn:country_code":"GE",
    "gn:dem":195,
    "gn:feature_class":"P",
    "gn:feature_code":"PPL",
    "gn:name":"Chkharetseri",
    "gn:population":0,
    "gn:timezone":"Asia/Tbilisi",
    "iso:country":"GE",
    "name:und_x_variant":[
        "Chkhari-Etseri",
        "Chkharetseri"
    ],
    "wof:name":"Chkharetseri",
    "wof:placetype":"locality"
},
  "geometry": {"coordinates":[42.93278,42.21763],"type":"Point"}
}