{
  "type": "Feature",
  "properties": {
    "gn:admin1_code":"00",
    "gn:asciiname":"Chapayevka",
    "gn:country_code":"GE",
    "gn:dem":1616,
    "gn:feature_class":"P",
    "gn:feature_code":"PPL",
    "gn:name":"Chapayevka",
    "gn:population":0,
    "gn:timezone":"Asia/Tbilisi",
    "iso:country":"GE",
    "name:ceb_x_preferred":[
        "Chapayevka"
    ],
    "name:deu_x_preferred":[
        "Tschapajewka"
    ],
    "name:hye_x_preferred":[
        "\u0549\u0561\u057a\u0561\u0587\u056f\u0561"
    ],
    "name:kat_x_preferred":[
        "\u10e9\u10d0\u10de\u10d0\u10d4\u10d5\u10d9\u10d0"
    ],
    "name:rus_x_preferred":[
        "\u0427\u0430\u043f\u0430\u0435\u0432\u043a\u0430"
    ],
    "name:ukr_x_preferred":[
        "\u0427\u0430\u043f\u0430\u0454\u0432\u043a\u0430"
    ],
    "name:und_x_variant":[
        "Yakublo",
        "Chapayevka"
    ],
    "wof:name":"Chapayevka",
    "wof:placetype":"locality"
},
  "geometry": {"coordinates":[44.08122,41.55188],"type":"Point"}
}