{
  "type": "Feature",
  "properties": {
    "gn:admin1_code":"00",
    "gn:asciiname":"Papari",
    "gn:country_code":"GE",
    "gn:dem":1758,
    "gn:feature_class":"P",
    "gn:feature_code":"PPL",
    "gn:name":"Papari",
    "gn:population":0,
    "gn:timezone":"Asia/Tbilisi",
    "iso:country":"GE",
    "wof:name":"Papari",
    "wof:placetype":"locality"
},
  "geometry": {"coordinates":[45.14444,42.33028],"type":"Point"}
}