{
  "type": "Feature",
  "properties": {
    "gn:admin1_code":"00",
    "gn:asciiname":"Papari",
    "gn:country_code":"GE",
    "gn:dem":1758,
    "gn:feature_class":"P",
    "gn:feature_code":"PPL",
    "gn:name":"Papari",
    "gn:population":0,
    "gn:timezone":"Asia/Tbilisi",
    "iso:country":"GE",
    "name:ara_x_preferred":[
        "\u0628\u0627\u0628\u0627\u0631\u064a"
    ],
    "name:bos_x_preferred":[
        "Papari"
    ],
    "name:ceb_x_preferred":[
        "Papari"
    ],
    "name:ell_x_preferred":[
        "\u03a0\u03ac\u03c0\u03b1\u03c1\u03b9"
    ],
    "name:fra_x_preferred":[
        "Papari"
    ],
    "name:hrv_x_preferred":[
        "Papari"
    ],
    "name:slv_x_preferred":[
        "Papari"
    ],
    "name:srp_x_preferred":[
        "\u041f\u0430\u043f\u0430\u0440\u0438"
    ],
    "wof:name":"Papari",
    "wof:placetype":"locality"
},
  "geometry": {"coordinates":[45.14444,42.33028],"type":"Point"}
}