{
  "type": "Feature",
  "properties": {
    "gn:admin1_code":"32",
    "gn:asciiname":"Juruqvet'i",
    "gn:country_code":"GE",
    "gn:dem":16,
    "gn:feature_class":"P",
    "gn:feature_code":"PPL",
    "gn:name":"Juruqvet\u2019i",
    "gn:population":0,
    "gn:timezone":"Asia/Tbilisi",
    "iso:country":"GE",
    "name:kat_x_preferred":[
        "Juruqvet\u2019i"
    ],
    "name:kat_x_variant":[
        "\u10ef\u10e3\u10e0\u10e3\u10e7\u10d5\u10d4\u10d7\u10d8"
    ],
    "name:und_x_variant":[
        "Dzhurukveti",
        "Jurukveti",
        "Dzhurkveti"
    ],
    "wof:name":"Juruqvet'i",
    "wof:placetype":"locality"
},
  "geometry": {"coordinates":[41.91167,42.07739],"type":"Point"}
}