{
  "type": "Feature",
  "properties": {
    "gn:admin1_code":"04",
    "gn:asciiname":"Kveda Agara",
    "gn:country_code":"GE",
    "gn:dem":264,
    "gn:feature_class":"P",
    "gn:feature_code":"PPL",
    "gn:name":"Kveda Agara",
    "gn:population":0,
    "gn:timezone":"Asia/Tbilisi",
    "iso:country":"GE",
    "name:kat_x_preferred":[
        "Kvemo-Agara"
    ],
    "name:kat_x_variant":[
        "Kveda Agara",
        "\u10e5\u10d5\u10d4\u10d3\u10d0 \u10d0\u10d2\u10d0\u10e0\u10d0"
    ],
    "wof:name":"Kveda Agara",
    "wof:placetype":"locality"
},
  "geometry": {"coordinates":[41.90067,41.59979000000001],"type":"Point"}
}