{
  "type": "Feature",
  "properties": {
    "gn:admin1_code":"72",
    "gn:asciiname":"Burnashet'i",
    "gn:country_code":"GE",
    "gn:dem":1840,
    "gn:feature_class":"P",
    "gn:feature_code":"PPL",
    "gn:name":"Burnashet\u2019i",
    "gn:population":0,
    "gn:timezone":"Asia/Tbilisi",
    "iso:country":"GE",
    "name:kat_x_preferred":[
        "\u10d1\u10e3\u10e0\u10dc\u10d0\u10e8\u10d4\u10d7\u10d8"
    ],
    "name:und_x_variant":[
        "Burnashet\u2019i"
    ],
    "wof:name":"Burnashet'i",
    "wof:placetype":"locality"
},
  "geometry": {"coordinates":[43.46894,41.58565],"type":"Point"}
}