{
  "type": "Feature",
  "properties": {
    "gn:admin1_code":"02",
    "gn:asciiname":"Chernigovk'a",
    "gn:country_code":"GE",
    "gn:dem":229,
    "gn:feature_class":"P",
    "gn:feature_code":"PPL",
    "gn:name":"Chernigovk\u2019a",
    "gn:population":0,
    "gn:timezone":"Asia/Tbilisi",
    "iso:country":"GE",
    "name:kat_x_preferred":[
        "Chernigovk\u2019a"
    ],
    "name:kat_x_variant":[
        "\u10e9\u10d4\u10e0\u10dc\u10d8\u10d2\u10dd\u10d5\u10d9\u10d0"
    ],
    "wof:name":"Chernigovk'a",
    "wof:placetype":"locality"
},
  "geometry": {"coordinates":[41.26414000000001,42.9485],"type":"Point"}
}