{
  "type": "Feature",
  "properties": {
    "gn:admin1_code":"00",
    "gn:asciiname":"Chanakhchi",
    "gn:country_code":"GE",
    "gn:dem":1067,
    "gn:feature_class":"P",
    "gn:feature_code":"PPL",
    "gn:name":"Chanakhchi",
    "gn:population":0,
    "gn:timezone":"Asia/Tbilisi",
    "iso:country":"GE",
    "name:kat_x_preferred":[
        "\u10e9\u10d0\u10dc\u10d0\u10ee\u10e9\u10d8"
    ],
    "name:und_x_variant":[
        "Dzilidza",
        "Chanakhchi"
    ],
    "wof:name":"Chanakhchi",
    "wof:placetype":"locality"
},
  "geometry": {"coordinates":[44.60139,41.23547],"type":"Point"}
}