{
  "type": "Feature",
  "properties": {
    "gn:admin1_code":"00",
    "gn:asciiname":"Gomaro",
    "gn:country_code":"GE",
    "gn:dem":1593,
    "gn:feature_class":"P",
    "gn:feature_code":"PPL",
    "gn:name":"Gomaro",
    "gn:population":0,
    "gn:timezone":"Asia/Tbilisi",
    "iso:country":"GE",
    "wof:name":"Gomaro",
    "wof:placetype":"locality"
},
  "geometry": {"coordinates":[42.74286,41.70589],"type":"Point"}
}