{
  "type": "Feature",
  "properties": {
    "gn:admin1_code":"66",
    "gn:asciiname":"Udzlouri",
    "gn:country_code":"GE",
    "gn:dem":166,
    "gn:feature_class":"P",
    "gn:feature_code":"PPL",
    "gn:name":"Udzlouri",
    "gn:population":0,
    "gn:timezone":"Asia/Tbilisi",
    "iso:country":"GE",
    "name:und_x_variant":[
        "Udzluri",
        "Udzlouri"
    ],
    "wof:name":"Udzlouri",
    "wof:placetype":"locality"
},
  "geometry": {"coordinates":[42.55833,42.39056],"type":"Point"}
}