{
  "type": "Feature",
  "properties": {
    "gn:admin1_code":"66",
    "gn:asciiname":"Ochopa-Gvimrala",
    "gn:country_code":"GE",
    "gn:dem":27,
    "gn:feature_class":"P",
    "gn:feature_code":"PPL",
    "gn:name":"Ochopa-Gvimrala",
    "gn:population":0,
    "gn:timezone":"Asia/Tbilisi",
    "iso:country":"GE",
    "name:und_x_variant":[
        "Ochopa",
        "Ochopa-Gvimrala"
    ],
    "wof:name":"Ochopa-Gvimrala",
    "wof:placetype":"locality"
},
  "geometry": {"coordinates":[42.36667,42.16667],"type":"Point"}
}