{
  "type": "Feature",
  "properties": {
    "gn:admin1_code":"00",
    "gn:asciiname":"Varketili",
    "gn:country_code":"GE",
    "gn:dem":564,
    "gn:feature_class":"P",
    "gn:feature_code":"PPL",
    "gn:name":"Varketili",
    "gn:population":0,
    "gn:timezone":"Asia/Tbilisi",
    "iso:country":"GE",
    "name:und_x_variant":[
        "Sovkhoz Varketili",
        "Varketili"
    ],
    "wof:name":"Varketili",
    "wof:placetype":"locality"
},
  "geometry": {"coordinates":[44.91629,41.70811],"type":"Point"}
}