{
  "type": "Feature",
  "properties": {
    "gn:admin1_code":"71",
    "gn:asciiname":"Lalkhorali",
    "gn:country_code":"GE",
    "gn:dem":595,
    "gn:feature_class":"P",
    "gn:feature_code":"PPL",
    "gn:name":"Lalkhorali",
    "gn:population":0,
    "gn:timezone":"Asia/Tbilisi",
    "iso:country":"GE",
    "name:kat_x_preferred":[
        "\u10da\u10d0\u10da\u10ee\u10dd\u10e0\u10d0\u10da\u10d8"
    ],
    "name:kat_x_variant":[
        "Lalkhorali"
    ],
    "name:und_x_variant":[
        "Lalkhora",
        "Lekhera"
    ],
    "wof:name":"Lalkhorali",
    "wof:placetype":"locality"
},
  "geometry": {"coordinates":[42.15275,42.94029000000001],"type":"Point"}
}