{
  "type": "Feature",
  "properties": {
    "gn:admin1_code":"00",
    "gn:asciiname":"Gnugi",
    "gn:country_code":"GE",
    "gn:dem":2021,
    "gn:feature_class":"P",
    "gn:feature_code":"PPL",
    "gn:name":"Gnugi",
    "gn:population":0,
    "gn:timezone":"Asia/Tbilisi",
    "iso:country":"GE",
    "wof:name":"Gnugi",
    "wof:placetype":"locality"
},
  "geometry": {"coordinates":[44.27258,42.45789],"type":"Point"}
}