{
  "type": "Feature",
  "properties": {
    "gn:admin1_code":"00",
    "gn:asciiname":"Vani",
    "gn:country_code":"GE",
    "gn:dem":2151,
    "gn:feature_class":"P",
    "gn:feature_code":"PPL",
    "gn:name":"Vani",
    "gn:population":0,
    "gn:timezone":"Asia/Tbilisi",
    "iso:country":"GE",
    "wof:name":"Vani",
    "wof:placetype":"locality"
},
  "geometry": {"coordinates":[43.13333,41.43333],"type":"Point"}
}