{
  "type": "Feature",
  "properties": {
    "gn:admin1_code":"00",
    "gn:asciiname":"Vani",
    "gn:country_code":"GE",
    "gn:dem":2151,
    "gn:feature_class":"P",
    "gn:feature_code":"PPL",
    "gn:name":"Vani",
    "gn:population":0,
    "gn:timezone":"Asia/Tbilisi",
    "iso:country":"GE",
    "name:aze_x_preferred":[
        "Vani"
    ],
    "name:bak_x_preferred":[
        "\u0412\u0430\u043d\u0438"
    ],
    "name:bul_x_preferred":[
        "\u0412\u0430\u043d\u0438"
    ],
    "name:ceb_x_preferred":[
        "Vani"
    ],
    "name:ces_x_preferred":[
        "Vani"
    ],
    "name:che_x_preferred":[
        "\u0412\u0430\u043d\u0438"
    ],
    "name:deu_x_preferred":[
        "Wani"
    ],
    "name:est_x_preferred":[
        "Vani"
    ],
    "name:fas_x_preferred":[
        "\u0648\u0627\u0646\u06cc"
    ],
    "name:fin_x_preferred":[
        "Vani"
    ],
    "name:fra_x_preferred":[
        "Vani"
    ],
    "name:heb_x_preferred":[
        "\u05d5\u05d0\u05e0\u05d9"
    ],
    "name:hsb_x_preferred":[
        "Wani"
    ],
    "name:hun_x_preferred":[
        "Vani"
    ],
    "name:hye_x_preferred":[
        "\u054e\u0561\u0576"
    ],
    "name:ita_x_preferred":[
        "Vani"
    ],
    "name:kat_x_preferred":[
        "\u10d5\u10d0\u10dc\u10d8"
    ],
    "name:lit_x_preferred":[
        "Vanis"
    ],
    "name:mal_x_preferred":[
        "\u0d35\u0d3e\u0d28\u0d3f"
    ],
    "name:mzn_x_preferred":[
        "\u0648\u0627\u0646\u06cc"
    ],
    "name:nld_x_preferred":[
        "Vani"
    ],
    "name:oss_x_preferred":[
        "\u0412\u0430\u043d\u0438"
    ],
    "name:pol_x_preferred":[
        "Wani"
    ],
    "name:por_x_preferred":[
        "Vani"
    ],
    "name:rus_x_preferred":[
        "\u0412\u0430\u043d\u0438"
    ],
    "name:srp_x_preferred":[
        "\u0412\u0430\u043d\u0438"
    ],
    "name:swe_x_preferred":[
        "Vani"
    ],
    "name:tur_x_preferred":[
        "Vani"
    ],
    "name:ukr_x_preferred":[
        "\u0412\u0430\u043d\u0456"
    ],
    "name:urd_x_preferred":[
        "\u0648\u0627\u0646\u06cc"
    ],
    "name:vie_x_preferred":[
        "Vani"
    ],
    "name:war_x_preferred":[
        "Vani"
    ],
    "name:xmf_x_preferred":[
        "\u10d5\u10d0\u10dc\u10d8"
    ],
    "name:zho_x_preferred":[
        "\u74e6\u5c3c"
    ],
    "wof:name":"Vani",
    "wof:placetype":"locality"
},
  "geometry": {"coordinates":[43.13333,41.43333],"type":"Point"}
}