{
  "type": "Feature",
  "properties": {
    "gn:admin1_code":"45",
    "gn:asciiname":"Jalaurt'a",
    "gn:country_code":"GE",
    "gn:dem":781,
    "gn:feature_class":"P",
    "gn:feature_code":"PPL",
    "gn:name":"Jalaurt\u2019a",
    "gn:population":0,
    "gn:timezone":"Asia/Tbilisi",
    "iso:country":"GE",
    "name:und_x_variant":[
        "Dzhalaurta",
        "Dzhalauri",
        "Jalaurt\u2019a"
    ],
    "wof:name":"Jalaurt'a",
    "wof:placetype":"locality"
},
  "geometry": {"coordinates":[43.39722,42.24875],"type":"Point"}
}