{
  "type": "Feature",
  "properties": {
    "gn:admin1_code":"67",
    "gn:asciiname":"Shenak'o",
    "gn:country_code":"GE",
    "gn:dem":1891,
    "gn:feature_class":"P",
    "gn:feature_code":"PPL",
    "gn:name":"Shenak\u2019o",
    "gn:population":0,
    "gn:timezone":"Asia/Tbilisi",
    "iso:country":"GE",
    "name:ces_x_preferred":[
        "\u0160enako"
    ],
    "name:che_x_preferred":[
        "\u0428\u0435\u043d\u0430\u043a\u043e"
    ],
    "name:heb_x_preferred":[
        "\u05e9\u05e0\u05d0\u05db\u05d5"
    ],
    "name:hye_x_preferred":[
        "\u0547\u0565\u0576\u0561\u0584\u0578"
    ],
    "name:kat_x_preferred":[
        "\u10e8\u10d4\u10dc\u10d0\u10e5\u10dd"
    ],
    "name:nld_x_preferred":[
        "Sjenako"
    ],
    "name:rus_x_preferred":[
        "\u0428\u0435\u043d\u0430\u043a\u043e"
    ],
    "name:ukr_x_preferred":[
        "\u0428\u0435\u043d\u0430\u043a\u043e"
    ],
    "name:und_x_variant":[
        "Shenak\u2019o"
    ],
    "wof:name":"Shenak'o",
    "wof:placetype":"locality"
},
  "geometry": {"coordinates":[45.66232,42.37338],"type":"Point"}
}