{
  "type": "Feature",
  "properties": {
    "gn:admin1_code":"67",
    "gn:asciiname":"Shenak'o",
    "gn:country_code":"GE",
    "gn:dem":1891,
    "gn:feature_class":"P",
    "gn:feature_code":"PPL",
    "gn:name":"Shenak\u2019o",
    "gn:population":0,
    "gn:timezone":"Asia/Tbilisi",
    "iso:country":"GE",
    "name:kat_x_preferred":[
        "\u10e8\u10d4\u10dc\u10d0\u10e5\u10dd"
    ],
    "name:und_x_variant":[
        "Shenak\u2019o"
    ],
    "wof:name":"Shenak'o",
    "wof:placetype":"locality"
},
  "geometry": {"coordinates":[45.66232,42.37338],"type":"Point"}
}