{
  "type": "Feature",
  "properties": {
    "gn:admin1_code":"00",
    "gn:asciiname":"Skhliti",
    "gn:country_code":"GE",
    "gn:dem":980,
    "gn:feature_class":"P",
    "gn:feature_code":"PPL",
    "gn:name":"Skhliti",
    "gn:population":0,
    "gn:timezone":"Asia/Tbilisi",
    "iso:country":"GE",
    "name:und_x_variant":[
        "Skhlit",
        "Skhliti"
    ],
    "wof:name":"Skhliti",
    "wof:placetype":"locality"
},
  "geometry": {"coordinates":[43.81451,42.17768],"type":"Point"}
}