{
  "type": "Feature",
  "properties": {
    "gn:admin1_code":"72",
    "gn:asciiname":"Tsinubani",
    "gn:country_code":"GE",
    "gn:dem":1529,
    "gn:feature_class":"P",
    "gn:feature_code":"PPL",
    "gn:name":"Tsinubani",
    "gn:population":0,
    "gn:timezone":"Asia/Tbilisi",
    "iso:country":"GE",
    "name:kat_x_preferred":[
        "\u10ec\u10d8\u10dc\u10e3\u10d1\u10d0\u10dc\u10d8"
    ],
    "wof:name":"Tsinubani",
    "wof:placetype":"locality"
},
  "geometry": {"coordinates":[43.64661,41.79857],"type":"Point"}
}