{
  "type": "Feature",
  "properties": {
    "gn:admin1_code":"00",
    "gn:asciiname":"Asanuri",
    "gn:country_code":"GE",
    "gn:dem":380,
    "gn:feature_class":"P",
    "gn:feature_code":"PPL",
    "gn:name":"Asanuri",
    "gn:population":0,
    "gn:timezone":"Asia/Tbilisi",
    "iso:country":"GE",
    "name:und_x_variant":[
        "Asanauri",
        "Asanuri"
    ],
    "wof:name":"Asanuri",
    "wof:placetype":"locality"
},
  "geometry": {"coordinates":[45.97275,41.60636],"type":"Point"}
}