{
  "type": "Feature",
  "properties": {
    "gn:admin1_code":"70",
    "gn:asciiname":"Tsagera",
    "gn:country_code":"GE",
    "gn:dem":633,
    "gn:feature_class":"P",
    "gn:feature_code":"PPL",
    "gn:name":"Tsagera",
    "gn:population":0,
    "gn:timezone":"Asia/Tbilisi",
    "iso:country":"GE",
    "name:kat_x_preferred":[
        "Tsagera"
    ],
    "name:kat_x_variant":[
        "\u10ea\u10d0\u10d2\u10d4\u10e0\u10d0"
    ],
    "wof:name":"Tsagera",
    "wof:placetype":"locality"
},
  "geometry": {"coordinates":[42.83313,42.54921],"type":"Point"}
}