{
  "type": "Feature",
  "properties": {
    "gn:admin1_code":"00",
    "gn:asciiname":"Zekota",
    "gn:country_code":"GE",
    "gn:dem":879,
    "gn:feature_class":"P",
    "gn:feature_code":"PPL",
    "gn:name":"Zekota",
    "gn:population":0,
    "gn:timezone":"Asia/Tbilisi",
    "iso:country":"GE",
    "wof:name":"Zekota",
    "wof:placetype":"locality"
},
  "geometry": {"coordinates":[43.51709,42.03944],"type":"Point"}
}