{
  "type": "Feature",
  "properties": {
    "gn:admin1_code":"02",
    "gn:asciiname":"Verkhnaia Mts'ara",
    "gn:country_code":"GE",
    "gn:dem":400,
    "gn:feature_class":"P",
    "gn:feature_code":"PPL",
    "gn:name":"Verkhnaia Mts\u2019ara",
    "gn:population":0,
    "gn:timezone":"Asia/Tbilisi",
    "iso:country":"GE",
    "name:kat_x_preferred":[
        "\u10d5\u10d4\u10e0\u10ee\u10dc\u10d0\u10d8\u10d0 \u10db\u10ec\u10d0\u10e0\u10d0"
    ],
    "name:kat_x_variant":[
        "Verkhnaia Mts\u2019ara"
    ],
    "name:und_x_variant":[
        "Verkhnyaya Mtsara"
    ],
    "wof:name":"Verkhnaia Mts'ara",
    "wof:placetype":"locality"
},
  "geometry": {"coordinates":[40.76457,43.17069],"type":"Point"}
}