{
  "type": "Feature",
  "properties": {
    "gn:admin1_code":"02",
    "gn:asciiname":"Mugudzirkhva",
    "gn:country_code":"GE",
    "gn:dem":77,
    "gn:feature_class":"P",
    "gn:feature_code":"PPL",
    "gn:name":"Mugudzirkhva",
    "gn:population":0,
    "gn:timezone":"Asia/Tbilisi",
    "iso:country":"GE",
    "name:kat_x_preferred":[
        "\u10db\u10e3\u10d2\u10e3\u10eb\u10d8\u10e0\u10ee\u10d5\u10d0"
    ],
    "name:kat_x_variant":[
        "Mugudzirkhva"
    ],
    "name:und_x_variant":[
        "Mugudzyrkhva",
        "Myuzurkhya",
        "Mugudzirkhua",
        "Mguzurkhva",
        "Muguzyrkhva"
    ],
    "wof:name":"Mugudzirkhva",
    "wof:placetype":"locality"
},
  "geometry": {"coordinates":[40.51295,43.15338],"type":"Point"}
}