{
  "type": "Feature",
  "properties": {
    "gn:admin1_code":"00",
    "gn:asciiname":"Bikurta",
    "gn:country_code":"GE",
    "gn:dem":2312,
    "gn:feature_class":"P",
    "gn:feature_code":"PPL",
    "gn:name":"Bikurta",
    "gn:population":0,
    "gn:timezone":"Asia/Tbilisi",
    "iso:country":"GE",
    "wof:name":"Bikurta",
    "wof:placetype":"locality"
},
  "geometry": {"coordinates":[45.47833,42.39639],"type":"Point"}
}