{
  "type": "Feature",
  "properties": {
    "gn:admin1_code":"00",
    "gn:asciiname":"Garistavi",
    "gn:cc2":"GE",
    "gn:country_code":"GE",
    "gn:dem":953,
    "gn:feature_class":"P",
    "gn:feature_code":"PPL",
    "gn:name":"Garistavi",
    "gn:population":0,
    "gn:timezone":"Asia/Tbilisi",
    "iso:country":"GE",
    "name:und_x_variant":[
        "Goristavi",
        "Garistavi"
    ],
    "wof:name":"Garistavi",
    "wof:placetype":"locality"
},
  "geometry": {"coordinates":[43.75,42.21667],"type":"Point"}
}