{
  "type": "Feature",
  "properties": {
    "gn:admin1_code":"65",
    "gn:asciiname":"Buk'istsikhe",
    "gn:country_code":"GE",
    "gn:dem":226,
    "gn:feature_class":"P",
    "gn:feature_code":"PPL",
    "gn:name":"Buk\u2019istsikhe",
    "gn:population":0,
    "gn:timezone":"Asia/Tbilisi",
    "iso:country":"GE",
    "name:kat_x_preferred":[
        "Buk\u2019istsikhe"
    ],
    "name:kat_x_variant":[
        "\u10d1\u10e3\u10d9\u10d8\u10e1\u10ea\u10d8\u10ee\u10d4"
    ],
    "wof:name":"Buk'istsikhe",
    "wof:placetype":"locality"
},
  "geometry": {"coordinates":[42.29145,42.00202],"type":"Point"}
}