{
  "type": "Feature",
  "properties": {
    "gn:admin1_code":"69",
    "gn:asciiname":"Zaridzeebi",
    "gn:country_code":"GE",
    "gn:dem":1192,
    "gn:feature_class":"P",
    "gn:feature_code":"PPL",
    "gn:name":"Zaridzeebi",
    "gn:population":0,
    "gn:timezone":"Asia/Tbilisi",
    "iso:country":"GE",
    "name:und_x_variant":[
        "Khopsa",
        "Zaridzeyebi",
        "Khoptsa",
        "Zaridzebi",
        "Zaridzeebi"
    ],
    "wof:name":"Zaridzeebi",
    "wof:placetype":"locality"
},
  "geometry": {"coordinates":[44.8925,42.13681],"type":"Point"}
}