{
  "type": "Feature",
  "properties": {
    "gn:admin1_code":"02",
    "gn:asciiname":"Khapshira",
    "gn:country_code":"GE",
    "gn:dem":91,
    "gn:feature_class":"P",
    "gn:feature_code":"PPL",
    "gn:name":"Khapshira",
    "gn:population":0,
    "gn:timezone":"Asia/Tbilisi",
    "iso:country":"GE",
    "name:kat_x_preferred":[
        "Hapshira"
    ],
    "name:kat_x_variant":[
        "\u10f0\u10d0\u10e4\u10e8\u10d8\u10e0\u10d0"
    ],
    "wof:name":"Khapshira",
    "wof:placetype":"locality"
},
  "geometry": {"coordinates":[40.63001,43.133],"type":"Point"}
}