{
  "type": "Feature",
  "properties": {
    "gn:admin1_code":"00",
    "gn:asciiname":"Kutsakhta",
    "gn:country_code":"GE",
    "gn:dem":601,
    "gn:feature_class":"P",
    "gn:feature_code":"PPL",
    "gn:name":"Kutsakhta",
    "gn:population":0,
    "gn:timezone":"Asia/Tbilisi",
    "iso:country":"GE",
    "wof:name":"Kutsakhta",
    "wof:placetype":"locality"
},
  "geometry": {"coordinates":[45.27417,42.1279],"type":"Point"}
}