{
  "type": "Feature",
  "properties": {
    "gn:admin1_code":"70",
    "gn:asciiname":"Didi-Chordzho",
    "gn:country_code":"GE",
    "gn:dem":842,
    "gn:feature_class":"P",
    "gn:feature_code":"PPL",
    "gn:name":"Didi-Chordzho",
    "gn:population":0,
    "gn:timezone":"Asia/Tbilisi",
    "iso:country":"GE",
    "name:und_x_variant":[
        "Chordzho",
        "Didi-Chordzho"
    ],
    "wof:name":"Didi-Chordzho",
    "wof:placetype":"locality"
},
  "geometry": {"coordinates":[43.07509,42.55751],"type":"Point"}
}