{
  "type": "Feature",
  "properties": {
    "gn:admin1_code":"70",
    "gn:asciiname":"Chibrevi",
    "gn:country_code":"GE",
    "gn:dem":1134,
    "gn:feature_class":"P",
    "gn:feature_code":"PPL",
    "gn:name":"Chibrevi",
    "gn:population":0,
    "gn:timezone":"Asia/Tbilisi",
    "iso:country":"GE",
    "name:kat_x_preferred":[
        "\u10ed\u10d8\u10d1\u10e0\u10d4\u10d5\u10d8"
    ],
    "wof:name":"Chibrevi",
    "wof:placetype":"locality"
},
  "geometry": {"coordinates":[43.32027,42.53845],"type":"Point"}
}