{
  "type": "Feature",
  "properties": {
    "gn:admin1_code":"71",
    "gn:asciiname":"Abashisp'iri",
    "gn:country_code":"GE",
    "gn:dem":18,
    "gn:feature_class":"P",
    "gn:feature_code":"PPL",
    "gn:name":"Abashisp\u2019iri",
    "gn:population":0,
    "gn:timezone":"Asia/Tbilisi",
    "iso:country":"GE",
    "name:kat_x_preferred":[
        "Abashisp\u2019iri"
    ],
    "name:kat_x_variant":[
        "\u10d0\u10d1\u10d0\u10e8\u10d8\u10e1\u10de\u10d8\u10e0\u10d8"
    ],
    "wof:name":"Abashisp'iri",
    "wof:placetype":"locality"
},
  "geometry": {"coordinates":[42.15681,42.19958],"type":"Point"}
}