{
  "type": "Feature",
  "properties": {
    "gn:admin1_code":"00",
    "gn:asciiname":"Zemo Kodistsqaro",
    "gn:cc2":"GE",
    "gn:country_code":"GE",
    "gn:dem":910,
    "gn:feature_class":"P",
    "gn:feature_code":"PPL",
    "gn:name":"Zemo Kodistsqaro",
    "gn:population":0,
    "gn:timezone":"Asia/Tbilisi",
    "iso:country":"GE",
    "name:kat_x_preferred":[
        "Zemo Kodistsqaro"
    ],
    "name:und_x_variant":[
        "Zemo-Kodistskaro"
    ],
    "wof:name":"Zemo Kodistsqaro",
    "wof:placetype":"locality"
},
  "geometry": {"coordinates":[44.55861,42.0125],"type":"Point"}
}