{
  "type": "Feature",
  "properties": {
    "gn:admin1_code":"00",
    "gn:asciiname":"Khvtse",
    "gn:country_code":"GE",
    "gn:dem":1522,
    "gn:feature_class":"P",
    "gn:feature_code":"PPL",
    "gn:name":"Khvtse",
    "gn:population":0,
    "gn:timezone":"Asia/Tbilisi",
    "iso:country":"GE",
    "wof:name":"Khvtse",
    "wof:placetype":"locality"
},
  "geometry": {"coordinates":[44.12778,41.85694],"type":"Point"}
}