{
  "type": "Feature",
  "properties": {
    "gn:admin1_code":"69",
    "gn:asciiname":"Vedzatkhevi",
    "gn:country_code":"GE",
    "gn:dem":993,
    "gn:feature_class":"P",
    "gn:feature_code":"PPL",
    "gn:name":"Vedzatkhevi",
    "gn:population":0,
    "gn:timezone":"Asia/Tbilisi",
    "iso:country":"GE",
    "wof:name":"Vedzatkhevi",
    "wof:placetype":"locality"
},
  "geometry": {"coordinates":[44.66708,42.13153],"type":"Point"}
}