{
  "type": "Feature",
  "properties": {
    "gn:admin1_code":"00",
    "gn:asciiname":"Marts'khena Rkvia",
    "gn:country_code":"GE",
    "gn:dem":566,
    "gn:feature_class":"P",
    "gn:feature_code":"PPL",
    "gn:name":"Marts\u2019khena Rkvia",
    "gn:population":0,
    "gn:timezone":"Asia/Tbilisi",
    "iso:country":"GE",
    "name:und_x_variant":[
        "Rkvia Levaya",
        "Marts\u2019khena Rkvia"
    ],
    "wof:name":"Marts'khena Rkvia",
    "wof:placetype":"locality"
},
  "geometry": {"coordinates":[43.15556,42.19944],"type":"Point"}
}