{
  "type": "Feature",
  "properties": {
    "gn:admin1_code":"68",
    "gn:asciiname":"Khutor Lezhbadini",
    "gn:country_code":"GE",
    "gn:dem":342,
    "gn:feature_class":"P",
    "gn:feature_code":"PPL",
    "gn:name":"Khutor Lezhbadini",
    "gn:population":0,
    "gn:timezone":"Asia/Tbilisi",
    "iso:country":"GE",
    "name:kat_x_preferred":[
        "Khutor Lezhbadini"
    ],
    "name:kat_x_variant":[
        "\u10ee\u10e3\u10d7\u10dd\u10e0-\u10da\u10d4\u10df\u10d1\u10d0\u10d3\u10d8\u10dc\u10d8"
    ],
    "wof:name":"Khutor Lezhbadini",
    "wof:placetype":"locality"
},
  "geometry": {"coordinates":[44.91994,41.4325],"type":"Point"}
}