{
  "type": "Feature",
  "properties": {
    "gn:admin1_code":"00",
    "gn:asciiname":"Deltasubani",
    "gn:country_code":"GE",
    "gn:dem":237,
    "gn:feature_class":"P",
    "gn:feature_code":"PPL",
    "gn:name":"Deltasubani",
    "gn:population":0,
    "gn:timezone":"Asia/Tbilisi",
    "iso:country":"GE",
    "wof:name":"Deltasubani",
    "wof:placetype":"locality"
},
  "geometry": {"coordinates":[43.04653,42.22597],"type":"Point"}
}