{
  "type": "Feature",
  "properties": {
    "gn:admin1_code":"65",
    "gn:asciiname":"Gogieti",
    "gn:country_code":"GE",
    "gn:dem":298,
    "gn:feature_class":"P",
    "gn:feature_code":"PPL",
    "gn:name":"Gogieti",
    "gn:population":0,
    "gn:timezone":"Asia/Tbilisi",
    "iso:country":"GE",
    "name:kat_x_preferred":[
        "Gogieti"
    ],
    "name:kat_x_variant":[
        "\u10d2\u10dd\u10d2\u10d8\u10d4\u10d7\u10d8"
    ],
    "name:und_x_variant":[
        "Gogiyeti"
    ],
    "wof:name":"Gogieti",
    "wof:placetype":"locality"
},
  "geometry": {"coordinates":[42.05174,41.88157],"type":"Point"}
}