{
  "type": "Feature",
  "properties": {
    "gn:admin1_code":"71",
    "gn:asciiname":"Letsitskhvaie",
    "gn:country_code":"GE",
    "gn:dem":150,
    "gn:feature_class":"P",
    "gn:feature_code":"PPL",
    "gn:name":"Letsitskhvaie",
    "gn:population":0,
    "gn:timezone":"Asia/Tbilisi",
    "iso:country":"GE",
    "name:kat_x_preferred":[
        "Letsitskhvaie"
    ],
    "name:kat_x_variant":[
        "\u10da\u10d4\u10ea\u10d8\u10ea\u10ee\u10d5\u10d0\u10d8\u10d4"
    ],
    "name:und_x_variant":[
        "Letsitskhuayye"
    ],
    "wof:name":"Letsitskhvaie",
    "wof:placetype":"locality"
},
  "geometry": {"coordinates":[42.3828,42.38057],"type":"Point"}
}