{
  "type": "Feature",
  "properties": {
    "gn:admin1_code":"00",
    "gn:asciiname":"Kinoti",
    "gn:country_code":"GE",
    "gn:dem":350,
    "gn:feature_class":"P",
    "gn:feature_code":"PPL",
    "gn:name":"Kinoti",
    "gn:population":0,
    "gn:timezone":"Asia/Tbilisi",
    "iso:country":"GE",
    "wof:name":"Kinoti",
    "wof:placetype":"locality"
},
  "geometry": {"coordinates":[43.04056,42.05462],"type":"Point"}
}