{
  "type": "Feature",
  "properties": {
    "gn:admin1_code":"66",
    "gn:asciiname":"Boriti",
    "gn:country_code":"GE",
    "gn:dem":352,
    "gn:feature_class":"P",
    "gn:feature_code":"PPL",
    "gn:name":"Boriti",
    "gn:population":0,
    "gn:timezone":"Asia/Tbilisi",
    "iso:country":"GE",
    "name:che_x_preferred":[
        "\u0411\u043e\u0440\u0438\u0442\u0438"
    ],
    "name:eng_x_preferred":[
        "Borit'i"
    ],
    "name:hye_x_preferred":[
        "\u0532\u0578\u0580\u056b\u0569"
    ],
    "name:kat_x_preferred":[
        "Boriti"
    ],
    "name:kat_x_variant":[
        "\u10d1\u10dd\u10e0\u10d8\u10d7\u10d8"
    ],
    "name:rus_x_preferred":[
        "\u0411\u043e\u0440\u0438\u0442\u0438"
    ],
    "wof:name":"Boriti",
    "wof:placetype":"locality"
},
  "geometry": {"coordinates":[43.27027,42.1241],"type":"Point"}
}