{
  "type": "Feature",
  "properties": {
    "gn:admin1_code":"00",
    "gn:asciiname":"Gupta",
    "gn:country_code":"GE",
    "gn:dem":1919,
    "gn:feature_class":"P",
    "gn:feature_code":"PPL",
    "gn:name":"Gupta",
    "gn:population":0,
    "gn:timezone":"Asia/Tbilisi",
    "iso:country":"GE",
    "wof:name":"Gupta",
    "wof:placetype":"locality"
},
  "geometry": {"coordinates":[44.32444,42.32472],"type":"Point"}
}