{
  "type": "Feature",
  "properties": {
    "gn:admin1_code":"66",
    "gn:asciiname":"Kvemo Nogha",
    "gn:country_code":"GE",
    "gn:dem":158,
    "gn:feature_class":"P",
    "gn:feature_code":"PPL",
    "gn:name":"Kvemo Nogha",
    "gn:population":0,
    "gn:timezone":"Asia/Tbilisi",
    "iso:country":"GE",
    "name:kat_x_preferred":[
        "Kvemo Nogha"
    ],
    "name:und_x_variant":[
        "Noga",
        "Kvemo Noga",
        "Nhoga",
        "\u10e5\u10d5\u10d4\u10db\u10dd \u10dc\u10dd\u10e6\u10d0"
    ],
    "wof:name":"Kvemo Nogha",
    "wof:placetype":"locality"
},
  "geometry": {"coordinates":[42.27884,42.06826],"type":"Point"}
}