{
  "type": "Feature",
  "properties": {
    "gn:admin1_code":"70",
    "gn:asciiname":"K'vemo Bari",
    "gn:country_code":"GE",
    "gn:dem":1165,
    "gn:feature_class":"P",
    "gn:feature_code":"PPL",
    "gn:name":"K\u2019vemo Bari",
    "gn:population":0,
    "gn:timezone":"Asia/Tbilisi",
    "iso:country":"GE",
    "name:kat_x_preferred":[
        "\u10e5\u10d5\u10d4\u10db\u10dd \u10d1\u10d0\u10e0\u10d8"
    ],
    "name:und_x_variant":[
        "Bari",
        "K\u2019vemo Bari"
    ],
    "wof:name":"K'vemo Bari",
    "wof:placetype":"locality"
},
  "geometry": {"coordinates":[43.29893,42.52559],"type":"Point"}
}