{
  "type": "Feature",
  "properties": {
    "gn:admin1_code":"00",
    "gn:asciiname":"Patara-Chkhirauli",
    "gn:cc2":"GE",
    "gn:country_code":"GE",
    "gn:dem":690,
    "gn:feature_class":"P",
    "gn:feature_code":"PPL",
    "gn:name":"Patara-Chkhirauli",
    "gn:population":0,
    "gn:timezone":"Asia/Tbilisi",
    "iso:country":"GE",
    "name:und_x_variant":[
        "Chkhirouli Malyye",
        "Patara-Chkhirauli"
    ],
    "wof:name":"Patara-Chkhirauli",
    "wof:placetype":"locality"
},
  "geometry": {"coordinates":[43.25,42.18333],"type":"Point"}
}