{
  "type": "Feature",
  "properties": {
    "gn:admin1_code":"72",
    "gn:asciiname":"Baralet'i",
    "gn:country_code":"GE",
    "gn:dem":1697,
    "gn:feature_class":"P",
    "gn:feature_code":"PPL",
    "gn:name":"Baralet\u2019i",
    "gn:population":0,
    "gn:timezone":"Asia/Tbilisi",
    "iso:country":"GE",
    "name:eng_x_preferred":[
        "Baralet'i"
    ],
    "name:kat_x_preferred":[
        "\u10d1\u10d0\u10e0\u10d0\u10da\u10d4\u10d7\u10d8"
    ],
    "name:rus_x_preferred":[
        "\u0411\u0430\u0440\u0430\u043b\u0435\u0442\u0438"
    ],
    "name:und_x_variant":[
        "Baralet\u2019i"
    ],
    "wof:name":"Baralet'i",
    "wof:placetype":"locality"
},
  "geometry": {"coordinates":[43.50932,41.543],"type":"Point"}
}