{
  "type": "Feature",
  "properties": {
    "gn:admin1_code":"65",
    "gn:asciiname":"Nak'aduli",
    "gn:country_code":"GE",
    "gn:dem":208,
    "gn:feature_class":"P",
    "gn:feature_code":"PPL",
    "gn:name":"Nak\u2019aduli",
    "gn:population":0,
    "gn:timezone":"Asia/Tbilisi",
    "iso:country":"GE",
    "name:kat_x_preferred":[
        "Nak\u2019aduli"
    ],
    "name:kat_x_variant":[
        "\u10dc\u10d0\u10d9\u10d0\u10d3\u10e3\u10da\u10d8"
    ],
    "name:und_x_variant":[
        "Makaduli"
    ],
    "wof:name":"Nak'aduli",
    "wof:placetype":"locality"
},
  "geometry": {"coordinates":[42.32638,42.0318],"type":"Point"}
}