{
  "type": "Feature",
  "properties": {
    "gn:admin1_code":"71",
    "gn:asciiname":"Kvauti",
    "gn:country_code":"GE",
    "gn:dem":151,
    "gn:feature_class":"P",
    "gn:feature_code":"PPL",
    "gn:name":"Kvauti",
    "gn:population":0,
    "gn:timezone":"Asia/Tbilisi",
    "iso:country":"GE",
    "name:kat_x_preferred":[
        "\u10d9\u10d5\u10d0\u10e3\u10d7\u10d8"
    ],
    "wof:name":"Kvauti",
    "wof:placetype":"locality"
},
  "geometry": {"coordinates":[42.24248,42.40943],"type":"Point"}
}