{
  "type": "Feature",
  "properties": {
    "gn:admin1_code":"00",
    "gn:asciiname":"Gavazi",
    "gn:country_code":"GE",
    "gn:dem":258,
    "gn:feature_class":"P",
    "gn:feature_code":"PPL",
    "gn:name":"Gavazi",
    "gn:population":0,
    "gn:timezone":"Asia/Tbilisi",
    "iso:country":"GE",
    "name:eng_x_preferred":[
        "Gavazi"
    ],
    "name:rus_x_preferred":[
        "\u0413\u0430\u0432\u0430\u0437\u0438"
    ],
    "name:und_x_variant":[
        "Novo Gavazi",
        "Akhalgavazi",
        "Gavagi"
    ],
    "wof:name":"Gavazi",
    "wof:placetype":"locality"
},
  "geometry": {"coordinates":[45.86736,41.85278],"type":"Point"}
}