{
  "type": "Feature",
  "properties": {
    "gn:admin1_code":"02",
    "gn:asciiname":"Satave",
    "gn:country_code":"GE",
    "gn:dem":611,
    "gn:feature_class":"P",
    "gn:feature_code":"PPL",
    "gn:name":"Satave",
    "gn:population":0,
    "gn:timezone":"Asia/Tbilisi",
    "iso:country":"GE",
    "name:kat_x_preferred":[
        "\u10e1\u10d0\u10d7\u10d0\u10d5\u10d4"
    ],
    "name:kat_x_variant":[
        "Satave"
    ],
    "wof:name":"Satave",
    "wof:placetype":"locality"
},
  "geometry": {"coordinates":[41.02825,43.1535],"type":"Point"}
}