{
  "type": "Feature",
  "properties": {
    "gn:admin1_code":"71",
    "gn:asciiname":"Didi Inchkhuri",
    "gn:country_code":"GE",
    "gn:dem":248,
    "gn:feature_class":"P",
    "gn:feature_code":"PPL",
    "gn:name":"Didi Inchkhuri",
    "gn:population":0,
    "gn:timezone":"Asia/Tbilisi",
    "iso:country":"GE",
    "name:eng_x_preferred":[
        "Didi Inch'khuri"
    ],
    "name:kat_x_preferred":[
        "Didi Inchkhuri"
    ],
    "name:kat_x_variant":[
        "\u10d3\u10d8\u10d3\u10d8 \u10d8\u10dc\u10e9\u10ee\u10e3\u10e0\u10d8"
    ],
    "name:rus_x_preferred":[
        "\u0414\u0438\u0434\u0438-\u0418\u043d\u0447\u0445\u0443\u0440\u0438"
    ],
    "name:und_x_variant":[
        "Inchkhuri"
    ],
    "wof:name":"Didi Inchkhuri",
    "wof:placetype":"locality"
},
  "geometry": {"coordinates":[42.40492,42.44114],"type":"Point"}
}