{
  "type": "Feature",
  "properties": {
    "gn:admin1_code":"00",
    "gn:asciiname":"Kodistskaro",
    "gn:cc2":"GE",
    "gn:country_code":"GE",
    "gn:dem":1114,
    "gn:feature_class":"P",
    "gn:feature_code":"PPL",
    "gn:name":"Kodistskaro",
    "gn:population":0,
    "gn:timezone":"Asia/Tbilisi",
    "iso:country":"GE",
    "name:und_x_variant":[
        "Kldistskaro",
        "Kodistskaro"
    ],
    "wof:name":"Kodistskaro",
    "wof:placetype":"locality"
},
  "geometry": {"coordinates":[43.55,41.95],"type":"Point"}
}