{
  "type": "Feature",
  "properties": {
    "gn:admin1_code":"00",
    "gn:asciiname":"Nigvzara",
    "gn:country_code":"GE",
    "gn:dem":869,
    "gn:feature_class":"P",
    "gn:feature_code":"PPL",
    "gn:name":"Nigvzara",
    "gn:population":0,
    "gn:timezone":"Asia/Tbilisi",
    "iso:country":"GE",
    "wof:name":"Nigvzara",
    "wof:placetype":"locality"
},
  "geometry": {"coordinates":[43.46569,42.21444],"type":"Point"}
}