{
  "type": "Feature",
  "properties": {
    "gn:admin1_code":"02",
    "gn:asciiname":"Meore Gudava",
    "gn:country_code":"GE",
    "gn:dem":11,
    "gn:feature_class":"P",
    "gn:feature_code":"PPL",
    "gn:name":"Meore Gudava",
    "gn:population":0,
    "gn:timezone":"Asia/Tbilisi",
    "iso:country":"GE",
    "name:eng_x_preferred":[
        "Meore Gudava"
    ],
    "name:kat_x_preferred":[
        "Meore Gudava"
    ],
    "name:rus_x_preferred":[
        "\u041c\u0435\u043e\u0440\u0435-\u0413\u0443\u0434\u0430\u0432\u0430"
    ],
    "name:und_x_variant":[
        "Gudavsli",
        "Gudava"
    ],
    "wof:name":"Meore Gudava",
    "wof:placetype":"locality"
},
  "geometry": {"coordinates":[41.54282,42.64946],"type":"Point"}
}