{
  "type": "Feature",
  "properties": {
    "gn:admin1_code":"00",
    "gn:asciiname":"Patara-Gantiadi",
    "gn:country_code":"GE",
    "gn:dem":376,
    "gn:feature_class":"P",
    "gn:feature_code":"PPL",
    "gn:name":"Patara-Gantiadi",
    "gn:population":0,
    "gn:timezone":"Asia/Tbilisi",
    "iso:country":"GE",
    "name:und_x_variant":[
        "Gantiadi Malyye",
        "Patara-Gantiadi"
    ],
    "wof:name":"Patara-Gantiadi",
    "wof:placetype":"locality"
},
  "geometry": {"coordinates":[43.17531,42.08635],"type":"Point"}
}