{
  "type": "Feature",
  "properties": {
    "gn:admin1_code":"00",
    "gn:asciiname":"Shoraveli",
    "gn:country_code":"GE",
    "gn:dem":1141,
    "gn:feature_class":"P",
    "gn:feature_code":"PPL",
    "gn:name":"Shoraveli",
    "gn:population":0,
    "gn:timezone":"Asia/Tbilisi",
    "iso:country":"GE",
    "name:und_x_variant":[
        "Sholaveri",
        "Shoraveli"
    ],
    "wof:name":"Shoraveli",
    "wof:placetype":"locality"
},
  "geometry": {"coordinates":[42.80506,41.66506],"type":"Point"}
}