{
  "type": "Feature",
  "properties": {
    "gn:admin1_code":"00",
    "gn:asciiname":"Titvinistskaro",
    "gn:country_code":"GE",
    "gn:dem":987,
    "gn:feature_class":"P",
    "gn:feature_code":"PPL",
    "gn:name":"Titvinistskaro",
    "gn:population":0,
    "gn:timezone":"Asia/Tbilisi",
    "iso:country":"GE",
    "wof:name":"Titvinistskaro",
    "wof:placetype":"locality"
},
  "geometry": {"coordinates":[43.66908,42.12931],"type":"Point"}
}