{
  "type": "Feature",
  "properties": {
    "gn:admin1_code":"04",
    "gn:asciiname":"Dghvani",
    "gn:country_code":"GE",
    "gn:dem":1034,
    "gn:feature_class":"P",
    "gn:feature_code":"PPL",
    "gn:name":"Dghvani",
    "gn:population":0,
    "gn:timezone":"Asia/Tbilisi",
    "iso:country":"GE",
    "name:kat_x_preferred":[
        "Dghvani"
    ],
    "name:kat_x_variant":[
        "\u10d3\u10e6\u10d5\u10d0\u10dc\u10d8"
    ],
    "name:und_x_variant":[
        "Dgvani"
    ],
    "wof:name":"Dghvani",
    "wof:placetype":"locality"
},
  "geometry": {"coordinates":[42.21258,41.58144],"type":"Point"}
}