{
  "type": "Feature",
  "properties": {
    "gn:admin1_code":"70",
    "gn:asciiname":"Dzhudari",
    "gn:country_code":"GE",
    "gn:dem":1542,
    "gn:feature_class":"P",
    "gn:feature_code":"PPL",
    "gn:name":"Dzhudari",
    "gn:population":0,
    "gn:timezone":"Asia/Tbilisi",
    "iso:country":"GE",
    "wof:name":"Dzhudari",
    "wof:placetype":"locality"
},
  "geometry": {"coordinates":[42.51306,42.82861],"type":"Point"}
}