{
  "type": "Feature",
  "properties": {
    "gn:admin1_code":"00",
    "gn:asciiname":"Prinevi",
    "gn:country_code":"GE",
    "gn:dem":875,
    "gn:feature_class":"P",
    "gn:feature_code":"PPL",
    "gn:name":"Prinevi",
    "gn:population":0,
    "gn:timezone":"Asia/Tbilisi",
    "iso:country":"GE",
    "wof:name":"Prinevi",
    "wof:placetype":"locality"
},
  "geometry": {"coordinates":[43.84658,42.18936],"type":"Point"}
}