{
  "type": "Feature",
  "properties": {
    "gn:admin1_code":"00",
    "gn:asciiname":"Guliani",
    "gn:country_code":"GE",
    "gn:dem":58,
    "gn:feature_class":"P",
    "gn:feature_code":"PPL",
    "gn:name":"Guliani",
    "gn:population":0,
    "gn:timezone":"Asia/Tbilisi",
    "iso:country":"GE",
    "name:kat_x_preferred":[
        "\u10d2\u10e3\u10e0\u10d8\u10d0\u10dc\u10d8"
    ],
    "wof:name":"Guliani",
    "wof:placetype":"locality"
},
  "geometry": {"coordinates":[41.92176,42.02312],"type":"Point"}
}