{
  "type": "Feature",
  "properties": {
    "gn:admin1_code":"25",
    "gn:asciiname":"Bebnisi",
    "gn:country_code":"GE",
    "gn:dem":650,
    "gn:feature_class":"P",
    "gn:feature_code":"PPL",
    "gn:name":"Bebnisi",
    "gn:population":0,
    "gn:timezone":"Asia/Tbilisi",
    "iso:country":"GE",
    "wof:name":"Bebnisi",
    "wof:placetype":"locality"
},
  "geometry": {"coordinates":[43.90901,42.02868],"type":"Point"}
}