{
  "type": "Feature",
  "properties": {
    "gn:admin1_code":"71",
    "gn:asciiname":"Pirveli Balda",
    "gn:country_code":"GE",
    "gn:dem":277,
    "gn:feature_class":"P",
    "gn:feature_code":"PPL",
    "gn:name":"Pirveli Balda",
    "gn:population":0,
    "gn:timezone":"Asia/Tbilisi",
    "iso:country":"GE",
    "name:kat_x_preferred":[
        "Pirveli Balda"
    ],
    "name:kat_x_variant":[
        "\u10de\u10d8\u10e0\u10d5\u10d4\u10da\u10d8 \u10d1\u10d0\u10da\u10d3\u10d0"
    ],
    "name:und_x_variant":[
        "Balda Pervaya",
        "Balda",
        "Pirveli Balada"
    ],
    "wof:name":"Pirveli Balda",
    "wof:placetype":"locality"
},
  "geometry": {"coordinates":[42.39494000000001,42.48425],"type":"Point"}
}