{
  "type": "Feature",
  "properties": {
    "gn:admin1_code":"00",
    "gn:asciiname":"Freydental'",
    "gn:country_code":"GE",
    "gn:dem":677,
    "gn:feature_class":"P",
    "gn:feature_code":"PPL",
    "gn:name":"Freydental\u2019",
    "gn:population":0,
    "gn:timezone":"Asia/Tbilisi",
    "iso:country":"GE",
    "wof:name":"Freydental'",
    "wof:placetype":"locality"
},
  "geometry": {"coordinates":[45.21417,41.71083],"type":"Point"}
}