{
  "type": "Feature",
  "properties": {
    "gn:admin1_code":"02",
    "gn:asciiname":"T'q'aia",
    "gn:country_code":"GE",
    "gn:dem":155,
    "gn:feature_class":"P",
    "gn:feature_code":"PPL",
    "gn:name":"T\u2019q\u2019aia",
    "gn:population":0,
    "gn:timezone":"Asia/Tbilisi",
    "iso:country":"GE",
    "name:kat_x_preferred":[
        "T\u2019q\u2019aia"
    ],
    "name:kat_x_variant":[
        "\u10e2\u10e7\u10d0\u10d8\u10d0"
    ],
    "name:und_x_variant":[
        "Tkaia",
        "Tkaya"
    ],
    "wof:name":"T'q'aia",
    "wof:placetype":"locality"
},
  "geometry": {"coordinates":[41.91912,42.6154],"type":"Point"}
}