{
  "type": "Feature",
  "properties": {
    "gn:admin1_code":"00",
    "gn:asciiname":"Tsintsqaro",
    "gn:country_code":"GE",
    "gn:dem":873,
    "gn:feature_class":"P",
    "gn:feature_code":"PPL",
    "gn:name":"Tsintsqaro",
    "gn:population":0,
    "gn:timezone":"Asia/Tbilisi",
    "iso:country":"GE",
    "name:eng_x_preferred":[
        "Tsintsqaro"
    ],
    "name:rus_x_preferred":[
        "\u0426\u0438\u043d\u0446\u043a\u0430\u0440\u043e"
    ],
    "name:und_x_variant":[
        "Tsintskaro",
        "Tsintsqaro"
    ],
    "wof:name":"Tsintsqaro",
    "wof:placetype":"locality"
},
  "geometry": {"coordinates":[44.61957,41.54152],"type":"Point"}
}