{
  "type": "Feature",
  "properties": {
    "gn:admin1_code":"52",
    "gn:asciiname":"Nakhshirghele",
    "gn:country_code":"GE",
    "gn:dem":152,
    "gn:feature_class":"P",
    "gn:feature_code":"PPL",
    "gn:name":"Nakhshirghele",
    "gn:population":0,
    "gn:timezone":"Asia/Tbilisi",
    "iso:country":"GE",
    "name:und_x_variant":[
        "Nakhshirgele",
        "Nakhshirghele"
    ],
    "wof:name":"Nakhshirghele",
    "wof:placetype":"locality"
},
  "geometry": {"coordinates":[42.79388,42.21778],"type":"Point"}
}