{
  "type": "Feature",
  "properties": {
    "gn:admin1_code":"68",
    "gn:asciiname":"Tabakhmela",
    "gn:country_code":"GE",
    "gn:dem":1008,
    "gn:feature_class":"P",
    "gn:feature_code":"PPL",
    "gn:name":"Tabakhmela",
    "gn:population":0,
    "gn:timezone":"Asia/Tbilisi",
    "iso:country":"GE",
    "name:eng_x_preferred":[
        "Tabakhmela"
    ],
    "name:heb_x_preferred":[
        "\u05d8\u05d1\u05d7\u05de\u05dc\u05d4"
    ],
    "name:kat_x_preferred":[
        "Tabakhmela"
    ],
    "name:kat_x_variant":[
        "\u10e2\u10d0\u10d1\u10d0\u10ee\u10db\u10d4\u10da\u10d0"
    ],
    "name:nld_x_preferred":[
        "Tabachmela"
    ],
    "name:rus_x_preferred":[
        "\u0422\u0430\u0431\u0430\u0445\u043c\u0435\u043b\u0430"
    ],
    "wof:name":"Tabakhmela",
    "wof:placetype":"locality"
},
  "geometry": {"coordinates":[44.75699,41.65163],"type":"Point"}
}