{
  "type": "Feature",
  "properties": {
    "gn:admin1_code":"66",
    "gn:admin2_code":"7667554",
    "gn:asciiname":"T'erjola",
    "gn:country_code":"GE",
    "gn:dem":165,
    "gn:feature_class":"P",
    "gn:feature_code":"PPL",
    "gn:name":"T\u2019erjola",
    "gn:population":0,
    "gn:timezone":"Asia/Tbilisi",
    "iso:country":"GE",
    "name:ces_x_preferred":[
        "Terd\u017eola"
    ],
    "name:che_x_preferred":[
        "\u0422\u0435\u0440\u0436\u043e\u043b\u0430"
    ],
    "name:deu_x_preferred":[
        "Terdschola"
    ],
    "name:eng_x_preferred":[
        "T'erjola"
    ],
    "name:est_x_preferred":[
        "Therd\u017eola"
    ],
    "name:fas_x_preferred":[
        "\u062a\u0631\u062c\u0644\u0627"
    ],
    "name:fin_x_preferred":[
        "Terd\u017eola"
    ],
    "name:hsb_x_preferred":[
        "Terd\u017aola"
    ],
    "name:hye_x_preferred":[
        "\u0539\u0565\u0580\u057b\u0578\u056c\u0561"
    ],
    "name:ita_x_preferred":[
        "Terjola"
    ],
    "name:kat_x_preferred":[
        "\u10d7\u10d4\u10e0\u10ef\u10dd\u10da\u10d0"
    ],
    "name:lit_x_preferred":[
        "Terd\u017eola"
    ],
    "name:mal_x_preferred":[
        "\u0d31\u0d4d\u0d31\u0d46\u0d7c\u0d1c\u0d4b\u0d32"
    ],
    "name:mzn_x_preferred":[
        "\u062a\u0631\u062c\u0648\u0644\u0627"
    ],
    "name:nld_x_preferred":[
        "Terjola"
    ],
    "name:oss_x_preferred":[
        "\u0422\u0435\u0440\u0436\u043e\u043b\u0430"
    ],
    "name:rus_x_preferred":[
        "\u0422\u0435\u0440\u0436\u043e\u043b\u0430"
    ],
    "name:srp_x_preferred":[
        "\u0422\u0435\u0440\u0436\u043e\u043b\u0430"
    ],
    "name:swe_x_preferred":[
        "Terdzjola"
    ],
    "name:tur_x_preferred":[
        "Tercola"
    ],
    "name:ukr_x_preferred":[
        "\u0422\u0435\u0440\u0434\u0436\u043e\u043b\u0430"
    ],
    "name:und_x_variant":[
        "Terdzhola",
        "T\u2019erjola"
    ],
    "name:urd_x_preferred":[
        "\u062a\u0631\u062c\u0648\u0644\u0627"
    ],
    "name:war_x_preferred":[
        "Terjola"
    ],
    "name:xmf_x_preferred":[
        "\u10d7\u10d4\u10e0\u10ef\u10dd\u10da\u10d0"
    ],
    "name:zho_x_preferred":[
        "\u6cf0\u723e\u7126\u62c9"
    ],
    "wof:name":"T'erjola",
    "wof:placetype":"locality"
},
  "geometry": {"coordinates":[42.98362,42.1865],"type":"Point"}
}