{
  "type": "Feature",
  "properties": {
    "gn:admin1_code":"66",
    "gn:admin2_code":"7667554",
    "gn:asciiname":"T'erjola",
    "gn:country_code":"GE",
    "gn:dem":165,
    "gn:feature_class":"P",
    "gn:feature_code":"PPL",
    "gn:name":"T\u2019erjola",
    "gn:population":0,
    "gn:timezone":"Asia/Tbilisi",
    "iso:country":"GE",
    "name:eng_x_preferred":[
        "T'erjola"
    ],
    "name:rus_x_preferred":[
        "\u0422\u0435\u0440\u0436\u043e\u043b\u0430"
    ],
    "name:und_x_variant":[
        "Terdzhola",
        "T\u2019erjola",
        "Terjola"
    ],
    "wof:name":"T'erjola",
    "wof:placetype":"locality"
},
  "geometry": {"coordinates":[42.98362,42.1865],"type":"Point"}
}