{
  "type": "Feature",
  "properties": {
    "gn:admin1_code":"02",
    "gn:asciiname":"Lek'umkhara",
    "gn:country_code":"GE",
    "gn:dem":155,
    "gn:feature_class":"P",
    "gn:feature_code":"PPL",
    "gn:name":"Lek\u2019umkhara",
    "gn:population":0,
    "gn:timezone":"Asia/Tbilisi",
    "iso:country":"GE",
    "name:kat_x_preferred":[
        "Lek\u2019umkhara"
    ],
    "name:und_x_variant":[
        "\u10da\u10d4\u10d9\u10e3\u10db\u10ee\u10d0\u10e0\u10d0"
    ],
    "wof:name":"Lek'umkhara",
    "wof:placetype":"locality"
},
  "geometry": {"coordinates":[41.76394000000001,42.68037],"type":"Point"}
}