{
  "type": "Feature",
  "properties": {
    "gn:admin1_code":"68",
    "gn:asciiname":"Matsevani",
    "gn:country_code":"GE",
    "gn:dem":967,
    "gn:feature_class":"P",
    "gn:feature_code":"PPL",
    "gn:name":"Matsevani",
    "gn:population":0,
    "gn:timezone":"Asia/Tbilisi",
    "iso:country":"GE",
    "name:kat_x_preferred":[
        "\u10db\u10d0\u10ec\u10d4\u10d5\u10d0\u10dc\u10d8"
    ],
    "wof:name":"Matsevani",
    "wof:placetype":"locality"
},
  "geometry": {"coordinates":[44.54859,41.55488],"type":"Point"}
}