{
  "type": "Feature",
  "properties": {
    "gn:admin1_code":"02",
    "gn:asciiname":"Shabatk'vara",
    "gn:country_code":"GE",
    "gn:dem":693,
    "gn:feature_class":"P",
    "gn:feature_code":"PPL",
    "gn:name":"Shabatk\u2019vara",
    "gn:population":0,
    "gn:timezone":"Asia/Tbilisi",
    "iso:country":"GE",
    "name:kat_x_preferred":[
        "\u10e8\u10d0\u10d1\u10d0\u10d7\u10d9\u10d5\u10d0\u10e0\u10d0"
    ],
    "name:kat_x_variant":[
        "Shabatk\u2019vara"
    ],
    "wof:name":"Shabatk'vara",
    "wof:placetype":"locality"
},
  "geometry": {"coordinates":[41.67381,43.08775],"type":"Point"}
}