{
  "type": "Feature",
  "properties": {
    "gn:admin1_code":"00",
    "gn:asciiname":"Golt'et'i",
    "gn:country_code":"GE",
    "gn:dem":880,
    "gn:feature_class":"P",
    "gn:feature_code":"PPL",
    "gn:name":"Golt\u2019et\u2019i",
    "gn:population":0,
    "gn:timezone":"Asia/Tbilisi",
    "iso:country":"GE",
    "wof:name":"Golt'et'i",
    "wof:placetype":"locality"
},
  "geometry": {"coordinates":[44.58408,41.55774],"type":"Point"}
}