{
  "type": "Feature",
  "properties": {
    "gn:admin1_code":"70",
    "gn:asciiname":"Q'arishi",
    "gn:country_code":"GE",
    "gn:dem":879,
    "gn:feature_class":"P",
    "gn:feature_code":"PPL",
    "gn:name":"Q\u2019arishi",
    "gn:population":0,
    "gn:timezone":"Asia/Tbilisi",
    "iso:country":"GE",
    "name:kat_x_preferred":[
        "Q\u2019arishi"
    ],
    "name:kat_x_variant":[
        "\u10e7\u10d0\u10e0\u10d8\u10e8\u10d8"
    ],
    "wof:name":"Q'arishi",
    "wof:placetype":"locality"
},
  "geometry": {"coordinates":[42.74554000000001,42.78767],"type":"Point"}
}