{
  "type": "Feature",
  "properties": {
    "gn:admin1_code":"71",
    "gn:asciiname":"Orsant'ia",
    "gn:country_code":"GE",
    "gn:dem":17,
    "gn:feature_class":"P",
    "gn:feature_code":"PPL",
    "gn:name":"Orsant\u2019ia",
    "gn:population":1200,
    "gn:timezone":"Asia/Tbilisi",
    "iso:country":"GE",
    "name:eng_x_preferred":[
        "Orsantia"
    ],
    "name:kat_x_preferred":[
        "Orsant\u2019ia"
    ],
    "name:kat_x_variant":[
        "\u10dd\u10e0\u10e1\u10d0\u10dc\u10e2\u10d8\u10d0"
    ],
    "name:rus_x_preferred":[
        "\u041e\u0440\u0441\u0430\u043d\u0442\u0438\u0430"
    ],
    "wof:name":"Orsant'ia",
    "wof:placetype":"locality",
    "wof:population":1200
},
  "geometry": {"coordinates":[41.67377000000001,42.46777],"type":"Point"}
}