{
  "type": "Feature",
  "properties": {
    "gn:admin1_code":"00",
    "gn:asciiname":"Asmalari",
    "gn:cc2":"GE",
    "gn:country_code":"GE",
    "gn:dem":475,
    "gn:feature_class":"P",
    "gn:feature_code":"PPL",
    "gn:name":"Asmalari",
    "gn:population":0,
    "gn:timezone":"Asia/Tbilisi",
    "iso:country":"GE",
    "name:und_x_variant":[
        "Asmalyar",
        "Asmalari"
    ],
    "wof:name":"Asmalari",
    "wof:placetype":"locality"
},
  "geometry": {"coordinates":[44.61667,41.45],"type":"Point"}
}