{
  "type": "Feature",
  "properties": {
    "gn:admin1_code":"72",
    "gn:asciiname":"Katnatu",
    "gn:country_code":"GE",
    "gn:dem":2034,
    "gn:feature_class":"P",
    "gn:feature_code":"PPL",
    "gn:name":"Katnatu",
    "gn:population":0,
    "gn:timezone":"Asia/Tbilisi",
    "iso:country":"GE",
    "name:kat_x_preferred":[
        "\u10d9\u10d0\u10d7\u10dc\u10d0\u10e2\u10e3"
    ],
    "wof:name":"Katnatu",
    "wof:placetype":"locality"
},
  "geometry": {"coordinates":[43.60079,41.22453],"type":"Point"}
}