{
  "type": "Feature",
  "properties": {
    "gn:admin1_code":"00",
    "gn:asciiname":"Farazi",
    "gn:country_code":"GE",
    "gn:dem":1925,
    "gn:feature_class":"P",
    "gn:feature_code":"PPL",
    "gn:name":"Farazi",
    "gn:population":0,
    "gn:timezone":"Asia/Tbilisi",
    "iso:country":"GE",
    "wof:name":"Farazi",
    "wof:placetype":"locality"
},
  "geometry": {"coordinates":[44.27153,42.43957],"type":"Point"}
}