{
  "type": "Feature",
  "properties": {
    "gn:admin1_code":"02",
    "gn:asciiname":"Volodarskoye",
    "gn:country_code":"GE",
    "gn:dem":115,
    "gn:feature_class":"P",
    "gn:feature_code":"PPL",
    "gn:name":"Volodarskoye",
    "gn:population":0,
    "gn:timezone":"Asia/Tbilisi",
    "iso:country":"GE",
    "name:und_x_variant":[
        "Volodarovka",
        "Volodarskoye"
    ],
    "wof:name":"Volodarskoye",
    "wof:placetype":"locality"
},
  "geometry": {"coordinates":[41.05512,43.00403],"type":"Point"}
}