{
  "type": "Feature",
  "properties": {
    "gn:admin1_code":"00",
    "gn:asciiname":"Nizhniye Ganisi",
    "gn:country_code":"GE",
    "gn:dem":1654,
    "gn:feature_class":"P",
    "gn:feature_code":"PPL",
    "gn:name":"Nizhniye Ganisi",
    "gn:population":0,
    "gn:timezone":"Asia/Tbilisi",
    "iso:country":"GE",
    "wof:name":"Nizhniye Ganisi",
    "wof:placetype":"locality"
},
  "geometry": {"coordinates":[44.48333,42.43333],"type":"Point"}
}