{
  "type": "Feature",
  "properties": {
    "gn:admin1_code":"69",
    "gn:asciiname":"Akhali-Nichbisi",
    "gn:country_code":"GE",
    "gn:dem":583,
    "gn:feature_class":"P",
    "gn:feature_code":"PPL",
    "gn:name":"Akhali-Nichbisi",
    "gn:population":0,
    "gn:timezone":"Asia/Tbilisi",
    "iso:country":"GE",
    "wof:name":"Akhali-Nichbisi",
    "wof:placetype":"locality"
},
  "geometry": {"coordinates":[44.55042,41.84625],"type":"Point"}
}