{
  "type": "Feature",
  "properties": {
    "gn:admin1_code":"02",
    "gn:asciiname":"Bitaga",
    "gn:country_code":"GE",
    "gn:dem":969,
    "gn:feature_class":"P",
    "gn:feature_code":"PPL",
    "gn:name":"Bitaga",
    "gn:population":0,
    "gn:timezone":"Asia/Tbilisi",
    "iso:country":"GE",
    "name:kat_x_preferred":[
        "Bitaga"
    ],
    "name:kat_x_variant":[
        "\u10d1\u10d8\u10d7\u10d0\u10d2\u10d0"
    ],
    "name:und_x_variant":[
        "Zemo-Bytaga"
    ],
    "wof:name":"Bitaga",
    "wof:placetype":"locality"
},
  "geometry": {"coordinates":[40.85566,43.36126],"type":"Point"}
}