{
  "type": "Feature",
  "properties": {
    "gn:admin1_code":"02",
    "gn:asciiname":"Okumi",
    "gn:country_code":"GE",
    "gn:dem":157,
    "gn:feature_class":"P",
    "gn:feature_code":"PPL",
    "gn:name":"Okumi",
    "gn:population":0,
    "gn:timezone":"Asia/Tbilisi",
    "iso:country":"GE",
    "wof:name":"Okumi",
    "wof:placetype":"locality"
},
  "geometry": {"coordinates":[41.73639,42.71333],"type":"Point"}
}