{
  "type": "Feature",
  "properties": {
    "gn:admin1_code":"02",
    "gn:asciiname":"Sinirkhva",
    "gn:country_code":"GE",
    "gn:dem":135,
    "gn:feature_class":"P",
    "gn:feature_code":"PPL",
    "gn:name":"Sinirkhva",
    "gn:population":0,
    "gn:timezone":"Asia/Tbilisi",
    "iso:country":"GE",
    "name:kat_x_preferred":[
        "\u10e1\u10d8\u10dc\u10d8\u10e0\u10ee\u10d5\u10d0"
    ],
    "name:kat_x_variant":[
        "Sinirkhva"
    ],
    "name:und_x_variant":[
        "Synyrkhva"
    ],
    "wof:name":"Sinirkhva",
    "wof:placetype":"locality"
},
  "geometry": {"coordinates":[40.54816,43.19789],"type":"Point"}
}