{
  "type": "Feature",
  "properties": {
    "gn:admin1_code":"71",
    "gn:asciiname":"Chkvaleri",
    "gn:country_code":"GE",
    "gn:dem":368,
    "gn:feature_class":"P",
    "gn:feature_code":"PPL",
    "gn:name":"Chkvaleri",
    "gn:population":0,
    "gn:timezone":"Asia/Tbilisi",
    "iso:country":"GE",
    "name:kat_x_preferred":[
        "\u10e9\u10e5\u10d5\u10d0\u10da\u10d4\u10e0\u10d8"
    ],
    "wof:name":"Chkvaleri",
    "wof:placetype":"locality"
},
  "geometry": {"coordinates":[42.09403,42.71929],"type":"Point"}
}