{
  "type": "Feature",
  "properties": {
    "gn:admin1_code":"55",
    "gn:asciiname":"Orpiri",
    "gn:country_code":"GE",
    "gn:dem":284,
    "gn:feature_class":"P",
    "gn:feature_code":"PPL",
    "gn:name":"Orpiri",
    "gn:population":0,
    "gn:timezone":"Asia/Tbilisi",
    "iso:country":"GE",
    "name:kat_x_preferred":[
        "\u10dd\u10e0\u10de\u10d8\u10e0\u10d8"
    ],
    "wof:name":"Orpiri",
    "wof:placetype":"locality"
},
  "geometry": {"coordinates":[42.81537,42.32988],"type":"Point"}
}