{
  "type": "Feature",
  "properties": {
    "gn:admin1_code":"70",
    "gn:asciiname":"Kveda Ghvirishi",
    "gn:country_code":"GE",
    "gn:dem":737,
    "gn:feature_class":"P",
    "gn:feature_code":"PPL",
    "gn:name":"Kveda Ghvirishi",
    "gn:population":0,
    "gn:timezone":"Asia/Tbilisi",
    "iso:country":"GE",
    "name:kat_x_preferred":[
        "Kveda Ghvirishi"
    ],
    "name:kat_x_variant":[
        "\u10e5\u10d5\u10d4\u10d3\u10d0 \u10e6\u10d5\u10d8\u10e0\u10d8\u10e8\u10d8"
    ],
    "name:und_x_variant":[
        "Gvirishi",
        "Kveda Gvirishi"
    ],
    "wof:name":"Kveda Ghvirishi",
    "wof:placetype":"locality"
},
  "geometry": {"coordinates":[42.80293,42.57885],"type":"Point"}
}