{
  "type": "Feature",
  "properties": {
    "gn:admin1_code":"66",
    "gn:asciiname":"Kalagoni",
    "gn:country_code":"GE",
    "gn:dem":218,
    "gn:feature_class":"P",
    "gn:feature_code":"PPL",
    "gn:name":"Kalagoni",
    "gn:population":0,
    "gn:timezone":"Asia/Tbilisi",
    "iso:country":"GE",
    "wof:name":"Kalagoni",
    "wof:placetype":"locality"
},
  "geometry": {"coordinates":[42.36667,42.05],"type":"Point"}
}