{
  "type": "Feature",
  "properties": {
    "gn:admin1_code":"70",
    "gn:asciiname":"Gomi",
    "gn:country_code":"GE",
    "gn:dem":1181,
    "gn:feature_class":"P",
    "gn:feature_code":"PPL",
    "gn:name":"Gomi",
    "gn:population":0,
    "gn:timezone":"Asia/Tbilisi",
    "iso:country":"GE",
    "name:ceb_x_preferred":[
        "Gomi"
    ],
    "name:deu_x_preferred":[
        "Gomi"
    ],
    "name:rus_x_preferred":[
        "\u0413\u043e\u043c\u0438"
    ],
    "name:swe_x_preferred":[
        "Gomi"
    ],
    "wof:name":"Gomi",
    "wof:placetype":"locality"
},
  "geometry": {"coordinates":[43.53332,42.61293],"type":"Point"}
}