{
  "type": "Feature",
  "properties": {
    "gn:admin1_code":"04",
    "gn:asciiname":"Sk'urdidi",
    "gn:country_code":"GE",
    "gn:dem":965,
    "gn:feature_class":"P",
    "gn:feature_code":"PPL",
    "gn:name":"Sk\u2019urdidi",
    "gn:population":0,
    "gn:timezone":"Asia/Tbilisi",
    "iso:country":"GE",
    "name:kat_x_preferred":[
        "Sk\u2019urdidi"
    ],
    "name:kat_x_variant":[
        "\u10e1\u10d9\u10e3\u10e0\u10d3\u10d8\u10d3\u10d8"
    ],
    "wof:name":"Sk'urdidi",
    "wof:placetype":"locality"
},
  "geometry": {"coordinates":[41.815,41.49056],"type":"Point"}
}