{
  "type": "Feature",
  "properties": {
    "gn:admin1_code":"59",
    "gn:asciiname":"Banoja",
    "gn:country_code":"GE",
    "gn:dem":183,
    "gn:feature_class":"P",
    "gn:feature_code":"PPL",
    "gn:name":"Banoja",
    "gn:population":0,
    "gn:timezone":"Asia/Tbilisi",
    "iso:country":"GE",
    "name:kat_x_preferred":[
        "\u10d1\u10d0\u10dc\u10dd\u10ef\u10d0"
    ],
    "name:rus_x_preferred":[
        "\u0411\u0430\u043d\u043e\u0434\u0436\u0430"
    ],
    "name:und_x_variant":[
        "Bonodzha",
        "Banodzha",
        "Banoja"
    ],
    "wof:name":"Banoja",
    "wof:placetype":"locality"
},
  "geometry": {"coordinates":[42.66361,42.28472],"type":"Point"}
}