{
  "type": "Feature",
  "properties": {
    "gn:admin1_code":"66",
    "gn:asciiname":"Skhliti",
    "gn:country_code":"GE",
    "gn:dem":669,
    "gn:feature_class":"P",
    "gn:feature_code":"PPL",
    "gn:name":"Skhliti",
    "gn:population":0,
    "gn:timezone":"Asia/Tbilisi",
    "iso:country":"GE",
    "name:kat_x_preferred":[
        "Skhliti"
    ],
    "name:kat_x_variant":[
        "\u10e1\u10ee\u10da\u10d8\u10d7\u10d8"
    ],
    "wof:name":"Skhliti",
    "wof:placetype":"locality"
},
  "geometry": {"coordinates":[43.20354,41.97121],"type":"Point"}
}