{
  "type": "Feature",
  "properties": {
    "gn:admin1_code":"04",
    "gn:asciiname":"Ch'eri",
    "gn:country_code":"GE",
    "gn:dem":743,
    "gn:feature_class":"P",
    "gn:feature_code":"PPL",
    "gn:name":"Ch\u2019eri",
    "gn:population":0,
    "gn:timezone":"Asia/Tbilisi",
    "iso:country":"GE",
    "name:kat_x_preferred":[
        "Ch\u2019eri"
    ],
    "name:kat_x_variant":[
        "\u10ed\u10d4\u10e0\u10d8"
    ],
    "wof:name":"Ch'eri",
    "wof:placetype":"locality"
},
  "geometry": {"coordinates":[42.31255,41.59112],"type":"Point"}
}