{
  "type": "Feature",
  "properties": {
    "gn:admin1_code":"00",
    "gn:asciiname":"Belot'i",
    "gn:country_code":"GE",
    "gn:dem":1159,
    "gn:feature_class":"P",
    "gn:feature_code":"PPL",
    "gn:name":"Belot\u2019i",
    "gn:population":0,
    "gn:timezone":"Asia/Tbilisi",
    "iso:country":"GE",
    "name:eng_x_preferred":[
        "Belot'i"
    ],
    "name:kat_x_preferred":[
        "Belot\u2019i"
    ],
    "name:rus_x_preferred":[
        "\u0411\u0435\u043b\u043e\u0442\u0438"
    ],
    "wof:name":"Belot'i",
    "wof:placetype":"locality"
},
  "geometry": {"coordinates":[44.13049,42.30047],"type":"Point"}
}