{
  "type": "Feature",
  "properties": {
    "gn:admin1_code":"71",
    "gn:asciiname":"Rukhi",
    "gn:country_code":"GE",
    "gn:dem":141,
    "gn:feature_class":"P",
    "gn:feature_code":"PPL",
    "gn:name":"Rukhi",
    "gn:population":0,
    "gn:timezone":"Asia/Tbilisi",
    "iso:country":"GE",
    "name:eng_x_preferred":[
        "Rukhi"
    ],
    "name:kat_x_preferred":[
        "Rukhi"
    ],
    "name:kat_x_variant":[
        "\u10e0\u10e3\u10ee\u10d8"
    ],
    "name:rus_x_preferred":[
        "\u0420\u0443\u0445\u0438"
    ],
    "wof:name":"Rukhi",
    "wof:placetype":"locality"
},
  "geometry": {"coordinates":[41.8576,42.54845],"type":"Point"}
}