{
  "type": "Feature",
  "properties": {
    "gn:admin1_code":"00",
    "gn:asciiname":"Boslebi",
    "gn:country_code":"GE",
    "gn:dem":1017,
    "gn:feature_class":"P",
    "gn:feature_code":"PPL",
    "gn:name":"Boslebi",
    "gn:population":0,
    "gn:timezone":"Asia/Tbilisi",
    "iso:country":"GE",
    "wof:name":"Boslebi",
    "wof:placetype":"locality"
},
  "geometry": {"coordinates":[44.30276,41.35451],"type":"Point"}
}