{
  "type": "Feature",
  "properties": {
    "gn:admin1_code":"55",
    "gn:asciiname":"Ts'uts'khvat'i",
    "gn:country_code":"GE",
    "gn:dem":463,
    "gn:feature_class":"P",
    "gn:feature_code":"PPL",
    "gn:name":"Ts\u2019uts\u2019khvat\u2019i",
    "gn:population":0,
    "gn:timezone":"Asia/Tbilisi",
    "iso:country":"GE",
    "wof:name":"Ts'uts'khvat'i",
    "wof:placetype":"locality"
},
  "geometry": {"coordinates":[42.86458,42.28861],"type":"Point"}
}