{
  "type": "Feature",
  "properties": {
    "gn:admin1_code":"00",
    "gn:asciiname":"Navardzeti",
    "gn:country_code":"GE",
    "gn:dem":584,
    "gn:feature_class":"P",
    "gn:feature_code":"PPL",
    "gn:name":"Navardzeti",
    "gn:population":0,
    "gn:timezone":"Asia/Tbilisi",
    "iso:country":"GE",
    "wof:name":"Navardzeti",
    "wof:placetype":"locality"
},
  "geometry": {"coordinates":[43.20822,42.28793],"type":"Point"}
}