{
  "type": "Feature",
  "properties": {
    "gn:admin1_code":"69",
    "gn:asciiname":"Ts'khavat'i",
    "gn:country_code":"GE",
    "gn:dem":1305,
    "gn:feature_class":"P",
    "gn:feature_code":"PPL",
    "gn:name":"Ts\u2019khavat\u2019i",
    "gn:population":0,
    "gn:timezone":"Asia/Tbilisi",
    "iso:country":"GE",
    "name:kat_x_preferred":[
        "Ts\u2019khavat\u2019i"
    ],
    "wof:name":"Ts'khavat'i",
    "wof:placetype":"locality"
},
  "geometry": {"coordinates":[44.50722,42.24694],"type":"Point"}
}