{
  "type": "Feature",
  "properties": {
    "gn:admin1_code":"00",
    "gn:asciiname":"Patara-Goridzhvari",
    "gn:country_code":"GE",
    "gn:dem":707,
    "gn:feature_class":"P",
    "gn:feature_code":"PPL",
    "gn:name":"Patara-Goridzhvari",
    "gn:population":0,
    "gn:timezone":"Asia/Tbilisi",
    "iso:country":"GE",
    "name:und_x_variant":[
        "Malyye Gorisdzhvari",
        "Malyye Gorisdzhavari",
        "Patara-Goridzhvari"
    ],
    "wof:name":"Patara-Goridzhvari",
    "wof:placetype":"locality"
},
  "geometry": {"coordinates":[44.05978,41.97959],"type":"Point"}
}