{
  "type": "Feature",
  "properties": {
    "gn:admin1_code":"31",
    "gn:asciiname":"Vardisubani",
    "gn:country_code":"GE",
    "gn:dem":245,
    "gn:feature_class":"P",
    "gn:feature_code":"PPL",
    "gn:name":"Vardisubani",
    "gn:population":0,
    "gn:timezone":"Asia/Tbilisi",
    "iso:country":"GE",
    "name:eng_x_preferred":[
        "Vardisubani"
    ],
    "name:kat_x_preferred":[
        "Vardisubani"
    ],
    "name:rus_x_preferred":[
        "\u0412\u0430\u0440\u0434\u0438\u0441\u0443\u0431\u0430\u043d\u0438"
    ],
    "wof:name":"Vardisubani",
    "wof:placetype":"locality"
},
  "geometry": {"coordinates":[46.14944000000001,41.77278],"type":"Point"}
}