{
  "type": "Feature",
  "properties": {
    "gn:admin1_code":"66",
    "gn:asciiname":"Chrdili",
    "gn:country_code":"GE",
    "gn:dem":729,
    "gn:feature_class":"P",
    "gn:feature_code":"PPL",
    "gn:name":"Chrdili",
    "gn:population":0,
    "gn:timezone":"Asia/Tbilisi",
    "iso:country":"GE",
    "name:kat_x_preferred":[
        "Chrdili"
    ],
    "name:kat_x_variant":[
        "\u10e9\u10e0\u10d3\u10d8\u10da\u10d8"
    ],
    "wof:name":"Chrdili",
    "wof:placetype":"locality"
},
  "geometry": {"coordinates":[43.38845,41.96869],"type":"Point"}
}