{
  "type": "Feature",
  "properties": {
    "gn:admin1_code":"00",
    "gn:asciiname":"Varneti",
    "gn:country_code":"GE",
    "gn:dem":1795,
    "gn:feature_class":"P",
    "gn:feature_code":"PPL",
    "gn:name":"Varneti",
    "gn:population":0,
    "gn:timezone":"Asia/Tbilisi",
    "iso:country":"GE",
    "wof:name":"Varneti",
    "wof:placetype":"locality"
},
  "geometry": {"coordinates":[43.18333,41.31667],"type":"Point"}
}