{
  "type": "Feature",
  "properties": {
    "gn:admin1_code":"71",
    "gn:asciiname":"Darcheli",
    "gn:country_code":"GE",
    "gn:dem":11,
    "gn:feature_class":"P",
    "gn:feature_code":"PPL",
    "gn:name":"Darcheli",
    "gn:population":0,
    "gn:timezone":"Asia/Tbilisi",
    "iso:country":"GE",
    "name:eng_x_preferred":[
        "Darch'eli"
    ],
    "name:kat_x_preferred":[
        "Darcheli"
    ],
    "name:kat_x_variant":[
        "\u10d3\u10d0\u10e0\u10e9\u10d4\u10da\u10d8"
    ],
    "name:rus_x_preferred":[
        "\u0414\u0430\u0440\u0447\u0435\u043b\u0438"
    ],
    "wof:name":"Darcheli",
    "wof:placetype":"locality"
},
  "geometry": {"coordinates":[41.68657,42.43491],"type":"Point"}
}