{
  "type": "Feature",
  "properties": {
    "gn:admin1_code":"00",
    "gn:asciiname":"Salatario",
    "gn:country_code":"GE",
    "gn:dem":8,
    "gn:feature_class":"P",
    "gn:feature_code":"PPL",
    "gn:name":"Salatario",
    "gn:population":0,
    "gn:timezone":"Asia/Tbilisi",
    "iso:country":"GE",
    "wof:name":"Salatario",
    "wof:placetype":"locality"
},
  "geometry": {"coordinates":[41.79472,42.36361],"type":"Point"}
}