{
  "type": "Feature",
  "properties": {
    "gn:admin1_code":"72",
    "gn:asciiname":"Molit'i",
    "gn:country_code":"GE",
    "gn:dem":2049,
    "gn:feature_class":"P",
    "gn:feature_code":"PPL",
    "gn:name":"Molit\u2019i",
    "gn:population":0,
    "gn:timezone":"Asia/Tbilisi",
    "iso:country":"GE",
    "name:kat_x_preferred":[
        "\u10db\u10dd\u10da\u10d8\u10d7\u10d8"
    ],
    "name:und_x_variant":[
        "Molit\u2019i"
    ],
    "wof:name":"Molit'i",
    "wof:placetype":"locality"
},
  "geometry": {"coordinates":[43.58786,41.64496],"type":"Point"}
}