{
  "type": "Feature",
  "properties": {
    "gn:admin1_code":"69",
    "gn:asciiname":"Davat'i",
    "gn:country_code":"GE",
    "gn:dem":1145,
    "gn:feature_class":"P",
    "gn:feature_code":"PPL",
    "gn:name":"Davat\u2019i",
    "gn:population":0,
    "gn:timezone":"Asia/Tbilisi",
    "iso:country":"GE",
    "name:kat_x_preferred":[
        "Davat\u2019i"
    ],
    "wof:name":"Davat'i",
    "wof:placetype":"locality"
},
  "geometry": {"coordinates":[44.82693,41.99324],"type":"Point"}
}