{
  "type": "Feature",
  "properties": {
    "gn:admin1_code":"04",
    "gn:asciiname":"Didach'ara",
    "gn:country_code":"GE",
    "gn:dem":869,
    "gn:feature_class":"P",
    "gn:feature_code":"PPL",
    "gn:name":"Didach\u2019ara",
    "gn:population":0,
    "gn:timezone":"Asia/Tbilisi",
    "iso:country":"GE",
    "name:kat_x_preferred":[
        "Didach\u2019ara"
    ],
    "name:kat_x_variant":[
        "\u10d3\u10d8\u10d3\u10d0\u10ed\u10d0\u10e0\u10d0"
    ],
    "name:und_x_variant":[
        "Didadzhara",
        "Didi-Agara",
        "Didachara"
    ],
    "wof:name":"Didach'ara",
    "wof:placetype":"locality"
},
  "geometry": {"coordinates":[42.35321,41.66536],"type":"Point"}
}