{
  "type": "Feature",
  "properties": {
    "gn:admin1_code":"00",
    "gn:asciiname":"Bash-Gamamly",
    "gn:country_code":"GE",
    "gn:dem":1421,
    "gn:feature_class":"P",
    "gn:feature_code":"PPL",
    "gn:name":"Bash-Gamamly",
    "gn:population":0,
    "gn:timezone":"Asia/Tbilisi",
    "iso:country":"GE",
    "wof:name":"Bash-Gamamly",
    "wof:placetype":"locality"
},
  "geometry": {"coordinates":[44.23256,41.29942],"type":"Point"}
}