{
  "type": "Feature",
  "properties": {
    "gn:admin1_code":"32",
    "gn:asciiname":"Lesa",
    "gn:country_code":"GE",
    "gn:dem":17,
    "gn:feature_class":"P",
    "gn:feature_code":"PPL",
    "gn:name":"Lesa",
    "gn:population":0,
    "gn:timezone":"Asia/Tbilisi",
    "iso:country":"GE",
    "name:ara_x_preferred":[
        "\u0644\u0633\u0647"
    ],
    "name:azb_x_preferred":[
        "\u0644\u0633\u0627"
    ],
    "name:bel_x_preferred":[
        "\u041b\u0435\u0437\u0430"
    ],
    "name:bul_x_preferred":[
        "\u041b\u0435\u0437\u0430"
    ],
    "name:ceb_x_preferred":[
        "Lesa"
    ],
    "name:deu_x_preferred":[
        "Lesa"
    ],
    "name:epo_x_preferred":[
        "Lesa"
    ],
    "name:eus_x_preferred":[
        "Lesa"
    ],
    "name:fas_x_preferred":[
        "\u0644\u0633\u0627"
    ],
    "name:fin_x_preferred":[
        "Lesa"
    ],
    "name:fra_x_preferred":[
        "Lesa"
    ],
    "name:hun_x_preferred":[
        "Lesa"
    ],
    "name:hye_x_preferred":[
        "\u053c\u0565\u0566\u0561"
    ],
    "name:ind_x_preferred":[
        "Lesa"
    ],
    "name:ita_x_preferred":[
        "Lesa"
    ],
    "name:jpn_x_preferred":[
        "\u30ec\u30fc\u30b6"
    ],
    "name:kat_x_preferred":[
        "Lesa"
    ],
    "name:kat_x_variant":[
        "\u10da\u10d4\u10e1\u10d0"
    ],
    "name:kaz_x_preferred":[
        "\u041b\u0435\u0437\u0430"
    ],
    "name:lat_x_preferred":[
        "Lesia"
    ],
    "name:lit_x_preferred":[
        "Leza"
    ],
    "name:lmo_x_preferred":[
        "Lesa"
    ],
    "name:msa_x_preferred":[
        "Lesa"
    ],
    "name:nap_x_preferred":[
        "Lesa"
    ],
    "name:nld_x_preferred":[
        "Lesa"
    ],
    "name:pms_x_preferred":[
        "Lesa"
    ],
    "name:pol_x_preferred":[
        "Lesa"
    ],
    "name:por_x_preferred":[
        "Lesa"
    ],
    "name:ron_x_preferred":[
        "Lesa"
    ],
    "name:rus_x_preferred":[
        "\u041b\u0435\u0437\u0430"
    ],
    "name:scn_x_preferred":[
        "Lesa"
    ],
    "name:spa_x_preferred":[
        "Lesa"
    ],
    "name:srp_x_preferred":[
        "\u041b\u0435\u0437\u0430"
    ],
    "name:swe_x_preferred":[
        "Lesa"
    ],
    "name:tgl_x_preferred":[
        "Lesa"
    ],
    "name:ukr_x_preferred":[
        "\u041b\u0435\u0437\u0430"
    ],
    "name:uzb_x_preferred":[
        "Lesa"
    ],
    "name:vie_x_preferred":[
        "Lesa"
    ],
    "name:vol_x_preferred":[
        "Lesa"
    ],
    "name:war_x_preferred":[
        "Lesa"
    ],
    "wof:name":"Lesa",
    "wof:placetype":"locality"
},
  "geometry": {"coordinates":[41.95793,42.08417],"type":"Point"}
}