{
  "type": "Feature",
  "properties": {
    "gn:admin1_code":"32",
    "gn:asciiname":"Lesa",
    "gn:country_code":"GE",
    "gn:dem":17,
    "gn:feature_class":"P",
    "gn:feature_code":"PPL",
    "gn:name":"Lesa",
    "gn:population":0,
    "gn:timezone":"Asia/Tbilisi",
    "iso:country":"GE",
    "name:kat_x_preferred":[
        "Lesa"
    ],
    "name:kat_x_variant":[
        "\u10da\u10d4\u10e1\u10d0"
    ],
    "wof:name":"Lesa",
    "wof:placetype":"locality"
},
  "geometry": {"coordinates":[41.95793,42.08417],"type":"Point"}
}