{
  "type": "Feature",
  "properties": {
    "gn:admin1_code":"66",
    "gn:asciiname":"Chortisa",
    "gn:country_code":"GE",
    "gn:dem":527,
    "gn:feature_class":"P",
    "gn:feature_code":"PPL",
    "gn:name":"Chortisa",
    "gn:population":0,
    "gn:timezone":"Asia/Tbilisi",
    "iso:country":"GE",
    "wof:name":"Chortisa",
    "wof:placetype":"locality"
},
  "geometry": {"coordinates":[42.80417,42.43778],"type":"Point"}
}