{
  "type": "Feature",
  "properties": {
    "gn:admin1_code":"70",
    "gn:asciiname":"Kvemo Zhoshkha",
    "gn:country_code":"GE",
    "gn:dem":514,
    "gn:feature_class":"P",
    "gn:feature_code":"PPL",
    "gn:name":"Kvemo Zhoshkha",
    "gn:population":0,
    "gn:timezone":"Asia/Tbilisi",
    "iso:country":"GE",
    "name:kat_x_preferred":[
        "Kvemo Zhoshkha"
    ],
    "name:kat_x_variant":[
        "\u10e5\u10d5\u10d4\u10db\u10dd \u10df\u10dd\u10e8\u10ee\u10d0"
    ],
    "name:und_x_variant":[
        "Kveda Zhoshkha"
    ],
    "wof:name":"Kvemo Zhoshkha",
    "wof:placetype":"locality"
},
  "geometry": {"coordinates":[42.96688,42.57238],"type":"Point"}
}