{
  "type": "Feature",
  "properties": {
    "gn:admin1_code":"70",
    "gn:asciiname":"Khuruti",
    "gn:country_code":"GE",
    "gn:dem":958,
    "gn:feature_class":"P",
    "gn:feature_code":"PPL",
    "gn:name":"Khuruti",
    "gn:population":0,
    "gn:timezone":"Asia/Tbilisi",
    "iso:country":"GE",
    "name:und_x_variant":[
        "Khuruta",
        "Khuruti"
    ],
    "wof:name":"Khuruti",
    "wof:placetype":"locality"
},
  "geometry": {"coordinates":[43.41685,42.57686],"type":"Point"}
}