{
  "type": "Feature",
  "properties": {
    "gn:admin1_code":"00",
    "gn:asciiname":"Andisi",
    "gn:country_code":"GE",
    "gn:dem":1221,
    "gn:feature_class":"P",
    "gn:feature_code":"PPL",
    "gn:name":"Andisi",
    "gn:population":0,
    "gn:timezone":"Asia/Tbilisi",
    "iso:country":"GE",
    "wof:name":"Andisi",
    "wof:placetype":"locality"
},
  "geometry": {"coordinates":[43.93214,42.34377],"type":"Point"}
}