{
  "type": "Feature",
  "properties": {
    "gn:admin1_code":"02",
    "gn:asciiname":"Ts'vk'vara",
    "gn:country_code":"GE",
    "gn:dem":85,
    "gn:feature_class":"P",
    "gn:feature_code":"PPL",
    "gn:name":"Ts\u2019vk\u2019vara",
    "gn:population":0,
    "gn:timezone":"Asia/Tbilisi",
    "iso:country":"GE",
    "name:kat_x_preferred":[
        "\u10ec\u10d5\u10d9\u10d5\u10d0\u10e0\u10d0"
    ],
    "name:kat_x_variant":[
        "Ts\u2019vk\u2019vara"
    ],
    "name:und_x_variant":[
        "Tsekvara"
    ],
    "wof:name":"Ts'vk'vara",
    "wof:placetype":"locality"
},
  "geometry": {"coordinates":[40.75574,43.10065],"type":"Point"}
}