{
  "type": "Feature",
  "properties": {
    "gn:admin1_code":"72",
    "gn:asciiname":"Diliska",
    "gn:country_code":"GE",
    "gn:dem":1670,
    "gn:feature_class":"P",
    "gn:feature_code":"PPL",
    "gn:name":"Diliska",
    "gn:population":0,
    "gn:timezone":"Asia/Tbilisi",
    "iso:country":"GE",
    "name:eng_x_preferred":[
        "Diliska"
    ],
    "name:kat_x_preferred":[
        "\u10d3\u10d8\u10da\u10d8\u10e1\u10d9\u10d0"
    ],
    "name:rus_x_preferred":[
        "\u0414\u0438\u043b\u0438\u0441\u043a\u0430"
    ],
    "wof:name":"Diliska",
    "wof:placetype":"locality"
},
  "geometry": {"coordinates":[43.46208,41.42923],"type":"Point"}
}