{
  "type": "Feature",
  "properties": {
    "gn:admin1_code":"67",
    "gn:asciiname":"Naniani",
    "gn:country_code":"GE",
    "gn:dem":698,
    "gn:feature_class":"P",
    "gn:feature_code":"PPL",
    "gn:name":"Naniani",
    "gn:population":0,
    "gn:timezone":"Asia/Tbilisi",
    "iso:country":"GE",
    "name:kat_x_preferred":[
        "\u10dc\u10d0\u10dc\u10d8\u10d0\u10dc\u10d8"
    ],
    "wof:name":"Naniani",
    "wof:placetype":"locality"
},
  "geometry": {"coordinates":[45.70444000000001,41.665],"type":"Point"}
}