{
  "type": "Feature",
  "properties": {
    "gn:admin1_code":"72",
    "gn:asciiname":"Didi-Samsari",
    "gn:country_code":"GE",
    "gn:dem":2014,
    "gn:feature_class":"P",
    "gn:feature_code":"PPL",
    "gn:name":"Didi-Samsari",
    "gn:population":0,
    "gn:timezone":"Asia/Tbilisi",
    "iso:country":"GE",
    "name:kat_x_preferred":[
        "\u10d3\u10d8\u10d3\u10d8 \u10e1\u10d0\u10db\u10e1\u10d0\u10e0\u10d8"
    ],
    "name:und_x_variant":[
        "Samsari",
        "Didi-Samsari"
    ],
    "wof:name":"Didi-Samsari",
    "wof:placetype":"locality"
},
  "geometry": {"coordinates":[43.60032,41.53695],"type":"Point"}
}