{
  "type": "Feature",
  "properties": {
    "gn:admin1_code":"72",
    "gn:asciiname":"Didi-Samsari",
    "gn:country_code":"GE",
    "gn:dem":2014,
    "gn:feature_class":"P",
    "gn:feature_code":"PPL",
    "gn:name":"Didi-Samsari",
    "gn:population":0,
    "gn:timezone":"Asia/Tbilisi",
    "iso:country":"GE",
    "name:aze_x_preferred":[
        "Samsar da\u011f\u0131"
    ],
    "name:fra_x_preferred":[
        "Mont Samsari"
    ],
    "name:hye_x_preferred":[
        "\u054d\u0561\u0574\u057d\u0561\u0580"
    ],
    "name:jpn_x_preferred":[
        "\u30b5\u30e0\u30b5\u30ea\u5c71"
    ],
    "name:kat_x_preferred":[
        "\u10d3\u10d8\u10d3\u10d8 \u10e1\u10d0\u10db\u10e1\u10d0\u10e0\u10d8"
    ],
    "name:kat_x_variant":[
        "\u10e1\u10d0\u10db\u10e1\u10d0\u10e0\u10d8"
    ],
    "name:nld_x_preferred":[
        "Samsari"
    ],
    "name:nno_x_preferred":[
        "Samsari"
    ],
    "name:ukr_x_preferred":[
        "\u0421\u0430\u043c\u0441\u0430\u0440\u0456"
    ],
    "name:und_x_variant":[
        "Didi-Samsari"
    ],
    "wof:name":"Didi-Samsari",
    "wof:placetype":"locality"
},
  "geometry": {"coordinates":[43.60032,41.53695],"type":"Point"}
}