{
  "type": "Feature",
  "properties": {
    "gn:admin1_code":"66",
    "gn:asciiname":"Kitskhis Igoreti",
    "gn:country_code":"GE",
    "gn:dem":460,
    "gn:feature_class":"P",
    "gn:feature_code":"PPL",
    "gn:name":"Kitskhis Igoreti",
    "gn:population":0,
    "gn:timezone":"Asia/Tbilisi",
    "iso:country":"GE",
    "name:kat_x_preferred":[
        "Kitskhis Igoreti"
    ],
    "name:kat_x_variant":[
        "\u10d9\u10d8\u10ea\u10ee\u10d8\u10e1 \u10d8\u10d2\u10dd\u10e0\u10d4\u10d7\u10d8"
    ],
    "name:und_x_variant":[
        "Igoreti"
    ],
    "wof:name":"Kitskhis Igoreti",
    "wof:placetype":"locality"
},
  "geometry": {"coordinates":[43.15,42.05],"type":"Point"}
}