{
  "type": "Feature",
  "properties": {
    "gn:admin1_code":"02",
    "gn:asciiname":"Adzghapsha",
    "gn:country_code":"GE",
    "gn:dem":11,
    "gn:feature_class":"P",
    "gn:feature_code":"PPL",
    "gn:name":"Adzghapsha",
    "gn:population":0,
    "gn:timezone":"Asia/Tbilisi",
    "iso:country":"GE",
    "name:kat_x_preferred":[
        "\u10d0\u10eb\u10e6\u10d0\u10e4\u10e8\u10d0"
    ],
    "name:kat_x_variant":[
        "Adzghapsha"
    ],
    "name:und_x_variant":[
        "Adzkhapsha"
    ],
    "wof:name":"Adzghapsha",
    "wof:placetype":"locality"
},
  "geometry": {"coordinates":[40.75171,43.09047],"type":"Point"}
}