{
  "type": "Feature",
  "properties": {
    "gn:admin1_code":"00",
    "gn:asciiname":"Khodabula",
    "gn:country_code":"GE",
    "gn:dem":904,
    "gn:feature_class":"P",
    "gn:feature_code":"PPL",
    "gn:name":"Khodabula",
    "gn:population":0,
    "gn:timezone":"Asia/Tbilisi",
    "iso:country":"GE",
    "name:und_x_variant":[
        "Khudabuli",
        "Khodabula"
    ],
    "wof:name":"Khodabula",
    "wof:placetype":"locality"
},
  "geometry": {"coordinates":[43.81083,42.24431],"type":"Point"}
}