{
  "type": "Feature",
  "properties": {
    "gn:admin1_code":"70",
    "gn:asciiname":"Mazhiyeti",
    "gn:country_code":"GE",
    "gn:dem":1246,
    "gn:feature_class":"P",
    "gn:feature_code":"PPL",
    "gn:name":"Mazhiyeti",
    "gn:population":0,
    "gn:timezone":"Asia/Tbilisi",
    "iso:country":"GE",
    "wof:name":"Mazhiyeti",
    "wof:placetype":"locality"
},
  "geometry": {"coordinates":[43.4274,42.64218],"type":"Point"}
}