{
  "type": "Feature",
  "properties": {
    "gn:admin1_code":"32",
    "gn:asciiname":"K'vemo Ch'ibat'i",
    "gn:country_code":"GE",
    "gn:dem":13,
    "gn:feature_class":"P",
    "gn:feature_code":"PPL",
    "gn:name":"K\u2019vemo Ch\u2019ibat\u2019i",
    "gn:population":0,
    "gn:timezone":"Asia/Tbilisi",
    "iso:country":"GE",
    "name:kat_x_preferred":[
        "K\u2019vemo Ch\u2019ibat\u2019i"
    ],
    "name:kat_x_variant":[
        "\u10e5\u10d5\u10d4\u10db\u10dd \u10e9\u10d8\u10d1\u10d0\u10d7\u10d8"
    ],
    "name:und_x_variant":[
        "Chibati"
    ],
    "wof:name":"K'vemo Ch'ibat'i",
    "wof:placetype":"locality"
},
  "geometry": {"coordinates":[41.97709,42.08488],"type":"Point"}
}