{
  "type": "Feature",
  "properties": {
    "gn:admin1_code":"66",
    "gn:asciiname":"Marani",
    "gn:country_code":"GE",
    "gn:dem":25,
    "gn:feature_class":"P",
    "gn:feature_code":"PPL",
    "gn:name":"Marani",
    "gn:population":0,
    "gn:timezone":"Asia/Tbilisi",
    "iso:country":"GE",
    "name:deu_x_preferred":[
        "Marani"
    ],
    "name:ita_x_preferred":[
        "Marani"
    ],
    "name:por_x_preferred":[
        "Marani"
    ],
    "wof:name":"Marani",
    "wof:placetype":"locality"
},
  "geometry": {"coordinates":[42.29307,42.15836],"type":"Point"}
}