{
  "type": "Feature",
  "properties": {
    "gn:admin1_code":"25",
    "gn:asciiname":"Akhalsheni",
    "gn:country_code":"GE",
    "gn:dem":827,
    "gn:feature_class":"P",
    "gn:feature_code":"PPL",
    "gn:name":"Akhalsheni",
    "gn:population":0,
    "gn:timezone":"Asia/Tbilisi",
    "iso:country":"GE",
    "wof:name":"Akhalsheni",
    "wof:placetype":"locality"
},
  "geometry": {"coordinates":[43.77208,42.22695],"type":"Point"}
}