{
  "type": "Feature",
  "properties": {
    "gn:admin1_code":"71",
    "gn:asciiname":"P'aluri",
    "gn:country_code":"GE",
    "gn:dem":356,
    "gn:feature_class":"P",
    "gn:feature_code":"PPL",
    "gn:name":"P\u2019aluri",
    "gn:population":0,
    "gn:timezone":"Asia/Tbilisi",
    "iso:country":"GE",
    "name:kat_x_preferred":[
        "P\u2019aluri"
    ],
    "name:kat_x_variant":[
        "\u10de\u10d0\u10da\u10e3\u10e0\u10d8"
    ],
    "wof:name":"P'aluri",
    "wof:placetype":"locality"
},
  "geometry": {"coordinates":[42.05307,42.67998],"type":"Point"}
}