{
  "type": "Feature",
  "properties": {
    "gn:admin1_code":"67",
    "gn:asciiname":"Kakabet'i",
    "gn:country_code":"GE",
    "gn:dem":742,
    "gn:feature_class":"P",
    "gn:feature_code":"PPL",
    "gn:name":"Kakabet\u2019i",
    "gn:population":0,
    "gn:timezone":"Asia/Tbilisi",
    "iso:country":"GE",
    "name:eng_x_preferred":[
        "Kakabet'i"
    ],
    "name:kat_x_preferred":[
        "Kakabet\u2019i"
    ],
    "name:kat_x_variant":[
        "\u10d9\u10d0\u10d9\u10d0\u10d1\u10d4\u10d7\u10d8"
    ],
    "name:rus_x_preferred":[
        "\u041a\u0430\u043a\u0430\u0431\u0435\u0442\u0438"
    ],
    "wof:name":"Kakabet'i",
    "wof:placetype":"locality"
},
  "geometry": {"coordinates":[45.53544,41.70401],"type":"Point"}
}