{
  "type": "Feature",
  "properties": {
    "gn:admin1_code":"00",
    "gn:asciiname":"Vuallag-Gudisi",
    "gn:cc2":"GE",
    "gn:country_code":"GE",
    "gn:dem":2056,
    "gn:feature_class":"P",
    "gn:feature_code":"PPL",
    "gn:name":"Vuallag-Gudisi",
    "gn:population":0,
    "gn:timezone":"Asia/Tbilisi",
    "iso:country":"GE",
    "name:und_x_variant":[
        "Verkhniye Gudisi"
    ],
    "wof:name":"Vuallag-Gudisi",
    "wof:placetype":"locality"
},
  "geometry": {"coordinates":[44.14778,42.40083],"type":"Point"}
}