{
  "type": "Feature",
  "properties": {
    "gn:admin1_code":"00",
    "gn:asciiname":"Abisistavi",
    "gn:country_code":"GE",
    "gn:dem":738,
    "gn:feature_class":"P",
    "gn:feature_code":"PPL",
    "gn:name":"Abisistavi",
    "gn:population":0,
    "gn:timezone":"Asia/Tbilisi",
    "iso:country":"GE",
    "wof:name":"Abisistavi",
    "wof:placetype":"locality"
},
  "geometry": {"coordinates":[43.74037,42.09377],"type":"Point"}
}