{
  "type": "Feature",
  "properties": {
    "gn:admin1_code":"72",
    "gn:asciiname":"Aragva",
    "gn:country_code":"GE",
    "gn:dem":1678,
    "gn:feature_class":"P",
    "gn:feature_code":"PPL",
    "gn:name":"Aragva",
    "gn:population":0,
    "gn:timezone":"Asia/Tbilisi",
    "iso:country":"GE",
    "name:eng_x_preferred":[
        "Aragva"
    ],
    "name:kat_x_preferred":[
        "\u10d0\u10e0\u10d0\u10d2\u10d5\u10d0"
    ],
    "name:rus_x_preferred":[
        "\u0410\u0440\u0430\u0433\u0432\u0430"
    ],
    "name:und_x_variant":[
        "Arakva"
    ],
    "wof:name":"Aragva",
    "wof:placetype":"locality"
},
  "geometry": {"coordinates":[43.49379,41.48618],"type":"Point"}
}