{
  "type": "Feature",
  "properties": {
    "gn:admin1_code":"73",
    "gn:asciiname":"Chumateleti",
    "gn:country_code":"GE",
    "gn:dem":787,
    "gn:feature_class":"P",
    "gn:feature_code":"PPL",
    "gn:name":"Chumateleti",
    "gn:population":0,
    "gn:timezone":"Asia/Tbilisi",
    "iso:country":"GE",
    "wof:name":"Chumateleti",
    "wof:placetype":"locality"
},
  "geometry": {"coordinates":[43.55,42.03333],"type":"Point"}
}