{
  "type": "Feature",
  "properties": {
    "gn:admin1_code":"04",
    "gn:asciiname":"Mts'vane Kontskhi",
    "gn:country_code":"GE",
    "gn:dem":20,
    "gn:feature_class":"P",
    "gn:feature_code":"PPL",
    "gn:name":"Mts\u2019vane Kontskhi",
    "gn:population":0,
    "gn:timezone":"Asia/Tbilisi",
    "iso:country":"GE",
    "name:kat_x_preferred":[
        "Mts\u2019vane Kontskhi"
    ],
    "name:kat_x_variant":[
        "\u10db\u10ec\u10d5\u10d0\u10dc\u10d4 \u10d9\u10dd\u10dc\u10ea\u10ee\u10d8"
    ],
    "name:und_x_variant":[
        "Zel\u00ebnyy Mys",
        "Mzwane Konzzhi"
    ],
    "wof:name":"Mts'vane Kontskhi",
    "wof:placetype":"locality"
},
  "geometry": {"coordinates":[41.70444000000001,41.68722],"type":"Point"}
}