{
  "type": "Feature",
  "properties": {
    "gn:admin1_code":"66",
    "gn:asciiname":"Kveda Mukedi",
    "gn:country_code":"GE",
    "gn:dem":72,
    "gn:feature_class":"P",
    "gn:feature_code":"PPL",
    "gn:name":"Kveda Mukedi",
    "gn:population":0,
    "gn:timezone":"Asia/Tbilisi",
    "iso:country":"GE",
    "name:kat_x_preferred":[
        "Kveda Mukedi"
    ],
    "name:kat_x_variant":[
        "\u10e5\u10d5\u10d4\u10d3\u10d0 \u10db\u10e3\u10e5\u10d4\u10d3\u10d8"
    ],
    "wof:name":"Kveda Mukedi",
    "wof:placetype":"locality"
},
  "geometry": {"coordinates":[42.47482,42.07889],"type":"Point"}
}