{
  "type": "Feature",
  "properties": {
    "gn:admin1_code":"02",
    "gn:asciiname":"Ganakhleba",
    "gn:cc2":"GE",
    "gn:country_code":"GE",
    "gn:dem":136,
    "gn:feature_class":"P",
    "gn:feature_code":"PPL",
    "gn:name":"Ganakhleba",
    "gn:population":0,
    "gn:timezone":"Asia/Tbilisi",
    "iso:country":"GE",
    "name:eng_x_preferred":[
        "Ganakhleba"
    ],
    "name:kat_x_preferred":[
        "Ganakhleba"
    ],
    "name:rus_x_preferred":[
        "\u0413\u0430\u043d\u0430\u0445\u043b\u0435\u0431\u0430"
    ],
    "name:und_x_variant":[
        "Amastas\u2019yevka",
        "Kubasanti",
        "Anastasiyevka",
        "Kubasan",
        "Anastas\u2019yevka",
        "Guba-santy"
    ],
    "wof:name":"Ganakhleba",
    "wof:placetype":"locality"
},
  "geometry": {"coordinates":[41.28194000000001,42.93472],"type":"Point"}
}