{
  "type": "Feature",
  "properties": {
    "gn:admin1_code":"70",
    "gn:asciiname":"Likhet'i",
    "gn:country_code":"GE",
    "gn:dem":894,
    "gn:feature_class":"P",
    "gn:feature_code":"PPL",
    "gn:name":"Likhet\u2019i",
    "gn:population":0,
    "gn:timezone":"Asia/Tbilisi",
    "iso:country":"GE",
    "name:eng_x_preferred":[
        "Likhet'i"
    ],
    "name:kat_x_preferred":[
        "\u10da\u10d8\u10ee\u10d4\u10d7\u10d8"
    ],
    "name:rus_x_preferred":[
        "\u041b\u0438\u0445\u0435\u0442\u0438"
    ],
    "name:und_x_variant":[
        "Likhet\u2019i"
    ],
    "wof:name":"Likhet'i",
    "wof:placetype":"locality"
},
  "geometry": {"coordinates":[43.23408,42.60765],"type":"Point"}
}