{
  "type": "Feature",
  "properties": {
    "gn:admin1_code":"02",
    "gn:asciiname":"Rapits'a",
    "gn:country_code":"GE",
    "gn:dem":9,
    "gn:feature_class":"P",
    "gn:feature_code":"PPL",
    "gn:name":"Rapits\u2019a",
    "gn:population":0,
    "gn:timezone":"Asia/Tbilisi",
    "iso:country":"GE",
    "name:kat_x_preferred":[
        "\u10e0\u10d0\u10e4\u10d8\u10ec\u10d0"
    ],
    "name:kat_x_variant":[
        "Rapits\u2019a"
    ],
    "name:und_x_variant":[
        "Rapytsa"
    ],
    "wof:name":"Rapits'a",
    "wof:placetype":"locality"
},
  "geometry": {"coordinates":[40.34182,43.18275],"type":"Point"}
}