{
  "type": "Feature",
  "properties": {
    "gn:admin1_code":"24",
    "gn:asciiname":"K'vemo Jomagha",
    "gn:country_code":"GE",
    "gn:dem":1862,
    "gn:feature_class":"P",
    "gn:feature_code":"PPL",
    "gn:name":"K\u2019vemo Jomagha",
    "gn:population":0,
    "gn:timezone":"Asia/Tbilisi",
    "iso:country":"GE",
    "name:und_x_variant":[
        "Dzomagi",
        "Kvemo-Dzhomaga",
        "Dzomag",
        "K\u2019vemo Jomagha"
    ],
    "wof:name":"K'vemo Jomagha",
    "wof:placetype":"locality"
},
  "geometry": {"coordinates":[44.0452,42.57639],"type":"Point"}
}