{
  "type": "Feature",
  "properties": {
    "gn:admin1_code":"00",
    "gn:asciiname":"Muldarta",
    "gn:country_code":"GE",
    "gn:dem":1844,
    "gn:feature_class":"P",
    "gn:feature_code":"PPL",
    "gn:name":"Muldarta",
    "gn:population":0,
    "gn:timezone":"Asia/Tbilisi",
    "iso:country":"GE",
    "wof:name":"Muldarta",
    "wof:placetype":"locality"
},
  "geometry": {"coordinates":[43.86636,42.46044000000001],"type":"Point"}
}