{
  "type": "Feature",
  "properties": {
    "gn:admin1_code":"00",
    "gn:asciiname":"Muldarta",
    "gn:country_code":"GE",
    "gn:dem":1844,
    "gn:feature_class":"P",
    "gn:feature_code":"PPL",
    "gn:name":"Muldarta",
    "gn:population":0,
    "gn:timezone":"Asia/Tbilisi",
    "iso:country":"GE",
    "name:kat_x_preferred":[
        "\u10db\u10e3\u10da\u10d3\u10d0\u10e0\u10d7\u10d0"
    ],
    "name:oss_x_preferred":[
        "\u041c\u0443\u043b\u0434\u0430\u0440\u0442\u00e6"
    ],
    "wof:name":"Muldarta",
    "wof:placetype":"locality"
},
  "geometry": {"coordinates":[43.86636,42.46044000000001],"type":"Point"}
}