{
  "type": "Feature",
  "properties": {
    "gn:admin1_code":"00",
    "gn:asciiname":"Badiauri",
    "gn:country_code":"GE",
    "gn:dem":519,
    "gn:feature_class":"P",
    "gn:feature_code":"PPL",
    "gn:name":"Badiauri",
    "gn:population":0,
    "gn:timezone":"Asia/Tbilisi",
    "iso:country":"GE",
    "name:kat_x_preferred":[
        "Badiauri"
    ],
    "name:kat_x_variant":[
        "\u10d1\u10d0\u10d3\u10d8\u10d0\u10e3\u10e0\u10d8"
    ],
    "wof:name":"Badiauri",
    "wof:placetype":"locality"
},
  "geometry": {"coordinates":[45.55377,41.64442],"type":"Point"}
}