{
  "type": "Feature",
  "properties": {
    "gn:admin1_code":"02",
    "gn:asciiname":"Labra",
    "gn:country_code":"GE",
    "gn:dem":146,
    "gn:feature_class":"P",
    "gn:feature_code":"PPL",
    "gn:name":"Labra",
    "gn:population":0,
    "gn:timezone":"Asia/Tbilisi",
    "iso:country":"GE",
    "name:ceb_x_preferred":[
        "Labra"
    ],
    "name:srp_x_preferred":[
        "\u041b\u0430\u0431\u0440\u0430"
    ],
    "name:swe_x_preferred":[
        "Labra"
    ],
    "wof:name":"Labra",
    "wof:placetype":"locality"
},
  "geometry": {"coordinates":[41.45118,42.88446],"type":"Point"}
}