{
  "type": "Feature",
  "properties": {
    "gn:admin1_code":"00",
    "gn:asciiname":"Lipi",
    "gn:country_code":"GE",
    "gn:dem":1111,
    "gn:feature_class":"P",
    "gn:feature_code":"PPL",
    "gn:name":"Lipi",
    "gn:population":0,
    "gn:timezone":"Asia/Tbilisi",
    "iso:country":"GE",
    "wof:name":"Lipi",
    "wof:placetype":"locality"
},
  "geometry": {"coordinates":[44.38538,41.51966],"type":"Point"}
}