{
  "type": "Feature",
  "properties": {
    "gn:admin1_code":"66",
    "gn:asciiname":"Khunjulauri",
    "gn:country_code":"GE",
    "gn:dem":29,
    "gn:feature_class":"P",
    "gn:feature_code":"PPL",
    "gn:name":"Khunjulauri",
    "gn:population":0,
    "gn:timezone":"Asia/Tbilisi",
    "iso:country":"GE",
    "name:kat_x_preferred":[
        "Khunjulauri"
    ],
    "name:kat_x_variant":[
        "\u10ee\u10e3\u10dc\u10ef\u10e3\u10da\u10d0\u10e3\u10e0\u10d8"
    ],
    "name:und_x_variant":[
        "Khundzhulouri"
    ],
    "wof:name":"Khunjulauri",
    "wof:placetype":"locality"
},
  "geometry": {"coordinates":[42.29872,42.18655],"type":"Point"}
}