{
  "type": "Feature",
  "properties": {
    "gn:admin1_code":"69",
    "gn:asciiname":"Barisakho",
    "gn:country_code":"GE",
    "gn:dem":1450,
    "gn:feature_class":"P",
    "gn:feature_code":"PPL",
    "gn:name":"Barisakho",
    "gn:population":0,
    "gn:timezone":"Asia/Tbilisi",
    "iso:country":"GE",
    "name:eng_x_preferred":[
        "Barisakho"
    ],
    "name:kat_x_preferred":[
        "\u10d1\u10d0\u10e0\u10d8\u10e1\u10d0\u10ee\u10dd"
    ],
    "name:rus_x_preferred":[
        "\u0411\u0430\u0440\u0438\u0441\u0430\u0445\u043e"
    ],
    "wof:name":"Barisakho",
    "wof:placetype":"locality"
},
  "geometry": {"coordinates":[44.92124,42.4737],"type":"Point"}
}