{
  "type": "Feature",
  "properties": {
    "gn:admin1_code":"69",
    "gn:asciiname":"Chirdili",
    "gn:country_code":"GE",
    "gn:dem":1548,
    "gn:feature_class":"P",
    "gn:feature_code":"PPL",
    "gn:name":"Chirdili",
    "gn:population":0,
    "gn:timezone":"Asia/Tbilisi",
    "iso:country":"GE",
    "name:und_x_variant":[
        "Chrdilo",
        "Chirdili"
    ],
    "wof:name":"Chirdili",
    "wof:placetype":"locality"
},
  "geometry": {"coordinates":[44.90983,42.48652],"type":"Point"}
}