{
  "type": "Feature",
  "properties": {
    "gn:admin1_code":"00",
    "gn:asciiname":"Kadasar",
    "gn:country_code":"GE",
    "gn:dem":2049,
    "gn:feature_class":"P",
    "gn:feature_code":"PPL",
    "gn:name":"Kadasar",
    "gn:population":0,
    "gn:timezone":"Asia/Tbilisi",
    "iso:country":"GE",
    "wof:name":"Kadasar",
    "wof:placetype":"locality"
},
  "geometry": {"coordinates":[44.14222,42.46583],"type":"Point"}
}