{
  "type": "Feature",
  "properties": {
    "gn:admin1_code":"71",
    "gn:asciiname":"Jgali",
    "gn:country_code":"GE",
    "gn:dem":327,
    "gn:feature_class":"P",
    "gn:feature_code":"PPL",
    "gn:name":"Jgali",
    "gn:population":0,
    "gn:timezone":"Asia/Tbilisi",
    "iso:country":"GE",
    "name:kat_x_preferred":[
        "\u10ef\u10d2\u10d0\u10da\u10d8"
    ],
    "name:rus_x_preferred":[
        "\u0414\u0436\u0433\u0430\u043b\u0438"
    ],
    "name:und_x_variant":[
        "Dzhgala",
        "Jugheli",
        "Dzhagali",
        "Dzhegali",
        "Dzhgali",
        "Jgali"
    ],
    "wof:name":"Jgali",
    "wof:placetype":"locality"
},
  "geometry": {"coordinates":[42.13999,42.66176],"type":"Point"}
}