{
  "type": "Feature",
  "properties": {
    "gn:admin1_code":"43",
    "gn:asciiname":"Almati",
    "gn:country_code":"GE",
    "gn:dem":608,
    "gn:feature_class":"P",
    "gn:feature_code":"PPL",
    "gn:name":"Almati",
    "gn:population":0,
    "gn:timezone":"Asia/Tbilisi",
    "iso:country":"GE",
    "wof:name":"Almati",
    "wof:placetype":"locality"
},
  "geometry": {"coordinates":[45.68083,42.02972000000001],"type":"Point"}
}