{
  "type": "Feature",
  "properties": {
    "gn:admin1_code":"70",
    "gn:asciiname":"Sorgiti",
    "gn:country_code":"GE",
    "gn:dem":1109,
    "gn:feature_class":"P",
    "gn:feature_code":"PPL",
    "gn:name":"Sorgiti",
    "gn:population":0,
    "gn:timezone":"Asia/Tbilisi",
    "iso:country":"GE",
    "wof:name":"Sorgiti",
    "wof:placetype":"locality"
},
  "geometry": {"coordinates":[43.4958,42.55156],"type":"Point"}
}