{
  "type": "Feature",
  "properties": {
    "gn:admin1_code":"00",
    "gn:asciiname":"Kroza",
    "gn:country_code":"GE",
    "gn:dem":1015,
    "gn:feature_class":"P",
    "gn:feature_code":"PPL",
    "gn:name":"Kroza",
    "gn:population":0,
    "gn:timezone":"Asia/Tbilisi",
    "iso:country":"GE",
    "name:kat_x_preferred":[
        "\u10d9\u10e0\u10dd\u10d6\u10d0"
    ],
    "name:oss_x_preferred":[
        "\u041a\u044a\u0440\u043e\u0437"
    ],
    "name:und_x_variant":[
        "Krozi",
        "Kroza"
    ],
    "wof:name":"Kroza",
    "wof:placetype":"locality"
},
  "geometry": {"coordinates":[43.87541,42.22666],"type":"Point"}
}