{
  "type": "Feature",
  "properties": {
    "gn:admin1_code":"69",
    "gn:asciiname":"Khartisho",
    "gn:country_code":"GE",
    "gn:dem":1224,
    "gn:feature_class":"P",
    "gn:feature_code":"PPL",
    "gn:name":"Khartisho",
    "gn:population":0,
    "gn:timezone":"Asia/Tbilisi",
    "iso:country":"GE",
    "name:kat_x_preferred":[
        "\u10ee\u10d0\u10e0\u10e2\u10d8\u10e8\u10dd"
    ],
    "wof:name":"Khartisho",
    "wof:placetype":"locality"
},
  "geometry": {"coordinates":[44.84352,42.18528],"type":"Point"}
}