{
  "type": "Feature",
  "properties": {
    "gn:admin1_code":"70",
    "gn:asciiname":"Mele",
    "gn:country_code":"GE",
    "gn:dem":1304,
    "gn:feature_class":"P",
    "gn:feature_code":"PPL",
    "gn:name":"Mele",
    "gn:population":0,
    "gn:timezone":"Asia/Tbilisi",
    "iso:country":"GE",
    "name:eng_x_preferred":[
        "Mele"
    ],
    "name:kat_x_preferred":[
        "\u10db\u10d4\u10da\u10d4"
    ],
    "name:rus_x_preferred":[
        "\u041c\u0435\u043b\u0435"
    ],
    "wof:name":"Mele",
    "wof:placetype":"locality"
},
  "geometry": {"coordinates":[43.07161,42.7955],"type":"Point"}
}