{
  "type": "Feature",
  "properties": {
    "gn:admin1_code":"00",
    "gn:asciiname":"Koda",
    "gn:country_code":"GE",
    "gn:dem":819,
    "gn:feature_class":"P",
    "gn:feature_code":"PPL",
    "gn:name":"Koda",
    "gn:population":0,
    "gn:timezone":"Asia/Tbilisi",
    "iso:country":"GE",
    "name:ceb_x_preferred":[
        "Koda"
    ],
    "name:ces_x_preferred":[
        "Koda"
    ],
    "name:deu_x_preferred":[
        "Koda"
    ],
    "name:est_x_preferred":[
        "Koda"
    ],
    "name:fra_x_preferred":[
        "Koda"
    ],
    "name:pol_x_preferred":[
        "Koda"
    ],
    "name:swe_x_preferred":[
        "Koda"
    ],
    "wof:name":"Koda",
    "wof:placetype":"locality"
},
  "geometry": {"coordinates":[43.72087,42.14527],"type":"Point"}
}