{
  "type": "Feature",
  "properties": {
    "gn:admin1_code":"72",
    "gn:asciiname":"Khevasheni",
    "gn:country_code":"GE",
    "gn:dem":1133,
    "gn:feature_class":"P",
    "gn:feature_code":"PPL",
    "gn:name":"Khevasheni",
    "gn:population":0,
    "gn:timezone":"Asia/Tbilisi",
    "iso:country":"GE",
    "name:kat_x_preferred":[
        "\u10ee\u10d4\u10d5\u10d0\u10e8\u10d4\u10dc\u10d8"
    ],
    "wof:name":"Khevasheni",
    "wof:placetype":"locality"
},
  "geometry": {"coordinates":[42.8375,41.695],"type":"Point"}
}