{
  "type": "Feature",
  "properties": {
    "gn:admin1_code":"69",
    "gn:asciiname":"Kvernaula",
    "gn:country_code":"GE",
    "gn:dem":1185,
    "gn:feature_class":"P",
    "gn:feature_code":"PPL",
    "gn:name":"Kvernaula",
    "gn:population":0,
    "gn:timezone":"Asia/Tbilisi",
    "iso:country":"GE",
    "wof:name":"Kvernaula",
    "wof:placetype":"locality"
},
  "geometry": {"coordinates":[44.9868,42.17625],"type":"Point"}
}