{
  "type": "Feature",
  "properties": {
    "gn:admin1_code":"00",
    "gn:asciiname":"Pirveli-Kesalo",
    "gn:country_code":"GE",
    "gn:dem":308,
    "gn:feature_class":"P",
    "gn:feature_code":"PPL",
    "gn:name":"Pirveli-Kesalo",
    "gn:population":0,
    "gn:timezone":"Asia/Tbilisi",
    "iso:country":"GE",
    "name:aze_x_preferred":[
        "Pirv\u0259li Kesalo"
    ],
    "name:und_x_variant":[
        "Kesalo",
        "Pirveli-Kesalo"
    ],
    "wof:name":"Pirveli-Kesalo",
    "wof:placetype":"locality"
},
  "geometry": {"coordinates":[45.03271,41.39628],"type":"Point"}
}