{
  "type": "Feature",
  "properties": {
    "gn:admin1_code":"00",
    "gn:asciiname":"Mukhauri",
    "gn:country_code":"GE",
    "gn:dem":893,
    "gn:feature_class":"P",
    "gn:feature_code":"PPL",
    "gn:name":"Mukhauri",
    "gn:population":0,
    "gn:timezone":"Asia/Tbilisi",
    "iso:country":"GE",
    "wof:name":"Mukhauri",
    "wof:placetype":"locality"
},
  "geometry": {"coordinates":[43.73806,42.24444],"type":"Point"}
}