{
  "type": "Feature",
  "properties": {
    "gn:admin1_code":"71",
    "gn:asciiname":"Meore Chogha",
    "gn:country_code":"GE",
    "gn:dem":204,
    "gn:feature_class":"P",
    "gn:feature_code":"PPL",
    "gn:name":"Meore Chogha",
    "gn:population":0,
    "gn:timezone":"Asia/Tbilisi",
    "iso:country":"GE",
    "name:kat_x_preferred":[
        "\u10db\u10d4\u10dd\u10e0\u10d4 \u10ed\u10dd\u10e6\u10d0"
    ],
    "name:und_x_variant":[
        "Meore-Choga",
        "Meore Chogha"
    ],
    "wof:name":"Meore Chogha",
    "wof:placetype":"locality"
},
  "geometry": {"coordinates":[42.1939,42.55043],"type":"Point"}
}