{
  "type": "Feature",
  "properties": {
    "gn:admin1_code":"00",
    "gn:asciiname":"Zemo-Ambreti",
    "gn:country_code":"GE",
    "gn:dem":1117,
    "gn:feature_class":"P",
    "gn:feature_code":"PPL",
    "gn:name":"Zemo-Ambreti",
    "gn:population":0,
    "gn:timezone":"Asia/Tbilisi",
    "iso:country":"GE",
    "name:und_x_variant":[
        "Verkhniye Ambreti",
        "Zemo-Ambreti"
    ],
    "wof:name":"Zemo-Ambreti",
    "wof:placetype":"locality"
},
  "geometry": {"coordinates":[43.84597,42.25167],"type":"Point"}
}