{
  "type": "Feature",
  "properties": {
    "iso:country":"GE",
    "name:abk_x_preferred":[
        "\u0524\u0441\u0430\u0445\u0430\u0440\u0430"
    ],
    "name:ces_x_preferred":[
        "Psachara"
    ],
    "name:eng_x_preferred":[
        "Kolkhida"
    ],
    "name:fas_x_preferred":[
        "\u06a9\u0648\u0644\u062e\u06cc\u062f\u0627"
    ],
    "name:hye_x_preferred":[
        "\u053f\u0578\u056c\u056d\u056b\u0564\u0561"
    ],
    "name:jpn_x_preferred":[
        "\u30b3\u30eb\u30d2\u30fc\u30c0"
    ],
    "name:kat_x_preferred":[
        "K\u2019olkhida"
    ],
    "name:kat_x_variant":[
        "\u10d9\u10dd\u10da\u10ee\u10d8\u10d3\u10d0"
    ],
    "name:nld_x_preferred":[
        "Kolkhida"
    ],
    "name:pol_x_preferred":[
        "Kolchida"
    ],
    "name:rus_x_preferred":[
        "\u041a\u043e\u043b\u0445\u0438\u0434\u0430"
    ],
    "name:spa_x_preferred":[
        "Koljida"
    ],
    "name:swe_x_preferred":[
        "Kolchida"
    ],
    "name:und_x_variant":[
        "Sakartvelos Kheoba"
    ],
    "name:uzb_x_preferred":[
        "Kolxida"
    ],
    "qs:gn_country":"GE",
    "qs:gn_fcode":"PPL",
    "qs:gn_pop":0,
    "qs:name":"Kolkhida",
    "qs:name_adm0":"Georgia",
    "qs:name_adm1":"Abkhazia",
    "qs:photos":23,
    "qs:photos_1k":5,
    "qs:photos_9k":1,
    "qs:photos_9r":1,
    "qs:photos_all":23,
    "qs:photos_sr":1,
    "qs:placetype":"Town",
    "qs:pop_sr":"0",
    "qs:woe_adm0":23424823,
    "wof:name":"Kolkhida",
    "wof:placetype":"locality"
},
  "geometry": {"coordinates":[40.28766,43.25778],"type":"Point"}
}