{
  "type": "Feature",
  "properties": {
    "gn:admin1_code":"00",
    "gn:asciiname":"Burdadzori",
    "gn:country_code":"GE",
    "gn:dem":756,
    "gn:feature_class":"P",
    "gn:feature_code":"PPL",
    "gn:name":"Burdadzori",
    "gn:population":0,
    "gn:timezone":"Asia/Tbilisi",
    "iso:country":"GE",
    "name:und_x_variant":[
        "Brdadzoi",
        "Burdadzori"
    ],
    "wof:name":"Burdadzori",
    "wof:placetype":"locality"
},
  "geometry": {"coordinates":[44.72794,41.21031],"type":"Point"}
}