{
  "type": "Feature",
  "properties": {
    "gn:admin1_code":"69",
    "gn:asciiname":"K'vemo Zakhori",
    "gn:country_code":"GE",
    "gn:dem":985,
    "gn:feature_class":"P",
    "gn:feature_code":"PPL",
    "gn:name":"K\u2019vemo Zakhori",
    "gn:population":0,
    "gn:timezone":"Asia/Tbilisi",
    "iso:country":"GE",
    "name:kat_x_preferred":[
        "K\u2019vemo Zakhori"
    ],
    "name:und_x_variant":[
        "Zakhori",
        "Dallag-Zakor"
    ],
    "wof:name":"K'vemo Zakhori",
    "wof:placetype":"locality"
},
  "geometry": {"coordinates":[44.35,42.15028],"type":"Point"}
}