{
  "type": "Feature",
  "properties": {
    "gn:admin1_code":"00",
    "gn:asciiname":"Petriani",
    "gn:country_code":"GE",
    "gn:dem":1351,
    "gn:feature_class":"P",
    "gn:feature_code":"PPL",
    "gn:name":"Petriani",
    "gn:population":0,
    "gn:timezone":"Asia/Tbilisi",
    "iso:country":"GE",
    "wof:name":"Petriani",
    "wof:placetype":"locality"
},
  "geometry": {"coordinates":[44.60667,42.42167],"type":"Point"}
}