{
  "type": "Feature",
  "properties": {
    "gn:admin1_code":"00",
    "gn:asciiname":"Saputkre",
    "gn:country_code":"GE",
    "gn:dem":746,
    "gn:feature_class":"P",
    "gn:feature_code":"PPL",
    "gn:name":"Saputkre",
    "gn:population":0,
    "gn:timezone":"Asia/Tbilisi",
    "iso:country":"GE",
    "wof:name":"Saputkre",
    "wof:placetype":"locality"
},
  "geometry": {"coordinates":[45.10667,42.09056],"type":"Point"}
}