{
  "type": "Feature",
  "properties": {
    "gn:admin1_code":"02",
    "gn:asciiname":"Poltava-Aleksandrovskoye",
    "gn:country_code":"GE",
    "gn:dem":276,
    "gn:feature_class":"P",
    "gn:feature_code":"PPL",
    "gn:name":"Poltava-Aleksandrovskoye",
    "gn:population":0,
    "gn:timezone":"Asia/Tbilisi",
    "iso:country":"GE",
    "name:und_x_variant":[
        "Poltava",
        "Poltavskoye",
        "Poltava-Aleksandrovskoye"
    ],
    "wof:name":"Poltava-Aleksandrovskoye",
    "wof:placetype":"locality"
},
  "geometry": {"coordinates":[41.15542,43.04722],"type":"Point"}
}