{
  "type": "Feature",
  "properties": {
    "gn:admin1_code":"71",
    "gn:asciiname":"Let'kant'i",
    "gn:country_code":"GE",
    "gn:dem":289,
    "gn:feature_class":"P",
    "gn:feature_code":"PPL",
    "gn:name":"Let\u2019kant\u2019i",
    "gn:population":0,
    "gn:timezone":"Asia/Tbilisi",
    "iso:country":"GE",
    "name:kat_x_preferred":[
        "Let\u2019kant\u2019i"
    ],
    "name:kat_x_variant":[
        "\u10da\u10d4\u10d7\u10d9\u10d0\u10dc\u10d7\u10d8"
    ],
    "wof:name":"Let'kant'i",
    "wof:placetype":"locality"
},
  "geometry": {"coordinates":[42.15857000000001,42.65011],"type":"Point"}
}