{
  "type": "Feature",
  "properties": {
    "gn:admin1_code":"00",
    "gn:asciiname":"Kvemo-Akhkalapa",
    "gn:country_code":"GE",
    "gn:dem":1156,
    "gn:feature_class":"P",
    "gn:feature_code":"PPL",
    "gn:name":"Kvemo-Akhkalapa",
    "gn:population":0,
    "gn:timezone":"Asia/Tbilisi",
    "iso:country":"GE",
    "name:und_x_variant":[
        "Nizhnyaya Akhkalapa",
        "Kvemo-Akhkalafa",
        "Kvemo-Akhkalapa"
    ],
    "wof:name":"Kvemo-Akhkalapa",
    "wof:placetype":"locality"
},
  "geometry": {"coordinates":[44.29085,41.48823],"type":"Point"}
}