{
  "type": "Feature",
  "properties": {
    "gn:admin1_code":"72",
    "gn:asciiname":"Avranlo",
    "gn:country_code":"GE",
    "gn:dem":1569,
    "gn:feature_class":"P",
    "gn:feature_code":"PPL",
    "gn:name":"Avranlo",
    "gn:population":0,
    "gn:timezone":"Asia/Tbilisi",
    "iso:country":"GE",
    "name:eng_x_preferred":[
        "Avranlo"
    ],
    "name:kat_x_preferred":[
        "\u10d0\u10d5\u10e0\u10d0\u10dc\u10da\u10dd"
    ],
    "name:rus_x_preferred":[
        "\u0410\u0432\u0440\u0430\u043d\u043b\u043e"
    ],
    "wof:name":"Avranlo",
    "wof:placetype":"locality"
},
  "geometry": {"coordinates":[43.89129000000001,41.65589],"type":"Point"}
}