{
  "type": "Feature",
  "properties": {
    "gn:admin1_code":"02",
    "gn:asciiname":"Khashupse",
    "gn:country_code":"GE",
    "gn:dem":67,
    "gn:feature_class":"P",
    "gn:feature_code":"PPL",
    "gn:name":"Khashupse",
    "gn:population":0,
    "gn:timezone":"Asia/Tbilisi",
    "iso:country":"GE",
    "name:kat_x_preferred":[
        "Khashupse"
    ],
    "name:kat_x_variant":[
        "\u10ee\u10d0\u10e8\u10e3\u10e4\u10e1\u10d4"
    ],
    "name:und_x_variant":[
        "Khashupsa"
    ],
    "wof:name":"Khashupse",
    "wof:placetype":"locality"
},
  "geometry": {"coordinates":[40.11306,43.4079],"type":"Point"}
}