{
  "type": "Feature",
  "properties": {
    "gn:admin1_code":"69",
    "gn:asciiname":"Gamsi",
    "gn:country_code":"GE",
    "gn:dem":1457,
    "gn:feature_class":"P",
    "gn:feature_code":"PPL",
    "gn:name":"Gamsi",
    "gn:population":0,
    "gn:timezone":"Asia/Tbilisi",
    "iso:country":"GE",
    "name:eng_x_preferred":[
        "Gamsi"
    ],
    "name:rus_x_preferred":[
        "\u0413\u0430\u043c\u0441\u0438"
    ],
    "name:und_x_variant":[
        "Gamvi"
    ],
    "wof:name":"Gamsi",
    "wof:placetype":"locality"
},
  "geometry": {"coordinates":[44.71972,42.43849],"type":"Point"}
}