{
  "type": "Feature",
  "properties": {
    "gn:admin1_code":"68",
    "gn:asciiname":"Op'ret'i",
    "gn:country_code":"GE",
    "gn:dem":1041,
    "gn:feature_class":"P",
    "gn:feature_code":"PPL",
    "gn:name":"Op\u2019ret\u2019i",
    "gn:population":0,
    "gn:timezone":"Asia/Tbilisi",
    "iso:country":"GE",
    "name:eng_x_preferred":[
        "Op'ret'i"
    ],
    "name:kat_x_preferred":[
        "\u10dd\u10e4\u10e0\u10d4\u10d7\u10d8"
    ],
    "name:rus_x_preferred":[
        "\u041e\u043f\u0440\u0435\u0442\u0438"
    ],
    "name:und_x_variant":[
        "Op\u2019ret\u2019i"
    ],
    "wof:name":"Op'ret'i",
    "wof:placetype":"locality"
},
  "geometry": {"coordinates":[44.63212,41.25167],"type":"Point"}
}