{
  "type": "Feature",
  "properties": {
    "gn:admin1_code":"00",
    "gn:asciiname":"Eliatsminda",
    "gn:country_code":"GE",
    "gn:dem":1456,
    "gn:feature_class":"P",
    "gn:feature_code":"PPL",
    "gn:name":"Eliatsminda",
    "gn:population":0,
    "gn:timezone":"Asia/Tbilisi",
    "iso:country":"GE",
    "name:kat_x_preferred":[
        "\u10d4\u10da\u10d8\u10d0\u10ec\u10db\u10d8\u10dc\u10d3\u10d0"
    ],
    "wof:name":"Eliatsminda",
    "wof:placetype":"locality"
},
  "geometry": {"coordinates":[42.95881,41.70837],"type":"Point"}
}