{
  "type": "Feature",
  "properties": {
    "gn:admin1_code":"68",
    "gn:asciiname":"T'ek'ali",
    "gn:country_code":"GE",
    "gn:dem":310,
    "gn:feature_class":"P",
    "gn:feature_code":"PPL",
    "gn:name":"T\u2019ek\u2019ali",
    "gn:population":0,
    "gn:timezone":"Asia/Tbilisi",
    "iso:country":"GE",
    "name:fas_x_preferred":[
        "\u062a\u06a9\u0627\u0644\u06cc"
    ],
    "name:kat_x_preferred":[
        "\u10d7\u10d4\u10e5\u10d0\u10da\u10d8"
    ],
    "name:und_x_variant":[
        "Takyalo",
        "T\u2019ek\u2019ali"
    ],
    "wof:name":"T'ek'ali",
    "wof:placetype":"locality"
},
  "geometry": {"coordinates":[44.96547,41.35381],"type":"Point"}
}