{
  "type": "Feature",
  "properties": {
    "gn:admin1_code":"00",
    "gn:asciiname":"Tulari",
    "gn:cc2":"GE",
    "gn:country_code":"GE",
    "gn:dem":476,
    "gn:feature_class":"P",
    "gn:feature_code":"PPL",
    "gn:name":"Tulari",
    "gn:population":0,
    "gn:timezone":"Asia/Tbilisi",
    "iso:country":"GE",
    "name:ceb_x_preferred":[
        "Tulari"
    ],
    "name:fas_x_preferred":[
        "\u062a\u0648\u0644\u0627\u0631\u06cc"
    ],
    "name:fra_x_preferred":[
        "Tulari"
    ],
    "name:msa_x_preferred":[
        "Tulari"
    ],
    "name:nld_x_preferred":[
        "Tulari"
    ],
    "name:por_x_preferred":[
        "Tulari"
    ],
    "name:slv_x_preferred":[
        "Tulari"
    ],
    "name:srp_x_preferred":[
        "\u0422\u0443\u043b\u0430\u0440\u0438"
    ],
    "name:und_x_variant":[
        "Tullar"
    ],
    "wof:name":"Tulari",
    "wof:placetype":"locality"
},
  "geometry": {"coordinates":[45.55278,41.57972],"type":"Point"}
}