{
  "type": "Feature",
  "properties": {
    "gn:admin1_code":"00",
    "gn:asciiname":"Uriuli Nizhniye",
    "gn:country_code":"GE",
    "gn:dem":1293,
    "gn:feature_class":"P",
    "gn:feature_code":"PPL",
    "gn:name":"Uriuli Nizhniye",
    "gn:population":0,
    "gn:timezone":"Asia/Tbilisi",
    "iso:country":"GE",
    "wof:name":"Uriuli Nizhniye",
    "wof:placetype":"locality"
},
  "geometry": {"coordinates":[44.14472,41.86972],"type":"Point"}
}