{
  "type": "Feature",
  "properties": {
    "gn:admin1_code":"66",
    "gn:asciiname":"Sats'iskvilo",
    "gn:country_code":"GE",
    "gn:dem":726,
    "gn:feature_class":"P",
    "gn:feature_code":"PPL",
    "gn:name":"Sats\u2019iskvilo",
    "gn:population":0,
    "gn:timezone":"Asia/Tbilisi",
    "iso:country":"GE",
    "name:kat_x_preferred":[
        "Sats\u2019iskvilo"
    ],
    "name:kat_x_variant":[
        "\u10e1\u10d0\u10ec\u10d8\u10e1\u10e5\u10d5\u10d8\u10da\u10dd"
    ],
    "wof:name":"Sats'iskvilo",
    "wof:placetype":"locality"
},
  "geometry": {"coordinates":[42.54606,42.4812],"type":"Point"}
}