{
  "type": "Feature",
  "properties": {
    "gn:admin1_code":"65",
    "gn:asciiname":"Maghali Ets'eri",
    "gn:country_code":"GE",
    "gn:dem":172,
    "gn:feature_class":"P",
    "gn:feature_code":"PPL",
    "gn:name":"Maghali Ets\u2019eri",
    "gn:population":0,
    "gn:timezone":"Asia/Tbilisi",
    "iso:country":"GE",
    "name:kat_x_preferred":[
        "Maghali Ets\u2019eri"
    ],
    "name:kat_x_variant":[
        "\u10db\u10d0\u10e6\u10d0\u10da\u10d8 \u10d4\u10ec\u10d4\u10e0\u10d8"
    ],
    "wof:name":"Maghali Ets'eri",
    "wof:placetype":"locality"
},
  "geometry": {"coordinates":[42.12738,41.97242],"type":"Point"}
}