{
  "type": "Feature",
  "properties": {
    "gn:admin1_code":"02",
    "gn:asciiname":"Aats'i",
    "gn:country_code":"GE",
    "gn:dem":41,
    "gn:feature_class":"P",
    "gn:feature_code":"PPL",
    "gn:name":"Aats\u2019i",
    "gn:population":0,
    "gn:timezone":"Asia/Tbilisi",
    "iso:country":"GE",
    "name:kat_x_preferred":[
        "Aats\u2019i"
    ],
    "name:kat_x_variant":[
        "\u10d0\u10d0\u10ea\u10d8"
    ],
    "name:und_x_variant":[
        "Baklanovka",
        "Aatsy"
    ],
    "wof:name":"Aats'i",
    "wof:placetype":"locality"
},
  "geometry": {"coordinates":[40.73222,43.13639000000001],"type":"Point"}
}