{
  "type": "Feature",
  "properties": {
    "gn:admin1_code":"00",
    "gn:asciiname":"Sarach'lo",
    "gn:country_code":"GE",
    "gn:dem":521,
    "gn:feature_class":"P",
    "gn:feature_code":"PPL",
    "gn:name":"Sarach\u2019lo",
    "gn:population":0,
    "gn:timezone":"Asia/Tbilisi",
    "iso:country":"GE",
    "name:eng_x_preferred":[
        "Sarach'lo"
    ],
    "name:rus_x_preferred":[
        "\u0421\u0430\u0440\u0430\u0447\u043b\u043e"
    ],
    "name:und_x_variant":[
        "Sarach\u2019lo"
    ],
    "wof:name":"Sarach'lo",
    "wof:placetype":"locality"
},
  "geometry": {"coordinates":[44.72041,41.3843],"type":"Point"}
}