{
  "type": "Feature",
  "properties": {
    "gn:admin1_code":"71",
    "gn:asciiname":"Kvemo Khunts'i",
    "gn:country_code":"GE",
    "gn:dem":165,
    "gn:feature_class":"P",
    "gn:feature_code":"PPL",
    "gn:name":"Kvemo Khunts\u2019i",
    "gn:population":0,
    "gn:timezone":"Asia/Tbilisi",
    "iso:country":"GE",
    "name:kat_x_preferred":[
        "Kvemo Khunts\u2019i"
    ],
    "name:kat_x_variant":[
        "\u10e5\u10d5\u10d4\u10db\u10dd \u10ee\u10e3\u10dc\u10ec\u10d8"
    ],
    "name:und_x_variant":[
        "Khuntsa",
        "Kvemo-Khunts"
    ],
    "wof:name":"Kvemo Khunts'i",
    "wof:placetype":"locality"
},
  "geometry": {"coordinates":[42.40376,42.39087],"type":"Point"}
}