{
  "type": "Feature",
  "properties": {
    "gn:admin1_code":"00",
    "gn:asciiname":"Kelasuri",
    "gn:country_code":"GE",
    "gn:dem":164,
    "gn:feature_class":"P",
    "gn:feature_code":"PPL",
    "gn:name":"Kelasuri",
    "gn:population":0,
    "gn:timezone":"Asia/Tbilisi",
    "iso:country":"GE",
    "name:eng_x_preferred":[
        "Kelasuri"
    ],
    "name:rus_x_preferred":[
        "\u041a\u0435\u043b\u0430\u0441\u0443\u0440\u0438"
    ],
    "wof:name":"Kelasuri",
    "wof:placetype":"locality"
},
  "geometry": {"coordinates":[41.1025,43.01194],"type":"Point"}
}