{
  "type": "Feature",
  "properties": {
    "gn:admin1_code":"00",
    "gn:asciiname":"Kvemo-Samtskaro",
    "gn:country_code":"GE",
    "gn:dem":1235,
    "gn:feature_class":"P",
    "gn:feature_code":"PPL",
    "gn:name":"Kvemo-Samtskaro",
    "gn:population":0,
    "gn:timezone":"Asia/Tbilisi",
    "iso:country":"GE",
    "wof:name":"Kvemo-Samtskaro",
    "wof:placetype":"locality"
},
  "geometry": {"coordinates":[43.86667,42.25],"type":"Point"}
}