{
  "type": "Feature",
  "properties": {
    "gn:admin1_code":"72",
    "gn:asciiname":"Ts'ikhisjvari",
    "gn:country_code":"GE",
    "gn:dem":1639,
    "gn:feature_class":"P",
    "gn:feature_code":"PPL",
    "gn:name":"Ts\u2019ikhisjvari",
    "gn:population":0,
    "gn:timezone":"Asia/Tbilisi",
    "iso:country":"GE",
    "name:eng_x_preferred":[
        "Ts'ikhisjvari"
    ],
    "name:kat_x_preferred":[
        "\u10ea\u10d8\u10ee\u10d8\u10e1\u10ef\u10d5\u10d0\u10e0\u10d8"
    ],
    "name:rus_x_preferred":[
        "\u0426\u0438\u0445\u0438\u0441\u0434\u0436\u0432\u0430\u0440\u0438"
    ],
    "name:und_x_variant":[
        "Tsikhisdzhvari",
        "Tsikhidzhvari",
        "Ts\u2019ikhisjvari"
    ],
    "wof:name":"Ts'ikhisjvari",
    "wof:placetype":"locality"
},
  "geometry": {"coordinates":[43.44276,41.71861],"type":"Point"}
}