{
  "type": "Feature",
  "properties": {
    "gn:admin1_code":"02",
    "gn:asciiname":"Ajra",
    "gn:country_code":"GE",
    "gn:dem":245,
    "gn:feature_class":"P",
    "gn:feature_code":"PPL",
    "gn:name":"Ajra",
    "gn:population":0,
    "gn:timezone":"Asia/Tbilisi",
    "iso:country":"GE",
    "name:kat_x_preferred":[
        "Ajra"
    ],
    "name:kat_x_variant":[
        "\u10d0\u10ef\u10e0\u10d0"
    ],
    "name:und_x_variant":[
        "Adzhra"
    ],
    "wof:name":"Ajra",
    "wof:placetype":"locality"
},
  "geometry": {"coordinates":[41.69618,42.74889],"type":"Point"}
}