{
  "type": "Feature",
  "properties": {
    "gn:admin1_code":"71",
    "gn:asciiname":"Nach'k'adu",
    "gn:country_code":"GE",
    "gn:dem":6,
    "gn:feature_class":"P",
    "gn:feature_code":"PPL",
    "gn:name":"Nach\u2019k\u2019adu",
    "gn:population":0,
    "gn:timezone":"Asia/Tbilisi",
    "iso:country":"GE",
    "name:kat_x_preferred":[
        "Nach\u2019k\u2019adu"
    ],
    "name:kat_x_variant":[
        "\u10dc\u10d0\u10ed\u10d9\u10d0\u10d3\u10e3"
    ],
    "name:und_x_variant":[
        "Nachkadou"
    ],
    "wof:name":"Nach'k'adu",
    "wof:placetype":"locality"
},
  "geometry": {"coordinates":[41.69052,42.36521],"type":"Point"}
}