{
  "type": "Feature",
  "properties": {
    "gn:admin1_code":"00",
    "gn:asciiname":"Sanamer",
    "gn:country_code":"GE",
    "gn:dem":1534,
    "gn:feature_class":"P",
    "gn:feature_code":"PPL",
    "gn:name":"Sanamer",
    "gn:population":0,
    "gn:timezone":"Asia/Tbilisi",
    "iso:country":"GE",
    "wof:name":"Sanamer",
    "wof:placetype":"locality"
},
  "geometry": {"coordinates":[44.04556,41.60472],"type":"Point"}
}