{
  "type": "Feature",
  "properties": {
    "gn:admin1_code":"00",
    "gn:asciiname":"Tslunkaani",
    "gn:country_code":"GE",
    "gn:dem":564,
    "gn:feature_class":"P",
    "gn:feature_code":"PPL",
    "gn:name":"Tslunkaani",
    "gn:population":0,
    "gn:timezone":"Asia/Tbilisi",
    "iso:country":"GE",
    "wof:name":"Tslunkaani",
    "wof:placetype":"locality"
},
  "geometry": {"coordinates":[45.98997,41.54513],"type":"Point"}
}