{
  "type": "Feature",
  "properties": {
    "gn:asciiname":"Upper Svaneti",
    "gn:country_code":"GE",
    "gn:dem":2093,
    "gn:feature_class":"P",
    "gn:feature_code":"PPL",
    "gn:name":"Upper Svaneti",
    "gn:population":0,
    "gn:timezone":"Asia/Tbilisi",
    "iso:country":"GE",
    "wof:name":"Upper Svaneti",
    "wof:placetype":"locality"
},
  "geometry": {"coordinates":[43.01139000000001,42.91639],"type":"Point"}
}