{
  "type": "Feature",
  "properties": {
    "gn:admin1_code":"65",
    "gn:asciiname":"K'virik'eti",
    "gn:country_code":"GE",
    "gn:dem":98,
    "gn:feature_class":"P",
    "gn:feature_code":"PPL",
    "gn:name":"K\u2019virik\u2019eti",
    "gn:population":0,
    "gn:timezone":"Asia/Tbilisi",
    "iso:country":"GE",
    "name:kat_x_preferred":[
        "K\u2019virik\u2019eti"
    ],
    "name:kat_x_variant":[
        "\u10d9\u10d5\u10d8\u10e0\u10d8\u10d9\u10d4\u10d7\u10d8"
    ],
    "wof:name":"K'virik'eti",
    "wof:placetype":"locality"
},
  "geometry": {"coordinates":[42.02591,41.91615],"type":"Point"}
}