{
  "type": "Feature",
  "properties": {
    "gn:admin1_code":"05",
    "gn:asciiname":"Dzukat'a",
    "gn:country_code":"GE",
    "gn:dem":843,
    "gn:feature_class":"P",
    "gn:feature_code":"PPL",
    "gn:name":"Dzukat\u2019a",
    "gn:population":0,
    "gn:timezone":"Asia/Tbilisi",
    "iso:country":"GE",
    "name:kat_x_preferred":[
        "Dzukat\u2019a"
    ],
    "name:und_x_variant":[
        "Duzkatikau",
        "Dzukato",
        "Dzugoytikau"
    ],
    "wof:name":"Dzukat'a",
    "wof:placetype":"locality"
},
  "geometry": {"coordinates":[44.30722,42.06903],"type":"Point"}
}