{
  "type": "Feature",
  "properties": {
    "gn:admin1_code":"02",
    "gn:asciiname":"Amzara",
    "gn:country_code":"GE",
    "gn:dem":285,
    "gn:feature_class":"P",
    "gn:feature_code":"PPL",
    "gn:name":"Amzara",
    "gn:population":0,
    "gn:timezone":"Asia/Tbilisi",
    "iso:country":"GE",
    "name:eng_x_preferred":[
        "Amzara"
    ],
    "name:rus_x_preferred":[
        "\u0410\u043c\u0437\u0430\u0440\u0430"
    ],
    "name:und_x_variant":[
        "Asterovka",
        "Amzara"
    ],
    "wof:name":"Amzara",
    "wof:placetype":"locality"
},
  "geometry": {"coordinates":[41.35079,43.01815],"type":"Point"}
}