{
  "type": "Feature",
  "properties": {
    "gn:admin1_code":"72",
    "gn:asciiname":"Ep'removka",
    "gn:country_code":"GE",
    "gn:dem":2119,
    "gn:feature_class":"P",
    "gn:feature_code":"PPL",
    "gn:name":"Ep\u2019removka",
    "gn:population":0,
    "gn:timezone":"Asia/Tbilisi",
    "iso:country":"GE",
    "name:kat_x_preferred":[
        "\u10d4\u10e4\u10e0\u10d4\u10db\u10dd\u10d5\u10d9\u10d0"
    ],
    "name:und_x_variant":[
        "Yefremovka",
        "Jefremowka",
        "Ep\u2019removka"
    ],
    "wof:name":"Ep'removka",
    "wof:placetype":"locality"
},
  "geometry": {"coordinates":[43.74344,41.19089],"type":"Point"}
}