{
  "type": "Feature",
  "properties": {
    "gn:admin1_code":"04",
    "gn:asciiname":"K'okhi",
    "gn:country_code":"GE",
    "gn:dem":156,
    "gn:feature_class":"P",
    "gn:feature_code":"PPL",
    "gn:name":"K\u2019okhi",
    "gn:population":0,
    "gn:timezone":"Asia/Tbilisi",
    "iso:country":"GE",
    "name:kat_x_preferred":[
        "\u10d9\u10dd\u10ee\u10d8"
    ],
    "name:rus_x_preferred":[
        "K\u2019okhi"
    ],
    "wof:name":"K'okhi",
    "wof:placetype":"locality"
},
  "geometry": {"coordinates":[41.89972,41.80056],"type":"Point"}
}