{
  "type": "Feature",
  "properties": {
    "gn:admin1_code":"00",
    "gn:asciiname":"Ganakhleba",
    "gn:country_code":"GE",
    "gn:dem":1338,
    "gn:feature_class":"P",
    "gn:feature_code":"PPL",
    "gn:name":"Ganakhleba",
    "gn:population":0,
    "gn:timezone":"Asia/Tbilisi",
    "iso:country":"GE",
    "name:und_x_variant":[
        "Ambarlo",
        "Ganakhleba"
    ],
    "wof:name":"Ganakhleba",
    "wof:placetype":"locality"
},
  "geometry": {"coordinates":[44.11136,41.48737],"type":"Point"}
}