{
  "type": "Feature",
  "properties": {
    "gn:admin1_code":"00",
    "gn:asciiname":"Khorchana",
    "gn:cc2":"GE",
    "gn:country_code":"GE",
    "gn:dem":487,
    "gn:feature_class":"P",
    "gn:feature_code":"PPL",
    "gn:name":"Khorchana",
    "gn:population":0,
    "gn:timezone":"Asia/Tbilisi",
    "iso:country":"GE",
    "name:und_x_variant":[
        "Khorehama",
        "Khorchana"
    ],
    "wof:name":"Khorchana",
    "wof:placetype":"locality"
},
  "geometry": {"coordinates":[42.81611,42.38306],"type":"Point"}
}