{
  "type": "Feature",
  "properties": {
    "gn:admin1_code":"04",
    "gn:asciiname":"K'ant'auri",
    "gn:country_code":"GE",
    "gn:dem":361,
    "gn:feature_class":"P",
    "gn:feature_code":"PPL",
    "gn:name":"K\u2019ant\u2019auri",
    "gn:population":0,
    "gn:timezone":"Asia/Tbilisi",
    "iso:country":"GE",
    "name:kat_x_preferred":[
        "K\u2019ant\u2019auri"
    ],
    "name:kat_x_variant":[
        "\u10d9\u10d0\u10dc\u10e2\u10d0\u10e3\u10e0\u10d8"
    ],
    "wof:name":"K'ant'auri",
    "wof:placetype":"locality"
},
  "geometry": {"coordinates":[42.01345,41.63549],"type":"Point"}
}