{
  "type": "Feature",
  "properties": {
    "gn:admin1_code":"71",
    "gn:asciiname":"Gejeti",
    "gn:country_code":"GE",
    "gn:dem":62,
    "gn:feature_class":"P",
    "gn:feature_code":"PPL",
    "gn:name":"Gejeti",
    "gn:population":0,
    "gn:timezone":"Asia/Tbilisi",
    "iso:country":"GE",
    "name:kat_x_preferred":[
        "Gejeti"
    ],
    "name:kat_x_variant":[
        "\u10d2\u10d4\u10ef\u10d4\u10d7\u10d8"
    ],
    "name:und_x_variant":[
        "Gedzheti"
    ],
    "wof:name":"Gejeti",
    "wof:placetype":"locality"
},
  "geometry": {"coordinates":[42.22383,42.31057],"type":"Point"}
}