{
  "type": "Feature",
  "properties": {
    "gn:admin1_code":"22",
    "gn:asciiname":"Dzari",
    "gn:country_code":"GE",
    "gn:dem":1245,
    "gn:feature_class":"P",
    "gn:feature_code":"PPL",
    "gn:name":"Dzari",
    "gn:population":0,
    "gn:timezone":"Asia/Tbilisi",
    "iso:country":"GE",
    "name:und_x_variant":[
        "Vuallag-Dzari",
        "Dzari Verkhniye",
        "Zemo-Dzari",
        "Dzari"
    ],
    "wof:name":"Dzari",
    "wof:placetype":"locality"
},
  "geometry": {"coordinates":[43.87472,42.28666],"type":"Point"}
}