{
  "type": "Feature",
  "properties": {
    "gn:admin1_code":"00",
    "gn:asciiname":"Sabe",
    "gn:cc2":"GE",
    "gn:country_code":"GE",
    "gn:dem":502,
    "gn:feature_class":"P",
    "gn:feature_code":"PPL",
    "gn:name":"Sabe",
    "gn:population":0,
    "gn:timezone":"Asia/Tbilisi",
    "iso:country":"GE",
    "name:und_x_variant":[
        "Kvadaura",
        "Sabe-Kvadaura",
        "Sabe"
    ],
    "wof:name":"Sabe",
    "wof:placetype":"locality"
},
  "geometry": {"coordinates":[43.28028,42.06167],"type":"Point"}
}