{
  "type": "Feature",
  "properties": {
    "gn:admin1_code":"04",
    "gn:asciiname":"Rakvta",
    "gn:country_code":"GE",
    "gn:dem":1359,
    "gn:feature_class":"P",
    "gn:feature_code":"PPL",
    "gn:name":"Rakvta",
    "gn:population":0,
    "gn:timezone":"Asia/Tbilisi",
    "iso:country":"GE",
    "name:kat_x_preferred":[
        "Rakvta"
    ],
    "name:kat_x_variant":[
        "\u10e0\u10d0\u10e5\u10d5\u10d7\u10d0"
    ],
    "name:und_x_variant":[
        "Ragsta"
    ],
    "wof:name":"Rakvta",
    "wof:placetype":"locality"
},
  "geometry": {"coordinates":[42.48003,41.56997],"type":"Point"}
}