{
  "type": "Feature",
  "properties": {
    "gn:admin1_code":"69",
    "gn:asciiname":"Zemo Ubani",
    "gn:country_code":"GE",
    "gn:dem":1170,
    "gn:feature_class":"P",
    "gn:feature_code":"PPL",
    "gn:name":"Zemo Ubani",
    "gn:population":0,
    "gn:timezone":"Asia/Tbilisi",
    "iso:country":"GE",
    "wof:name":"Zemo Ubani",
    "wof:placetype":"locality"
},
  "geometry": {"coordinates":[44.8088,42.0346],"type":"Point"}
}