{
  "type": "Feature",
  "properties": {
    "gn:admin1_code":"00",
    "gn:asciiname":"Gvara",
    "gn:country_code":"GE",
    "gn:dem":113,
    "gn:feature_class":"P",
    "gn:feature_code":"PPL",
    "gn:name":"Gvara",
    "gn:population":0,
    "gn:timezone":"Asia/Tbilisi",
    "iso:country":"GE",
    "wof:name":"Gvara",
    "wof:placetype":"locality"
},
  "geometry": {"coordinates":[41.73333,41.51667],"type":"Point"}
}