{
  "type": "Feature",
  "properties": {
    "gn:admin1_code":"71",
    "gn:asciiname":"Lek'almakhi",
    "gn:country_code":"GE",
    "gn:dem":798,
    "gn:feature_class":"P",
    "gn:feature_code":"PPL",
    "gn:name":"Lek\u2019almakhi",
    "gn:population":0,
    "gn:timezone":"Asia/Tbilisi",
    "iso:country":"GE",
    "name:kat_x_preferred":[
        "Lek\u2019almakhi"
    ],
    "name:kat_x_variant":[
        "\u10da\u10d4\u10ee\u10d0\u10da\u10db\u10d0\u10ee\u10d8"
    ],
    "name:und_x_variant":[
        "Leka Imakhi"
    ],
    "wof:name":"Lek'almakhi",
    "wof:placetype":"locality"
},
  "geometry": {"coordinates":[42.1899,43.00899],"type":"Point"}
}