{
  "type": "Feature",
  "properties": {
    "gn:admin1_code":"71",
    "gn:asciiname":"Didi Chqoni",
    "gn:country_code":"GE",
    "gn:dem":231,
    "gn:feature_class":"P",
    "gn:feature_code":"PPL",
    "gn:name":"Didi Chqoni",
    "gn:population":0,
    "gn:timezone":"Asia/Tbilisi",
    "iso:country":"GE",
    "name:kat_x_preferred":[
        "\u10d3\u10d8\u10d3\u10d8 \u10ed\u10e7\u10dd\u10dc\u10d8"
    ],
    "name:und_x_variant":[
        "Didi Tchkoni",
        "Didi-Chkoni",
        "Didi Chqoni"
    ],
    "wof:name":"Didi Chqoni",
    "wof:placetype":"locality"
},
  "geometry": {"coordinates":[42.33712,42.48873],"type":"Point"}
}