{
  "type": "Feature",
  "properties": {
    "gn:admin1_code":"73",
    "gn:asciiname":"Bret'i",
    "gn:country_code":"GE",
    "gn:dem":688,
    "gn:feature_class":"P",
    "gn:feature_code":"PPL",
    "gn:name":"Bret\u2019i",
    "gn:population":0,
    "gn:timezone":"Asia/Tbilisi",
    "iso:country":"GE",
    "name:eng_x_preferred":[
        "Bret'i"
    ],
    "name:rus_x_preferred":[
        "\u0411\u0440\u0435\u0442\u0438"
    ],
    "name:und_x_variant":[
        "Bret\u2019i"
    ],
    "wof:name":"Bret'i",
    "wof:placetype":"locality"
},
  "geometry": {"coordinates":[43.90156,42.08463],"type":"Point"}
}