{
  "type": "Feature",
  "properties": {
    "gn:admin1_code":"00",
    "gn:asciiname":"Akqulari",
    "gn:country_code":"GE",
    "gn:dem":650,
    "gn:feature_class":"P",
    "gn:feature_code":"PPL",
    "gn:name":"Akqulari",
    "gn:population":0,
    "gn:timezone":"Asia/Tbilisi",
    "iso:country":"GE",
    "name:und_x_variant":[
        "Akkulari",
        "Akqulari"
    ],
    "wof:name":"Akqulari",
    "wof:placetype":"locality"
},
  "geometry": {"coordinates":[44.7342,41.31081],"type":"Point"}
}