{
  "type": "Feature",
  "properties": {
    "gn:admin1_code":"65",
    "gn:asciiname":"Ts'ipnagvara",
    "gn:country_code":"GE",
    "gn:dem":230,
    "gn:feature_class":"P",
    "gn:feature_code":"PPL",
    "gn:name":"Ts\u2019ipnagvara",
    "gn:population":0,
    "gn:timezone":"Asia/Tbilisi",
    "iso:country":"GE",
    "name:kat_x_preferred":[
        "Ts\u2019ipnagvara"
    ],
    "name:kat_x_variant":[
        "\u10ec\u10d8\u10e4\u10dc\u10d0\u10d2\u10d5\u10d0\u10e0\u10d0"
    ],
    "wof:name":"Ts'ipnagvara",
    "wof:placetype":"locality"
},
  "geometry": {"coordinates":[42.21969,41.96039],"type":"Point"}
}