{
  "type": "Feature",
  "properties": {
    "gn:admin1_code":"70",
    "gn:asciiname":"Shk'edi",
    "gn:country_code":"GE",
    "gn:dem":1316,
    "gn:feature_class":"P",
    "gn:feature_code":"PPL",
    "gn:name":"Shk\u2019edi",
    "gn:population":0,
    "gn:timezone":"Asia/Tbilisi",
    "iso:country":"GE",
    "name:kat_x_preferred":[
        "Shk\u2019edi"
    ],
    "name:kat_x_variant":[
        "\u10e8\u10d9\u10d4\u10d3\u10d8"
    ],
    "wof:name":"Shk'edi",
    "wof:placetype":"locality"
},
  "geometry": {"coordinates":[43.06571,42.78619000000001],"type":"Point"}
}