{
  "type": "Feature",
  "properties": {
    "gn:admin1_code":"65",
    "gn:asciiname":"Meria",
    "gn:country_code":"GE",
    "gn:dem":23,
    "gn:feature_class":"P",
    "gn:feature_code":"PPL",
    "gn:name":"Meria",
    "gn:population":0,
    "gn:timezone":"Asia/Tbilisi",
    "iso:country":"GE",
    "name:cat_x_preferred":[
        "Meria"
    ],
    "name:ceb_x_preferred":[
        "Meria"
    ],
    "name:cos_x_preferred":[
        "Meria"
    ],
    "name:deu_x_preferred":[
        "Meria"
    ],
    "name:eng_x_preferred":[
        "Meria"
    ],
    "name:eus_x_preferred":[
        "Meria"
    ],
    "name:fra_x_preferred":[
        "Meria"
    ],
    "name:hun_x_preferred":[
        "Meria"
    ],
    "name:ita_x_preferred":[
        "Meria"
    ],
    "name:kat_x_preferred":[
        "Meria"
    ],
    "name:kat_x_variant":[
        "\u10db\u10d4\u10e0\u10d8\u10d0"
    ],
    "name:kaz_x_preferred":[
        "\u041c\u0435\u0440\u0438\u044f"
    ],
    "name:lat_x_preferred":[
        "Meria"
    ],
    "name:lmo_x_preferred":[
        "Meria"
    ],
    "name:mlg_x_preferred":[
        "Meria"
    ],
    "name:msa_x_preferred":[
        "Meria"
    ],
    "name:nld_x_preferred":[
        "Meria"
    ],
    "name:oci_x_preferred":[
        "Meria"
    ],
    "name:pol_x_preferred":[
        "Meria"
    ],
    "name:por_x_preferred":[
        "Meria"
    ],
    "name:rus_x_preferred":[
        "\u041c\u0435\u0440\u0438\u0430"
    ],
    "name:rus_x_variant":[
        "\u041c\u0435\u0440\u0438\u044f"
    ],
    "name:slk_x_preferred":[
        "Meria"
    ],
    "name:slv_x_preferred":[
        "Meria"
    ],
    "name:spa_x_preferred":[
        "Meria"
    ],
    "name:swe_x_preferred":[
        "Meria"
    ],
    "name:ukr_x_preferred":[
        "\u041c\u0435\u0440\u0456\u044f"
    ],
    "name:und_x_variant":[
        "Maria"
    ],
    "name:vie_x_preferred":[
        "Meria"
    ],
    "name:vol_x_preferred":[
        "Meria"
    ],
    "name:war_x_preferred":[
        "Meria"
    ],
    "wof:name":"Meria",
    "wof:placetype":"locality"
},
  "geometry": {"coordinates":[41.88315,41.94226],"type":"Point"}
}