{
  "type": "Feature",
  "properties": {
    "gn:admin1_code":"65",
    "gn:asciiname":"Meria",
    "gn:country_code":"GE",
    "gn:dem":23,
    "gn:feature_class":"P",
    "gn:feature_code":"PPL",
    "gn:name":"Meria",
    "gn:population":0,
    "gn:timezone":"Asia/Tbilisi",
    "iso:country":"GE",
    "name:eng_x_preferred":[
        "Meria"
    ],
    "name:kat_x_preferred":[
        "Meria"
    ],
    "name:kat_x_variant":[
        "\u10db\u10d4\u10e0\u10d8\u10d0"
    ],
    "name:rus_x_preferred":[
        "\u041c\u0435\u0440\u0438\u0430"
    ],
    "name:und_x_variant":[
        "Maria"
    ],
    "wof:name":"Meria",
    "wof:placetype":"locality"
},
  "geometry": {"coordinates":[41.88315,41.94226],"type":"Point"}
}