{
  "type": "Feature",
  "properties": {
    "gn:admin1_code":"00",
    "gn:asciiname":"Ch'alaubani",
    "gn:country_code":"GE",
    "gn:dem":745,
    "gn:feature_class":"P",
    "gn:feature_code":"PPL",
    "gn:name":"Ch\u2019alaubani",
    "gn:population":0,
    "gn:timezone":"Asia/Tbilisi",
    "iso:country":"GE",
    "name:kat_x_preferred":[
        "Ch\u2019alaubani"
    ],
    "wof:name":"Ch'alaubani",
    "wof:placetype":"locality"
},
  "geometry": {"coordinates":[45.81722,41.635],"type":"Point"}
}