{
  "type": "Feature",
  "properties": {
    "gn:admin1_code":"71",
    "gn:asciiname":"Hebudi",
    "gn:country_code":"GE",
    "gn:dem":1681,
    "gn:feature_class":"P",
    "gn:feature_code":"PPL",
    "gn:name":"Hebudi",
    "gn:population":0,
    "gn:timezone":"Asia/Tbilisi",
    "iso:country":"GE",
    "name:kat_x_preferred":[
        "Hebudi"
    ],
    "name:kat_x_variant":[
        "\u10f0\u10d4\u10d1\u10e3\u10d3\u10d8"
    ],
    "name:und_x_variant":[
        "Khebudi",
        "Ebudi"
    ],
    "wof:name":"Hebudi",
    "wof:placetype":"locality"
},
  "geometry": {"coordinates":[42.55346,43.02808],"type":"Point"}
}