{
  "type": "Feature",
  "properties": {
    "gn:admin1_code":"00",
    "gn:asciiname":"Gugut'a",
    "gn:country_code":"GE",
    "gn:dem":1409,
    "gn:feature_class":"P",
    "gn:feature_code":"PPL",
    "gn:name":"Gugut\u2019a",
    "gn:population":0,
    "gn:timezone":"Asia/Tbilisi",
    "iso:country":"GE",
    "name:eng_x_preferred":[
        "Gugut'a"
    ],
    "name:rus_x_preferred":[
        "\u041c\u0443\u0433\u0430\u043d\u043b\u043e"
    ],
    "name:und_x_variant":[
        "Dag Muganlo",
        "Muganlo",
        "Gugut\u2019a"
    ],
    "wof:name":"Gugut'a",
    "wof:placetype":"locality"
},
  "geometry": {"coordinates":[44.31481,41.22241],"type":"Point"}
}