{
  "type": "Feature",
  "properties": {
    "gn:admin1_code":"67",
    "gn:asciiname":"Ikvlivgorana",
    "gn:country_code":"GE",
    "gn:dem":1156,
    "gn:feature_class":"P",
    "gn:feature_code":"PPL",
    "gn:name":"Ikvlivgorana",
    "gn:population":0,
    "gn:timezone":"Asia/Tbilisi",
    "iso:country":"GE",
    "name:kat_x_preferred":[
        "\u10d8\u10d9\u10d5\u10da\u10d8\u10d5\u10d2\u10dd\u10e0\u10d0\u10dc\u10d0"
    ],
    "wof:name":"Ikvlivgorana",
    "wof:placetype":"locality"
},
  "geometry": {"coordinates":[45.07555,41.86903],"type":"Point"}
}