{
  "type": "Feature",
  "properties": {
    "gn:admin1_code":"22",
    "gn:asciiname":"K'suisi",
    "gn:country_code":"GE",
    "gn:dem":943,
    "gn:feature_class":"P",
    "gn:feature_code":"PPL",
    "gn:name":"K\u2019suisi",
    "gn:population":0,
    "gn:timezone":"Asia/Tbilisi",
    "iso:country":"GE",
    "wof:name":"K'suisi",
    "wof:placetype":"locality"
},
  "geometry": {"coordinates":[44.07847,42.24264],"type":"Point"}
}