{
  "type": "Feature",
  "properties": {
    "gn:admin1_code":"55",
    "gn:asciiname":"Kit'khiji",
    "gn:country_code":"GE",
    "gn:dem":498,
    "gn:feature_class":"P",
    "gn:feature_code":"PPL",
    "gn:name":"Kit\u2019khiji",
    "gn:population":0,
    "gn:timezone":"Asia/Tbilisi",
    "iso:country":"GE",
    "name:und_x_variant":[
        "Kitkhidzhi",
        "Kit\u2019khiji"
    ],
    "wof:name":"Kit'khiji",
    "wof:placetype":"locality"
},
  "geometry": {"coordinates":[42.8698,42.38604],"type":"Point"}
}