{
  "type": "Feature",
  "properties": {
    "gn:admin1_code":"04",
    "gn:asciiname":"Zeda Tkhilnari",
    "gn:country_code":"GE",
    "gn:dem":185,
    "gn:feature_class":"P",
    "gn:feature_code":"PPL",
    "gn:name":"Zeda Tkhilnari",
    "gn:population":0,
    "gn:timezone":"Asia/Tbilisi",
    "iso:country":"GE",
    "name:kat_x_preferred":[
        "Zeda Tkhilnari"
    ],
    "name:kat_x_variant":[
        "\u10d6\u10d4\u10d3\u10d0 \u10d7\u10ee\u10d8\u10da\u10dc\u10d0\u10e0\u10d8"
    ],
    "wof:name":"Zeda Tkhilnari",
    "wof:placetype":"locality"
},
  "geometry": {"coordinates":[41.64333,41.5425],"type":"Point"}
}