{
  "type": "Feature",
  "properties": {
    "gn:admin1_code":"71",
    "gn:asciiname":"Lepochkhue",
    "gn:country_code":"GE",
    "gn:dem":75,
    "gn:feature_class":"P",
    "gn:feature_code":"PPL",
    "gn:name":"Lepochkhue",
    "gn:population":0,
    "gn:timezone":"Asia/Tbilisi",
    "iso:country":"GE",
    "name:kat_x_preferred":[
        "Lepochkhue"
    ],
    "name:kat_x_variant":[
        "\u10da\u10d4\u10e4\u10dd\u10e9\u10ee\u10e3\u10d4",
        "Lepochkhuye"
    ],
    "name:rus_x_preferred":[
        "\u041b\u0435\u043f\u043e\u0447\u0445\u0443\u0435"
    ],
    "name:und_x_variant":[
        "Lepochkhuye"
    ],
    "wof:name":"Lepochkhue",
    "wof:placetype":"locality"
},
  "geometry": {"coordinates":[42.25228,42.32682],"type":"Point"}
}