{
  "type": "Feature",
  "properties": {
    "gn:admin1_code":"72",
    "gn:asciiname":"Khulgumo",
    "gn:country_code":"GE",
    "gn:dem":1699,
    "gn:feature_class":"P",
    "gn:feature_code":"PPL",
    "gn:name":"Khulgumo",
    "gn:population":0,
    "gn:timezone":"Asia/Tbilisi",
    "iso:country":"GE",
    "name:kat_x_preferred":[
        "Khulgumo"
    ],
    "name:kat_x_variant":[
        "\u10ee\u10e3\u10da\u10d2\u10e3\u10db\u10dd"
    ],
    "wof:name":"Khulgumo",
    "wof:placetype":"locality"
},
  "geometry": {"coordinates":[43.49536,41.41551],"type":"Point"}
}