{
  "type": "Feature",
  "properties": {
    "gn:admin1_code":"00",
    "gn:asciiname":"T'amariani",
    "gn:country_code":"GE",
    "gn:dem":226,
    "gn:feature_class":"P",
    "gn:feature_code":"PPL",
    "gn:name":"T\u2019amariani",
    "gn:population":0,
    "gn:timezone":"Asia/Tbilisi",
    "iso:country":"GE",
    "name:kat_x_preferred":[
        "T\u2019amariani"
    ],
    "wof:name":"T'amariani",
    "wof:placetype":"locality"
},
  "geometry": {"coordinates":[46.16736,41.74916],"type":"Point"}
}