{
  "type": "Feature",
  "properties": {
    "gn:admin1_code":"00",
    "gn:asciiname":"Botko",
    "gn:country_code":"GE",
    "gn:dem":1175,
    "gn:feature_class":"P",
    "gn:feature_code":"PPL",
    "gn:name":"Botko",
    "gn:population":0,
    "gn:timezone":"Asia/Tbilisi",
    "iso:country":"GE",
    "name:und_x_variant":[
        "Bodko",
        "Botko"
    ],
    "wof:name":"Botko",
    "wof:placetype":"locality"
},
  "geometry": {"coordinates":[45.10841,41.90134000000001],"type":"Point"}
}