{
  "type": "Feature",
  "properties": {
    "gn:admin1_code":"71",
    "gn:asciiname":"T'vebishi",
    "gn:country_code":"GE",
    "gn:dem":1620,
    "gn:feature_class":"P",
    "gn:feature_code":"PPL",
    "gn:name":"T\u2019vebishi",
    "gn:population":0,
    "gn:timezone":"Asia/Tbilisi",
    "iso:country":"GE",
    "name:kat_x_preferred":[
        "T\u2019vebishi"
    ],
    "name:kat_x_variant":[
        "\u10e2\u10d5\u10d4\u10d1\u10d8\u10e8\u10d8"
    ],
    "wof:name":"T'vebishi",
    "wof:placetype":"locality"
},
  "geometry": {"coordinates":[42.59892,43.07116],"type":"Point"}
}