{
  "type": "Feature",
  "properties": {
    "gn:admin1_code":"00",
    "gn:asciiname":"Daredzhana",
    "gn:country_code":"GE",
    "gn:dem":793,
    "gn:feature_class":"P",
    "gn:feature_code":"PPL",
    "gn:name":"Daredzhana",
    "gn:population":0,
    "gn:timezone":"Asia/Tbilisi",
    "iso:country":"GE",
    "wof:name":"Daredzhana",
    "wof:placetype":"locality"
},
  "geometry": {"coordinates":[44.58861,42.03556],"type":"Point"}
}