{
  "type": "Feature",
  "properties": {
    "gn:admin1_code":"00",
    "gn:asciiname":"Zemo-Monasteri",
    "gn:country_code":"GE",
    "gn:dem":1167,
    "gn:feature_class":"P",
    "gn:feature_code":"PPL",
    "gn:name":"Zemo-Monasteri",
    "gn:population":50,
    "gn:timezone":"Asia/Tbilisi",
    "iso:country":"GE",
    "name:rus_x_preferred":[
        "\u0412\u0435\u0440\u0445\u043d\u0438\u0439 \u041c\u043e\u043d\u0430\u0441\u0442\u0435\u0440"
    ],
    "wof:name":"Zemo-Monasteri",
    "wof:placetype":"locality",
    "wof:population":50
},
  "geometry": {"coordinates":[43.91485,42.28583],"type":"Point"}
}