{
  "type": "Feature",
  "properties": {
    "gn:admin1_code":"67",
    "gn:asciiname":"Shalauri",
    "gn:country_code":"GE",
    "gn:dem":619,
    "gn:feature_class":"P",
    "gn:feature_code":"PPL",
    "gn:name":"Shalauri",
    "gn:population":0,
    "gn:timezone":"Asia/Tbilisi",
    "iso:country":"GE",
    "name:kat_x_preferred":[
        "\u10e8\u10d0\u10da\u10d0\u10e3\u10e0\u10d8"
    ],
    "wof:name":"Shalauri",
    "wof:placetype":"locality"
},
  "geometry": {"coordinates":[45.51156,41.91382],"type":"Point"}
}