{
  "type": "Feature",
  "properties": {
    "gn:admin1_code":"00",
    "gn:asciiname":"Lelubani",
    "gn:country_code":"GE",
    "gn:dem":1112,
    "gn:feature_class":"P",
    "gn:feature_code":"PPL",
    "gn:name":"Lelubani",
    "gn:population":0,
    "gn:timezone":"Asia/Tbilisi",
    "iso:country":"GE",
    "wof:name":"Lelubani",
    "wof:placetype":"locality"
},
  "geometry": {"coordinates":[44.93028,41.86472],"type":"Point"}
}