{
  "type": "Feature",
  "properties": {
    "gn:admin1_code":"02",
    "gn:asciiname":"Dgamsh",
    "gn:country_code":"GE",
    "gn:dem":187,
    "gn:feature_class":"P",
    "gn:feature_code":"PPL",
    "gn:name":"Dgamsh",
    "gn:population":0,
    "gn:timezone":"Asia/Tbilisi",
    "iso:country":"GE",
    "name:kat_x_preferred":[
        "Dghamshi"
    ],
    "name:kat_x_variant":[
        "\u10d3\u10e6\u10d0\u10db\u10e8\u10d8"
    ],
    "name:und_x_variant":[
        "Dgamishi",
        "Dgamshi",
        "Dgamsh"
    ],
    "wof:name":"Dgamsh",
    "wof:placetype":"locality"
},
  "geometry": {"coordinates":[41.41367,42.89693],"type":"Point"}
}