{
  "type": "Feature",
  "properties": {
    "gn:admin1_code":"02",
    "gn:asciiname":"Ts'alk'ot'i",
    "gn:country_code":"GE",
    "gn:dem":11,
    "gn:feature_class":"P",
    "gn:feature_code":"PPL",
    "gn:name":"Ts\u2019alk\u2019ot\u2019i",
    "gn:population":0,
    "gn:timezone":"Asia/Tbilisi",
    "iso:country":"GE",
    "name:kat_x_preferred":[
        "\u10ec\u10d0\u10da\u10d9\u10dd\u10e2\u10d8"
    ],
    "name:kat_x_variant":[
        "Lkoti",
        "Ts\u2019alk\u2019ot\u2019i"
    ],
    "wof:name":"Ts'alk'ot'i",
    "wof:placetype":"locality"
},
  "geometry": {"coordinates":[40.05248,43.40001],"type":"Point"}
}