{
  "type": "Feature",
  "properties": {
    "gn:admin1_code":"08",
    "gn:asciiname":"Bukhrebi",
    "gn:country_code":"GE",
    "gn:dem":885,
    "gn:feature_class":"P",
    "gn:feature_code":"PPL",
    "gn:name":"Bukhrebi",
    "gn:population":0,
    "gn:timezone":"Asia/Tbilisi",
    "iso:country":"GE",
    "wof:name":"Bukhrebi",
    "wof:placetype":"locality"
},
  "geometry": {"coordinates":[45.13278,42.16806],"type":"Point"}
}