{
  "type": "Feature",
  "properties": {
    "gn:admin1_code":"66",
    "gn:asciiname":"Kvaq'ude",
    "gn:country_code":"GE",
    "gn:dem":97,
    "gn:feature_class":"P",
    "gn:feature_code":"PPL",
    "gn:name":"Kvaq\u2019ude",
    "gn:population":0,
    "gn:timezone":"Asia/Tbilisi",
    "iso:country":"GE",
    "name:kat_x_preferred":[
        "Kvaq\u2019ude"
    ],
    "name:kat_x_variant":[
        "\u10e5\u10d5\u10d0\u10e7\u10e3\u10d3\u10d4"
    ],
    "name:und_x_variant":[
        "Kvakude"
    ],
    "wof:name":"Kvaq'ude",
    "wof:placetype":"locality"
},
  "geometry": {"coordinates":[42.29062,42.05463],"type":"Point"}
}