{
  "type": "Feature",
  "properties": {
    "gn:admin1_code":"68",
    "gn:asciiname":"Mushevani",
    "gn:country_code":"GE",
    "gn:dem":736,
    "gn:feature_class":"P",
    "gn:feature_code":"PPL",
    "gn:name":"Mushevani",
    "gn:population":0,
    "gn:timezone":"Asia/Tbilisi",
    "iso:country":"GE",
    "name:kat_x_preferred":[
        "\u10db\u10e3\u10e8\u10d4\u10d5\u10d0\u10dc\u10d8"
    ],
    "name:und_x_variant":[
        "Mushavani",
        "Mushevani"
    ],
    "wof:name":"Mushevani",
    "wof:placetype":"locality"
},
  "geometry": {"coordinates":[44.46104,41.41398],"type":"Point"}
}