{
  "type": "Feature",
  "properties": {
    "gn:admin1_code":"69",
    "gn:asciiname":"Bitsmendi",
    "gn:country_code":"GE",
    "gn:dem":647,
    "gn:feature_class":"P",
    "gn:feature_code":"PPL",
    "gn:name":"Bitsmendi",
    "gn:population":0,
    "gn:timezone":"Asia/Tbilisi",
    "iso:country":"GE",
    "name:eng_x_preferred":[
        "Bitsmendi"
    ],
    "name:kat_x_preferred":[
        "Bitsmendi"
    ],
    "name:rus_x_preferred":[
        "\u0411\u0438\u0446\u043c\u0435\u043d\u0434\u0438"
    ],
    "wof:name":"Bitsmendi",
    "wof:placetype":"locality"
},
  "geometry": {"coordinates":[44.79606,41.93678],"type":"Point"}
}