{
  "type": "Feature",
  "properties": {
    "gn:admin1_code":"00",
    "gn:asciiname":"K'eshalo",
    "gn:country_code":"GE",
    "gn:dem":462,
    "gn:feature_class":"P",
    "gn:feature_code":"PPL",
    "gn:name":"K\u2019eshalo",
    "gn:population":0,
    "gn:timezone":"Asia/Tbilisi",
    "iso:country":"GE",
    "name:kat_x_preferred":[
        "K\u2019eshalo"
    ],
    "wof:name":"K'eshalo",
    "wof:placetype":"locality"
},
  "geometry": {"coordinates":[45.5369,41.59153],"type":"Point"}
}