{
  "type": "Feature",
  "properties": {
    "gn:admin1_code":"29",
    "gn:asciiname":"Khamisquri",
    "gn:cc2":"GE",
    "gn:country_code":"GE",
    "gn:dem":47,
    "gn:feature_class":"P",
    "gn:feature_code":"PPL",
    "gn:name":"Khamisquri",
    "gn:population":0,
    "gn:timezone":"Asia/Tbilisi",
    "iso:country":"GE",
    "name:kat_x_preferred":[
        "Khamisquri"
    ],
    "name:und_x_variant":[
        "Khamiskuri"
    ],
    "wof:name":"Khamisquri",
    "wof:placetype":"locality"
},
  "geometry": {"coordinates":[41.80694,42.39361],"type":"Point"}
}