{
  "type": "Feature",
  "properties": {
    "gn:admin1_code":"71",
    "gn:asciiname":"Ipkhi",
    "gn:country_code":"GE",
    "gn:dem":1437,
    "gn:feature_class":"P",
    "gn:feature_code":"PPL",
    "gn:name":"Ipkhi",
    "gn:population":0,
    "gn:timezone":"Asia/Tbilisi",
    "iso:country":"GE",
    "name:kat_x_preferred":[
        "\u10d8\u10e4\u10ee\u10d8"
    ],
    "name:und_x_variant":[
        "Ifkhi",
        "Ipkhi"
    ],
    "wof:name":"Ipkhi",
    "wof:placetype":"locality"
},
  "geometry": {"coordinates":[42.61544,43.01828],"type":"Point"}
}