{
  "type": "Feature",
  "properties": {
    "gn:admin1_code":"00",
    "gn:asciiname":"Gulbagi",
    "gn:country_code":"GE",
    "gn:dem":665,
    "gn:feature_class":"P",
    "gn:feature_code":"PPL",
    "gn:name":"Gulbagi",
    "gn:population":0,
    "gn:timezone":"Asia/Tbilisi",
    "iso:country":"GE",
    "name:und_x_variant":[
        "Gyul-Dag",
        "Gulbagi"
    ],
    "wof:name":"Gulbagi",
    "wof:placetype":"locality"
},
  "geometry": {"coordinates":[44.72022,41.23135],"type":"Point"}
}