{
  "type": "Feature",
  "properties": {
    "gn:admin1_code":"73",
    "gn:asciiname":"Nigoza",
    "gn:country_code":"GE",
    "gn:dem":779,
    "gn:feature_class":"P",
    "gn:feature_code":"PPL",
    "gn:name":"Nigoza",
    "gn:population":0,
    "gn:timezone":"Asia/Tbilisi",
    "iso:country":"GE",
    "name:kat_x_preferred":[
        "Nigoza"
    ],
    "name:kat_x_variant":[
        "\u10dc\u10d8\u10d2\u10dd\u10d6\u10d0"
    ],
    "wof:name":"Nigoza",
    "wof:placetype":"locality"
},
  "geometry": {"coordinates":[44.32806,42.00889],"type":"Point"}
}