{
  "type": "Feature",
  "properties": {
    "gn:admin1_code":"00",
    "gn:asciiname":"Bektakari",
    "gn:country_code":"GE",
    "gn:dem":912,
    "gn:feature_class":"P",
    "gn:feature_code":"PPL",
    "gn:name":"Bektakari",
    "gn:population":0,
    "gn:timezone":"Asia/Tbilisi",
    "iso:country":"GE",
    "name:kat_x_preferred":[
        "\u10d1\u10d4\u10e0\u10d7\u10d0\u10d9\u10d0\u10e0\u10d8"
    ],
    "name:und_x_variant":[
        "Begtakari",
        "Bektakari"
    ],
    "wof:name":"Bektakari",
    "wof:placetype":"locality"
},
  "geometry": {"coordinates":[44.38349,41.47139],"type":"Point"}
}