{
  "type": "Feature",
  "properties": {
    "gn:admin1_code":"24",
    "gn:asciiname":"Qemult'a",
    "gn:country_code":"GE",
    "gn:dem":1405,
    "gn:feature_class":"P",
    "gn:feature_code":"PPL",
    "gn:name":"Qemult\u2019a",
    "gn:population":0,
    "gn:timezone":"Asia/Tbilisi",
    "iso:country":"GE",
    "name:eng_x_preferred":[
        "Qemult'a"
    ],
    "name:rus_x_preferred":[
        "\u041a\u0435\u043c\u0443\u043b\u0442\u0430"
    ],
    "name:und_x_variant":[
        "Kemul\u2019ta",
        "Kemul\u2019to",
        "Qemult\u2019a"
    ],
    "wof:name":"Qemult'a",
    "wof:placetype":"locality"
},
  "geometry": {"coordinates":[43.8425,42.44403],"type":"Point"}
}