{
  "type": "Feature",
  "properties": {
    "gn:admin1_code":"00",
    "gn:asciiname":"Sakaraulo",
    "gn:country_code":"GE",
    "gn:dem":1197,
    "gn:feature_class":"P",
    "gn:feature_code":"PPL",
    "gn:name":"Sakaraulo",
    "gn:population":0,
    "gn:timezone":"Asia/Tbilisi",
    "iso:country":"GE",
    "wof:name":"Sakaraulo",
    "wof:placetype":"locality"
},
  "geometry": {"coordinates":[43.71556,42.23111],"type":"Point"}
}