{
  "type": "Feature",
  "properties": {
    "gn:admin1_code":"00",
    "gn:asciiname":"Mayram",
    "gn:country_code":"GE",
    "gn:dem":1680,
    "gn:feature_class":"P",
    "gn:feature_code":"PPL",
    "gn:name":"Mayram",
    "gn:population":0,
    "gn:timezone":"Asia/Tbilisi",
    "iso:country":"GE",
    "name:und_x_variant":[
        "Mairami",
        "Mayram"
    ],
    "wof:name":"Mayram",
    "wof:placetype":"locality"
},
  "geometry": {"coordinates":[43.92841,42.47405],"type":"Point"}
}