{
  "type": "Feature",
  "properties": {
    "gn:admin1_code":"00",
    "gn:asciiname":"Ts'khvarichamia",
    "gn:country_code":"GE",
    "gn:dem":1094,
    "gn:feature_class":"P",
    "gn:feature_code":"PPL",
    "gn:name":"Ts\u2019khvarichamia",
    "gn:population":0,
    "gn:timezone":"Asia/Tbilisi",
    "iso:country":"GE",
    "name:eng_x_preferred":[
        "Ts'khvarichamia"
    ],
    "name:kat_x_preferred":[
        "Ts\u2019khvarichamia"
    ],
    "name:rus_x_preferred":[
        "\u0426\u0445\u0432\u0430\u0440\u0438\u0447\u0430\u043c\u0438\u0430"
    ],
    "name:und_x_variant":[
        "Tskhvarichamiya",
        "Tskhvarigamia",
        "Tskharichamia"
    ],
    "wof:name":"Ts'khvarichamia",
    "wof:placetype":"locality"
},
  "geometry": {"coordinates":[44.92637,41.88397],"type":"Point"}
}