{
  "type": "Feature",
  "properties": {
    "gn:admin1_code":"00",
    "gn:asciiname":"Patkineti",
    "gn:country_code":"GE",
    "gn:dem":944,
    "gn:feature_class":"P",
    "gn:feature_code":"PPL",
    "gn:name":"Patkineti",
    "gn:population":0,
    "gn:timezone":"Asia/Tbilisi",
    "iso:country":"GE",
    "wof:name":"Patkineti",
    "wof:placetype":"locality"
},
  "geometry": {"coordinates":[43.73154,42.18712],"type":"Point"}
}