{
  "type": "Feature",
  "properties": {
    "gn:admin1_code":"04",
    "gn:asciiname":"Ach'i",
    "gn:country_code":"GE",
    "gn:dem":445,
    "gn:feature_class":"P",
    "gn:feature_code":"PPL",
    "gn:name":"Ach\u2019i",
    "gn:population":0,
    "gn:timezone":"Asia/Tbilisi",
    "iso:country":"GE",
    "name:kat_x_preferred":[
        "Ach\u2019i"
    ],
    "name:kat_x_variant":[
        "\u10d0\u10ed\u10d8"
    ],
    "wof:name":"Ach'i",
    "wof:placetype":"locality"
},
  "geometry": {"coordinates":[41.99859,41.84119000000001],"type":"Point"}
}