{
  "type": "Feature",
  "properties": {
    "gn:admin1_code":"70",
    "gn:asciiname":"Zhakhunderi",
    "gn:country_code":"GE",
    "gn:dem":1355,
    "gn:feature_class":"P",
    "gn:feature_code":"PPL",
    "gn:name":"Zhakhunderi",
    "gn:population":0,
    "gn:timezone":"Asia/Tbilisi",
    "iso:country":"GE",
    "name:kat_x_preferred":[
        "Jakhunderi"
    ],
    "name:kat_x_variant":[
        "\u10ef\u10d0\u10ee\u10e3\u10dc\u10d3\u10d4\u10e0\u10d8",
        "\u10df\u10d0\u10ee\u10e3\u10dc\u10d3\u10d4\u10e0\u10d8"
    ],
    "name:rus_x_preferred":[
        "\u0414\u0436\u0430\u0445\u0443\u043d\u0434\u0435\u0440\u0438"
    ],
    "name:und_x_variant":[
        "Dzhakhunderi",
        "Zhakhunderi"
    ],
    "wof:name":"Zhakhunderi",
    "wof:placetype":"locality"
},
  "geometry": {"coordinates":[43.01927,42.79718],"type":"Point"}
}