{
  "type": "Feature",
  "properties": {
    "gn:admin1_code":"00",
    "gn:asciiname":"Sabarklet'i",
    "gn:country_code":"GE",
    "gn:dem":1851,
    "gn:feature_class":"P",
    "gn:feature_code":"PPL",
    "gn:name":"Sabarklet\u2019i",
    "gn:population":0,
    "gn:timezone":"Asia/Tbilisi",
    "iso:country":"GE",
    "name:eng_x_preferred":[
        "Sabarklet'i"
    ],
    "name:kat_x_preferred":[
        "Sabarklet\u2019i"
    ],
    "name:rus_x_preferred":[
        "\u0421\u0430\u0431\u0430\u0440\u043a\u043b\u0435\u0442\u0438"
    ],
    "wof:name":"Sabarklet'i",
    "wof:placetype":"locality"
},
  "geometry": {"coordinates":[44.39334,42.35306],"type":"Point"}
}