{
  "type": "Feature",
  "properties": {
    "gn:admin1_code":"00",
    "gn:asciiname":"Tserak'vi",
    "gn:country_code":"GE",
    "gn:dem":1013,
    "gn:feature_class":"P",
    "gn:feature_code":"PPL",
    "gn:name":"Tserak\u2019vi",
    "gn:population":0,
    "gn:timezone":"Asia/Tbilisi",
    "iso:country":"GE",
    "name:kat_x_preferred":[
        "\u10ec\u10d4\u10e0\u10d0\u10e5\u10d5\u10d8"
    ],
    "name:rus_x_preferred":[
        "\u0426\u0435\u0440\u0430\u043a\u0432\u0438"
    ],
    "name:und_x_variant":[
        "Tseravki",
        "VerkhniyeTserakvi",
        "Tserak\u2019vi"
    ],
    "wof:name":"Tserak'vi",
    "wof:placetype":"locality"
},
  "geometry": {"coordinates":[44.6565,41.29573],"type":"Point"}
}