{
  "type": "Feature",
  "properties": {
    "gn:admin1_code":"00",
    "gn:asciiname":"Kvemo-Makhisi",
    "gn:country_code":"GE",
    "gn:dem":1142,
    "gn:feature_class":"P",
    "gn:feature_code":"PPL",
    "gn:name":"Kvemo-Makhisi",
    "gn:population":0,
    "gn:timezone":"Asia/Tbilisi",
    "iso:country":"GE",
    "wof:name":"Kvemo-Makhisi",
    "wof:placetype":"locality"
},
  "geometry": {"coordinates":[44.22389,42.21222],"type":"Point"}
}