{
  "type": "Feature",
  "properties": {
    "gn:admin1_code":"69",
    "gn:asciiname":"Ghulelebi",
    "gn:country_code":"GE",
    "gn:dem":1086,
    "gn:feature_class":"P",
    "gn:feature_code":"PPL",
    "gn:name":"Ghulelebi",
    "gn:population":0,
    "gn:timezone":"Asia/Tbilisi",
    "iso:country":"GE",
    "name:kat_x_preferred":[
        "Ghulelebi"
    ],
    "name:kat_x_variant":[
        "\u10e6\u10e3\u10da\u10d4\u10da\u10d4\u10d1\u10d8"
    ],
    "name:und_x_variant":[
        "Gulelebi",
        "Guleleba"
    ],
    "wof:name":"Ghulelebi",
    "wof:placetype":"locality"
},
  "geometry": {"coordinates":[44.92754,41.93617],"type":"Point"}
}