{
  "type": "Feature",
  "properties": {
    "gn:admin1_code":"59",
    "gn:asciiname":"Mukhiani",
    "gn:country_code":"GE",
    "gn:dem":88,
    "gn:feature_class":"P",
    "gn:feature_code":"PPL",
    "gn:name":"Mukhiani",
    "gn:population":0,
    "gn:timezone":"Asia/Tbilisi",
    "iso:country":"GE",
    "wof:name":"Mukhiani",
    "wof:placetype":"locality"
},
  "geometry": {"coordinates":[42.60111,42.20403],"type":"Point"}
}