{
  "type": "Feature",
  "properties": {
    "gn:admin1_code":"68",
    "gn:asciiname":"Ulashlo",
    "gn:country_code":"GE",
    "gn:dem":365,
    "gn:feature_class":"P",
    "gn:feature_code":"PPL",
    "gn:name":"Ulashlo",
    "gn:population":0,
    "gn:timezone":"Asia/Tbilisi",
    "iso:country":"GE",
    "name:kat_x_preferred":[
        "\u10e3\u10da\u10d0\u10e8\u10da\u10dd"
    ],
    "wof:name":"Ulashlo",
    "wof:placetype":"locality"
},
  "geometry": {"coordinates":[44.8766,41.32321],"type":"Point"}
}