{
  "type": "Feature",
  "properties": {
    "gn:admin1_code":"00",
    "gn:asciiname":"Alek'seevka",
    "gn:country_code":"GE",
    "gn:dem":1207,
    "gn:feature_class":"P",
    "gn:feature_code":"PPL",
    "gn:name":"Alek\u2019seevka",
    "gn:population":0,
    "gn:timezone":"Asia/Tbilisi",
    "iso:country":"GE",
    "name:und_x_variant":[
        "Alekseyevka",
        "Alek\u2019seevka"
    ],
    "wof:name":"Alek'seevka",
    "wof:placetype":"locality"
},
  "geometry": {"coordinates":[44.36167,41.53639],"type":"Point"}
}