{
  "type": "Feature",
  "properties": {
    "gn:admin1_code":"00",
    "gn:asciiname":"Magi",
    "gn:country_code":"GE",
    "gn:dem":2048,
    "gn:feature_class":"P",
    "gn:feature_code":"PPL",
    "gn:name":"Magi",
    "gn:population":0,
    "gn:timezone":"Asia/Tbilisi",
    "iso:country":"GE",
    "name:und_x_variant":[
        "Mag",
        "Magi"
    ],
    "wof:name":"Magi",
    "wof:placetype":"locality"
},
  "geometry": {"coordinates":[44.07222,42.58933],"type":"Point"}
}