{
  "type": "Feature",
  "properties": {
    "gn:admin1_code":"68",
    "gn:asciiname":"Orbet'i",
    "gn:country_code":"GE",
    "gn:dem":1307,
    "gn:feature_class":"P",
    "gn:feature_code":"PPL",
    "gn:name":"Orbet\u2019i",
    "gn:population":0,
    "gn:timezone":"Asia/Tbilisi",
    "iso:country":"GE",
    "name:eng_x_preferred":[
        "Orbet'i"
    ],
    "name:kat_x_preferred":[
        "\u10dd\u10e0\u10d1\u10d4\u10d7\u10d8"
    ],
    "name:rus_x_preferred":[
        "\u041e\u0440\u0431\u0435\u0442\u0438"
    ],
    "name:und_x_variant":[
        "Priyut",
        "Orbet\u2019i"
    ],
    "wof:name":"Orbet'i",
    "wof:placetype":"locality"
},
  "geometry": {"coordinates":[44.53109,41.66468],"type":"Point"}
}