{
  "type": "Feature",
  "properties": {
    "gn:admin1_code":"00",
    "gn:asciiname":"Khidiskuri",
    "gn:country_code":"GE",
    "gn:dem":494,
    "gn:feature_class":"P",
    "gn:feature_code":"PPL",
    "gn:name":"Khidiskuri",
    "gn:population":0,
    "gn:timezone":"Asia/Tbilisi",
    "iso:country":"GE",
    "wof:name":"Khidiskuri",
    "wof:placetype":"locality"
},
  "geometry": {"coordinates":[44.56602,41.86982],"type":"Point"}
}