{
  "type": "Feature",
  "properties": {
    "gn:admin1_code":"00",
    "gn:asciiname":"Chetar",
    "gn:country_code":"GE",
    "gn:dem":1402,
    "gn:feature_class":"P",
    "gn:feature_code":"PPL",
    "gn:name":"Chetar",
    "gn:population":0,
    "gn:timezone":"Asia/Tbilisi",
    "iso:country":"GE",
    "wof:name":"Chetar",
    "wof:placetype":"locality"
},
  "geometry": {"coordinates":[44.01015,42.38578],"type":"Point"}
}