{
  "type": "Feature",
  "properties": {
    "gn:admin1_code":"00",
    "gn:asciiname":"Khalivdon",
    "gn:country_code":"GE",
    "gn:dem":1998,
    "gn:feature_class":"P",
    "gn:feature_code":"PPL",
    "gn:name":"Khalivdon",
    "gn:population":0,
    "gn:timezone":"Asia/Tbilisi",
    "iso:country":"GE",
    "wof:name":"Khalivdon",
    "wof:placetype":"locality"
},
  "geometry": {"coordinates":[43.83333,42.46667],"type":"Point"}
}