{
  "type": "Feature",
  "properties": {
    "gn:admin1_code":"66",
    "gn:asciiname":"Kalvata",
    "gn:country_code":"GE",
    "gn:dem":506,
    "gn:feature_class":"P",
    "gn:feature_code":"PPL",
    "gn:name":"Kalvata",
    "gn:population":0,
    "gn:timezone":"Asia/Tbilisi",
    "iso:country":"GE",
    "name:kat_x_preferred":[
        "\u10d9\u10d0\u10da\u10d5\u10d0\u10d7\u10d0"
    ],
    "name:und_x_variant":[
        "Kaluata",
        "Kalvata"
    ],
    "wof:name":"Kalvata",
    "wof:placetype":"locality"
},
  "geometry": {"coordinates":[43.39153,42.31836],"type":"Point"}
}