{
  "type": "Feature",
  "properties": {
    "gn:admin1_code":"70",
    "gn:asciiname":"P'arakhet'i",
    "gn:country_code":"GE",
    "gn:dem":912,
    "gn:feature_class":"P",
    "gn:feature_code":"PPL",
    "gn:name":"P\u2019arakhet\u2019i",
    "gn:population":0,
    "gn:timezone":"Asia/Tbilisi",
    "iso:country":"GE",
    "wof:name":"P'arakhet'i",
    "wof:placetype":"locality"
},
  "geometry": {"coordinates":[43.35083,42.5625],"type":"Point"}
}