{
  "type": "Feature",
  "properties": {
    "gn:admin1_code":"00",
    "gn:asciiname":"Tusrebi",
    "gn:country_code":"GE",
    "gn:dem":1908,
    "gn:feature_class":"P",
    "gn:feature_code":"PPL",
    "gn:name":"Tusrebi",
    "gn:population":0,
    "gn:timezone":"Asia/Tbilisi",
    "iso:country":"GE",
    "wof:name":"Tusrebi",
    "wof:placetype":"locality"
},
  "geometry": {"coordinates":[43.81667,41.73333],"type":"Point"}
}