{
  "type": "Feature",
  "properties": {
    "gn:admin1_code":"70",
    "gn:asciiname":"Tsakhi",
    "gn:country_code":"GE",
    "gn:dem":901,
    "gn:feature_class":"P",
    "gn:feature_code":"PPL",
    "gn:name":"Tsakhi",
    "gn:population":0,
    "gn:timezone":"Asia/Tbilisi",
    "iso:country":"GE",
    "name:kat_x_preferred":[
        "Tsakhi"
    ],
    "name:kat_x_variant":[
        "\u10ea\u10d0\u10ee\u10d8"
    ],
    "name:und_x_variant":[
        "Tsakha"
    ],
    "wof:name":"Tsakhi",
    "wof:placetype":"locality"
},
  "geometry": {"coordinates":[42.92545,42.52224],"type":"Point"}
}