{
  "type": "Feature",
  "properties": {
    "gn:admin1_code":"00",
    "gn:asciiname":"Arjevan-Sarvani",
    "gn:country_code":"GE",
    "gn:dem":1691,
    "gn:feature_class":"P",
    "gn:feature_code":"PPL",
    "gn:name":"Arjevan-Sarvani",
    "gn:population":0,
    "gn:timezone":"Asia/Tbilisi",
    "iso:country":"GE",
    "name:und_x_variant":[
        "Ardzhevan-Sarvani",
        "Arjevan-Sarvani"
    ],
    "wof:name":"Arjevan-Sarvani",
    "wof:placetype":"locality"
},
  "geometry": {"coordinates":[44.15944,41.69502],"type":"Point"}
}