{
  "type": "Feature",
  "properties": {
    "gn:admin1_code":"66",
    "gn:asciiname":"Dablagomi",
    "gn:country_code":"GE",
    "gn:dem":57,
    "gn:feature_class":"P",
    "gn:feature_code":"PPL",
    "gn:name":"Dablagomi",
    "gn:population":0,
    "gn:timezone":"Asia/Tbilisi",
    "iso:country":"GE",
    "name:eng_x_preferred":[
        "Dablagomi"
    ],
    "name:kat_x_preferred":[
        "\u10d3\u10d0\u10d1\u10da\u10d0\u10d2\u10dd\u10db\u10d8"
    ],
    "name:rus_x_preferred":[
        "\u0414\u0430\u0431\u043b\u0430\u0433\u043e\u043c\u0438"
    ],
    "wof:name":"Dablagomi",
    "wof:placetype":"locality"
},
  "geometry": {"coordinates":[42.38197,42.0944],"type":"Point"}
}